Workbook

Sheet Start Here
A1: Wedding Budget Tracker
A2: Simple Sheets Co. — Excel + Google Sheets
A4: Setup
A5: 1. Enter your total budget and who's contributing on the Budget tab.
A6: 2. Every category has a typical share of budget pre-filled so you get a starting allocation instantly. Change any percentage.
A7: 3. As you book vendors, enter the quoted price, deposit paid, and what's still due. Over/under per category and overall updates live.
A8: 4. Payment Schedule tab lists every payment with its due date so nothing sneaks up on you.
A10: Conventions
A11: • Yellow cells with blue text are inputs. Type over the sample numbers.
A12: • Black text is a formula. Leave it alone unless you know what you're changing.
A13: • Green text pulls from another tab.
A14: • Works in Excel 2016+ and Google Sheets (File > Import > Upload > Replace). No macros.
A16: For planning and educational use only. Not financial, legal, or tax advice. Every number is an estimate you should verify for your own business.

Sheet Dashboard
B2: Wedding Budget
B3: Where the money is going, at a glance.
B5: TOTAL BUDGET | E5: COMMITTED (QUOTES & BOOKINGS) | H5: REMAINING TO SPEND | K5: STILL OWED TO VENDORS
B6: =Budget!B5 -> 35000 | E6: =Budget!D27 -> 33450 | H6: =Budget!B5-Budget!D27 -> 1550 | K6: ='Payment Schedule'!G33 -> 18400
B9: COST PER GUEST | E9: DUE IN NEXT 30 DAYS | H9: BUDGET USED
B10: =IF(Budget!B6=0,0,Budget!D27/Budget!B6) -> 278.75 | E10: ='Payment Schedule'!G34 -> 3700 | H10: =IF(Budget!B5=0,0,Budget!D27/Budget!B5) -> 0.95571429
B13: Budget used
B14: =REPT("█",ROUND(MIN(1,MAX(0,IF(Budget!B5=0,0,Budget!D27/Budget!B5)))*40,0))&REPT("░",40-ROUND(MIN(1,MAX(0,IF(Budget!B5=0,0,Budget!D27/Budget!B5)))*40,0))&" "&TEXT(IF(Budget!B5=0,0,Budget!D27/Budget!B5),"0%") -> ██████████████████████████████████████░░ 96%

Sheet Budget
A1: Wedding Budget
A2: Allocation vs actual.
A4: How to use: type your numbers in the yellow cells (blue text). Everything else calculates.
A5: Total budget | B5: 35000
A6: Guest count | B6: 120
A8: Category | B8: Typical % | C8: Allocated | D8: Quoted / actual | E8: Deposit paid | F8: Still due | G8: Over / (under) allocation | H8: Vendor / notes
A9: Venue & rentals | B9: 0.3 | C9: =B9*$B$5 -> 10500 | D9: 10400 | E9: 3000 | F9: =D9-E9 -> 7400 | G9: =D9-C9 -> -100
A10: Catering & bar | B10: 0.25 | C10: =B10*$B$5 -> 8750 | D10: 8600 | E10: 2000 | F10: =D10-E10 -> 6600 | G10: =D10-C10 -> -150
A11: Photography & video | B11: 0.12 | C11: =B11*$B$5 -> 4200 | D11: 4200 | E11: 1000 | F11: =D11-E11 -> 3200 | G11: =D11-C11 -> 0
A12: Flowers & décor | B12: 0.08 | C12: =B12*$B$5 -> 2800 | D12: 2600 | E12: 500 | F12: =D12-E12 -> 2100 | G12: =D12-C12 -> -200
A13: Music / DJ / band | B13: 0.06 | C13: =B13*$B$5 -> 2100 | D13: 1800 | E13: 400 | F13: =D13-E13 -> 1400 | G13: =D13-C13 -> -300
A14: Attire & beauty | B14: 0.06 | C14: =B14*$B$5 -> 2100 | D14: 2300 | E14: 900 | F14: =D14-E14 -> 1400 | G14: =D14-C14 -> 200
A15: Invitations & stationery | B15: 0.02 | C15: =B15*$B$5 -> 700 | D15: 650 | E15: 650 | F15: =D15-E15 -> 0 | G15: =D15-C15 -> -50
A16: Cake & desserts | B16: 0.02 | C16: =B16*$B$5 -> 700 | D16: 700 | E16: 200 | F16: =D16-E16 -> 500 | G16: =D16-C16 -> 0
A17: Officiant & ceremony | B17: 0.02 | C17: =B17*$B$5 -> 700 | D17: 500 | E17: 0 | F17: =D17-E17 -> 500 | G17: =D17-C17 -> -200
A18: Transportation | B18: 0.02 | C18: =B18*$B$5 -> 700 | D18: 600 | E18: 0 | F18: =D18-E18 -> 600 | G18: =D18-C18 -> -100
A19: Rings | B19: 0.03 | C19: =B19*$B$5 -> 1050 | D19: 1100 | E19: 1100 | F19: =D19-E19 -> 0 | G19: =D19-C19 -> 50
A20: Favors & gifts | B20: 0.02 | C20: =B20*$B$5 -> 700 | D20: 0 | E20: 0 | F20: =D20-E20 -> 0 | G20: =D20-C20 -> -700
B21: 0 | C21: =B21*$B$5 -> 0 | F21: =D21-E21 -> 0 | G21: =D21-C21 -> 0
B22: 0 | C22: =B22*$B$5 -> 0 | F22: =D22-E22 -> 0 | G22: =D22-C22 -> 0
B23: 0 | C23: =B23*$B$5 -> 0 | F23: =D23-E23 -> 0 | G23: =D23-C23 -> 0
B24: 0 | C24: =B24*$B$5 -> 0 | F24: =D24-E24 -> 0 | G24: =D24-C24 -> 0
B25: 0 | C25: =B25*$B$5 -> 0 | F25: =D25-E25 -> 0 | G25: =D25-C25 -> 0
B26: 0 | C26: =B26*$B$5 -> 0 | F26: =D26-E26 -> 0 | G26: =D26-C26 -> 0
A27: TOTAL | B27: =SUM(B9:B26) -> 1 | C27: =SUM(C9:C26) -> 35000 | D27: =SUM(D9:D26) -> 33450 | E27: =SUM(E9:E26) -> 9750 | F27: =SUM(F9:F26) -> 23700 | G27: =SUM(G9:G26) -> -1550
A29: Remaining vs total budget | B29: =B5-D27 -> 1550
A30: Cost per guest so far | B30: =IF(B6=0,0,D27/B6) -> 278.75
A31: Allocation check | B31: =IF(ABS(B27-1)<0.005,"Percentages add to 100%","Percentages add to "&TEXT(B27,"0%")&" — adjust") -> Percentages add to 100%

Sheet Payment Schedule
A1: Payment Schedule
A2: Every payment, in date order.
A4: How to use: type your numbers in the yellow cells (blue text). Everything else calculates.
A5: Due date | B5: Vendor | C5: Category | D5: Amount | E5: Paid? | F5: Paid date | G5: Outstanding
A6: 2026-10-01 | B6: The Grove Venue | C6: Venue & rentals | D6: 3000 | E6: Y | F6: 2026-09-15 | G6: =IF(E6="Y",0,D6) -> 0
A7: 2026-10-10 | B7: The Grove Venue | C7: Venue & rentals | D7: 3700 | E7: N | G7: =IF(E7="Y",0,D7) -> 3700
A8: 2027-04-01 | B8: The Grove Venue | C8: Venue & rentals | D8: 4100 | E8: N | G8: =IF(E8="Y",0,D8) -> 4100
A9: 2026-11-01 | B9: Blue Fig Catering | C9: Catering & bar | D9: 2000 | E9: Y | F9: 2026-10-28 | G9: =IF(E9="Y",0,D9) -> 0
A10: 2027-03-15 | B10: Blue Fig Catering | C10: Catering & bar | D10: 7400 | E10: N | G10: =IF(E10="Y",0,D10) -> 7400
A11: 2026-10-20 | B11: Ellie Rose Photo | C11: Photography & video | D11: 1000 | E11: Y | F11: 2026-10-20 | G11: =IF(E11="Y",0,D11) -> 0
A12: 2027-04-20 | B12: Ellie Rose Photo | C12: Photography & video | D12: 3200 | E12: N | G12: =IF(E12="Y",0,D12) -> 3200
G13: =IF(D13="","",IF(E13="Y",0,D13))
G14: =IF(D14="","",IF(E14="Y",0,D14))
G15: =IF(D15="","",IF(E15="Y",0,D15))
G16: =IF(D16="","",IF(E16="Y",0,D16))
G17: =IF(D17="","",IF(E17="Y",0,D17))
G18: =IF(D18="","",IF(E18="Y",0,D18))
G19: =IF(D19="","",IF(E19="Y",0,D19))
G20: =IF(D20="","",IF(E20="Y",0,D20))
G21: =IF(D21="","",IF(E21="Y",0,D21))
G22: =IF(D22="","",IF(E22="Y",0,D22))
G23: =IF(D23="","",IF(E23="Y",0,D23))
G24: =IF(D24="","",IF(E24="Y",0,D24))
... G32: =IF(D32="","",IF(E32="Y",0,D32))
A33: TOTAL | D33: =SUM(D6:D32) -> 24400 | G33: =SUM(G6:G32) -> 18400
A34: Due in next 30 days | G34: =SUMPRODUCT((G6:G32<>"")*(E6:E32<>"Y")*(A6:A32<>"")*(DATEVALUE(A6:A32&"")-TODAY()<=30)*(DATEVALUE(A6:A32&"")-TODAY()>=0),G6:G32) -> 3700
