Workbook

Sheet Start Here
A1: Monthly Budget Planner (Zero-Based)
A2: Simple Sheets Co. — Excel + Google Sheets
A4: Setup
A5: 1. Enter income sources at the top of each month column, then plan every dollar into a category until 'Left to assign' is zero.
A6: 2. Enter actual spend as the month goes. The Dashboard compares planned vs actual by category and shows your savings rate.
A7: 3. 12 months are laid out side by side so you can see trends.
A9: Conventions
A10: • Yellow cells with blue text are inputs. Type over the sample numbers.
A11: • Black text is a formula. Leave it alone unless you know what you're changing.
A12: • Green text pulls from another tab.
A13: • Works in Excel 2016+ and Google Sheets (File > Import > Upload > Replace). No macros.
A15: For planning and educational use only. Not financial, legal, or tax advice. Every number is an estimate you should verify for your own business.

Sheet Dashboard
B2: Money Dashboard
B3: Year to date: what came in, what went out, what you kept.
B5: INCOME (YTD ACTUAL) | E5: SPENT (YTD ACTUAL) | H5: SAVED (YTD) | K5: SAVINGS RATE
B6: =Details!B23 -> 82080 | E6: =Details!C21 -> 70935 | H6: =Details!B24 -> 9443 | K6: =Details!B25 -> 0.1150463
B9: BUDGETED (YTD) | E9: UNDER / (OVER) BUDGET
B10: =Details!B21 -> 70800 | E10: =Details!D21 -> -135
N13: Month | O13: Income | P13: Expenses
N14: Jan | O14: =Budget!C10 -> 6714 | P14: =Budget!C35 -> 6056
N15: Feb | O15: =Budget!E10 -> 6945 | P15: =Budget!E35 -> 6219
N16: Mar | O16: =Budget!G10 -> 7049 | P16: =Budget!G35 -> 6127
N17: Apr | O17: =Budget!I10 -> 6717 | P17: =Budget!I35 -> 6245
N18: May | O18: =Budget!K10 -> 6976 | P18: =Budget!K35 -> 5588
N19: Jun | O19: =Budget!M10 -> 7017 | P19: =Budget!M35 -> 5595
N20: Jul | O20: =Budget!O10 -> 6768 | P20: =Budget!O35 -> 5761
N21: Aug | O21: =Budget!Q10 -> 6890 | P21: =Budget!Q35 -> 5497
N22: Sep | O22: =Budget!S10 -> 6812 | P22: =Budget!S35 -> 6154
N23: Oct | O23: =Budget!U10 -> 6844 | P23: =Budget!U35 -> 5828
N24: Nov | O24: =Budget!W10 -> 6698 | P24: =Budget!W35 -> 6028
N25: Dec | O25: =Budget!Y10 -> 6650 | P25: =Budget!Y35 -> 5837

Sheet Details
A1: Year Dashboard
A2: Planned vs actual, whole year.
A4: Category | B4: Planned (YTD) | C4: Actual (YTD) | D4: Difference | E4: % of actual spend
A5: =Budget!A13 -> Rent / mortgage | B5: =Budget!B13+Budget!D13+Budget!F13+Budget!H13+Budget!J13+Budget!L13+Budget!N13+Budget!P13+Budget!R13+Budget!T13+Budget!V13+Budget!X13 -> 22200 | C5: =Budget!C13+Budget!E13+Budget!G13+Budget!I13+Budget!K13+Budget!M13+Budget!O13+Budget!Q13+Budget!S13+Budget!U13+Budget!W13+Budget!Y13 -> 22825 | D5: =B5-C5 -> -625 | E5: =IF($C$21=0,0,C5/$C$21) -> 0.32177345
A6: =Budget!A14 -> Utilities | B6: =Budget!B14+Budget!D14+Budget!F14+Budget!H14+Budget!J14+Budget!L14+Budget!N14+Budget!P14+Budget!R14+Budget!T14+Budget!V14+Budget!X14 -> 2640 | C6: =Budget!C14+Budget!E14+Budget!G14+Budget!I14+Budget!K14+Budget!M14+Budget!O14+Budget!Q14+Budget!S14+Budget!U14+Budget!W14+Budget!Y14 -> 2685 | D6: =B6-C6 -> -45 | E6: =IF($C$21=0,0,C6/$C$21) -> 0.037851554
A7: =Budget!A15 -> Groceries | B7: =Budget!B15+Budget!D15+Budget!F15+Budget!H15+Budget!J15+Budget!L15+Budget!N15+Budget!P15+Budget!R15+Budget!T15+Budget!V15+Budget!X15 -> 7800 | C7: =Budget!C15+Budget!E15+Budget!G15+Budget!I15+Budget!K15+Budget!M15+Budget!O15+Budget!Q15+Budget!S15+Budget!U15+Budget!W15+Budget!Y15 -> 7448 | D7: =B7-C7 -> 352 | E7: =IF($C$21=0,0,C7/$C$21) -> 0.10499753
A8: =Budget!A16 -> Dining out | B8: =Budget!B16+Budget!D16+Budget!F16+Budget!H16+Budget!J16+Budget!L16+Budget!N16+Budget!P16+Budget!R16+Budget!T16+Budget!V16+Budget!X16 -> 3000 | C8: =Budget!C16+Budget!E16+Budget!G16+Budget!I16+Budget!K16+Budget!M16+Budget!O16+Budget!Q16+Budget!S16+Budget!U16+Budget!W16+Budget!Y16 -> 2966 | D8: =B8-C8 -> 34 | E8: =IF($C$21=0,0,C8/$C$21) -> 0.041812927
A9: =Budget!A17 -> Transportation / gas | B9: =Budget!B17+Budget!D17+Budget!F17+Budget!H17+Budget!J17+Budget!L17+Budget!N17+Budget!P17+Budget!R17+Budget!T17+Budget!V17+Budget!X17 -> 3600 | C9: =Budget!C17+Budget!E17+Budget!G17+Budget!I17+Budget!K17+Budget!M17+Budget!O17+Budget!Q17+Budget!S17+Budget!U17+Budget!W17+Budget!Y17 -> 3497 | D9: =B9-C9 -> 103 | E9: =IF($C$21=0,0,C9/$C$21) -> 0.049298654
A10: =Budget!A18 -> Insurance | B10: =Budget!B18+Budget!D18+Budget!F18+Budget!H18+Budget!J18+Budget!L18+Budget!N18+Budget!P18+Budget!R18+Budget!T18+Budget!V18+Budget!X18 -> 3120 | C10: =Budget!C18+Budget!E18+Budget!G18+Budget!I18+Budget!K18+Budget!M18+Budget!O18+Budget!Q18+Budget!S18+Budget!U18+Budget!W18+Budget!Y18 -> 3075 | D10: =B10-C10 -> 45 | E10: =IF($C$21=0,0,C10/$C$21) -> 0.043349545
A11: =Budget!A19 -> Phone & internet | B11: =Budget!B19+Budget!D19+Budget!F19+Budget!H19+Budget!J19+Budget!L19+Budget!N19+Budget!P19+Budget!R19+Budget!T19+Budget!V19+Budget!X19 -> 1680 | C11: =Budget!C19+Budget!E19+Budget!G19+Budget!I19+Budget!K19+Budget!M19+Budget!O19+Budget!Q19+Budget!S19+Budget!U19+Budget!W19+Budget!Y19 -> 1737 | D11: =B11-C11 -> -57 | E11: =IF($C$21=0,0,C11/$C$21) -> 0.024487207
A12: =Budget!A20 -> Subscriptions | B12: =Budget!B20+Budget!D20+Budget!F20+Budget!H20+Budget!J20+Budget!L20+Budget!N20+Budget!P20+Budget!R20+Budget!T20+Budget!V20+Budget!X20 -> 720 | C12: =Budget!C20+Budget!E20+Budget!G20+Budget!I20+Budget!K20+Budget!M20+Budget!O20+Budget!Q20+Budget!S20+Budget!U20+Budget!W20+Budget!Y20 -> 698 | D12: =B12-C12 -> 22 | E12: =IF($C$21=0,0,C12/$C$21) -> 0.0098399944
A13: =Budget!A21 -> Debt payments | B13: =Budget!B21+Budget!D21+Budget!F21+Budget!H21+Budget!J21+Budget!L21+Budget!N21+Budget!P21+Budget!R21+Budget!T21+Budget!V21+Budget!X21 -> 5400 | C13: =Budget!C21+Budget!E21+Budget!G21+Budget!I21+Budget!K21+Budget!M21+Budget!O21+Budget!Q21+Budget!S21+Budget!U21+Budget!W21+Budget!Y21 -> 5177 | D13: =B13-C13 -> 223 | E13: =IF($C$21=0,0,C13/$C$21) -> 0.072982308
A14: =Budget!A22 -> Childcare / pets | B14: =Budget!B22+Budget!D22+Budget!F22+Budget!H22+Budget!J22+Budget!L22+Budget!N22+Budget!P22+Budget!R22+Budget!T22+Budget!V22+Budget!X22 -> 2400 | C14: =Budget!C22+Budget!E22+Budget!G22+Budget!I22+Budget!K22+Budget!M22+Budget!O22+Budget!Q22+Budget!S22+Budget!U22+Budget!W22+Budget!Y22 -> 2398 | D14: =B14-C14 -> 2 | E14: =IF($C$21=0,0,C14/$C$21) -> 0.033805597
A15: =Budget!A23 -> Personal & clothing | B15: =Budget!B23+Budget!D23+Budget!F23+Budget!H23+Budget!J23+Budget!L23+Budget!N23+Budget!P23+Budget!R23+Budget!T23+Budget!V23+Budget!X23 -> 1800 | C15: =Budget!C23+Budget!E23+Budget!G23+Budget!I23+Budget!K23+Budget!M23+Budget!O23+Budget!Q23+Budget!S23+Budget!U23+Budget!W23+Budget!Y23 -> 1867 | D15: =B15-C15 -> -67 | E15: =IF($C$21=0,0,C15/$C$21) -> 0.02631987
A16: =Budget!A24 -> Health | B16: =Budget!B24+Budget!D24+Budget!F24+Budget!H24+Budget!J24+Budget!L24+Budget!N24+Budget!P24+Budget!R24+Budget!T24+Budget!V24+Budget!X24 -> 1440 | C16: =Budget!C24+Budget!E24+Budget!G24+Budget!I24+Budget!K24+Budget!M24+Budget!O24+Budget!Q24+Budget!S24+Budget!U24+Budget!W24+Budget!Y24 -> 1564 | D16: =B16-C16 -> -124 | E16: =IF($C$21=0,0,C16/$C$21) -> 0.022048354
... A20: =Budget!A28 -> Misc / buffer | B20: =Budget!B28+Budget!D28+Budget!F28+Budget!H28+Budget!J28+Budget!L28+Budget!N28+Budget!P28+Budget!R28+Budget!T28+Budget!V28+Budget!X28 -> 1800 | C20: =Budget!C28+Budget!E28+Budget!G28+Budget!I28+Budget!K28+Budget!M28+Budget!O28+Budget!Q28+Budget!S28+Budget!U28+Budget!W28+Budget!Y28 -> 1850 | D20: =B20-C20 -> -50 | E20: =IF($C$21=0,0,C20/$C$21) -> 0.026080214
A21: TOTAL | B21: =SUM(B5:B20) -> 70800 | C21: =SUM(C5:C20) -> 70935 | D21: =SUM(D5:D20) -> -135 | E21: =SUM(E5:E20) -> 1
A23: Income YTD (actual) | B23: =Budget!C10+Budget!E10+Budget!G10+Budget!I10+Budget!K10+Budget!M10+Budget!O10+Budget!Q10+Budget!S10+Budget!U10+Budget!W10+Budget!Y10 -> 82080
A24: Saved YTD (actual) | B24: =C19 -> 9443
A25: Savings rate YTD | B25: =IF(B23=0,0,B24/B23) -> 0.1150463

Sheet Budget
A1: Monthly Budget
A2: Planned vs actual, 12 months.
A4: How to use: type your numbers in the yellow cells (blue text). Everything else calculates.
A5: Category | B5: Jan plan | C5: Jan actual | D5: Feb plan | E5: Feb actual | F5: Mar plan | G5: Mar actual | H5: Apr plan | I5: Apr actual | J5: May plan | K5: May actual | L5: Jun plan | M5: Jun actual | N5: Jul plan | O5: Jul actual | P5: Aug plan | Q5: Aug actual | R5: Sep plan | S5: Sep actual | T5: Oct plan | U5: Oct actual | V5: Nov plan | W5: Nov actual | X5: Dec plan | Y5: Dec actual
A6: INCOME
A7: Paycheck 1 | B7: 3900 | C7: 3881 | D7: 3900 | E7: 3923 | F7: 3900 | G7: 4065 | H7: 3900 | I7: 3887 | J7: 3900 | K7: 3903 | L7: 3900 | M7: 3934 | N7: 3900 | O7: 3777 | P7: 3900 | Q7: 3905 | R7: 3900 | S7: 3951 | T7: 3900 | U7: 4014 | V7: 3900 | W7: 3742 | X7: 3900 | Y7: 3823
A8: Paycheck 2 | B8: 2600 | C8: 2494 | D8: 2600 | E8: 2681 | F8: 2600 | G8: 2650 | H8: 2600 | I8: 2481 | J8: 2600 | K8: 2725 | L8: 2600 | M8: 2721 | N8: 2600 | O8: 2640 | P8: 2600 | Q8: 2630 | R8: 2600 | S8: 2511 | T8: 2600 | U8: 2474 | V8: 2600 | W8: 2607 | X8: 2600 | Y8: 2485
A9: Side income | B9: 350 | C9: 339 | D9: 350 | E9: 341 | F9: 350 | G9: 334 | H9: 350 | I9: 349 | J9: 350 | K9: 348 | L9: 350 | M9: 362 | N9: 350 | O9: 351 | P9: 350 | Q9: 355 | R9: 350 | S9: 350 | T9: 350 | U9: 356 | V9: 350 | W9: 349 | X9: 350 | Y9: 342
A10: Total income | B10: =SUM(B7:B9) -> 6850 | C10: =SUM(C7:C9) -> 6714 | D10: =SUM(D7:D9) -> 6850 | E10: =SUM(E7:E9) -> 6945 | F10: =SUM(F7:F9) -> 6850 | G10: =SUM(G7:G9) -> 7049 | H10: =SUM(H7:H9) -> 6850 | I10: =SUM(I7:I9) -> 6717 | ... Y10: =SUM(Y7:Y9) -> 6650
A12: EXPENSES
A13: Rent / mortgage | B13: 1850 | C13: 2218 | D13: 1850 | E13: 2217 | F13: 1850 | G13: 2102 | H13: 1850 | I13: 2004 | J13: 1850 | K13: 1713 | L13: 1850 | M13: 1650 | N13: 1850 | O13: 1694 | P13: 1850 | Q13: 1532 | R13: 1850 | S13: 2047 | T13: 1850 | U13: 1776 | V13: 1850 | W13: 2106 | X13: 1850 | Y13: 1766
A14: Utilities | B14: 220 | C14: 260 | D14: 220 | E14: 251 | F14: 220 | G14: 176 | H14: 220 | I14: 194 | J14: 220 | K14: 256 | L14: 220 | M14: 217 | N14: 220 | O14: 262 | P14: 220 | Q14: 211 | R14: 220 | S14: 182 | T14: 220 | U14: 231 | V14: 220 | W14: 245 | X14: 220 | Y14: 200
A15: Groceries | B15: 650 | C15: 543 | D15: 650 | E15: 606 | F15: 650 | G15: 771 | H15: 650 | I15: 717 | J15: 650 | K15: 551 | L15: 650 | M15: 584 | N15: 650 | O15: 546 | P15: 650 | Q15: 536 | R15: 650 | S15: 727 | T15: 650 | U15: 566 | V15: 650 | W15: 665 | X15: 650 | Y15: 636
A16: Dining out | B16: 250 | C16: 219 | D16: 250 | E16: 273 | F16: 250 | G16: 213 | H16: 250 | I16: 264 | J16: 250 | K16: 212 | L16: 250 | M16: 242 | N16: 250 | O16: 221 | P16: 250 | Q16: 227 | R16: 250 | S16: 297 | T16: 250 | U16: 280 | V16: 250 | W16: 230 | X16: 250 | Y16: 288
A17: Transportation / gas | B17: 300 | C17: 265 | D17: 300 | E17: 287 | F17: 300 | G17: 343 | H17: 300 | I17: 317 | J17: 300 | K17: 252 | L17: 300 | M17: 359 | N17: 300 | O17: 266 | P17: 300 | Q17: 271 | R17: 300 | S17: 333 | T17: 300 | U17: 279 | V17: 300 | W17: 276 | X17: 300 | Y17: 249
A18: Insurance | B18: 260 | C18: 217 | D18: 260 | E18: 269 | F18: 260 | G18: 233 | H18: 260 | I18: 271 | J18: 260 | K18: 247 | L18: 260 | M18: 255 | N18: 260 | O18: 308 | P18: 260 | Q18: 258 | R18: 260 | S18: 268 | T18: 260 | U18: 298 | V18: 260 | W18: 227 | X18: 260 | Y18: 224
A19: Phone & internet | B19: 140 | C19: 163 | D19: 140 | E19: 158 | F19: 140 | G19: 126 | H19: 140 | I19: 123 | J19: 140 | K19: 153 | L19: 140 | M19: 165 | N19: 140 | O19: 123 | P19: 140 | Q19: 165 | R19: 140 | S19: 161 | T19: 140 | U19: 146 | V19: 140 | W19: 136 | X19: 140 | Y19: 118
A20: Subscriptions | B20: 60 | C20: 49 | D20: 60 | E20: 71 | F20: 60 | G20: 54 | H20: 60 | I20: 65 | J20: 60 | K20: 54 | L20: 60 | M20: 68 | N20: 60 | O20: 62 | P20: 60 | Q20: 55 | R20: 60 | S20: 52 | T20: 60 | U20: 65 | V20: 60 | W20: 50 | X20: 60 | Y20: 53
A21: Debt payments | B21: 450 | C21: 461 | D21: 450 | E21: 513 | F21: 450 | G21: 471 | H21: 450 | I21: 410 | J21: 450 | K21: 525 | L21: 450 | M21: 397 | N21: 450 | O21: 363 | P21: 450 | Q21: 408 | R21: 450 | S21: 440 | T21: 450 | U21: 371 | V21: 450 | W21: 392 | X21: 450 | Y21: 426
A22: Childcare / pets | B22: 200 | C22: 206 | D22: 200 | E22: 171 | F22: 200 | G22: 189 | H22: 200 | I22: 231 | J22: 200 | K22: 238 | L22: 200 | M22: 213 | N22: 200 | O22: 215 | P22: 200 | Q22: 207 | R22: 200 | S22: 171 | T22: 200 | U22: 163 | V22: 200 | W22: 161 | X22: 200 | Y22: 233
A23: Personal & clothing | B23: 150 | C23: 162 | D23: 150 | E23: 178 | F23: 150 | G23: 121 | H23: 150 | I23: 158 | J23: 150 | K23: 149 | L23: 150 | M23: 164 | N23: 150 | O23: 139 | P23: 150 | Q23: 180 | R23: 150 | S23: 125 | T23: 150 | U23: 153 | V23: 150 | W23: 164 | X23: 150 | Y23: 174
A24: Health | B24: 120 | C24: 131 | D24: 120 | E24: 130 | F24: 120 | G24: 134 | H24: 120 | I24: 140 | J24: 120 | K24: 113 | L24: 120 | M24: 129 | N24: 120 | O24: 139 | P24: 120 | Q24: 138 | R24: 120 | S24: 116 | T24: 120 | U24: 134 | V24: 120 | W24: 137 | X24: 120 | Y24: 123
... A28: Misc / buffer | B28: 150 | C28: 132 | D28: 150 | E28: 146 | F28: 150 | G28: 168 | H28: 150 | I28: 175 | J28: 150 | K28: 173 | L28: 150 | M28: 143 | N28: 150 | O28: 155 | P28: 150 | Q28: 139 | R28: 150 | S28: 128 | T28: 150 | U28: 150 | V28: 150 | W28: 170 | X28: 150 | Y28: 171
A35: Total expenses | B35: =SUM(B13:B34) -> 5900 | C35: =SUM(C13:C34) -> 6056 | D35: =SUM(D13:D34) -> 5900 | E35: =SUM(E13:E34) -> 6219 | F35: =SUM(F13:F34) -> 5900 | G35: =SUM(G13:G34) -> 6127 | H35: =SUM(H13:H34) -> 5900 | I35: =SUM(I13:I34) -> 6245 | ... Y35: =SUM(Y13:Y34) -> 5837
A36: Left to assign / left over | B36: =B10-B35 -> 950 | C36: =C10-C35 -> 658 | D36: =D10-D35 -> 950 | E36: =E10-E35 -> 726 | F36: =F10-F35 -> 950 | G36: =G10-G35 -> 922 | H36: =H10-H35 -> 950 | I36: =I10-I35 -> 472 | ... Y36: =Y10-Y35 -> 813
A37: Savings rate | B37: =IF(B10=0,0,B27/B10) -> 0.11678832 | C37: =IF(C10=0,0,C27/C10) -> 0.10753649 | D37: =IF(D10=0,0,D27/D10) -> 0.11678832 | E37: =IF(E10=0,0,E27/E10) -> 0.092728582 | F37: =IF(F10=0,0,F27/F10) -> 0.11678832 | G37: =IF(G10=0,0,G27/G10) -> 0.10441197 | H37: =IF(H10=0,0,H27/H10) -> 0.11678832 | I37: =IF(I10=0,0,I27/I10) -> 0.12758672 | ... Y37: =IF(Y10=0,0,Y27/Y10) -> 0.12827068
