Workbook

Sheet Start Here
A1: Debt Payoff Planner — Snowball & Avalanche
A2: Simple Sheets Co. — Excel + Google Sheets
A4: Setup
A5: 1. List every debt with balance, APR and minimum payment. Enter how much extra you can pay each month.
A6: 2. Choose Snowball (smallest balance first) or Avalanche (highest rate first). The plan shows payoff order, months to debt-free, and total interest paid.
A7: 3. The Schedule tab simulates month by month (up to 120 months).
A9: Conventions
A10: • Yellow cells with blue text are inputs. Type over the sample numbers.
A11: • Black text is a formula. Leave it alone unless you know what you're changing.
A12: • Green text pulls from another tab.
A13: • Works in Excel 2016+ and Google Sheets (File > Import > Upload > Replace). No macros.
A14: • Simulation applies extra payment to the target debt, then rolls each paid-off minimum into the next one.
A16: For planning and educational use only. Not financial, legal, or tax advice. Every number is an estimate you should verify for your own business.

Sheet Dashboard
B2: Debt-Free Dashboard
B3: Your payoff plan, month by month.
B5: TOTAL DEBT TODAY | E5: PAYING PER MONTH | H5: MONTHS TO DEBT-FREE | K5: TOTAL INTEREST YOU'LL PAY
B6: =Debts!B16 -> 39800 | E6: =Debts!B17 -> 1200 | H6: =Debts!B18 -> 39 | K6: =Debts!B19 -> 5112.0052
B9: DEBT-FREE DATE | E9: EXTRA PAYMENT / MONTH | H9: AVERAGE APR
B10: =IF(ISNUMBER(Debts!B18),TEXT(EDATE(TODAY(),Debts!B18),"mmm yyyy"),"—") -> Dec 2029 | E10: =Debts!B4 -> 400 | H10: =IF(Debts!B16=0,0,SUMPRODUCT(Debts!B8:B15,Debts!C8:C15)/Debts!B16) -> 0.098017588

Sheet Debts
A1: Debts
A3: How to use: type your numbers in the yellow cells (blue text). Everything else calculates.
A4: Extra payment per month (beyond minimums) | B4: 400
A5: Method (Snowball or Avalanche) | B5: Avalanche
A7: Debt | B7: Balance | C7: APR | D7: Minimum payment | E7: Payoff order | F7: Months to payoff (alone)
A8: Credit card A | B8: 6200 | C8: 0.249 | D8: 155 | E8: =IF(A8="","",IF($B$5="Snowball",RANK(B8,$B$8:$B$15,1),RANK(C8,$C$8:$C$15,0))) -> 1 | F8: =IF(OR(A8="",D8=0),"",IF(C8=0,ROUNDUP(B8/D8,0),IF(D8<=B8*C8/12,"min too low",ROUNDUP(-LOG(1-B8*C8/12/D8)/LOG(1+C8/12),0)))) -> 87
A9: Credit card B | B9: 2400 | C9: 0.219 | D9: 75 | E9: =IF(A9="","",IF($B$5="Snowball",RANK(B9,$B$8:$B$15,1),RANK(C9,$C$8:$C$15,0))) -> 2 | F9: =IF(OR(A9="",D9=0),"",IF(C9=0,ROUNDUP(B9/D9,0),IF(D9<=B9*C9/12,"min too low",ROUNDUP(-LOG(1-B9*C9/12/D9)/LOG(1+C9/12),0)))) -> 49
A10: Car loan | B10: 11800 | C10: 0.069 | D10: 310 | E10: =IF(A10="","",IF($B$5="Snowball",RANK(B10,$B$8:$B$15,1),RANK(C10,$C$8:$C$15,0))) -> 3 | F10: =IF(OR(A10="",D10=0),"",IF(C10=0,ROUNDUP(B10/D10,0),IF(D10<=B10*C10/12,"min too low",ROUNDUP(-LOG(1-B10*C10/12/D10)/LOG(1+C10/12),0)))) -> 44
A11: Student loan | B11: 18500 | C11: 0.055 | D11: 210 | E11: =IF(A11="","",IF($B$5="Snowball",RANK(B11,$B$8:$B$15,1),RANK(C11,$C$8:$C$15,0))) -> 4 | F11: =IF(OR(A11="",D11=0),"",IF(C11=0,ROUNDUP(B11/D11,0),IF(D11<=B11*C11/12,"min too low",ROUNDUP(-LOG(1-B11*C11/12/D11)/LOG(1+C11/12),0)))) -> 114
A12: Medical bill | B12: 900 | C12: 0 | D12: 50 | E12: =IF(A12="","",IF($B$5="Snowball",RANK(B12,$B$8:$B$15,1),RANK(C12,$C$8:$C$15,0))) -> 5 | F12: =IF(OR(A12="",D12=0),"",IF(C12=0,ROUNDUP(B12/D12,0),IF(D12<=B12*C12/12,"min too low",ROUNDUP(-LOG(1-B12*C12/12/D12)/LOG(1+C12/12),0)))) -> 18
E13: =IF(A13="","",IF($B$5="Snowball",RANK(B13,$B$8:$B$15,1),RANK(C13,$C$8:$C$15,0))) | F13: =IF(OR(A13="",D13=0),"",IF(C13=0,ROUNDUP(B13/D13,0),IF(D13<=B13*C13/12,"min too low",ROUNDUP(-LOG(1-B13*C13/12/D13)/LOG(1+C13/12),0))))
E14: =IF(A14="","",IF($B$5="Snowball",RANK(B14,$B$8:$B$15,1),RANK(C14,$C$8:$C$15,0))) | F14: =IF(OR(A14="",D14=0),"",IF(C14=0,ROUNDUP(B14/D14,0),IF(D14<=B14*C14/12,"min too low",ROUNDUP(-LOG(1-B14*C14/12/D14)/LOG(1+C14/12),0))))
E15: =IF(A15="","",IF($B$5="Snowball",RANK(B15,$B$8:$B$15,1),RANK(C15,$C$8:$C$15,0))) | F15: =IF(OR(A15="",D15=0),"",IF(C15=0,ROUNDUP(B15/D15,0),IF(D15<=B15*C15/12,"min too low",ROUNDUP(-LOG(1-B15*C15/12/D15)/LOG(1+C15/12),0))))
A16: TOTAL | B16: =SUM(B8:B15) -> 39800 | D16: =SUM(D8:D15) -> 800
A17: Total monthly toward debt | B17: =B16*0+D16+B4 -> 1200
A18: Debt-free in (months) | B18: =Schedule!$B$3 -> 39
A19: Total interest paid | B19: =Schedule!$B$4 -> 5112.0052

Sheet Schedule
A1: Payoff Schedule
A2: Simulated month by month. Balances after payment.
A3: Months to debt-free | B3: =IFERROR(MATCH(TRUE(),INDEX(L8:L127<=0.5,0),0),">120") -> 39
A4: Total interest paid | B4: =SUM(K8:K127) -> 5112.0052
A6: Month | B6: Available | C6: D1 bal | D6: D2 bal | E6: D3 bal | F6: D4 bal | G6: D5 bal | H6: D6 bal | I6: D7 bal | J6: D8 bal | K6: Interest this month | L6: Total balance
A7: =0 -> 0 | C7: =IF(Debts!$B$8="",0,Debts!$B$8) -> 6200 | D7: =IF(Debts!$B$9="",0,Debts!$B$9) -> 2400 | E7: =IF(Debts!$B$10="",0,Debts!$B$10) -> 11800 | F7: =IF(Debts!$B$11="",0,Debts!$B$11) -> 18500 | G7: =IF(Debts!$B$12="",0,Debts!$B$12) -> 900 | H7: =IF(Debts!$B$13="",0,Debts!$B$13) -> 0 | I7: =IF(Debts!$B$14="",0,Debts!$B$14) -> 0 | J7: =IF(Debts!$B$15="",0,Debts!$B$15) -> 0 | K7: =0 -> 0 | L7: =SUM(C7:J7) -> 39800
A8: =1 -> 1 | B8: =IF(L7<=0,0,Debts!$D$16+Debts!$B$4) -> 1200 | C8: =IF(C7<=0,0,MAX(0,C7*(1+Debts!$C$8/12)-MIN(C7*(1+Debts!$C$8/12),Debts!$D$8)-IF(AND(C7>0,Debts!$E$8=MIN(IF(C7>0,Debts!$E$8,999),IF(D7>0,Debts!$E$9,999),IF(E7>0,Debts!$E$10,999),IF(F7>0,Debts!$E$11,999),IF(G7>0,Debts!$E$12,999),IF(H7>0,Debts!$E$13,999),IF(I7>0,Debts!$E$14,999),IF(J7>0,Debts!$E$15,999))),MAX(0,(B8-(MIN(C7+0,C7*(1+Debts!$C$8/12))*0+MIN(C7*(1+Debts!$C$8/12),Debts!$D$8)+MIN(C7+0,D7*(1+Debts!$C$9/12))*0+MIN(D7*(1+Debts!$C$9/12),Debts!$D$9)+MIN(C7+0,E7*(1+Debts!$C$10/12))*0+MIN(E7*(1+Debts!$C$10/12),Debts!$D$10)+MIN(C7+0,F7*(1+Debts!$C$11/12))*0+MIN(F7*(1+Debts!$C$11/12),Debts!$D$11)+MIN(C7+0,G7*(1+Debts!$C$12/12))*0+MIN(G7*(1+Debts!$C$12/12),Debts!$D$12)+MIN(C7+0,H7*(1+Debts!$C$13/12))*0+MIN(H7*(1+Debts!$C$13/12),Debts!$D$13)+MIN(C7+0,I7*(1+Debts!$C$14/12))*0+MIN(I7*(1+Debts!$C$14/12),Debts!$D$14)+MIN(C7+0,J7*(1+Debts!$C$15/12))*0+MIN(J7*(1+Debts!$C$15/12),Debts!$D$15)))),0))) -> 5773.65 | D8: =IF(D7<=0,0,MAX(0,D7*(1+Debts!$C$9/12)-MIN(D7*(1+Debts!$C$9/12),Debts!$D$9)-IF(AND(D7>0,Debts!$E$9=MIN(IF(C7>0,Debts!$E$8,999),IF(D7>0,Debts!$E$9,999),IF(E7>0,Debts!$E$10,999),IF(F7>0,Debts!$E$11,999),IF(G7>0,Debts!$E$12,999),IF(H7>0,Debts!$E$13,999),IF(I7>0,Debts!$E$14,999),IF(J7>0,Debts!$E$15,999))),MAX(0,(B8-(MIN(C7+0,C7*(1+Debts!$C$8/12))*0+MIN(C7*(1+Debts!$C$8/12),Debts!$D$8)+MIN(C7+0,D7*(1+Debts!$C$9/12))*0+MIN(D7*(1+Debts!$C$9/12),Debts!$D$9)+MIN(C7+0,E7*(1+Debts!$C$10/12))*0+MIN(E7*(1+Debts!$C$10/12),Debts!$D$10)+MIN(C7+0,F7*(1+Debts!$C$11/12))*0+MIN(F7*(1+Debts!$C$11/12),Debts!$D$11)+MIN(C7+0,G7*(1+Debts!$C$12/12))*0+MIN(G7*(1+Debts!$C$12/12),Debts!$D$12)+MIN(C7+0,H7*(1+Debts!$C$13/12))*0+MIN(H7*(1+Debts!$C$13/12),Debts!$D$13)+MIN(C7+0,I7*(1+Debts!$C$14/12))*0+MIN(I7*(1+Debts!$C$14/12),Debts!$D$14)+MIN(C7+0,J7*(1+Debts!$C$15/12))*0+MIN(J7*(1+Debts!$C$15/12),Debts!$D$15)))),0))) -> 2368.8 | E8: =IF(E7<=0,0,MAX(0,E7*(1+Debts!$C$10/12)-MIN(E7*(1+Debts!$C$10/12),Debts!$D$10)-IF(AND(E7>0,Debts!$E$10=MIN(IF(C7>0,Debts!$E$8,999),IF(D7>0,Debts!$E$9,999),IF(E7>0,Debts!$E$10,999),IF(F7>0,Debts!$E$11,999),IF(G7>0,Debts!$E$12,999),IF(H7>0,Debts!$E$13,999),IF(I7>0,Debts!$E$14,999),IF(J7>0,Debts!$E$15,999))),MAX(0,(B8-(MIN(C7+0,C7*(1+Debts!$C$8/12))*0+MIN(C7*(1+Debts!$C$8/12),Debts!$D$8)+MIN(C7+0,D7*(1+Debts!$C$9/12))*0+MIN(D7*(1+Debts!$C$9/12),Debts!$D$9)+MIN(C7+0,E7*(1+Debts!$C$10/12))*0+MIN(E7*(1+Debts!$C$10/12),Debts!$D$10)+MIN(C7+0,F7*(1+Debts!$C$11/12))*0+MIN(F7*(1+Debts!$C$11/12),Debts!$D$11)+MIN(C7+0,G7*(1+Debts!$C$12/12))*0+MIN(G7*(1+Debts!$C$12/12),Debts!$D$12)+MIN(C7+0,H7*(1+Debts!$C$13/12))*0+MIN(H7*(1+Debts!$C$13/12),Debts!$D$13)+MIN(C7+0,I7*(1+Debts!$C$14/12))*0+MIN(I7*(1+Debts!$C$14/12),Debts!$D$14)+MIN(C7+0,J7*(1+Debts!$C$15/12))*0+MIN(J7*(1+Debts!$C$15/12),Debts!$D$15)))),0))) -> 11557.85 | F8: =IF(F7<=0,0,MAX(0,F7*(1+Debts!$C$11/12)-MIN(F7*(1+Debts!$C$11/12),Debts!$D$11)-IF(AND(F7>0,Debts!$E$11=MIN(IF(C7>0,Debts!$E$8,999),IF(D7>0,Debts!$E$9,999),IF(E7>0,Debts!$E$10,999),IF(F7>0,Debts!$E$11,999),IF(G7>0,Debts!$E$12,999),IF(H7>0,Debts!$E$13,999),IF(I7>0,Debts!$E$14,999),IF(J7>0,Debts!$E$15,999))),MAX(0,(B8-(MIN(C7+0,C7*(1+Debts!$C$8/12))*0+MIN(C7*(1+Debts!$C$8/12),Debts!$D$8)+MIN(C7+0,D7*(1+Debts!$C$9/12))*0+MIN(D7*(1+Debts!$C$9/12),Debts!$D$9)+MIN(C7+0,E7*(1+Debts!$C$10/12))*0+MIN(E7*(1+Debts!$C$10/12),Debts!$D$10)+MIN(C7+0,F7*(1+Debts!$C$11/12))*0+MIN(F7*(1+Debts!$C$11/12),Debts!$D$11)+MIN(C7+0,G7*(1+Debts!$C$12/12))*0+MIN(G7*(1+Debts!$C$12/12),Debts!$D$12)+MIN(C7+0,H7*(1+Debts!$C$13/12))*0+MIN(H7*(1+Debts!$C$13/12),Debts!$D$13)+MIN(C7+0,I7*(1+Debts!$C$14/12))*0+MIN(I7*(1+Debts!$C$14/12),Debts!$D$14)+MIN(C7+0,J7*(1+Debts!$C$15/12))*0+MIN(J7*(1+Debts!$C$15/12),Debts!$D$15)))),0))) -> 18374.792 | G8: =IF(G7<=0,0,MAX(0,G7*(1+Debts!$C$12/12)-MIN(G7*(1+Debts!$C$12/12),Debts!$D$12)-IF(AND(G7>0,Debts!$E$12=MIN(IF(C7>0,Debts!$E$8,999),IF(D7>0,Debts!$E$9,999),IF(E7>0,Debts!$E$10,999),IF(F7>0,Debts!$E$11,999),IF(G7>0,Debts!$E$12,999),IF(H7>0,Debts!$E$13,999),IF(I7>0,Debts!$E$14,999),IF(J7>0,Debts!$E$15,999))),MAX(0,(B8-(MIN(C7+0,C7*(1+Debts!$C$8/12))*0+MIN(C7*(1+Debts!$C$8/12),Debts!$D$8)+MIN(C7+0,D7*(1+Debts!$C$9/12))*0+MIN(D7*(1+Debts!$C$9/12),Debts!$D$9)+MIN(C7+0,E7*(1+Debts!$C$10/12))*0+MIN(E7*(1+Debts!$C$10/12),Debts!$D$10)+MIN(C7+0,F7*(1+Debts!$C$11/12))*0+MIN(F7*(1+Debts!$C$11/12),Debts!$D$11)+MIN(C7+0,G7*(1+Debts!$C$12/12))*0+MIN(G7*(1+Debts!$C$12/12),Debts!$D$12)+MIN(C7+0,H7*(1+Debts!$C$13/12))*0+MIN(H7*(1+Debts!$C$13/12),Debts!$D$13)+MIN(C7+0,I7*(1+Debts!$C$14/12))*0+MIN(I7*(1+Debts!$C$14/12),Debts!$D$14)+MIN(C7+0,J7*(1+Debts!$C$15/12))*0+MIN(J7*(1+Debts!$C$15/12),Debts!$D$15)))),0))) -> 850 | H8: =IF(H7<=0,0,MAX(0,H7*(1+Debts!$C$13/12)-MIN(H7*(1+Debts!$C$13/12),Debts!$D$13)-IF(AND(H7>0,Debts!$E$13=MIN(IF(C7>0,Debts!$E$8,999),IF(D7>0,Debts!$E$9,999),IF(E7>0,Debts!$E$10,999),IF(F7>0,Debts!$E$11,999),IF(G7>0,Debts!$E$12,999),IF(H7>0,Debts!$E$13,999),IF(I7>0,Debts!$E$14,999),IF(J7>0,Debts!$E$15,999))),MAX(0,(B8-(MIN(C7+0,C7*(1+Debts!$C$8/12))*0+MIN(C7*(1+Debts!$C$8/12),Debts!$D$8)+MIN(C7+0,D7*(1+Debts!$C$9/12))*0+MIN(D7*(1+Debts!$C$9/12),Debts!$D$9)+MIN(C7+0,E7*(1+Debts!$C$10/12))*0+MIN(E7*(1+Debts!$C$10/12),Debts!$D$10)+MIN(C7+0,F7*(1+Debts!$C$11/12))*0+MIN(F7*(1+Debts!$C$11/12),Debts!$D$11)+MIN(C7+0,G7*(1+Debts!$C$12/12))*0+MIN(G7*(1+Debts!$C$12/12),Debts!$D$12)+MIN(C7+0,H7*(1+Debts!$C$13/12))*0+MIN(H7*(1+Debts!$C$13/12),Debts!$D$13)+MIN(C7+0,I7*(1+Debts!$C$14/12))*0+MIN(I7*(1+Debts!$C$14/12),Debts!$D$14)+MIN(C7+0,J7*(1+Debts!$C$15/12))*0+MIN(J7*(1+Debts!$C$15/12),Debts!$D$15)))),0))) -> 0 | I8: =IF(I7<=0,0,MAX(0,I7*(1+Debts!$C$14/12)-MIN(I7*(1+Debts!$C$14/12),Debts!$D$14)-IF(AND(I7>0,Debts!$E$14=MIN(IF(C7>0,Debts!$E$8,999),IF(D7>0,Debts!$E$9,999),IF(E7>0,Debts!$E$10,999),IF(F7>0,Debts!$E$11,999),IF(G7>0,Debts!$E$12,999),IF(H7>0,Debts!$E$13,999),IF(I7>0,Debts!$E$14,999),IF(J7>0,Debts!$E$15,999))),MAX(0,(B8-(MIN(C7+0,C7*(1+Debts!$C$8/12))*0+MIN(C7*(1+Debts!$C$8/12),Debts!$D$8)+MIN(C7+0,D7*(1+Debts!$C$9/12))*0+MIN(D7*(1+Debts!$C$9/12),Debts!$D$9)+MIN(C7+0,E7*(1+Debts!$C$10/12))*0+MIN(E7*(1+Debts!$C$10/12),Debts!$D$10)+MIN(C7+0,F7*(1+Debts!$C$11/12))*0+MIN(F7*(1+Debts!$C$11/12),Debts!$D$11)+MIN(C7+0,G7*(1+Debts!$C$12/12))*0+MIN(G7*(1+Debts!$C$12/12),Debts!$D$12)+MIN(C7+0,H7*(1+Debts!$C$13/12))*0+MIN(H7*(1+Debts!$C$13/12),Debts!$D$13)+MIN(C7+0,I7*(1+Debts!$C$14/12))*0+MIN(I7*(1+Debts!$C$14/12),Debts!$D$14)+MIN(C7+0,J7*(1+Debts!$C$15/12))*0+MIN(J7*(1+Debts!$C$15/12),Debts!$D$15)))),0))) -> 0 | J8: =IF(J7<=0,0,MAX(0,J7*(1+Debts!$C$15/12)-MIN(J7*(1+Debts!$C$15/12),Debts!$D$15)-IF(AND(J7>0,Debts!$E$15=MIN(IF(C7>0,Debts!$E$8,999),IF(D7>0,Debts!$E$9,999),IF(E7>0,Debts!$E$10,999),IF(F7>0,Debts!$E$11,999),IF(G7>0,Debts!$E$12,999),IF(H7>0,Debts!$E$13,999),IF(I7>0,Debts!$E$14,999),IF(J7>0,Debts!$E$15,999))),MAX(0,(B8-(MIN(C7+0,C7*(1+Debts!$C$8/12))*0+MIN(C7*(1+Debts!$C$8/12),Debts!$D$8)+MIN(C7+0,D7*(1+Debts!$C$9/12))*0+MIN(D7*(1+Debts!$C$9/12),Debts!$D$9)+MIN(C7+0,E7*(1+Debts!$C$10/12))*0+MIN(E7*(1+Debts!$C$10/12),Debts!$D$10)+MIN(C7+0,F7*(1+Debts!$C$11/12))*0+MIN(F7*(1+Debts!$C$11/12),Debts!$D$11)+MIN(C7+0,G7*(1+Debts!$C$12/12))*0+MIN(G7*(1+Debts!$C$12/12),Debts!$D$12)+MIN(C7+0,H7*(1+Debts!$C$13/12))*0+MIN(H7*(1+Debts!$C$13/12),Debts!$D$13)+MIN(C7+0,I7*(1+Debts!$C$14/12))*0+MIN(I7*(1+Debts!$C$14/12),Debts!$D$14)+MIN(C7+0,J7*(1+Debts!$C$15/12))*0+MIN(J7*(1+Debts!$C$15/12),Debts!$D$15)))),0))) -> 0 | K8: =IF(C7>0,C7*Debts!$C$8/12,0)+IF(D7>0,D7*Debts!$C$9/12,0)+IF(E7>0,E7*Debts!$C$10/12,0)+IF(F7>0,F7*Debts!$C$11/12,0)+IF(G7>0,G7*Debts!$C$12/12,0)+IF(H7>0,H7*Debts!$C$13/12,0)+IF(I7>0,I7*Debts!$C$14/12,0)+IF(J7>0,J7*Debts!$C$15/12,0) -> 325.09167 | L8: =SUM(C8:J8) -> 38925.092
A9: =2 -> 2 | B9: =IF(L8<=0,0,Debts!$D$16+Debts!$B$4) -> 1200 | C9: =IF(C8<=0,0,MAX(0,C8*(1+Debts!$C$8/12)-MIN(C8*(1+Debts!$C$8/12),Debts!$D$8)-IF(AND(C8>0,Debts!$E$8=MIN(IF(C8>0,Debts!$E$8,999),IF(D8>0,Debts!$E$9,999),IF(E8>0,Debts!$E$10,999),IF(F8>0,Debts!$E$11,999),IF(G8>0,Debts!$E$12,999),IF(H8>0,Debts!$E$13,999),IF(I8>0,Debts!$E$14,999),IF(J8>0,Debts!$E$15,999))),MAX(0,(B9-(MIN(C8+0,C8*(1+Debts!$C$8/12))*0+MIN(C8*(1+Debts!$C$8/12),Debts!$D$8)+MIN(C8+0,D8*(1+Debts!$C$9/12))*0+MIN(D8*(1+Debts!$C$9/12),Debts!$D$9)+MIN(C8+0,E8*(1+Debts!$C$10/12))*0+MIN(E8*(1+Debts!$C$10/12),Debts!$D$10)+MIN(C8+0,F8*(1+Debts!$C$11/12))*0+MIN(F8*(1+Debts!$C$11/12),Debts!$D$11)+MIN(C8+0,G8*(1+Debts!$C$12/12))*0+MIN(G8*(1+Debts!$C$12/12),Debts!$D$12)+MIN(C8+0,H8*(1+Debts!$C$13/12))*0+MIN(H8*(1+Debts!$C$13/12),Debts!$D$13)+MIN(C8+0,I8*(1+Debts!$C$14/12))*0+MIN(I8*(1+Debts!$C$14/12),Debts!$D$14)+MIN(C8+0,J8*(1+Debts!$C$15/12))*0+MIN(J8*(1+Debts!$C$15/12),Debts!$D$15)))),0))) -> 5338.4532 | D9: =IF(D8<=0,0,MAX(0,D8*(1+Debts!$C$9/12)-MIN(D8*(1+Debts!$C$9/12),Debts!$D$9)-IF(AND(D8>0,Debts!$E$9=MIN(IF(C8>0,Debts!$E$8,999),IF(D8>0,Debts!$E$9,999),IF(E8>0,Debts!$E$10,999),IF(F8>0,Debts!$E$11,999),IF(G8>0,Debts!$E$12,999),IF(H8>0,Debts!$E$13,999),IF(I8>0,Debts!$E$14,999),IF(J8>0,Debts!$E$15,999))),MAX(0,(B9-(MIN(C8+0,C8*(1+Debts!$C$8/12))*0+MIN(C8*(1+Debts!$C$8/12),Debts!$D$8)+MIN(C8+0,D8*(1+Debts!$C$9/12))*0+MIN(D8*(1+Debts!$C$9/12),Debts!$D$9)+MIN(C8+0,E8*(1+Debts!$C$10/12))*0+MIN(E8*(1+Debts!$C$10/12),Debts!$D$10)+MIN(C8+0,F8*(1+Debts!$C$11/12))*0+MIN(F8*(1+Debts!$C$11/12),Debts!$D$11)+MIN(C8+0,G8*(1+Debts!$C$12/12))*0+MIN(G8*(1+Debts!$C$12/12),Debts!$D$12)+MIN(C8+0,H8*(1+Debts!$C$13/12))*0+MIN(H8*(1+Debts!$C$13/12),Debts!$D$13)+MIN(C8+0,I8*(1+Debts!$C$14/12))*0+MIN(I8*(1+Debts!$C$14/12),Debts!$D$14)+MIN(C8+0,J8*(1+Debts!$C$15/12))*0+MIN(J8*(1+Debts!$C$15/12),Debts!$D$15)))),0))) -> 2337.0306 | E9: =IF(E8<=0,0,MAX(0,E8*(1+Debts!$C$10/12)-MIN(E8*(1+Debts!$C$10/12),Debts!$D$10)-IF(AND(E8>0,Debts!$E$10=MIN(IF(C8>0,Debts!$E$8,999),IF(D8>0,Debts!$E$9,999),IF(E8>0,Debts!$E$10,999),IF(F8>0,Debts!$E$11,999),IF(G8>0,Debts!$E$12,999),IF(H8>0,Debts!$E$13,999),IF(I8>0,Debts!$E$14,999),IF(J8>0,Debts!$E$15,999))),MAX(0,(B9-(MIN(C8+0,C8*(1+Debts!$C$8/12))*0+MIN(C8*(1+Debts!$C$8/12),Debts!$D$8)+MIN(C8+0,D8*(1+Debts!$C$9/12))*0+MIN(D8*(1+Debts!$C$9/12),Debts!$D$9)+MIN(C8+0,E8*(1+Debts!$C$10/12))*0+MIN(E8*(1+Debts!$C$10/12),Debts!$D$10)+MIN(C8+0,F8*(1+Debts!$C$11/12))*0+MIN(F8*(1+Debts!$C$11/12),Debts!$D$11)+MIN(C8+0,G8*(1+Debts!$C$12/12))*0+MIN(G8*(1+Debts!$C$12/12),Debts!$D$12)+MIN(C8+0,H8*(1+Debts!$C$13/12))*0+MIN(H8*(1+Debts!$C$13/12),Debts!$D$13)+MIN(C8+0,I8*(1+Debts!$C$14/12))*0+MIN(I8*(1+Debts!$C$14/12),Debts!$D$14)+MIN(C8+0,J8*(1+Debts!$C$15/12))*0+MIN(J8*(1+Debts!$C$15/12),Debts!$D$15)))),0))) -> 11314.308 | F9: =IF(F8<=0,0,MAX(0,F8*(1+Debts!$C$11/12)-MIN(F8*(1+Debts!$C$11/12),Debts!$D$11)-IF(AND(F8>0,Debts!$E$11=MIN(IF(C8>0,Debts!$E$8,999),IF(D8>0,Debts!$E$9,999),IF(E8>0,Debts!$E$10,999),IF(F8>0,Debts!$E$11,999),IF(G8>0,Debts!$E$12,999),IF(H8>0,Debts!$E$13,999),IF(I8>0,Debts!$E$14,999),IF(J8>0,Debts!$E$15,999))),MAX(0,(B9-(MIN(C8+0,C8*(1+Debts!$C$8/12))*0+MIN(C8*(1+Debts!$C$8/12),Debts!$D$8)+MIN(C8+0,D8*(1+Debts!$C$9/12))*0+MIN(D8*(1+Debts!$C$9/12),Debts!$D$9)+MIN(C8+0,E8*(1+Debts!$C$10/12))*0+MIN(E8*(1+Debts!$C$10/12),Debts!$D$10)+MIN(C8+0,F8*(1+Debts!$C$11/12))*0+MIN(F8*(1+Debts!$C$11/12),Debts!$D$11)+MIN(C8+0,G8*(1+Debts!$C$12/12))*0+MIN(G8*(1+Debts!$C$12/12),Debts!$D$12)+MIN(C8+0,H8*(1+Debts!$C$13/12))*0+MIN(H8*(1+Debts!$C$13/12),Debts!$D$13)+MIN(C8+0,I8*(1+Debts!$C$14/12))*0+MIN(I8*(1+Debts!$C$14/12),Debts!$D$14)+MIN(C8+0,J8*(1+Debts!$C$15/12))*0+MIN(J8*(1+Debts!$C$15/12),Debts!$D$15)))),0))) -> 18249.009 | G9: =IF(G8<=0,0,MAX(0,G8*(1+Debts!$C$12/12)-MIN(G8*(1+Debts!$C$12/12),Debts!$D$12)-IF(AND(G8>0,Debts!$E$12=MIN(IF(C8>0,Debts!$E$8,999),IF(D8>0,Debts!$E$9,999),IF(E8>0,Debts!$E$10,999),IF(F8>0,Debts!$E$11,999),IF(G8>0,Debts!$E$12,999),IF(H8>0,Debts!$E$13,999),IF(I8>0,Debts!$E$14,999),IF(J8>0,Debts!$E$15,999))),MAX(0,(B9-(MIN(C8+0,C8*(1+Debts!$C$8/12))*0+MIN(C8*(1+Debts!$C$8/12),Debts!$D$8)+MIN(C8+0,D8*(1+Debts!$C$9/12))*0+MIN(D8*(1+Debts!$C$9/12),Debts!$D$9)+MIN(C8+0,E8*(1+Debts!$C$10/12))*0+MIN(E8*(1+Debts!$C$10/12),Debts!$D$10)+MIN(C8+0,F8*(1+Debts!$C$11/12))*0+MIN(F8*(1+Debts!$C$11/12),Debts!$D$11)+MIN(C8+0,G8*(1+Debts!$C$12/12))*0+MIN(G8*(1+Debts!$C$12/12),Debts!$D$12)+MIN(C8+0,H8*(1+Debts!$C$13/12))*0+MIN(H8*(1+Debts!$C$13/12),Debts!$D$13)+MIN(C8+0,I8*(1+Debts!$C$14/12))*0+MIN(I8*(1+Debts!$C$14/12),Debts!$D$14)+MIN(C8+0,J8*(1+Debts!$C$15/12))*0+MIN(J8*(1+Debts!$C$15/12),Debts!$D$15)))),0))) -> 800 | H9: =IF(H8<=0,0,MAX(0,H8*(1+Debts!$C$13/12)-MIN(H8*(1+Debts!$C$13/12),Debts!$D$13)-IF(AND(H8>0,Debts!$E$13=MIN(IF(C8>0,Debts!$E$8,999),IF(D8>0,Debts!$E$9,999),IF(E8>0,Debts!$E$10,999),IF(F8>0,Debts!$E$11,999),IF(G8>0,Debts!$E$12,999),IF(H8>0,Debts!$E$13,999),IF(I8>0,Debts!$E$14,999),IF(J8>0,Debts!$E$15,999))),MAX(0,(B9-(MIN(C8+0,C8*(1+Debts!$C$8/12))*0+MIN(C8*(1+Debts!$C$8/12),Debts!$D$8)+MIN(C8+0,D8*(1+Debts!$C$9/12))*0+MIN(D8*(1+Debts!$C$9/12),Debts!$D$9)+MIN(C8+0,E8*(1+Debts!$C$10/12))*0+MIN(E8*(1+Debts!$C$10/12),Debts!$D$10)+MIN(C8+0,F8*(1+Debts!$C$11/12))*0+MIN(F8*(1+Debts!$C$11/12),Debts!$D$11)+MIN(C8+0,G8*(1+Debts!$C$12/12))*0+MIN(G8*(1+Debts!$C$12/12),Debts!$D$12)+MIN(C8+0,H8*(1+Debts!$C$13/12))*0+MIN(H8*(1+Debts!$C$13/12),Debts!$D$13)+MIN(C8+0,I8*(1+Debts!$C$14/12))*0+MIN(I8*(1+Debts!$C$14/12),Debts!$D$14)+MIN(C8+0,J8*(1+Debts!$C$15/12))*0+MIN(J8*(1+Debts!$C$15/12),Debts!$D$15)))),0))) -> 0 | I9: =IF(I8<=0,0,MAX(0,I8*(1+Debts!$C$14/12)-MIN(I8*(1+Debts!$C$14/12),Debts!$D$14)-IF(AND(I8>0,Debts!$E$14=MIN(IF(C8>0,Debts!$E$8,999),IF(D8>0,Debts!$E$9,999),IF(E8>0,Debts!$E$10,999),IF(F8>0,Debts!$E$11,999),IF(G8>0,Debts!$E$12,999),IF(H8>0,Debts!$E$13,999),IF(I8>0,Debts!$E$14,999),IF(J8>0,Debts!$E$15,999))),MAX(0,(B9-(MIN(C8+0,C8*(1+Debts!$C$8/12))*0+MIN(C8*(1+Debts!$C$8/12),Debts!$D$8)+MIN(C8+0,D8*(1+Debts!$C$9/12))*0+MIN(D8*(1+Debts!$C$9/12),Debts!$D$9)+MIN(C8+0,E8*(1+Debts!$C$10/12))*0+MIN(E8*(1+Debts!$C$10/12),Debts!$D$10)+MIN(C8+0,F8*(1+Debts!$C$11/12))*0+MIN(F8*(1+Debts!$C$11/12),Debts!$D$11)+MIN(C8+0,G8*(1+Debts!$C$12/12))*0+MIN(G8*(1+Debts!$C$12/12),Debts!$D$12)+MIN(C8+0,H8*(1+Debts!$C$13/12))*0+MIN(H8*(1+Debts!$C$13/12),Debts!$D$13)+MIN(C8+0,I8*(1+Debts!$C$14/12))*0+MIN(I8*(1+Debts!$C$14/12),Debts!$D$14)+MIN(C8+0,J8*(1+Debts!$C$15/12))*0+MIN(J8*(1+Debts!$C$15/12),Debts!$D$15)))),0))) -> 0 | J9: =IF(J8<=0,0,MAX(0,J8*(1+Debts!$C$15/12)-MIN(J8*(1+Debts!$C$15/12),Debts!$D$15)-IF(AND(J8>0,Debts!$E$15=MIN(IF(C8>0,Debts!$E$8,999),IF(D8>0,Debts!$E$9,999),IF(E8>0,Debts!$E$10,999),IF(F8>0,Debts!$E$11,999),IF(G8>0,Debts!$E$12,999),IF(H8>0,Debts!$E$13,999),IF(I8>0,Debts!$E$14,999),IF(J8>0,Debts!$E$15,999))),MAX(0,(B9-(MIN(C8+0,C8*(1+Debts!$C$8/12))*0+MIN(C8*(1+Debts!$C$8/12),Debts!$D$8)+MIN(C8+0,D8*(1+Debts!$C$9/12))*0+MIN(D8*(1+Debts!$C$9/12),Debts!$D$9)+MIN(C8+0,E8*(1+Debts!$C$10/12))*0+MIN(E8*(1+Debts!$C$10/12),Debts!$D$10)+MIN(C8+0,F8*(1+Debts!$C$11/12))*0+MIN(F8*(1+Debts!$C$11/12),Debts!$D$11)+MIN(C8+0,G8*(1+Debts!$C$12/12))*0+MIN(G8*(1+Debts!$C$12/12),Debts!$D$12)+MIN(C8+0,H8*(1+Debts!$C$13/12))*0+MIN(H8*(1+Debts!$C$13/12),Debts!$D$13)+MIN(C8+0,I8*(1+Debts!$C$14/12))*0+MIN(I8*(1+Debts!$C$14/12),Debts!$D$14)+MIN(C8+0,J8*(1+Debts!$C$15/12))*0+MIN(J8*(1+Debts!$C$15/12),Debts!$D$15)))),0))) -> 0 | K9: =IF(C8>0,C8*Debts!$C$8/12,0)+IF(D8>0,D8*Debts!$C$9/12,0)+IF(E8>0,E8*Debts!$C$10/12,0)+IF(F8>0,F8*Debts!$C$11/12,0)+IF(G8>0,G8*Debts!$C$12/12,0)+IF(H8>0,H8*Debts!$C$13/12,0)+IF(I8>0,I8*Debts!$C$14/12,0)+IF(J8>0,J8*Debts!$C$15/12,0) -> 313.70927 | L9: =SUM(C9:J9) -> 38038.801
A10: =3 -> 3 | B10: =IF(L9<=0,0,Debts!$D$16+Debts!$B$4) -> 1200 | C10: =IF(C9<=0,0,MAX(0,C9*(1+Debts!$C$8/12)-MIN(C9*(1+Debts!$C$8/12),Debts!$D$8)-IF(AND(C9>0,Debts!$E$8=MIN(IF(C9>0,Debts!$E$8,999),IF(D9>0,Debts!$E$9,999),IF(E9>0,Debts!$E$10,999),IF(F9>0,Debts!$E$11,999),IF(G9>0,Debts!$E$12,999),IF(H9>0,Debts!$E$13,999),IF(I9>0,Debts!$E$14,999),IF(J9>0,Debts!$E$15,999))),MAX(0,(B10-(MIN(C9+0,C9*(1+Debts!$C$8/12))*0+MIN(C9*(1+Debts!$C$8/12),Debts!$D$8)+MIN(C9+0,D9*(1+Debts!$C$9/12))*0+MIN(D9*(1+Debts!$C$9/12),Debts!$D$9)+MIN(C9+0,E9*(1+Debts!$C$10/12))*0+MIN(E9*(1+Debts!$C$10/12),Debts!$D$10)+MIN(C9+0,F9*(1+Debts!$C$11/12))*0+MIN(F9*(1+Debts!$C$11/12),Debts!$D$11)+MIN(C9+0,G9*(1+Debts!$C$12/12))*0+MIN(G9*(1+Debts!$C$12/12),Debts!$D$12)+MIN(C9+0,H9*(1+Debts!$C$13/12))*0+MIN(H9*(1+Debts!$C$13/12),Debts!$D$13)+MIN(C9+0,I9*(1+Debts!$C$14/12))*0+MIN(I9*(1+Debts!$C$14/12),Debts!$D$14)+MIN(C9+0,J9*(1+Debts!$C$15/12))*0+MIN(J9*(1+Debts!$C$15/12),Debts!$D$15)))),0))) -> 4894.2261 | D10: =IF(D9<=0,0,MAX(0,D9*(1+Debts!$C$9/12)-MIN(D9*(1+Debts!$C$9/12),Debts!$D$9)-IF(AND(D9>0,Debts!$E$9=MIN(IF(C9>0,Debts!$E$8,999),IF(D9>0,Debts!$E$9,999),IF(E9>0,Debts!$E$10,999),IF(F9>0,Debts!$E$11,999),IF(G9>0,Debts!$E$12,999),IF(H9>0,Debts!$E$13,999),IF(I9>0,Debts!$E$14,999),IF(J9>0,Debts!$E$15,999))),MAX(0,(B10-(MIN(C9+0,C9*(1+Debts!$C$8/12))*0+MIN(C9*(1+Debts!$C$8/12),Debts!$D$8)+MIN(C9+0,D9*(1+Debts!$C$9/12))*0+MIN(D9*(1+Debts!$C$9/12),Debts!$D$9)+MIN(C9+0,E9*(1+Debts!$C$10/12))*0+MIN(E9*(1+Debts!$C$10/12),Debts!$D$10)+MIN(C9+0,F9*(1+Debts!$C$11/12))*0+MIN(F9*(1+Debts!$C$11/12),Debts!$D$11)+MIN(C9+0,G9*(1+Debts!$C$12/12))*0+MIN(G9*(1+Debts!$C$12/12),Debts!$D$12)+MIN(C9+0,H9*(1+Debts!$C$13/12))*0+MIN(H9*(1+Debts!$C$13/12),Debts!$D$13)+MIN(C9+0,I9*(1+Debts!$C$14/12))*0+MIN(I9*(1+Debts!$C$14/12),Debts!$D$14)+MIN(C9+0,J9*(1+Debts!$C$15/12))*0+MIN(J9*(1+Debts!$C$15/12),Debts!$D$15)))),0))) -> 2304.6814 | E10: =IF(E9<=0,0,MAX(0,E9*(1+Debts!$C$10/12)-MIN(E9*(1+Debts!$C$10/12),Debts!$D$10)-IF(AND(E9>0,Debts!$E$10=MIN(IF(C9>0,Debts!$E$8,999),IF(D9>0,Debts!$E$9,999),IF(E9>0,Debts!$E$10,999),IF(F9>0,Debts!$E$11,999),IF(G9>0,Debts!$E$12,999),IF(H9>0,Debts!$E$13,999),IF(I9>0,Debts!$E$14,999),IF(J9>0,Debts!$E$15,999))),MAX(0,(B10-(MIN(C9+0,C9*(1+Debts!$C$8/12))*0+MIN(C9*(1+Debts!$C$8/12),Debts!$D$8)+MIN(C9+0,D9*(1+Debts!$C$9/12))*0+MIN(D9*(1+Debts!$C$9/12),Debts!$D$9)+MIN(C9+0,E9*(1+Debts!$C$10/12))*0+MIN(E9*(1+Debts!$C$10/12),Debts!$D$10)+MIN(C9+0,F9*(1+Debts!$C$11/12))*0+MIN(F9*(1+Debts!$C$11/12),Debts!$D$11)+MIN(C9+0,G9*(1+Debts!$C$12/12))*0+MIN(G9*(1+Debts!$C$12/12),Debts!$D$12)+MIN(C9+0,H9*(1+Debts!$C$13/12))*0+MIN(H9*(1+Debts!$C$13/12),Debts!$D$13)+MIN(C9+0,I9*(1+Debts!$C$14/12))*0+MIN(I9*(1+Debts!$C$14/12),Debts!$D$14)+MIN(C9+0,J9*(1+Debts!$C$15/12))*0+MIN(J9*(1+Debts!$C$15/12),Debts!$D$15)))),0))) -> 11069.365 | F10: =IF(F9<=0,0,MAX(0,F9*(1+Debts!$C$11/12)-MIN(F9*(1+Debts!$C$11/12),Debts!$D$11)-IF(AND(F9>0,Debts!$E$11=MIN(IF(C9>0,Debts!$E$8,999),IF(D9>0,Debts!$E$9,999),IF(E9>0,Debts!$E$10,999),IF(F9>0,Debts!$E$11,999),IF(G9>0,Debts!$E$12,999),IF(H9>0,Debts!$E$13,999),IF(I9>0,Debts!$E$14,999),IF(J9>0,Debts!$E$15,999))),MAX(0,(B10-(MIN(C9+0,C9*(1+Debts!$C$8/12))*0+MIN(C9*(1+Debts!$C$8/12),Debts!$D$8)+MIN(C9+0,D9*(1+Debts!$C$9/12))*0+MIN(D9*(1+Debts!$C$9/12),Debts!$D$9)+MIN(C9+0,E9*(1+Debts!$C$10/12))*0+MIN(E9*(1+Debts!$C$10/12),Debts!$D$10)+MIN(C9+0,F9*(1+Debts!$C$11/12))*0+MIN(F9*(1+Debts!$C$11/12),Debts!$D$11)+MIN(C9+0,G9*(1+Debts!$C$12/12))*0+MIN(G9*(1+Debts!$C$12/12),Debts!$D$12)+MIN(C9+0,H9*(1+Debts!$C$13/12))*0+MIN(H9*(1+Debts!$C$13/12),Debts!$D$13)+MIN(C9+0,I9*(1+Debts!$C$14/12))*0+MIN(I9*(1+Debts!$C$14/12),Debts!$D$14)+MIN(C9+0,J9*(1+Debts!$C$15/12))*0+MIN(J9*(1+Debts!$C$15/12),Debts!$D$15)))),0))) -> 18122.651 | G10: =IF(G9<=0,0,MAX(0,G9*(1+Debts!$C$12/12)-MIN(G9*(1+Debts!$C$12/12),Debts!$D$12)-IF(AND(G9>0,Debts!$E$12=MIN(IF(C9>0,Debts!$E$8,999),IF(D9>0,Debts!$E$9,999),IF(E9>0,Debts!$E$10,999),IF(F9>0,Debts!$E$11,999),IF(G9>0,Debts!$E$12,999),IF(H9>0,Debts!$E$13,999),IF(I9>0,Debts!$E$14,999),IF(J9>0,Debts!$E$15,999))),MAX(0,(B10-(MIN(C9+0,C9*(1+Debts!$C$8/12))*0+MIN(C9*(1+Debts!$C$8/12),Debts!$D$8)+MIN(C9+0,D9*(1+Debts!$C$9/12))*0+MIN(D9*(1+Debts!$C$9/12),Debts!$D$9)+MIN(C9+0,E9*(1+Debts!$C$10/12))*0+MIN(E9*(1+Debts!$C$10/12),Debts!$D$10)+MIN(C9+0,F9*(1+Debts!$C$11/12))*0+MIN(F9*(1+Debts!$C$11/12),Debts!$D$11)+MIN(C9+0,G9*(1+Debts!$C$12/12))*0+MIN(G9*(1+Debts!$C$12/12),Debts!$D$12)+MIN(C9+0,H9*(1+Debts!$C$13/12))*0+MIN(H9*(1+Debts!$C$13/12),Debts!$D$13)+MIN(C9+0,I9*(1+Debts!$C$14/12))*0+MIN(I9*(1+Debts!$C$14/12),Debts!$D$14)+MIN(C9+0,J9*(1+Debts!$C$15/12))*0+MIN(J9*(1+Debts!$C$15/12),Debts!$D$15)))),0))) -> 750 | H10: =IF(H9<=0,0,MAX(0,H9*(1+Debts!$C$13/12)-MIN(H9*(1+Debts!$C$13/12),Debts!$D$13)-IF(AND(H9>0,Debts!$E$13=MIN(IF(C9>0,Debts!$E$8,999),IF(D9>0,Debts!$E$9,999),IF(E9>0,Debts!$E$10,999),IF(F9>0,Debts!$E$11,999),IF(G9>0,Debts!$E$12,999),IF(H9>0,Debts!$E$13,999),IF(I9>0,Debts!$E$14,999),IF(J9>0,Debts!$E$15,999))),MAX(0,(B10-(MIN(C9+0,C9*(1+Debts!$C$8/12))*0+MIN(C9*(1+Debts!$C$8/12),Debts!$D$8)+MIN(C9+0,D9*(1+Debts!$C$9/12))*0+MIN(D9*(1+Debts!$C$9/12),Debts!$D$9)+MIN(C9+0,E9*(1+Debts!$C$10/12))*0+MIN(E9*(1+Debts!$C$10/12),Debts!$D$10)+MIN(C9+0,F9*(1+Debts!$C$11/12))*0+MIN(F9*(1+Debts!$C$11/12),Debts!$D$11)+MIN(C9+0,G9*(1+Debts!$C$12/12))*0+MIN(G9*(1+Debts!$C$12/12),Debts!$D$12)+MIN(C9+0,H9*(1+Debts!$C$13/12))*0+MIN(H9*(1+Debts!$C$13/12),Debts!$D$13)+MIN(C9+0,I9*(1+Debts!$C$14/12))*0+MIN(I9*(1+Debts!$C$14/12),Debts!$D$14)+MIN(C9+0,J9*(1+Debts!$C$15/12))*0+MIN(J9*(1+Debts!$C$15/12),Debts!$D$15)))),0))) -> 0 | I10: =IF(I9<=0,0,MAX(0,I9*(1+Debts!$C$14/12)-MIN(I9*(1+Debts!$C$14/12),Debts!$D$14)-IF(AND(I9>0,Debts!$E$14=MIN(IF(C9>0,Debts!$E$8,999),IF(D9>0,Debts!$E$9,999),IF(E9>0,Debts!$E$10,999),IF(F9>0,Debts!$E$11,999),IF(G9>0,Debts!$E$12,999),IF(H9>0,Debts!$E$13,999),IF(I9>0,Debts!$E$14,999),IF(J9>0,Debts!$E$15,999))),MAX(0,(B10-(MIN(C9+0,C9*(1+Debts!$C$8/12))*0+MIN(C9*(1+Debts!$C$8/12),Debts!$D$8)+MIN(C9+0,D9*(1+Debts!$C$9/12))*0+MIN(D9*(1+Debts!$C$9/12),Debts!$D$9)+MIN(C9+0,E9*(1+Debts!$C$10/12))*0+MIN(E9*(1+Debts!$C$10/12),Debts!$D$10)+MIN(C9+0,F9*(1+Debts!$C$11/12))*0+MIN(F9*(1+Debts!$C$11/12),Debts!$D$11)+MIN(C9+0,G9*(1+Debts!$C$12/12))*0+MIN(G9*(1+Debts!$C$12/12),Debts!$D$12)+MIN(C9+0,H9*(1+Debts!$C$13/12))*0+MIN(H9*(1+Debts!$C$13/12),Debts!$D$13)+MIN(C9+0,I9*(1+Debts!$C$14/12))*0+MIN(I9*(1+Debts!$C$14/12),Debts!$D$14)+MIN(C9+0,J9*(1+Debts!$C$15/12))*0+MIN(J9*(1+Debts!$C$15/12),Debts!$D$15)))),0))) -> 0 | J10: =IF(J9<=0,0,MAX(0,J9*(1+Debts!$C$15/12)-MIN(J9*(1+Debts!$C$15/12),Debts!$D$15)-IF(AND(J9>0,Debts!$E$15=MIN(IF(C9>0,Debts!$E$8,999),IF(D9>0,Debts!$E$9,999),IF(E9>0,Debts!$E$10,999),IF(F9>0,Debts!$E$11,999),IF(G9>0,Debts!$E$12,999),IF(H9>0,Debts!$E$13,999),IF(I9>0,Debts!$E$14,999),IF(J9>0,Debts!$E$15,999))),MAX(0,(B10-(MIN(C9+0,C9*(1+Debts!$C$8/12))*0+MIN(C9*(1+Debts!$C$8/12),Debts!$D$8)+MIN(C9+0,D9*(1+Debts!$C$9/12))*0+MIN(D9*(1+Debts!$C$9/12),Debts!$D$9)+MIN(C9+0,E9*(1+Debts!$C$10/12))*0+MIN(E9*(1+Debts!$C$10/12),Debts!$D$10)+MIN(C9+0,F9*(1+Debts!$C$11/12))*0+MIN(F9*(1+Debts!$C$11/12),Debts!$D$11)+MIN(C9+0,G9*(1+Debts!$C$12/12))*0+MIN(G9*(1+Debts!$C$12/12),Debts!$D$12)+MIN(C9+0,H9*(1+Debts!$C$13/12))*0+MIN(H9*(1+Debts!$C$13/12),Debts!$D$13)+MIN(C9+0,I9*(1+Debts!$C$14/12))*0+MIN(I9*(1+Debts!$C$14/12),Debts!$D$14)+MIN(C9+0,J9*(1+Debts!$C$15/12))*0+MIN(J9*(1+Debts!$C$15/12),Debts!$D$15)))),0))) -> 0 | K10: =IF(C9>0,C9*Debts!$C$8/12,0)+IF(D9>0,D9*Debts!$C$9/12,0)+IF(E9>0,E9*Debts!$C$10/12,0)+IF(F9>0,F9*Debts!$C$11/12,0)+IF(G9>0,G9*Debts!$C$12/12,0)+IF(H9>0,H9*Debts!$C$13/12,0)+IF(I9>0,I9*Debts!$C$14/12,0)+IF(J9>0,J9*Debts!$C$15/12,0) -> 302.12228 | L10: =SUM(C10:J10) -> 37140.923
A11: =4 -> 4 | B11: =IF(L10<=0,0,Debts!$D$16+Debts!$B$4) -> 1200 | C11: =IF(C10<=0,0,MAX(0,C10*(1+Debts!$C$8/12)-MIN(C10*(1+Debts!$C$8/12),Debts!$D$8)-IF(AND(C10>0,Debts!$E$8=MIN(IF(C10>0,Debts!$E$8,999),IF(D10>0,Debts!$E$9,999),IF(E10>0,Debts!$E$10,999),IF(F10>0,Debts!$E$11,999),IF(G10>0,Debts!$E$12,999),IF(H10>0,Debts!$E$13,999),IF(I10>0,Debts!$E$14,999),IF(J10>0,Debts!$E$15,999))),MAX(0,(B11-(MIN(C10+0,C10*(1+Debts!$C$8/12))*0+MIN(C10*(1+Debts!$C$8/12),Debts!$D$8)+MIN(C10+0,D10*(1+Debts!$C$9/12))*0+MIN(D10*(1+Debts!$C$9/12),Debts!$D$9)+MIN(C10+0,E10*(1+Debts!$C$10/12))*0+MIN(E10*(1+Debts!$C$10/12),Debts!$D$10)+MIN(C10+0,F10*(1+Debts!$C$11/12))*0+MIN(F10*(1+Debts!$C$11/12),Debts!$D$11)+MIN(C10+0,G10*(1+Debts!$C$12/12))*0+MIN(G10*(1+Debts!$C$12/12),Debts!$D$12)+MIN(C10+0,H10*(1+Debts!$C$13/12))*0+MIN(H10*(1+Debts!$C$13/12),Debts!$D$13)+MIN(C10+0,I10*(1+Debts!$C$14/12))*0+MIN(I10*(1+Debts!$C$14/12),Debts!$D$14)+MIN(C10+0,J10*(1+Debts!$C$15/12))*0+MIN(J10*(1+Debts!$C$15/12),Debts!$D$15)))),0))) -> 4440.7813 | D11: =IF(D10<=0,0,MAX(0,D10*(1+Debts!$C$9/12)-MIN(D10*(1+Debts!$C$9/12),Debts!$D$9)-IF(AND(D10>0,Debts!$E$9=MIN(IF(C10>0,Debts!$E$8,999),IF(D10>0,Debts!$E$9,999),IF(E10>0,Debts!$E$10,999),IF(F10>0,Debts!$E$11,999),IF(G10>0,Debts!$E$12,999),IF(H10>0,Debts!$E$13,999),IF(I10>0,Debts!$E$14,999),IF(J10>0,Debts!$E$15,999))),MAX(0,(B11-(MIN(C10+0,C10*(1+Debts!$C$8/12))*0+MIN(C10*(1+Debts!$C$8/12),Debts!$D$8)+MIN(C10+0,D10*(1+Debts!$C$9/12))*0+MIN(D10*(1+Debts!$C$9/12),Debts!$D$9)+MIN(C10+0,E10*(1+Debts!$C$10/12))*0+MIN(E10*(1+Debts!$C$10/12),Debts!$D$10)+MIN(C10+0,F10*(1+Debts!$C$11/12))*0+MIN(F10*(1+Debts!$C$11/12),Debts!$D$11)+MIN(C10+0,G10*(1+Debts!$C$12/12))*0+MIN(G10*(1+Debts!$C$12/12),Debts!$D$12)+MIN(C10+0,H10*(1+Debts!$C$13/12))*0+MIN(H10*(1+Debts!$C$13/12),Debts!$D$13)+MIN(C10+0,I10*(1+Debts!$C$14/12))*0+MIN(I10*(1+Debts!$C$14/12),Debts!$D$14)+MIN(C10+0,J10*(1+Debts!$C$15/12))*0+MIN(J10*(1+Debts!$C$15/12),Debts!$D$15)))),0))) -> 2271.7418 | E11: =IF(E10<=0,0,MAX(0,E10*(1+Debts!$C$10/12)-MIN(E10*(1+Debts!$C$10/12),Debts!$D$10)-IF(AND(E10>0,Debts!$E$10=MIN(IF(C10>0,Debts!$E$8,999),IF(D10>0,Debts!$E$9,999),IF(E10>0,Debts!$E$10,999),IF(F10>0,Debts!$E$11,999),IF(G10>0,Debts!$E$12,999),IF(H10>0,Debts!$E$13,999),IF(I10>0,Debts!$E$14,999),IF(J10>0,Debts!$E$15,999))),MAX(0,(B11-(MIN(C10+0,C10*(1+Debts!$C$8/12))*0+MIN(C10*(1+Debts!$C$8/12),Debts!$D$8)+MIN(C10+0,D10*(1+Debts!$C$9/12))*0+MIN(D10*(1+Debts!$C$9/12),Debts!$D$9)+MIN(C10+0,E10*(1+Debts!$C$10/12))*0+MIN(E10*(1+Debts!$C$10/12),Debts!$D$10)+MIN(C10+0,F10*(1+Debts!$C$11/12))*0+MIN(F10*(1+Debts!$C$11/12),Debts!$D$11)+MIN(C10+0,G10*(1+Debts!$C$12/12))*0+MIN(G10*(1+Debts!$C$12/12),Debts!$D$12)+MIN(C10+0,H10*(1+Debts!$C$13/12))*0+MIN(H10*(1+Debts!$C$13/12),Debts!$D$13)+MIN(C10+0,I10*(1+Debts!$C$14/12))*0+MIN(I10*(1+Debts!$C$14/12),Debts!$D$14)+MIN(C10+0,J10*(1+Debts!$C$15/12))*0+MIN(J10*(1+Debts!$C$15/12),Debts!$D$15)))),0))) -> 10823.014 | F11: =IF(F10<=0,0,MAX(0,F10*(1+Debts!$C$11/12)-MIN(F10*(1+Debts!$C$11/12),Debts!$D$11)-IF(AND(F10>0,Debts!$E$11=MIN(IF(C10>0,Debts!$E$8,999),IF(D10>0,Debts!$E$9,999),IF(E10>0,Debts!$E$10,999),IF(F10>0,Debts!$E$11,999),IF(G10>0,Debts!$E$12,999),IF(H10>0,Debts!$E$13,999),IF(I10>0,Debts!$E$14,999),IF(J10>0,Debts!$E$15,999))),MAX(0,(B11-(MIN(C10+0,C10*(1+Debts!$C$8/12))*0+MIN(C10*(1+Debts!$C$8/12),Debts!$D$8)+MIN(C10+0,D10*(1+Debts!$C$9/12))*0+MIN(D10*(1+Debts!$C$9/12),Debts!$D$9)+MIN(C10+0,E10*(1+Debts!$C$10/12))*0+MIN(E10*(1+Debts!$C$10/12),Debts!$D$10)+MIN(C10+0,F10*(1+Debts!$C$11/12))*0+MIN(F10*(1+Debts!$C$11/12),Debts!$D$11)+MIN(C10+0,G10*(1+Debts!$C$12/12))*0+MIN(G10*(1+Debts!$C$12/12),Debts!$D$12)+MIN(C10+0,H10*(1+Debts!$C$13/12))*0+MIN(H10*(1+Debts!$C$13/12),Debts!$D$13)+MIN(C10+0,I10*(1+Debts!$C$14/12))*0+MIN(I10*(1+Debts!$C$14/12),Debts!$D$14)+MIN(C10+0,J10*(1+Debts!$C$15/12))*0+MIN(J10*(1+Debts!$C$15/12),Debts!$D$15)))),0))) -> 17995.713 | G11: =IF(G10<=0,0,MAX(0,G10*(1+Debts!$C$12/12)-MIN(G10*(1+Debts!$C$12/12),Debts!$D$12)-IF(AND(G10>0,Debts!$E$12=MIN(IF(C10>0,Debts!$E$8,999),IF(D10>0,Debts!$E$9,999),IF(E10>0,Debts!$E$10,999),IF(F10>0,Debts!$E$11,999),IF(G10>0,Debts!$E$12,999),IF(H10>0,Debts!$E$13,999),IF(I10>0,Debts!$E$14,999),IF(J10>0,Debts!$E$15,999))),MAX(0,(B11-(MIN(C10+0,C10*(1+Debts!$C$8/12))*0+MIN(C10*(1+Debts!$C$8/12),Debts!$D$8)+MIN(C10+0,D10*(1+Debts!$C$9/12))*0+MIN(D10*(1+Debts!$C$9/12),Debts!$D$9)+MIN(C10+0,E10*(1+Debts!$C$10/12))*0+MIN(E10*(1+Debts!$C$10/12),Debts!$D$10)+MIN(C10+0,F10*(1+Debts!$C$11/12))*0+MIN(F10*(1+Debts!$C$11/12),Debts!$D$11)+MIN(C10+0,G10*(1+Debts!$C$12/12))*0+MIN(G10*(1+Debts!$C$12/12),Debts!$D$12)+MIN(C10+0,H10*(1+Debts!$C$13/12))*0+MIN(H10*(1+Debts!$C$13/12),Debts!$D$13)+MIN(C10+0,I10*(1+Debts!$C$14/12))*0+MIN(I10*(1+Debts!$C$14/12),Debts!$D$14)+MIN(C10+0,J10*(1+Debts!$C$15/12))*0+MIN(J10*(1+Debts!$C$15/12),Debts!$D$15)))),0))) -> 700 | H11: =IF(H10<=0,0,MAX(0,H10*(1+Debts!$C$13/12)-MIN(H10*(1+Debts!$C$13/12),Debts!$D$13)-IF(AND(H10>0,Debts!$E$13=MIN(IF(C10>0,Debts!$E$8,999),IF(D10>0,Debts!$E$9,999),IF(E10>0,Debts!$E$10,999),IF(F10>0,Debts!$E$11,999),IF(G10>0,Debts!$E$12,999),IF(H10>0,Debts!$E$13,999),IF(I10>0,Debts!$E$14,999),IF(J10>0,Debts!$E$15,999))),MAX(0,(B11-(MIN(C10+0,C10*(1+Debts!$C$8/12))*0+MIN(C10*(1+Debts!$C$8/12),Debts!$D$8)+MIN(C10+0,D10*(1+Debts!$C$9/12))*0+MIN(D10*(1+Debts!$C$9/12),Debts!$D$9)+MIN(C10+0,E10*(1+Debts!$C$10/12))*0+MIN(E10*(1+Debts!$C$10/12),Debts!$D$10)+MIN(C10+0,F10*(1+Debts!$C$11/12))*0+MIN(F10*(1+Debts!$C$11/12),Debts!$D$11)+MIN(C10+0,G10*(1+Debts!$C$12/12))*0+MIN(G10*(1+Debts!$C$12/12),Debts!$D$12)+MIN(C10+0,H10*(1+Debts!$C$13/12))*0+MIN(H10*(1+Debts!$C$13/12),Debts!$D$13)+MIN(C10+0,I10*(1+Debts!$C$14/12))*0+MIN(I10*(1+Debts!$C$14/12),Debts!$D$14)+MIN(C10+0,J10*(1+Debts!$C$15/12))*0+MIN(J10*(1+Debts!$C$15/12),Debts!$D$15)))),0))) -> 0 | I11: =IF(I10<=0,0,MAX(0,I10*(1+Debts!$C$14/12)-MIN(I10*(1+Debts!$C$14/12),Debts!$D$14)-IF(AND(I10>0,Debts!$E$14=MIN(IF(C10>0,Debts!$E$8,999),IF(D10>0,Debts!$E$9,999),IF(E10>0,Debts!$E$10,999),IF(F10>0,Debts!$E$11,999),IF(G10>0,Debts!$E$12,999),IF(H10>0,Debts!$E$13,999),IF(I10>0,Debts!$E$14,999),IF(J10>0,Debts!$E$15,999))),MAX(0,(B11-(MIN(C10+0,C10*(1+Debts!$C$8/12))*0+MIN(C10*(1+Debts!$C$8/12),Debts!$D$8)+MIN(C10+0,D10*(1+Debts!$C$9/12))*0+MIN(D10*(1+Debts!$C$9/12),Debts!$D$9)+MIN(C10+0,E10*(1+Debts!$C$10/12))*0+MIN(E10*(1+Debts!$C$10/12),Debts!$D$10)+MIN(C10+0,F10*(1+Debts!$C$11/12))*0+MIN(F10*(1+Debts!$C$11/12),Debts!$D$11)+MIN(C10+0,G10*(1+Debts!$C$12/12))*0+MIN(G10*(1+Debts!$C$12/12),Debts!$D$12)+MIN(C10+0,H10*(1+Debts!$C$13/12))*0+MIN(H10*(1+Debts!$C$13/12),Debts!$D$13)+MIN(C10+0,I10*(1+Debts!$C$14/12))*0+MIN(I10*(1+Debts!$C$14/12),Debts!$D$14)+MIN(C10+0,J10*(1+Debts!$C$15/12))*0+MIN(J10*(1+Debts!$C$15/12),Debts!$D$15)))),0))) -> 0 | J11: =IF(J10<=0,0,MAX(0,J10*(1+Debts!$C$15/12)-MIN(J10*(1+Debts!$C$15/12),Debts!$D$15)-IF(AND(J10>0,Debts!$E$15=MIN(IF(C10>0,Debts!$E$8,999),IF(D10>0,Debts!$E$9,999),IF(E10>0,Debts!$E$10,999),IF(F10>0,Debts!$E$11,999),IF(G10>0,Debts!$E$12,999),IF(H10>0,Debts!$E$13,999),IF(I10>0,Debts!$E$14,999),IF(J10>0,Debts!$E$15,999))),MAX(0,(B11-(MIN(C10+0,C10*(1+Debts!$C$8/12))*0+MIN(C10*(1+Debts!$C$8/12),Debts!$D$8)+MIN(C10+0,D10*(1+Debts!$C$9/12))*0+MIN(D10*(1+Debts!$C$9/12),Debts!$D$9)+MIN(C10+0,E10*(1+Debts!$C$10/12))*0+MIN(E10*(1+Debts!$C$10/12),Debts!$D$10)+MIN(C10+0,F10*(1+Debts!$C$11/12))*0+MIN(F10*(1+Debts!$C$11/12),Debts!$D$11)+MIN(C10+0,G10*(1+Debts!$C$12/12))*0+MIN(G10*(1+Debts!$C$12/12),Debts!$D$12)+MIN(C10+0,H10*(1+Debts!$C$13/12))*0+MIN(H10*(1+Debts!$C$13/12),Debts!$D$13)+MIN(C10+0,I10*(1+Debts!$C$14/12))*0+MIN(I10*(1+Debts!$C$14/12),Debts!$D$14)+MIN(C10+0,J10*(1+Debts!$C$15/12))*0+MIN(J10*(1+Debts!$C$15/12),Debts!$D$15)))),0))) -> 0 | K11: =IF(C10>0,C10*Debts!$C$8/12,0)+IF(D10>0,D10*Debts!$C$9/12,0)+IF(E10>0,E10*Debts!$C$10/12,0)+IF(F10>0,F10*Debts!$C$11/12,0)+IF(G10>0,G10*Debts!$C$12/12,0)+IF(H10>0,H10*Debts!$C$13/12,0)+IF(I10>0,I10*Debts!$C$14/12,0)+IF(J10>0,J10*Debts!$C$15/12,0) -> 290.32663 | L11: =SUM(C11:J11) -> 36231.25
A12: =5 -> 5 | B12: =IF(L11<=0,0,Debts!$D$16+Debts!$B$4) -> 1200 | C12: =IF(C11<=0,0,MAX(0,C11*(1+Debts!$C$8/12)-MIN(C11*(1+Debts!$C$8/12),Debts!$D$8)-IF(AND(C11>0,Debts!$E$8=MIN(IF(C11>0,Debts!$E$8,999),IF(D11>0,Debts!$E$9,999),IF(E11>0,Debts!$E$10,999),IF(F11>0,Debts!$E$11,999),IF(G11>0,Debts!$E$12,999),IF(H11>0,Debts!$E$13,999),IF(I11>0,Debts!$E$14,999),IF(J11>0,Debts!$E$15,999))),MAX(0,(B12-(MIN(C11+0,C11*(1+Debts!$C$8/12))*0+MIN(C11*(1+Debts!$C$8/12),Debts!$D$8)+MIN(C11+0,D11*(1+Debts!$C$9/12))*0+MIN(D11*(1+Debts!$C$9/12),Debts!$D$9)+MIN(C11+0,E11*(1+Debts!$C$10/12))*0+MIN(E11*(1+Debts!$C$10/12),Debts!$D$10)+MIN(C11+0,F11*(1+Debts!$C$11/12))*0+MIN(F11*(1+Debts!$C$11/12),Debts!$D$11)+MIN(C11+0,G11*(1+Debts!$C$12/12))*0+MIN(G11*(1+Debts!$C$12/12),Debts!$D$12)+MIN(C11+0,H11*(1+Debts!$C$13/12))*0+MIN(H11*(1+Debts!$C$13/12),Debts!$D$13)+MIN(C11+0,I11*(1+Debts!$C$14/12))*0+MIN(I11*(1+Debts!$C$14/12),Debts!$D$14)+MIN(C11+0,J11*(1+Debts!$C$15/12))*0+MIN(J11*(1+Debts!$C$15/12),Debts!$D$15)))),0))) -> 3977.9275 | D12: =IF(D11<=0,0,MAX(0,D11*(1+Debts!$C$9/12)-MIN(D11*(1+Debts!$C$9/12),Debts!$D$9)-IF(AND(D11>0,Debts!$E$9=MIN(IF(C11>0,Debts!$E$8,999),IF(D11>0,Debts!$E$9,999),IF(E11>0,Debts!$E$10,999),IF(F11>0,Debts!$E$11,999),IF(G11>0,Debts!$E$12,999),IF(H11>0,Debts!$E$13,999),IF(I11>0,Debts!$E$14,999),IF(J11>0,Debts!$E$15,999))),MAX(0,(B12-(MIN(C11+0,C11*(1+Debts!$C$8/12))*0+MIN(C11*(1+Debts!$C$8/12),Debts!$D$8)+MIN(C11+0,D11*(1+Debts!$C$9/12))*0+MIN(D11*(1+Debts!$C$9/12),Debts!$D$9)+MIN(C11+0,E11*(1+Debts!$C$10/12))*0+MIN(E11*(1+Debts!$C$10/12),Debts!$D$10)+MIN(C11+0,F11*(1+Debts!$C$11/12))*0+MIN(F11*(1+Debts!$C$11/12),Debts!$D$11)+MIN(C11+0,G11*(1+Debts!$C$12/12))*0+MIN(G11*(1+Debts!$C$12/12),Debts!$D$12)+MIN(C11+0,H11*(1+Debts!$C$13/12))*0+MIN(H11*(1+Debts!$C$13/12),Debts!$D$13)+MIN(C11+0,I11*(1+Debts!$C$14/12))*0+MIN(I11*(1+Debts!$C$14/12),Debts!$D$14)+MIN(C11+0,J11*(1+Debts!$C$15/12))*0+MIN(J11*(1+Debts!$C$15/12),Debts!$D$15)))),0))) -> 2238.2011 | E12: =IF(E11<=0,0,MAX(0,E11*(1+Debts!$C$10/12)-MIN(E11*(1+Debts!$C$10/12),Debts!$D$10)-IF(AND(E11>0,Debts!$E$10=MIN(IF(C11>0,Debts!$E$8,999),IF(D11>0,Debts!$E$9,999),IF(E11>0,Debts!$E$10,999),IF(F11>0,Debts!$E$11,999),IF(G11>0,Debts!$E$12,999),IF(H11>0,Debts!$E$13,999),IF(I11>0,Debts!$E$14,999),IF(J11>0,Debts!$E$15,999))),MAX(0,(B12-(MIN(C11+0,C11*(1+Debts!$C$8/12))*0+MIN(C11*(1+Debts!$C$8/12),Debts!$D$8)+MIN(C11+0,D11*(1+Debts!$C$9/12))*0+MIN(D11*(1+Debts!$C$9/12),Debts!$D$9)+MIN(C11+0,E11*(1+Debts!$C$10/12))*0+MIN(E11*(1+Debts!$C$10/12),Debts!$D$10)+MIN(C11+0,F11*(1+Debts!$C$11/12))*0+MIN(F11*(1+Debts!$C$11/12),Debts!$D$11)+MIN(C11+0,G11*(1+Debts!$C$12/12))*0+MIN(G11*(1+Debts!$C$12/12),Debts!$D$12)+MIN(C11+0,H11*(1+Debts!$C$13/12))*0+MIN(H11*(1+Debts!$C$13/12),Debts!$D$13)+MIN(C11+0,I11*(1+Debts!$C$14/12))*0+MIN(I11*(1+Debts!$C$14/12),Debts!$D$14)+MIN(C11+0,J11*(1+Debts!$C$15/12))*0+MIN(J11*(1+Debts!$C$15/12),Debts!$D$15)))),0))) -> 10575.246 | F12: =IF(F11<=0,0,MAX(0,F11*(1+Debts!$C$11/12)-MIN(F11*(1+Debts!$C$11/12),Debts!$D$11)-IF(AND(F11>0,Debts!$E$11=MIN(IF(C11>0,Debts!$E$8,999),IF(D11>0,Debts!$E$9,999),IF(E11>0,Debts!$E$10,999),IF(F11>0,Debts!$E$11,999),IF(G11>0,Debts!$E$12,999),IF(H11>0,Debts!$E$13,999),IF(I11>0,Debts!$E$14,999),IF(J11>0,Debts!$E$15,999))),MAX(0,(B12-(MIN(C11+0,C11*(1+Debts!$C$8/12))*0+MIN(C11*(1+Debts!$C$8/12),Debts!$D$8)+MIN(C11+0,D11*(1+Debts!$C$9/12))*0+MIN(D11*(1+Debts!$C$9/12),Debts!$D$9)+MIN(C11+0,E11*(1+Debts!$C$10/12))*0+MIN(E11*(1+Debts!$C$10/12),Debts!$D$10)+MIN(C11+0,F11*(1+Debts!$C$11/12))*0+MIN(F11*(1+Debts!$C$11/12),Debts!$D$11)+MIN(C11+0,G11*(1+Debts!$C$12/12))*0+MIN(G11*(1+Debts!$C$12/12),Debts!$D$12)+MIN(C11+0,H11*(1+Debts!$C$13/12))*0+MIN(H11*(1+Debts!$C$13/12),Debts!$D$13)+MIN(C11+0,I11*(1+Debts!$C$14/12))*0+MIN(I11*(1+Debts!$C$14/12),Debts!$D$14)+MIN(C11+0,J11*(1+Debts!$C$15/12))*0+MIN(J11*(1+Debts!$C$15/12),Debts!$D$15)))),0))) -> 17868.193 | G12: =IF(G11<=0,0,MAX(0,G11*(1+Debts!$C$12/12)-MIN(G11*(1+Debts!$C$12/12),Debts!$D$12)-IF(AND(G11>0,Debts!$E$12=MIN(IF(C11>0,Debts!$E$8,999),IF(D11>0,Debts!$E$9,999),IF(E11>0,Debts!$E$10,999),IF(F11>0,Debts!$E$11,999),IF(G11>0,Debts!$E$12,999),IF(H11>0,Debts!$E$13,999),IF(I11>0,Debts!$E$14,999),IF(J11>0,Debts!$E$15,999))),MAX(0,(B12-(MIN(C11+0,C11*(1+Debts!$C$8/12))*0+MIN(C11*(1+Debts!$C$8/12),Debts!$D$8)+MIN(C11+0,D11*(1+Debts!$C$9/12))*0+MIN(D11*(1+Debts!$C$9/12),Debts!$D$9)+MIN(C11+0,E11*(1+Debts!$C$10/12))*0+MIN(E11*(1+Debts!$C$10/12),Debts!$D$10)+MIN(C11+0,F11*(1+Debts!$C$11/12))*0+MIN(F11*(1+Debts!$C$11/12),Debts!$D$11)+MIN(C11+0,G11*(1+Debts!$C$12/12))*0+MIN(G11*(1+Debts!$C$12/12),Debts!$D$12)+MIN(C11+0,H11*(1+Debts!$C$13/12))*0+MIN(H11*(1+Debts!$C$13/12),Debts!$D$13)+MIN(C11+0,I11*(1+Debts!$C$14/12))*0+MIN(I11*(1+Debts!$C$14/12),Debts!$D$14)+MIN(C11+0,J11*(1+Debts!$C$15/12))*0+MIN(J11*(1+Debts!$C$15/12),Debts!$D$15)))),0))) -> 650 | H12: =IF(H11<=0,0,MAX(0,H11*(1+Debts!$C$13/12)-MIN(H11*(1+Debts!$C$13/12),Debts!$D$13)-IF(AND(H11>0,Debts!$E$13=MIN(IF(C11>0,Debts!$E$8,999),IF(D11>0,Debts!$E$9,999),IF(E11>0,Debts!$E$10,999),IF(F11>0,Debts!$E$11,999),IF(G11>0,Debts!$E$12,999),IF(H11>0,Debts!$E$13,999),IF(I11>0,Debts!$E$14,999),IF(J11>0,Debts!$E$15,999))),MAX(0,(B12-(MIN(C11+0,C11*(1+Debts!$C$8/12))*0+MIN(C11*(1+Debts!$C$8/12),Debts!$D$8)+MIN(C11+0,D11*(1+Debts!$C$9/12))*0+MIN(D11*(1+Debts!$C$9/12),Debts!$D$9)+MIN(C11+0,E11*(1+Debts!$C$10/12))*0+MIN(E11*(1+Debts!$C$10/12),Debts!$D$10)+MIN(C11+0,F11*(1+Debts!$C$11/12))*0+MIN(F11*(1+Debts!$C$11/12),Debts!$D$11)+MIN(C11+0,G11*(1+Debts!$C$12/12))*0+MIN(G11*(1+Debts!$C$12/12),Debts!$D$12)+MIN(C11+0,H11*(1+Debts!$C$13/12))*0+MIN(H11*(1+Debts!$C$13/12),Debts!$D$13)+MIN(C11+0,I11*(1+Debts!$C$14/12))*0+MIN(I11*(1+Debts!$C$14/12),Debts!$D$14)+MIN(C11+0,J11*(1+Debts!$C$15/12))*0+MIN(J11*(1+Debts!$C$15/12),Debts!$D$15)))),0))) -> 0 | I12: =IF(I11<=0,0,MAX(0,I11*(1+Debts!$C$14/12)-MIN(I11*(1+Debts!$C$14/12),Debts!$D$14)-IF(AND(I11>0,Debts!$E$14=MIN(IF(C11>0,Debts!$E$8,999),IF(D11>0,Debts!$E$9,999),IF(E11>0,Debts!$E$10,999),IF(F11>0,Debts!$E$11,999),IF(G11>0,Debts!$E$12,999),IF(H11>0,Debts!$E$13,999),IF(I11>0,Debts!$E$14,999),IF(J11>0,Debts!$E$15,999))),MAX(0,(B12-(MIN(C11+0,C11*(1+Debts!$C$8/12))*0+MIN(C11*(1+Debts!$C$8/12),Debts!$D$8)+MIN(C11+0,D11*(1+Debts!$C$9/12))*0+MIN(D11*(1+Debts!$C$9/12),Debts!$D$9)+MIN(C11+0,E11*(1+Debts!$C$10/12))*0+MIN(E11*(1+Debts!$C$10/12),Debts!$D$10)+MIN(C11+0,F11*(1+Debts!$C$11/12))*0+MIN(F11*(1+Debts!$C$11/12),Debts!$D$11)+MIN(C11+0,G11*(1+Debts!$C$12/12))*0+MIN(G11*(1+Debts!$C$12/12),Debts!$D$12)+MIN(C11+0,H11*(1+Debts!$C$13/12))*0+MIN(H11*(1+Debts!$C$13/12),Debts!$D$13)+MIN(C11+0,I11*(1+Debts!$C$14/12))*0+MIN(I11*(1+Debts!$C$14/12),Debts!$D$14)+MIN(C11+0,J11*(1+Debts!$C$15/12))*0+MIN(J11*(1+Debts!$C$15/12),Debts!$D$15)))),0))) -> 0 | J12: =IF(J11<=0,0,MAX(0,J11*(1+Debts!$C$15/12)-MIN(J11*(1+Debts!$C$15/12),Debts!$D$15)-IF(AND(J11>0,Debts!$E$15=MIN(IF(C11>0,Debts!$E$8,999),IF(D11>0,Debts!$E$9,999),IF(E11>0,Debts!$E$10,999),IF(F11>0,Debts!$E$11,999),IF(G11>0,Debts!$E$12,999),IF(H11>0,Debts!$E$13,999),IF(I11>0,Debts!$E$14,999),IF(J11>0,Debts!$E$15,999))),MAX(0,(B12-(MIN(C11+0,C11*(1+Debts!$C$8/12))*0+MIN(C11*(1+Debts!$C$8/12),Debts!$D$8)+MIN(C11+0,D11*(1+Debts!$C$9/12))*0+MIN(D11*(1+Debts!$C$9/12),Debts!$D$9)+MIN(C11+0,E11*(1+Debts!$C$10/12))*0+MIN(E11*(1+Debts!$C$10/12),Debts!$D$10)+MIN(C11+0,F11*(1+Debts!$C$11/12))*0+MIN(F11*(1+Debts!$C$11/12),Debts!$D$11)+MIN(C11+0,G11*(1+Debts!$C$12/12))*0+MIN(G11*(1+Debts!$C$12/12),Debts!$D$12)+MIN(C11+0,H11*(1+Debts!$C$13/12))*0+MIN(H11*(1+Debts!$C$13/12),Debts!$D$13)+MIN(C11+0,I11*(1+Debts!$C$14/12))*0+MIN(I11*(1+Debts!$C$14/12),Debts!$D$14)+MIN(C11+0,J11*(1+Debts!$C$15/12))*0+MIN(J11*(1+Debts!$C$15/12),Debts!$D$15)))),0))) -> 0 | K12: =IF(C11>0,C11*Debts!$C$8/12,0)+IF(D11>0,D11*Debts!$C$9/12,0)+IF(E11>0,E11*Debts!$C$10/12,0)+IF(F11>0,F11*Debts!$C$11/12,0)+IF(G11>0,G11*Debts!$C$12/12,0)+IF(H11>0,H11*Debts!$C$13/12,0)+IF(I11>0,I11*Debts!$C$14/12,0)+IF(J11>0,J11*Debts!$C$15/12,0) -> 278.31818 | L12: =SUM(C12:J12) -> 35309.568
A13: =6 -> 6 | B13: =IF(L12<=0,0,Debts!$D$16+Debts!$B$4) -> 1200 | C13: =IF(C12<=0,0,MAX(0,C12*(1+Debts!$C$8/12)-MIN(C12*(1+Debts!$C$8/12),Debts!$D$8)-IF(AND(C12>0,Debts!$E$8=MIN(IF(C12>0,Debts!$E$8,999),IF(D12>0,Debts!$E$9,999),IF(E12>0,Debts!$E$10,999),IF(F12>0,Debts!$E$11,999),IF(G12>0,Debts!$E$12,999),IF(H12>0,Debts!$E$13,999),IF(I12>0,Debts!$E$14,999),IF(J12>0,Debts!$E$15,999))),MAX(0,(B13-(MIN(C12+0,C12*(1+Debts!$C$8/12))*0+MIN(C12*(1+Debts!$C$8/12),Debts!$D$8)+MIN(C12+0,D12*(1+Debts!$C$9/12))*0+MIN(D12*(1+Debts!$C$9/12),Debts!$D$9)+MIN(C12+0,E12*(1+Debts!$C$10/12))*0+MIN(E12*(1+Debts!$C$10/12),Debts!$D$10)+MIN(C12+0,F12*(1+Debts!$C$11/12))*0+MIN(F12*(1+Debts!$C$11/12),Debts!$D$11)+MIN(C12+0,G12*(1+Debts!$C$12/12))*0+MIN(G12*(1+Debts!$C$12/12),Debts!$D$12)+MIN(C12+0,H12*(1+Debts!$C$13/12))*0+MIN(H12*(1+Debts!$C$13/12),Debts!$D$13)+MIN(C12+0,I12*(1+Debts!$C$14/12))*0+MIN(I12*(1+Debts!$C$14/12),Debts!$D$14)+MIN(C12+0,J12*(1+Debts!$C$15/12))*0+MIN(J12*(1+Debts!$C$15/12),Debts!$D$15)))),0))) -> 3505.4695 | D13: =IF(D12<=0,0,MAX(0,D12*(1+Debts!$C$9/12)-MIN(D12*(1+Debts!$C$9/12),Debts!$D$9)-IF(AND(D12>0,Debts!$E$9=MIN(IF(C12>0,Debts!$E$8,999),IF(D12>0,Debts!$E$9,999),IF(E12>0,Debts!$E$10,999),IF(F12>0,Debts!$E$11,999),IF(G12>0,Debts!$E$12,999),IF(H12>0,Debts!$E$13,999),IF(I12>0,Debts!$E$14,999),IF(J12>0,Debts!$E$15,999))),MAX(0,(B13-(MIN(C12+0,C12*(1+Debts!$C$8/12))*0+MIN(C12*(1+Debts!$C$8/12),Debts!$D$8)+MIN(C12+0,D12*(1+Debts!$C$9/12))*0+MIN(D12*(1+Debts!$C$9/12),Debts!$D$9)+MIN(C12+0,E12*(1+Debts!$C$10/12))*0+MIN(E12*(1+Debts!$C$10/12),Debts!$D$10)+MIN(C12+0,F12*(1+Debts!$C$11/12))*0+MIN(F12*(1+Debts!$C$11/12),Debts!$D$11)+MIN(C12+0,G12*(1+Debts!$C$12/12))*0+MIN(G12*(1+Debts!$C$12/12),Debts!$D$12)+MIN(C12+0,H12*(1+Debts!$C$13/12))*0+MIN(H12*(1+Debts!$C$13/12),Debts!$D$13)+MIN(C12+0,I12*(1+Debts!$C$14/12))*0+MIN(I12*(1+Debts!$C$14/12),Debts!$D$14)+MIN(C12+0,J12*(1+Debts!$C$15/12))*0+MIN(J12*(1+Debts!$C$15/12),Debts!$D$15)))),0))) -> 2204.0483 | E13: =IF(E12<=0,0,MAX(0,E12*(1+Debts!$C$10/12)-MIN(E12*(1+Debts!$C$10/12),Debts!$D$10)-IF(AND(E12>0,Debts!$E$10=MIN(IF(C12>0,Debts!$E$8,999),IF(D12>0,Debts!$E$9,999),IF(E12>0,Debts!$E$10,999),IF(F12>0,Debts!$E$11,999),IF(G12>0,Debts!$E$12,999),IF(H12>0,Debts!$E$13,999),IF(I12>0,Debts!$E$14,999),IF(J12>0,Debts!$E$15,999))),MAX(0,(B13-(MIN(C12+0,C12*(1+Debts!$C$8/12))*0+MIN(C12*(1+Debts!$C$8/12),Debts!$D$8)+MIN(C12+0,D12*(1+Debts!$C$9/12))*0+MIN(D12*(1+Debts!$C$9/12),Debts!$D$9)+MIN(C12+0,E12*(1+Debts!$C$10/12))*0+MIN(E12*(1+Debts!$C$10/12),Debts!$D$10)+MIN(C12+0,F12*(1+Debts!$C$11/12))*0+MIN(F12*(1+Debts!$C$11/12),Debts!$D$11)+MIN(C12+0,G12*(1+Debts!$C$12/12))*0+MIN(G12*(1+Debts!$C$12/12),Debts!$D$12)+MIN(C12+0,H12*(1+Debts!$C$13/12))*0+MIN(H12*(1+Debts!$C$13/12),Debts!$D$13)+MIN(C12+0,I12*(1+Debts!$C$14/12))*0+MIN(I12*(1+Debts!$C$14/12),Debts!$D$14)+MIN(C12+0,J12*(1+Debts!$C$15/12))*0+MIN(J12*(1+Debts!$C$15/12),Debts!$D$15)))),0))) -> 10326.054 | F13: =IF(F12<=0,0,MAX(0,F12*(1+Debts!$C$11/12)-MIN(F12*(1+Debts!$C$11/12),Debts!$D$11)-IF(AND(F12>0,Debts!$E$11=MIN(IF(C12>0,Debts!$E$8,999),IF(D12>0,Debts!$E$9,999),IF(E12>0,Debts!$E$10,999),IF(F12>0,Debts!$E$11,999),IF(G12>0,Debts!$E$12,999),IF(H12>0,Debts!$E$13,999),IF(I12>0,Debts!$E$14,999),IF(J12>0,Debts!$E$15,999))),MAX(0,(B13-(MIN(C12+0,C12*(1+Debts!$C$8/12))*0+MIN(C12*(1+Debts!$C$8/12),Debts!$D$8)+MIN(C12+0,D12*(1+Debts!$C$9/12))*0+MIN(D12*(1+Debts!$C$9/12),Debts!$D$9)+MIN(C12+0,E12*(1+Debts!$C$10/12))*0+MIN(E12*(1+Debts!$C$10/12),Debts!$D$10)+MIN(C12+0,F12*(1+Debts!$C$11/12))*0+MIN(F12*(1+Debts!$C$11/12),Debts!$D$11)+MIN(C12+0,G12*(1+Debts!$C$12/12))*0+MIN(G12*(1+Debts!$C$12/12),Debts!$D$12)+MIN(C12+0,H12*(1+Debts!$C$13/12))*0+MIN(H12*(1+Debts!$C$13/12),Debts!$D$13)+MIN(C12+0,I12*(1+Debts!$C$14/12))*0+MIN(I12*(1+Debts!$C$14/12),Debts!$D$14)+MIN(C12+0,J12*(1+Debts!$C$15/12))*0+MIN(J12*(1+Debts!$C$15/12),Debts!$D$15)))),0))) -> 17740.089 | G13: =IF(G12<=0,0,MAX(0,G12*(1+Debts!$C$12/12)-MIN(G12*(1+Debts!$C$12/12),Debts!$D$12)-IF(AND(G12>0,Debts!$E$12=MIN(IF(C12>0,Debts!$E$8,999),IF(D12>0,Debts!$E$9,999),IF(E12>0,Debts!$E$10,999),IF(F12>0,Debts!$E$11,999),IF(G12>0,Debts!$E$12,999),IF(H12>0,Debts!$E$13,999),IF(I12>0,Debts!$E$14,999),IF(J12>0,Debts!$E$15,999))),MAX(0,(B13-(MIN(C12+0,C12*(1+Debts!$C$8/12))*0+MIN(C12*(1+Debts!$C$8/12),Debts!$D$8)+MIN(C12+0,D12*(1+Debts!$C$9/12))*0+MIN(D12*(1+Debts!$C$9/12),Debts!$D$9)+MIN(C12+0,E12*(1+Debts!$C$10/12))*0+MIN(E12*(1+Debts!$C$10/12),Debts!$D$10)+MIN(C12+0,F12*(1+Debts!$C$11/12))*0+MIN(F12*(1+Debts!$C$11/12),Debts!$D$11)+MIN(C12+0,G12*(1+Debts!$C$12/12))*0+MIN(G12*(1+Debts!$C$12/12),Debts!$D$12)+MIN(C12+0,H12*(1+Debts!$C$13/12))*0+MIN(H12*(1+Debts!$C$13/12),Debts!$D$13)+MIN(C12+0,I12*(1+Debts!$C$14/12))*0+MIN(I12*(1+Debts!$C$14/12),Debts!$D$14)+MIN(C12+0,J12*(1+Debts!$C$15/12))*0+MIN(J12*(1+Debts!$C$15/12),Debts!$D$15)))),0))) -> 600 | H13: =IF(H12<=0,0,MAX(0,H12*(1+Debts!$C$13/12)-MIN(H12*(1+Debts!$C$13/12),Debts!$D$13)-IF(AND(H12>0,Debts!$E$13=MIN(IF(C12>0,Debts!$E$8,999),IF(D12>0,Debts!$E$9,999),IF(E12>0,Debts!$E$10,999),IF(F12>0,Debts!$E$11,999),IF(G12>0,Debts!$E$12,999),IF(H12>0,Debts!$E$13,999),IF(I12>0,Debts!$E$14,999),IF(J12>0,Debts!$E$15,999))),MAX(0,(B13-(MIN(C12+0,C12*(1+Debts!$C$8/12))*0+MIN(C12*(1+Debts!$C$8/12),Debts!$D$8)+MIN(C12+0,D12*(1+Debts!$C$9/12))*0+MIN(D12*(1+Debts!$C$9/12),Debts!$D$9)+MIN(C12+0,E12*(1+Debts!$C$10/12))*0+MIN(E12*(1+Debts!$C$10/12),Debts!$D$10)+MIN(C12+0,F12*(1+Debts!$C$11/12))*0+MIN(F12*(1+Debts!$C$11/12),Debts!$D$11)+MIN(C12+0,G12*(1+Debts!$C$12/12))*0+MIN(G12*(1+Debts!$C$12/12),Debts!$D$12)+MIN(C12+0,H12*(1+Debts!$C$13/12))*0+MIN(H12*(1+Debts!$C$13/12),Debts!$D$13)+MIN(C12+0,I12*(1+Debts!$C$14/12))*0+MIN(I12*(1+Debts!$C$14/12),Debts!$D$14)+MIN(C12+0,J12*(1+Debts!$C$15/12))*0+MIN(J12*(1+Debts!$C$15/12),Debts!$D$15)))),0))) -> 0 | I13: =IF(I12<=0,0,MAX(0,I12*(1+Debts!$C$14/12)-MIN(I12*(1+Debts!$C$14/12),Debts!$D$14)-IF(AND(I12>0,Debts!$E$14=MIN(IF(C12>0,Debts!$E$8,999),IF(D12>0,Debts!$E$9,999),IF(E12>0,Debts!$E$10,999),IF(F12>0,Debts!$E$11,999),IF(G12>0,Debts!$E$12,999),IF(H12>0,Debts!$E$13,999),IF(I12>0,Debts!$E$14,999),IF(J12>0,Debts!$E$15,999))),MAX(0,(B13-(MIN(C12+0,C12*(1+Debts!$C$8/12))*0+MIN(C12*(1+Debts!$C$8/12),Debts!$D$8)+MIN(C12+0,D12*(1+Debts!$C$9/12))*0+MIN(D12*(1+Debts!$C$9/12),Debts!$D$9)+MIN(C12+0,E12*(1+Debts!$C$10/12))*0+MIN(E12*(1+Debts!$C$10/12),Debts!$D$10)+MIN(C12+0,F12*(1+Debts!$C$11/12))*0+MIN(F12*(1+Debts!$C$11/12),Debts!$D$11)+MIN(C12+0,G12*(1+Debts!$C$12/12))*0+MIN(G12*(1+Debts!$C$12/12),Debts!$D$12)+MIN(C12+0,H12*(1+Debts!$C$13/12))*0+MIN(H12*(1+Debts!$C$13/12),Debts!$D$13)+MIN(C12+0,I12*(1+Debts!$C$14/12))*0+MIN(I12*(1+Debts!$C$14/12),Debts!$D$14)+MIN(C12+0,J12*(1+Debts!$C$15/12))*0+MIN(J12*(1+Debts!$C$15/12),Debts!$D$15)))),0))) -> 0 | J13: =IF(J12<=0,0,MAX(0,J12*(1+Debts!$C$15/12)-MIN(J12*(1+Debts!$C$15/12),Debts!$D$15)-IF(AND(J12>0,Debts!$E$15=MIN(IF(C12>0,Debts!$E$8,999),IF(D12>0,Debts!$E$9,999),IF(E12>0,Debts!$E$10,999),IF(F12>0,Debts!$E$11,999),IF(G12>0,Debts!$E$12,999),IF(H12>0,Debts!$E$13,999),IF(I12>0,Debts!$E$14,999),IF(J12>0,Debts!$E$15,999))),MAX(0,(B13-(MIN(C12+0,C12*(1+Debts!$C$8/12))*0+MIN(C12*(1+Debts!$C$8/12),Debts!$D$8)+MIN(C12+0,D12*(1+Debts!$C$9/12))*0+MIN(D12*(1+Debts!$C$9/12),Debts!$D$9)+MIN(C12+0,E12*(1+Debts!$C$10/12))*0+MIN(E12*(1+Debts!$C$10/12),Debts!$D$10)+MIN(C12+0,F12*(1+Debts!$C$11/12))*0+MIN(F12*(1+Debts!$C$11/12),Debts!$D$11)+MIN(C12+0,G12*(1+Debts!$C$12/12))*0+MIN(G12*(1+Debts!$C$12/12),Debts!$D$12)+MIN(C12+0,H12*(1+Debts!$C$13/12))*0+MIN(H12*(1+Debts!$C$13/12),Debts!$D$13)+MIN(C12+0,I12*(1+Debts!$C$14/12))*0+MIN(I12*(1+Debts!$C$14/12),Debts!$D$14)+MIN(C12+0,J12*(1+Debts!$C$15/12))*0+MIN(J12*(1+Debts!$C$15/12),Debts!$D$15)))),0))) -> 0 | K13: =IF(C12>0,C12*Debts!$C$8/12,0)+IF(D12>0,D12*Debts!$C$9/12,0)+IF(E12>0,E12*Debts!$C$10/12,0)+IF(F12>0,F12*Debts!$C$11/12,0)+IF(G12>0,G12*Debts!$C$12/12,0)+IF(H12>0,H12*Debts!$C$13/12,0)+IF(I12>0,I12*Debts!$C$14/12,0)+IF(J12>0,J12*Debts!$C$15/12,0) -> 266.09272 | L13: =SUM(C13:J13) -> 34375.661
A14: =7 -> 7 | B14: =IF(L13<=0,0,Debts!$D$16+Debts!$B$4) -> 1200 | C14: =IF(C13<=0,0,MAX(0,C13*(1+Debts!$C$8/12)-MIN(C13*(1+Debts!$C$8/12),Debts!$D$8)-IF(AND(C13>0,Debts!$E$8=MIN(IF(C13>0,Debts!$E$8,999),IF(D13>0,Debts!$E$9,999),IF(E13>0,Debts!$E$10,999),IF(F13>0,Debts!$E$11,999),IF(G13>0,Debts!$E$12,999),IF(H13>0,Debts!$E$13,999),IF(I13>0,Debts!$E$14,999),IF(J13>0,Debts!$E$15,999))),MAX(0,(B14-(MIN(C13+0,C13*(1+Debts!$C$8/12))*0+MIN(C13*(1+Debts!$C$8/12),Debts!$D$8)+MIN(C13+0,D13*(1+Debts!$C$9/12))*0+MIN(D13*(1+Debts!$C$9/12),Debts!$D$9)+MIN(C13+0,E13*(1+Debts!$C$10/12))*0+MIN(E13*(1+Debts!$C$10/12),Debts!$D$10)+MIN(C13+0,F13*(1+Debts!$C$11/12))*0+MIN(F13*(1+Debts!$C$11/12),Debts!$D$11)+MIN(C13+0,G13*(1+Debts!$C$12/12))*0+MIN(G13*(1+Debts!$C$12/12),Debts!$D$12)+MIN(C13+0,H13*(1+Debts!$C$13/12))*0+MIN(H13*(1+Debts!$C$13/12),Debts!$D$13)+MIN(C13+0,I13*(1+Debts!$C$14/12))*0+MIN(I13*(1+Debts!$C$14/12),Debts!$D$14)+MIN(C13+0,J13*(1+Debts!$C$15/12))*0+MIN(J13*(1+Debts!$C$15/12),Debts!$D$15)))),0))) -> 3023.208 | D14: =IF(D13<=0,0,MAX(0,D13*(1+Debts!$C$9/12)-MIN(D13*(1+Debts!$C$9/12),Debts!$D$9)-IF(AND(D13>0,Debts!$E$9=MIN(IF(C13>0,Debts!$E$8,999),IF(D13>0,Debts!$E$9,999),IF(E13>0,Debts!$E$10,999),IF(F13>0,Debts!$E$11,999),IF(G13>0,Debts!$E$12,999),IF(H13>0,Debts!$E$13,999),IF(I13>0,Debts!$E$14,999),IF(J13>0,Debts!$E$15,999))),MAX(0,(B14-(MIN(C13+0,C13*(1+Debts!$C$8/12))*0+MIN(C13*(1+Debts!$C$8/12),Debts!$D$8)+MIN(C13+0,D13*(1+Debts!$C$9/12))*0+MIN(D13*(1+Debts!$C$9/12),Debts!$D$9)+MIN(C13+0,E13*(1+Debts!$C$10/12))*0+MIN(E13*(1+Debts!$C$10/12),Debts!$D$10)+MIN(C13+0,F13*(1+Debts!$C$11/12))*0+MIN(F13*(1+Debts!$C$11/12),Debts!$D$11)+MIN(C13+0,G13*(1+Debts!$C$12/12))*0+MIN(G13*(1+Debts!$C$12/12),Debts!$D$12)+MIN(C13+0,H13*(1+Debts!$C$13/12))*0+MIN(H13*(1+Debts!$C$13/12),Debts!$D$13)+MIN(C13+0,I13*(1+Debts!$C$14/12))*0+MIN(I13*(1+Debts!$C$14/12),Debts!$D$14)+MIN(C13+0,J13*(1+Debts!$C$15/12))*0+MIN(J13*(1+Debts!$C$15/12),Debts!$D$15)))),0))) -> 2169.2722 | E14: =IF(E13<=0,0,MAX(0,E13*(1+Debts!$C$10/12)-MIN(E13*(1+Debts!$C$10/12),Debts!$D$10)-IF(AND(E13>0,Debts!$E$10=MIN(IF(C13>0,Debts!$E$8,999),IF(D13>0,Debts!$E$9,999),IF(E13>0,Debts!$E$10,999),IF(F13>0,Debts!$E$11,999),IF(G13>0,Debts!$E$12,999),IF(H13>0,Debts!$E$13,999),IF(I13>0,Debts!$E$14,999),IF(J13>0,Debts!$E$15,999))),MAX(0,(B14-(MIN(C13+0,C13*(1+Debts!$C$8/12))*0+MIN(C13*(1+Debts!$C$8/12),Debts!$D$8)+MIN(C13+0,D13*(1+Debts!$C$9/12))*0+MIN(D13*(1+Debts!$C$9/12),Debts!$D$9)+MIN(C13+0,E13*(1+Debts!$C$10/12))*0+MIN(E13*(1+Debts!$C$10/12),Debts!$D$10)+MIN(C13+0,F13*(1+Debts!$C$11/12))*0+MIN(F13*(1+Debts!$C$11/12),Debts!$D$11)+MIN(C13+0,G13*(1+Debts!$C$12/12))*0+MIN(G13*(1+Debts!$C$12/12),Debts!$D$12)+MIN(C13+0,H13*(1+Debts!$C$13/12))*0+MIN(H13*(1+Debts!$C$13/12),Debts!$D$13)+MIN(C13+0,I13*(1+Debts!$C$14/12))*0+MIN(I13*(1+Debts!$C$14/12),Debts!$D$14)+MIN(C13+0,J13*(1+Debts!$C$15/12))*0+MIN(J13*(1+Debts!$C$15/12),Debts!$D$15)))),0))) -> 10075.429 | F14: =IF(F13<=0,0,MAX(0,F13*(1+Debts!$C$11/12)-MIN(F13*(1+Debts!$C$11/12),Debts!$D$11)-IF(AND(F13>0,Debts!$E$11=MIN(IF(C13>0,Debts!$E$8,999),IF(D13>0,Debts!$E$9,999),IF(E13>0,Debts!$E$10,999),IF(F13>0,Debts!$E$11,999),IF(G13>0,Debts!$E$12,999),IF(H13>0,Debts!$E$13,999),IF(I13>0,Debts!$E$14,999),IF(J13>0,Debts!$E$15,999))),MAX(0,(B14-(MIN(C13+0,C13*(1+Debts!$C$8/12))*0+MIN(C13*(1+Debts!$C$8/12),Debts!$D$8)+MIN(C13+0,D13*(1+Debts!$C$9/12))*0+MIN(D13*(1+Debts!$C$9/12),Debts!$D$9)+MIN(C13+0,E13*(1+Debts!$C$10/12))*0+MIN(E13*(1+Debts!$C$10/12),Debts!$D$10)+MIN(C13+0,F13*(1+Debts!$C$11/12))*0+MIN(F13*(1+Debts!$C$11/12),Debts!$D$11)+MIN(C13+0,G13*(1+Debts!$C$12/12))*0+MIN(G13*(1+Debts!$C$12/12),Debts!$D$12)+MIN(C13+0,H13*(1+Debts!$C$13/12))*0+MIN(H13*(1+Debts!$C$13/12),Debts!$D$13)+MIN(C13+0,I13*(1+Debts!$C$14/12))*0+MIN(I13*(1+Debts!$C$14/12),Debts!$D$14)+MIN(C13+0,J13*(1+Debts!$C$15/12))*0+MIN(J13*(1+Debts!$C$15/12),Debts!$D$15)))),0))) -> 17611.398 | G14: =IF(G13<=0,0,MAX(0,G13*(1+Debts!$C$12/12)-MIN(G13*(1+Debts!$C$12/12),Debts!$D$12)-IF(AND(G13>0,Debts!$E$12=MIN(IF(C13>0,Debts!$E$8,999),IF(D13>0,Debts!$E$9,999),IF(E13>0,Debts!$E$10,999),IF(F13>0,Debts!$E$11,999),IF(G13>0,Debts!$E$12,999),IF(H13>0,Debts!$E$13,999),IF(I13>0,Debts!$E$14,999),IF(J13>0,Debts!$E$15,999))),MAX(0,(B14-(MIN(C13+0,C13*(1+Debts!$C$8/12))*0+MIN(C13*(1+Debts!$C$8/12),Debts!$D$8)+MIN(C13+0,D13*(1+Debts!$C$9/12))*0+MIN(D13*(1+Debts!$C$9/12),Debts!$D$9)+MIN(C13+0,E13*(1+Debts!$C$10/12))*0+MIN(E13*(1+Debts!$C$10/12),Debts!$D$10)+MIN(C13+0,F13*(1+Debts!$C$11/12))*0+MIN(F13*(1+Debts!$C$11/12),Debts!$D$11)+MIN(C13+0,G13*(1+Debts!$C$12/12))*0+MIN(G13*(1+Debts!$C$12/12),Debts!$D$12)+MIN(C13+0,H13*(1+Debts!$C$13/12))*0+MIN(H13*(1+Debts!$C$13/12),Debts!$D$13)+MIN(C13+0,I13*(1+Debts!$C$14/12))*0+MIN(I13*(1+Debts!$C$14/12),Debts!$D$14)+MIN(C13+0,J13*(1+Debts!$C$15/12))*0+MIN(J13*(1+Debts!$C$15/12),Debts!$D$15)))),0))) -> 550 | H14: =IF(H13<=0,0,MAX(0,H13*(1+Debts!$C$13/12)-MIN(H13*(1+Debts!$C$13/12),Debts!$D$13)-IF(AND(H13>0,Debts!$E$13=MIN(IF(C13>0,Debts!$E$8,999),IF(D13>0,Debts!$E$9,999),IF(E13>0,Debts!$E$10,999),IF(F13>0,Debts!$E$11,999),IF(G13>0,Debts!$E$12,999),IF(H13>0,Debts!$E$13,999),IF(I13>0,Debts!$E$14,999),IF(J13>0,Debts!$E$15,999))),MAX(0,(B14-(MIN(C13+0,C13*(1+Debts!$C$8/12))*0+MIN(C13*(1+Debts!$C$8/12),Debts!$D$8)+MIN(C13+0,D13*(1+Debts!$C$9/12))*0+MIN(D13*(1+Debts!$C$9/12),Debts!$D$9)+MIN(C13+0,E13*(1+Debts!$C$10/12))*0+MIN(E13*(1+Debts!$C$10/12),Debts!$D$10)+MIN(C13+0,F13*(1+Debts!$C$11/12))*0+MIN(F13*(1+Debts!$C$11/12),Debts!$D$11)+MIN(C13+0,G13*(1+Debts!$C$12/12))*0+MIN(G13*(1+Debts!$C$12/12),Debts!$D$12)+MIN(C13+0,H13*(1+Debts!$C$13/12))*0+MIN(H13*(1+Debts!$C$13/12),Debts!$D$13)+MIN(C13+0,I13*(1+Debts!$C$14/12))*0+MIN(I13*(1+Debts!$C$14/12),Debts!$D$14)+MIN(C13+0,J13*(1+Debts!$C$15/12))*0+MIN(J13*(1+Debts!$C$15/12),Debts!$D$15)))),0))) -> 0 | I14: =IF(I13<=0,0,MAX(0,I13*(1+Debts!$C$14/12)-MIN(I13*(1+Debts!$C$14/12),Debts!$D$14)-IF(AND(I13>0,Debts!$E$14=MIN(IF(C13>0,Debts!$E$8,999),IF(D13>0,Debts!$E$9,999),IF(E13>0,Debts!$E$10,999),IF(F13>0,Debts!$E$11,999),IF(G13>0,Debts!$E$12,999),IF(H13>0,Debts!$E$13,999),IF(I13>0,Debts!$E$14,999),IF(J13>0,Debts!$E$15,999))),MAX(0,(B14-(MIN(C13+0,C13*(1+Debts!$C$8/12))*0+MIN(C13*(1+Debts!$C$8/12),Debts!$D$8)+MIN(C13+0,D13*(1+Debts!$C$9/12))*0+MIN(D13*(1+Debts!$C$9/12),Debts!$D$9)+MIN(C13+0,E13*(1+Debts!$C$10/12))*0+MIN(E13*(1+Debts!$C$10/12),Debts!$D$10)+MIN(C13+0,F13*(1+Debts!$C$11/12))*0+MIN(F13*(1+Debts!$C$11/12),Debts!$D$11)+MIN(C13+0,G13*(1+Debts!$C$12/12))*0+MIN(G13*(1+Debts!$C$12/12),Debts!$D$12)+MIN(C13+0,H13*(1+Debts!$C$13/12))*0+MIN(H13*(1+Debts!$C$13/12),Debts!$D$13)+MIN(C13+0,I13*(1+Debts!$C$14/12))*0+MIN(I13*(1+Debts!$C$14/12),Debts!$D$14)+MIN(C13+0,J13*(1+Debts!$C$15/12))*0+MIN(J13*(1+Debts!$C$15/12),Debts!$D$15)))),0))) -> 0 | J14: =IF(J13<=0,0,MAX(0,J13*(1+Debts!$C$15/12)-MIN(J13*(1+Debts!$C$15/12),Debts!$D$15)-IF(AND(J13>0,Debts!$E$15=MIN(IF(C13>0,Debts!$E$8,999),IF(D13>0,Debts!$E$9,999),IF(E13>0,Debts!$E$10,999),IF(F13>0,Debts!$E$11,999),IF(G13>0,Debts!$E$12,999),IF(H13>0,Debts!$E$13,999),IF(I13>0,Debts!$E$14,999),IF(J13>0,Debts!$E$15,999))),MAX(0,(B14-(MIN(C13+0,C13*(1+Debts!$C$8/12))*0+MIN(C13*(1+Debts!$C$8/12),Debts!$D$8)+MIN(C13+0,D13*(1+Debts!$C$9/12))*0+MIN(D13*(1+Debts!$C$9/12),Debts!$D$9)+MIN(C13+0,E13*(1+Debts!$C$10/12))*0+MIN(E13*(1+Debts!$C$10/12),Debts!$D$10)+MIN(C13+0,F13*(1+Debts!$C$11/12))*0+MIN(F13*(1+Debts!$C$11/12),Debts!$D$11)+MIN(C13+0,G13*(1+Debts!$C$12/12))*0+MIN(G13*(1+Debts!$C$12/12),Debts!$D$12)+MIN(C13+0,H13*(1+Debts!$C$13/12))*0+MIN(H13*(1+Debts!$C$13/12),Debts!$D$13)+MIN(C13+0,I13*(1+Debts!$C$14/12))*0+MIN(I13*(1+Debts!$C$14/12),Debts!$D$14)+MIN(C13+0,J13*(1+Debts!$C$15/12))*0+MIN(J13*(1+Debts!$C$15/12),Debts!$D$15)))),0))) -> 0 | K14: =IF(C13>0,C13*Debts!$C$8/12,0)+IF(D13>0,D13*Debts!$C$9/12,0)+IF(E13>0,E13*Debts!$C$10/12,0)+IF(F13>0,F13*Debts!$C$11/12,0)+IF(G13>0,G13*Debts!$C$12/12,0)+IF(H13>0,H13*Debts!$C$13/12,0)+IF(I13>0,I13*Debts!$C$14/12,0)+IF(J13>0,J13*Debts!$C$15/12,0) -> 253.64593 | L14: =SUM(C14:J14) -> 33429.307
A15: =8 -> 8 | B15: =IF(L14<=0,0,Debts!$D$16+Debts!$B$4) -> 1200 | C15: =IF(C14<=0,0,MAX(0,C14*(1+Debts!$C$8/12)-MIN(C14*(1+Debts!$C$8/12),Debts!$D$8)-IF(AND(C14>0,Debts!$E$8=MIN(IF(C14>0,Debts!$E$8,999),IF(D14>0,Debts!$E$9,999),IF(E14>0,Debts!$E$10,999),IF(F14>0,Debts!$E$11,999),IF(G14>0,Debts!$E$12,999),IF(H14>0,Debts!$E$13,999),IF(I14>0,Debts!$E$14,999),IF(J14>0,Debts!$E$15,999))),MAX(0,(B15-(MIN(C14+0,C14*(1+Debts!$C$8/12))*0+MIN(C14*(1+Debts!$C$8/12),Debts!$D$8)+MIN(C14+0,D14*(1+Debts!$C$9/12))*0+MIN(D14*(1+Debts!$C$9/12),Debts!$D$9)+MIN(C14+0,E14*(1+Debts!$C$10/12))*0+MIN(E14*(1+Debts!$C$10/12),Debts!$D$10)+MIN(C14+0,F14*(1+Debts!$C$11/12))*0+MIN(F14*(1+Debts!$C$11/12),Debts!$D$11)+MIN(C14+0,G14*(1+Debts!$C$12/12))*0+MIN(G14*(1+Debts!$C$12/12),Debts!$D$12)+MIN(C14+0,H14*(1+Debts!$C$13/12))*0+MIN(H14*(1+Debts!$C$13/12),Debts!$D$13)+MIN(C14+0,I14*(1+Debts!$C$14/12))*0+MIN(I14*(1+Debts!$C$14/12),Debts!$D$14)+MIN(C14+0,J14*(1+Debts!$C$15/12))*0+MIN(J14*(1+Debts!$C$15/12),Debts!$D$15)))),0))) -> 2530.9396 | D15: =IF(D14<=0,0,MAX(0,D14*(1+Debts!$C$9/12)-MIN(D14*(1+Debts!$C$9/12),Debts!$D$9)-IF(AND(D14>0,Debts!$E$9=MIN(IF(C14>0,Debts!$E$8,999),IF(D14>0,Debts!$E$9,999),IF(E14>0,Debts!$E$10,999),IF(F14>0,Debts!$E$11,999),IF(G14>0,Debts!$E$12,999),IF(H14>0,Debts!$E$13,999),IF(I14>0,Debts!$E$14,999),IF(J14>0,Debts!$E$15,999))),MAX(0,(B15-(MIN(C14+0,C14*(1+Debts!$C$8/12))*0+MIN(C14*(1+Debts!$C$8/12),Debts!$D$8)+MIN(C14+0,D14*(1+Debts!$C$9/12))*0+MIN(D14*(1+Debts!$C$9/12),Debts!$D$9)+MIN(C14+0,E14*(1+Debts!$C$10/12))*0+MIN(E14*(1+Debts!$C$10/12),Debts!$D$10)+MIN(C14+0,F14*(1+Debts!$C$11/12))*0+MIN(F14*(1+Debts!$C$11/12),Debts!$D$11)+MIN(C14+0,G14*(1+Debts!$C$12/12))*0+MIN(G14*(1+Debts!$C$12/12),Debts!$D$12)+MIN(C14+0,H14*(1+Debts!$C$13/12))*0+MIN(H14*(1+Debts!$C$13/12),Debts!$D$13)+MIN(C14+0,I14*(1+Debts!$C$14/12))*0+MIN(I14*(1+Debts!$C$14/12),Debts!$D$14)+MIN(C14+0,J14*(1+Debts!$C$15/12))*0+MIN(J14*(1+Debts!$C$15/12),Debts!$D$15)))),0))) -> 2133.8614 | E15: =IF(E14<=0,0,MAX(0,E14*(1+Debts!$C$10/12)-MIN(E14*(1+Debts!$C$10/12),Debts!$D$10)-IF(AND(E14>0,Debts!$E$10=MIN(IF(C14>0,Debts!$E$8,999),IF(D14>0,Debts!$E$9,999),IF(E14>0,Debts!$E$10,999),IF(F14>0,Debts!$E$11,999),IF(G14>0,Debts!$E$12,999),IF(H14>0,Debts!$E$13,999),IF(I14>0,Debts!$E$14,999),IF(J14>0,Debts!$E$15,999))),MAX(0,(B15-(MIN(C14+0,C14*(1+Debts!$C$8/12))*0+MIN(C14*(1+Debts!$C$8/12),Debts!$D$8)+MIN(C14+0,D14*(1+Debts!$C$9/12))*0+MIN(D14*(1+Debts!$C$9/12),Debts!$D$9)+MIN(C14+0,E14*(1+Debts!$C$10/12))*0+MIN(E14*(1+Debts!$C$10/12),Debts!$D$10)+MIN(C14+0,F14*(1+Debts!$C$11/12))*0+MIN(F14*(1+Debts!$C$11/12),Debts!$D$11)+MIN(C14+0,G14*(1+Debts!$C$12/12))*0+MIN(G14*(1+Debts!$C$12/12),Debts!$D$12)+MIN(C14+0,H14*(1+Debts!$C$13/12))*0+MIN(H14*(1+Debts!$C$13/12),Debts!$D$13)+MIN(C14+0,I14*(1+Debts!$C$14/12))*0+MIN(I14*(1+Debts!$C$14/12),Debts!$D$14)+MIN(C14+0,J14*(1+Debts!$C$15/12))*0+MIN(J14*(1+Debts!$C$15/12),Debts!$D$15)))),0))) -> 9823.3623 | F15: =IF(F14<=0,0,MAX(0,F14*(1+Debts!$C$11/12)-MIN(F14*(1+Debts!$C$11/12),Debts!$D$11)-IF(AND(F14>0,Debts!$E$11=MIN(IF(C14>0,Debts!$E$8,999),IF(D14>0,Debts!$E$9,999),IF(E14>0,Debts!$E$10,999),IF(F14>0,Debts!$E$11,999),IF(G14>0,Debts!$E$12,999),IF(H14>0,Debts!$E$13,999),IF(I14>0,Debts!$E$14,999),IF(J14>0,Debts!$E$15,999))),MAX(0,(B15-(MIN(C14+0,C14*(1+Debts!$C$8/12))*0+MIN(C14*(1+Debts!$C$8/12),Debts!$D$8)+MIN(C14+0,D14*(1+Debts!$C$9/12))*0+MIN(D14*(1+Debts!$C$9/12),Debts!$D$9)+MIN(C14+0,E14*(1+Debts!$C$10/12))*0+MIN(E14*(1+Debts!$C$10/12),Debts!$D$10)+MIN(C14+0,F14*(1+Debts!$C$11/12))*0+MIN(F14*(1+Debts!$C$11/12),Debts!$D$11)+MIN(C14+0,G14*(1+Debts!$C$12/12))*0+MIN(G14*(1+Debts!$C$12/12),Debts!$D$12)+MIN(C14+0,H14*(1+Debts!$C$13/12))*0+MIN(H14*(1+Debts!$C$13/12),Debts!$D$13)+MIN(C14+0,I14*(1+Debts!$C$14/12))*0+MIN(I14*(1+Debts!$C$14/12),Debts!$D$14)+MIN(C14+0,J14*(1+Debts!$C$15/12))*0+MIN(J14*(1+Debts!$C$15/12),Debts!$D$15)))),0))) -> 17482.117 | G15: =IF(G14<=0,0,MAX(0,G14*(1+Debts!$C$12/12)-MIN(G14*(1+Debts!$C$12/12),Debts!$D$12)-IF(AND(G14>0,Debts!$E$12=MIN(IF(C14>0,Debts!$E$8,999),IF(D14>0,Debts!$E$9,999),IF(E14>0,Debts!$E$10,999),IF(F14>0,Debts!$E$11,999),IF(G14>0,Debts!$E$12,999),IF(H14>0,Debts!$E$13,999),IF(I14>0,Debts!$E$14,999),IF(J14>0,Debts!$E$15,999))),MAX(0,(B15-(MIN(C14+0,C14*(1+Debts!$C$8/12))*0+MIN(C14*(1+Debts!$C$8/12),Debts!$D$8)+MIN(C14+0,D14*(1+Debts!$C$9/12))*0+MIN(D14*(1+Debts!$C$9/12),Debts!$D$9)+MIN(C14+0,E14*(1+Debts!$C$10/12))*0+MIN(E14*(1+Debts!$C$10/12),Debts!$D$10)+MIN(C14+0,F14*(1+Debts!$C$11/12))*0+MIN(F14*(1+Debts!$C$11/12),Debts!$D$11)+MIN(C14+0,G14*(1+Debts!$C$12/12))*0+MIN(G14*(1+Debts!$C$12/12),Debts!$D$12)+MIN(C14+0,H14*(1+Debts!$C$13/12))*0+MIN(H14*(1+Debts!$C$13/12),Debts!$D$13)+MIN(C14+0,I14*(1+Debts!$C$14/12))*0+MIN(I14*(1+Debts!$C$14/12),Debts!$D$14)+MIN(C14+0,J14*(1+Debts!$C$15/12))*0+MIN(J14*(1+Debts!$C$15/12),Debts!$D$15)))),0))) -> 500 | H15: =IF(H14<=0,0,MAX(0,H14*(1+Debts!$C$13/12)-MIN(H14*(1+Debts!$C$13/12),Debts!$D$13)-IF(AND(H14>0,Debts!$E$13=MIN(IF(C14>0,Debts!$E$8,999),IF(D14>0,Debts!$E$9,999),IF(E14>0,Debts!$E$10,999),IF(F14>0,Debts!$E$11,999),IF(G14>0,Debts!$E$12,999),IF(H14>0,Debts!$E$13,999),IF(I14>0,Debts!$E$14,999),IF(J14>0,Debts!$E$15,999))),MAX(0,(B15-(MIN(C14+0,C14*(1+Debts!$C$8/12))*0+MIN(C14*(1+Debts!$C$8/12),Debts!$D$8)+MIN(C14+0,D14*(1+Debts!$C$9/12))*0+MIN(D14*(1+Debts!$C$9/12),Debts!$D$9)+MIN(C14+0,E14*(1+Debts!$C$10/12))*0+MIN(E14*(1+Debts!$C$10/12),Debts!$D$10)+MIN(C14+0,F14*(1+Debts!$C$11/12))*0+MIN(F14*(1+Debts!$C$11/12),Debts!$D$11)+MIN(C14+0,G14*(1+Debts!$C$12/12))*0+MIN(G14*(1+Debts!$C$12/12),Debts!$D$12)+MIN(C14+0,H14*(1+Debts!$C$13/12))*0+MIN(H14*(1+Debts!$C$13/12),Debts!$D$13)+MIN(C14+0,I14*(1+Debts!$C$14/12))*0+MIN(I14*(1+Debts!$C$14/12),Debts!$D$14)+MIN(C14+0,J14*(1+Debts!$C$15/12))*0+MIN(J14*(1+Debts!$C$15/12),Debts!$D$15)))),0))) -> 0 | I15: =IF(I14<=0,0,MAX(0,I14*(1+Debts!$C$14/12)-MIN(I14*(1+Debts!$C$14/12),Debts!$D$14)-IF(AND(I14>0,Debts!$E$14=MIN(IF(C14>0,Debts!$E$8,999),IF(D14>0,Debts!$E$9,999),IF(E14>0,Debts!$E$10,999),IF(F14>0,Debts!$E$11,999),IF(G14>0,Debts!$E$12,999),IF(H14>0,Debts!$E$13,999),IF(I14>0,Debts!$E$14,999),IF(J14>0,Debts!$E$15,999))),MAX(0,(B15-(MIN(C14+0,C14*(1+Debts!$C$8/12))*0+MIN(C14*(1+Debts!$C$8/12),Debts!$D$8)+MIN(C14+0,D14*(1+Debts!$C$9/12))*0+MIN(D14*(1+Debts!$C$9/12),Debts!$D$9)+MIN(C14+0,E14*(1+Debts!$C$10/12))*0+MIN(E14*(1+Debts!$C$10/12),Debts!$D$10)+MIN(C14+0,F14*(1+Debts!$C$11/12))*0+MIN(F14*(1+Debts!$C$11/12),Debts!$D$11)+MIN(C14+0,G14*(1+Debts!$C$12/12))*0+MIN(G14*(1+Debts!$C$12/12),Debts!$D$12)+MIN(C14+0,H14*(1+Debts!$C$13/12))*0+MIN(H14*(1+Debts!$C$13/12),Debts!$D$13)+MIN(C14+0,I14*(1+Debts!$C$14/12))*0+MIN(I14*(1+Debts!$C$14/12),Debts!$D$14)+MIN(C14+0,J14*(1+Debts!$C$15/12))*0+MIN(J14*(1+Debts!$C$15/12),Debts!$D$15)))),0))) -> 0 | J15: =IF(J14<=0,0,MAX(0,J14*(1+Debts!$C$15/12)-MIN(J14*(1+Debts!$C$15/12),Debts!$D$15)-IF(AND(J14>0,Debts!$E$15=MIN(IF(C14>0,Debts!$E$8,999),IF(D14>0,Debts!$E$9,999),IF(E14>0,Debts!$E$10,999),IF(F14>0,Debts!$E$11,999),IF(G14>0,Debts!$E$12,999),IF(H14>0,Debts!$E$13,999),IF(I14>0,Debts!$E$14,999),IF(J14>0,Debts!$E$15,999))),MAX(0,(B15-(MIN(C14+0,C14*(1+Debts!$C$8/12))*0+MIN(C14*(1+Debts!$C$8/12),Debts!$D$8)+MIN(C14+0,D14*(1+Debts!$C$9/12))*0+MIN(D14*(1+Debts!$C$9/12),Debts!$D$9)+MIN(C14+0,E14*(1+Debts!$C$10/12))*0+MIN(E14*(1+Debts!$C$10/12),Debts!$D$10)+MIN(C14+0,F14*(1+Debts!$C$11/12))*0+MIN(F14*(1+Debts!$C$11/12),Debts!$D$11)+MIN(C14+0,G14*(1+Debts!$C$12/12))*0+MIN(G14*(1+Debts!$C$12/12),Debts!$D$12)+MIN(C14+0,H14*(1+Debts!$C$13/12))*0+MIN(H14*(1+Debts!$C$13/12),Debts!$D$13)+MIN(C14+0,I14*(1+Debts!$C$14/12))*0+MIN(I14*(1+Debts!$C$14/12),Debts!$D$14)+MIN(C14+0,J14*(1+Debts!$C$15/12))*0+MIN(J14*(1+Debts!$C$15/12),Debts!$D$15)))),0))) -> 0 | K15: =IF(C14>0,C14*Debts!$C$8/12,0)+IF(D14>0,D14*Debts!$C$9/12,0)+IF(E14>0,E14*Debts!$C$10/12,0)+IF(F14>0,F14*Debts!$C$11/12,0)+IF(G14>0,G14*Debts!$C$12/12,0)+IF(H14>0,H14*Debts!$C$13/12,0)+IF(I14>0,I14*Debts!$C$14/12,0)+IF(J14>0,J14*Debts!$C$15/12,0) -> 240.97341 | L15: =SUM(C15:J15) -> 32470.28
A16: =9 -> 9 | B16: =IF(L15<=0,0,Debts!$D$16+Debts!$B$4) -> 1200 | C16: =IF(C15<=0,0,MAX(0,C15*(1+Debts!$C$8/12)-MIN(C15*(1+Debts!$C$8/12),Debts!$D$8)-IF(AND(C15>0,Debts!$E$8=MIN(IF(C15>0,Debts!$E$8,999),IF(D15>0,Debts!$E$9,999),IF(E15>0,Debts!$E$10,999),IF(F15>0,Debts!$E$11,999),IF(G15>0,Debts!$E$12,999),IF(H15>0,Debts!$E$13,999),IF(I15>0,Debts!$E$14,999),IF(J15>0,Debts!$E$15,999))),MAX(0,(B16-(MIN(C15+0,C15*(1+Debts!$C$8/12))*0+MIN(C15*(1+Debts!$C$8/12),Debts!$D$8)+MIN(C15+0,D15*(1+Debts!$C$9/12))*0+MIN(D15*(1+Debts!$C$9/12),Debts!$D$9)+MIN(C15+0,E15*(1+Debts!$C$10/12))*0+MIN(E15*(1+Debts!$C$10/12),Debts!$D$10)+MIN(C15+0,F15*(1+Debts!$C$11/12))*0+MIN(F15*(1+Debts!$C$11/12),Debts!$D$11)+MIN(C15+0,G15*(1+Debts!$C$12/12))*0+MIN(G15*(1+Debts!$C$12/12),Debts!$D$12)+MIN(C15+0,H15*(1+Debts!$C$13/12))*0+MIN(H15*(1+Debts!$C$13/12),Debts!$D$13)+MIN(C15+0,I15*(1+Debts!$C$14/12))*0+MIN(I15*(1+Debts!$C$14/12),Debts!$D$14)+MIN(C15+0,J15*(1+Debts!$C$15/12))*0+MIN(J15*(1+Debts!$C$15/12),Debts!$D$15)))),0))) -> 2028.4566 | D16: =IF(D15<=0,0,MAX(0,D15*(1+Debts!$C$9/12)-MIN(D15*(1+Debts!$C$9/12),Debts!$D$9)-IF(AND(D15>0,Debts!$E$9=MIN(IF(C15>0,Debts!$E$8,999),IF(D15>0,Debts!$E$9,999),IF(E15>0,Debts!$E$10,999),IF(F15>0,Debts!$E$11,999),IF(G15>0,Debts!$E$12,999),IF(H15>0,Debts!$E$13,999),IF(I15>0,Debts!$E$14,999),IF(J15>0,Debts!$E$15,999))),MAX(0,(B16-(MIN(C15+0,C15*(1+Debts!$C$8/12))*0+MIN(C15*(1+Debts!$C$8/12),Debts!$D$8)+MIN(C15+0,D15*(1+Debts!$C$9/12))*0+MIN(D15*(1+Debts!$C$9/12),Debts!$D$9)+MIN(C15+0,E15*(1+Debts!$C$10/12))*0+MIN(E15*(1+Debts!$C$10/12),Debts!$D$10)+MIN(C15+0,F15*(1+Debts!$C$11/12))*0+MIN(F15*(1+Debts!$C$11/12),Debts!$D$11)+MIN(C15+0,G15*(1+Debts!$C$12/12))*0+MIN(G15*(1+Debts!$C$12/12),Debts!$D$12)+MIN(C15+0,H15*(1+Debts!$C$13/12))*0+MIN(H15*(1+Debts!$C$13/12),Debts!$D$13)+MIN(C15+0,I15*(1+Debts!$C$14/12))*0+MIN(I15*(1+Debts!$C$14/12),Debts!$D$14)+MIN(C15+0,J15*(1+Debts!$C$15/12))*0+MIN(J15*(1+Debts!$C$15/12),Debts!$D$15)))),0))) -> 2097.8044 | E16: =IF(E15<=0,0,MAX(0,E15*(1+Debts!$C$10/12)-MIN(E15*(1+Debts!$C$10/12),Debts!$D$10)-IF(AND(E15>0,Debts!$E$10=MIN(IF(C15>0,Debts!$E$8,999),IF(D15>0,Debts!$E$9,999),IF(E15>0,Debts!$E$10,999),IF(F15>0,Debts!$E$11,999),IF(G15>0,Debts!$E$12,999),IF(H15>0,Debts!$E$13,999),IF(I15>0,Debts!$E$14,999),IF(J15>0,Debts!$E$15,999))),MAX(0,(B16-(MIN(C15+0,C15*(1+Debts!$C$8/12))*0+MIN(C15*(1+Debts!$C$8/12),Debts!$D$8)+MIN(C15+0,D15*(1+Debts!$C$9/12))*0+MIN(D15*(1+Debts!$C$9/12),Debts!$D$9)+MIN(C15+0,E15*(1+Debts!$C$10/12))*0+MIN(E15*(1+Debts!$C$10/12),Debts!$D$10)+MIN(C15+0,F15*(1+Debts!$C$11/12))*0+MIN(F15*(1+Debts!$C$11/12),Debts!$D$11)+MIN(C15+0,G15*(1+Debts!$C$12/12))*0+MIN(G15*(1+Debts!$C$12/12),Debts!$D$12)+MIN(C15+0,H15*(1+Debts!$C$13/12))*0+MIN(H15*(1+Debts!$C$13/12),Debts!$D$13)+MIN(C15+0,I15*(1+Debts!$C$14/12))*0+MIN(I15*(1+Debts!$C$14/12),Debts!$D$14)+MIN(C15+0,J15*(1+Debts!$C$15/12))*0+MIN(J15*(1+Debts!$C$15/12),Debts!$D$15)))),0))) -> 9569.8466 | F16: =IF(F15<=0,0,MAX(0,F15*(1+Debts!$C$11/12)-MIN(F15*(1+Debts!$C$11/12),Debts!$D$11)-IF(AND(F15>0,Debts!$E$11=MIN(IF(C15>0,Debts!$E$8,999),IF(D15>0,Debts!$E$9,999),IF(E15>0,Debts!$E$10,999),IF(F15>0,Debts!$E$11,999),IF(G15>0,Debts!$E$12,999),IF(H15>0,Debts!$E$13,999),IF(I15>0,Debts!$E$14,999),IF(J15>0,Debts!$E$15,999))),MAX(0,(B16-(MIN(C15+0,C15*(1+Debts!$C$8/12))*0+MIN(C15*(1+Debts!$C$8/12),Debts!$D$8)+MIN(C15+0,D15*(1+Debts!$C$9/12))*0+MIN(D15*(1+Debts!$C$9/12),Debts!$D$9)+MIN(C15+0,E15*(1+Debts!$C$10/12))*0+MIN(E15*(1+Debts!$C$10/12),Debts!$D$10)+MIN(C15+0,F15*(1+Debts!$C$11/12))*0+MIN(F15*(1+Debts!$C$11/12),Debts!$D$11)+MIN(C15+0,G15*(1+Debts!$C$12/12))*0+MIN(G15*(1+Debts!$C$12/12),Debts!$D$12)+MIN(C15+0,H15*(1+Debts!$C$13/12))*0+MIN(H15*(1+Debts!$C$13/12),Debts!$D$13)+MIN(C15+0,I15*(1+Debts!$C$14/12))*0+MIN(I15*(1+Debts!$C$14/12),Debts!$D$14)+MIN(C15+0,J15*(1+Debts!$C$15/12))*0+MIN(J15*(1+Debts!$C$15/12),Debts!$D$15)))),0))) -> 17352.243 | G16: =IF(G15<=0,0,MAX(0,G15*(1+Debts!$C$12/12)-MIN(G15*(1+Debts!$C$12/12),Debts!$D$12)-IF(AND(G15>0,Debts!$E$12=MIN(IF(C15>0,Debts!$E$8,999),IF(D15>0,Debts!$E$9,999),IF(E15>0,Debts!$E$10,999),IF(F15>0,Debts!$E$11,999),IF(G15>0,Debts!$E$12,999),IF(H15>0,Debts!$E$13,999),IF(I15>0,Debts!$E$14,999),IF(J15>0,Debts!$E$15,999))),MAX(0,(B16-(MIN(C15+0,C15*(1+Debts!$C$8/12))*0+MIN(C15*(1+Debts!$C$8/12),Debts!$D$8)+MIN(C15+0,D15*(1+Debts!$C$9/12))*0+MIN(D15*(1+Debts!$C$9/12),Debts!$D$9)+MIN(C15+0,E15*(1+Debts!$C$10/12))*0+MIN(E15*(1+Debts!$C$10/12),Debts!$D$10)+MIN(C15+0,F15*(1+Debts!$C$11/12))*0+MIN(F15*(1+Debts!$C$11/12),Debts!$D$11)+MIN(C15+0,G15*(1+Debts!$C$12/12))*0+MIN(G15*(1+Debts!$C$12/12),Debts!$D$12)+MIN(C15+0,H15*(1+Debts!$C$13/12))*0+MIN(H15*(1+Debts!$C$13/12),Debts!$D$13)+MIN(C15+0,I15*(1+Debts!$C$14/12))*0+MIN(I15*(1+Debts!$C$14/12),Debts!$D$14)+MIN(C15+0,J15*(1+Debts!$C$15/12))*0+MIN(J15*(1+Debts!$C$15/12),Debts!$D$15)))),0))) -> 450 | H16: =IF(H15<=0,0,MAX(0,H15*(1+Debts!$C$13/12)-MIN(H15*(1+Debts!$C$13/12),Debts!$D$13)-IF(AND(H15>0,Debts!$E$13=MIN(IF(C15>0,Debts!$E$8,999),IF(D15>0,Debts!$E$9,999),IF(E15>0,Debts!$E$10,999),IF(F15>0,Debts!$E$11,999),IF(G15>0,Debts!$E$12,999),IF(H15>0,Debts!$E$13,999),IF(I15>0,Debts!$E$14,999),IF(J15>0,Debts!$E$15,999))),MAX(0,(B16-(MIN(C15+0,C15*(1+Debts!$C$8/12))*0+MIN(C15*(1+Debts!$C$8/12),Debts!$D$8)+MIN(C15+0,D15*(1+Debts!$C$9/12))*0+MIN(D15*(1+Debts!$C$9/12),Debts!$D$9)+MIN(C15+0,E15*(1+Debts!$C$10/12))*0+MIN(E15*(1+Debts!$C$10/12),Debts!$D$10)+MIN(C15+0,F15*(1+Debts!$C$11/12))*0+MIN(F15*(1+Debts!$C$11/12),Debts!$D$11)+MIN(C15+0,G15*(1+Debts!$C$12/12))*0+MIN(G15*(1+Debts!$C$12/12),Debts!$D$12)+MIN(C15+0,H15*(1+Debts!$C$13/12))*0+MIN(H15*(1+Debts!$C$13/12),Debts!$D$13)+MIN(C15+0,I15*(1+Debts!$C$14/12))*0+MIN(I15*(1+Debts!$C$14/12),Debts!$D$14)+MIN(C15+0,J15*(1+Debts!$C$15/12))*0+MIN(J15*(1+Debts!$C$15/12),Debts!$D$15)))),0))) -> 0 | I16: =IF(I15<=0,0,MAX(0,I15*(1+Debts!$C$14/12)-MIN(I15*(1+Debts!$C$14/12),Debts!$D$14)-IF(AND(I15>0,Debts!$E$14=MIN(IF(C15>0,Debts!$E$8,999),IF(D15>0,Debts!$E$9,999),IF(E15>0,Debts!$E$10,999),IF(F15>0,Debts!$E$11,999),IF(G15>0,Debts!$E$12,999),IF(H15>0,Debts!$E$13,999),IF(I15>0,Debts!$E$14,999),IF(J15>0,Debts!$E$15,999))),MAX(0,(B16-(MIN(C15+0,C15*(1+Debts!$C$8/12))*0+MIN(C15*(1+Debts!$C$8/12),Debts!$D$8)+MIN(C15+0,D15*(1+Debts!$C$9/12))*0+MIN(D15*(1+Debts!$C$9/12),Debts!$D$9)+MIN(C15+0,E15*(1+Debts!$C$10/12))*0+MIN(E15*(1+Debts!$C$10/12),Debts!$D$10)+MIN(C15+0,F15*(1+Debts!$C$11/12))*0+MIN(F15*(1+Debts!$C$11/12),Debts!$D$11)+MIN(C15+0,G15*(1+Debts!$C$12/12))*0+MIN(G15*(1+Debts!$C$12/12),Debts!$D$12)+MIN(C15+0,H15*(1+Debts!$C$13/12))*0+MIN(H15*(1+Debts!$C$13/12),Debts!$D$13)+MIN(C15+0,I15*(1+Debts!$C$14/12))*0+MIN(I15*(1+Debts!$C$14/12),Debts!$D$14)+MIN(C15+0,J15*(1+Debts!$C$15/12))*0+MIN(J15*(1+Debts!$C$15/12),Debts!$D$15)))),0))) -> 0 | J16: =IF(J15<=0,0,MAX(0,J15*(1+Debts!$C$15/12)-MIN(J15*(1+Debts!$C$15/12),Debts!$D$15)-IF(AND(J15>0,Debts!$E$15=MIN(IF(C15>0,Debts!$E$8,999),IF(D15>0,Debts!$E$9,999),IF(E15>0,Debts!$E$10,999),IF(F15>0,Debts!$E$11,999),IF(G15>0,Debts!$E$12,999),IF(H15>0,Debts!$E$13,999),IF(I15>0,Debts!$E$14,999),IF(J15>0,Debts!$E$15,999))),MAX(0,(B16-(MIN(C15+0,C15*(1+Debts!$C$8/12))*0+MIN(C15*(1+Debts!$C$8/12),Debts!$D$8)+MIN(C15+0,D15*(1+Debts!$C$9/12))*0+MIN(D15*(1+Debts!$C$9/12),Debts!$D$9)+MIN(C15+0,E15*(1+Debts!$C$10/12))*0+MIN(E15*(1+Debts!$C$10/12),Debts!$D$10)+MIN(C15+0,F15*(1+Debts!$C$11/12))*0+MIN(F15*(1+Debts!$C$11/12),Debts!$D$11)+MIN(C15+0,G15*(1+Debts!$C$12/12))*0+MIN(G15*(1+Debts!$C$12/12),Debts!$D$12)+MIN(C15+0,H15*(1+Debts!$C$13/12))*0+MIN(H15*(1+Debts!$C$13/12),Debts!$D$13)+MIN(C15+0,I15*(1+Debts!$C$14/12))*0+MIN(I15*(1+Debts!$C$14/12),Debts!$D$14)+MIN(C15+0,J15*(1+Debts!$C$15/12))*0+MIN(J15*(1+Debts!$C$15/12),Debts!$D$15)))),0))) -> 0 | K16: =IF(C15>0,C15*Debts!$C$8/12,0)+IF(D15>0,D15*Debts!$C$9/12,0)+IF(E15>0,E15*Debts!$C$10/12,0)+IF(F15>0,F15*Debts!$C$11/12,0)+IF(G15>0,G15*Debts!$C$12/12,0)+IF(H15>0,H15*Debts!$C$13/12,0)+IF(I15>0,I15*Debts!$C$14/12,0)+IF(J15>0,J15*Debts!$C$15/12,0) -> 228.07067 | L16: =SUM(C16:J16) -> 31498.351
A17: =10 -> 10 | B17: =IF(L16<=0,0,Debts!$D$16+Debts!$B$4) -> 1200 | C17: =IF(C16<=0,0,MAX(0,C16*(1+Debts!$C$8/12)-MIN(C16*(1+Debts!$C$8/12),Debts!$D$8)-IF(AND(C16>0,Debts!$E$8=MIN(IF(C16>0,Debts!$E$8,999),IF(D16>0,Debts!$E$9,999),IF(E16>0,Debts!$E$10,999),IF(F16>0,Debts!$E$11,999),IF(G16>0,Debts!$E$12,999),IF(H16>0,Debts!$E$13,999),IF(I16>0,Debts!$E$14,999),IF(J16>0,Debts!$E$15,999))),MAX(0,(B17-(MIN(C16+0,C16*(1+Debts!$C$8/12))*0+MIN(C16*(1+Debts!$C$8/12),Debts!$D$8)+MIN(C16+0,D16*(1+Debts!$C$9/12))*0+MIN(D16*(1+Debts!$C$9/12),Debts!$D$9)+MIN(C16+0,E16*(1+Debts!$C$10/12))*0+MIN(E16*(1+Debts!$C$10/12),Debts!$D$10)+MIN(C16+0,F16*(1+Debts!$C$11/12))*0+MIN(F16*(1+Debts!$C$11/12),Debts!$D$11)+MIN(C16+0,G16*(1+Debts!$C$12/12))*0+MIN(G16*(1+Debts!$C$12/12),Debts!$D$12)+MIN(C16+0,H16*(1+Debts!$C$13/12))*0+MIN(H16*(1+Debts!$C$13/12),Debts!$D$13)+MIN(C16+0,I16*(1+Debts!$C$14/12))*0+MIN(I16*(1+Debts!$C$14/12),Debts!$D$14)+MIN(C16+0,J16*(1+Debts!$C$15/12))*0+MIN(J16*(1+Debts!$C$15/12),Debts!$D$15)))),0))) -> 1515.5471 | D17: =IF(D16<=0,0,MAX(0,D16*(1+Debts!$C$9/12)-MIN(D16*(1+Debts!$C$9/12),Debts!$D$9)-IF(AND(D16>0,Debts!$E$9=MIN(IF(C16>0,Debts!$E$8,999),IF(D16>0,Debts!$E$9,999),IF(E16>0,Debts!$E$10,999),IF(F16>0,Debts!$E$11,999),IF(G16>0,Debts!$E$12,999),IF(H16>0,Debts!$E$13,999),IF(I16>0,Debts!$E$14,999),IF(J16>0,Debts!$E$15,999))),MAX(0,(B17-(MIN(C16+0,C16*(1+Debts!$C$8/12))*0+MIN(C16*(1+Debts!$C$8/12),Debts!$D$8)+MIN(C16+0,D16*(1+Debts!$C$9/12))*0+MIN(D16*(1+Debts!$C$9/12),Debts!$D$9)+MIN(C16+0,E16*(1+Debts!$C$10/12))*0+MIN(E16*(1+Debts!$C$10/12),Debts!$D$10)+MIN(C16+0,F16*(1+Debts!$C$11/12))*0+MIN(F16*(1+Debts!$C$11/12),Debts!$D$11)+MIN(C16+0,G16*(1+Debts!$C$12/12))*0+MIN(G16*(1+Debts!$C$12/12),Debts!$D$12)+MIN(C16+0,H16*(1+Debts!$C$13/12))*0+MIN(H16*(1+Debts!$C$13/12),Debts!$D$13)+MIN(C16+0,I16*(1+Debts!$C$14/12))*0+MIN(I16*(1+Debts!$C$14/12),Debts!$D$14)+MIN(C16+0,J16*(1+Debts!$C$15/12))*0+MIN(J16*(1+Debts!$C$15/12),Debts!$D$15)))),0))) -> 2061.0893 | E17: =IF(E16<=0,0,MAX(0,E16*(1+Debts!$C$10/12)-MIN(E16*(1+Debts!$C$10/12),Debts!$D$10)-IF(AND(E16>0,Debts!$E$10=MIN(IF(C16>0,Debts!$E$8,999),IF(D16>0,Debts!$E$9,999),IF(E16>0,Debts!$E$10,999),IF(F16>0,Debts!$E$11,999),IF(G16>0,Debts!$E$12,999),IF(H16>0,Debts!$E$13,999),IF(I16>0,Debts!$E$14,999),IF(J16>0,Debts!$E$15,999))),MAX(0,(B17-(MIN(C16+0,C16*(1+Debts!$C$8/12))*0+MIN(C16*(1+Debts!$C$8/12),Debts!$D$8)+MIN(C16+0,D16*(1+Debts!$C$9/12))*0+MIN(D16*(1+Debts!$C$9/12),Debts!$D$9)+MIN(C16+0,E16*(1+Debts!$C$10/12))*0+MIN(E16*(1+Debts!$C$10/12),Debts!$D$10)+MIN(C16+0,F16*(1+Debts!$C$11/12))*0+MIN(F16*(1+Debts!$C$11/12),Debts!$D$11)+MIN(C16+0,G16*(1+Debts!$C$12/12))*0+MIN(G16*(1+Debts!$C$12/12),Debts!$D$12)+MIN(C16+0,H16*(1+Debts!$C$13/12))*0+MIN(H16*(1+Debts!$C$13/12),Debts!$D$13)+MIN(C16+0,I16*(1+Debts!$C$14/12))*0+MIN(I16*(1+Debts!$C$14/12),Debts!$D$14)+MIN(C16+0,J16*(1+Debts!$C$15/12))*0+MIN(J16*(1+Debts!$C$15/12),Debts!$D$15)))),0))) -> 9314.8732 | F17: =IF(F16<=0,0,MAX(0,F16*(1+Debts!$C$11/12)-MIN(F16*(1+Debts!$C$11/12),Debts!$D$11)-IF(AND(F16>0,Debts!$E$11=MIN(IF(C16>0,Debts!$E$8,999),IF(D16>0,Debts!$E$9,999),IF(E16>0,Debts!$E$10,999),IF(F16>0,Debts!$E$11,999),IF(G16>0,Debts!$E$12,999),IF(H16>0,Debts!$E$13,999),IF(I16>0,Debts!$E$14,999),IF(J16>0,Debts!$E$15,999))),MAX(0,(B17-(MIN(C16+0,C16*(1+Debts!$C$8/12))*0+MIN(C16*(1+Debts!$C$8/12),Debts!$D$8)+MIN(C16+0,D16*(1+Debts!$C$9/12))*0+MIN(D16*(1+Debts!$C$9/12),Debts!$D$9)+MIN(C16+0,E16*(1+Debts!$C$10/12))*0+MIN(E16*(1+Debts!$C$10/12),Debts!$D$10)+MIN(C16+0,F16*(1+Debts!$C$11/12))*0+MIN(F16*(1+Debts!$C$11/12),Debts!$D$11)+MIN(C16+0,G16*(1+Debts!$C$12/12))*0+MIN(G16*(1+Debts!$C$12/12),Debts!$D$12)+MIN(C16+0,H16*(1+Debts!$C$13/12))*0+MIN(H16*(1+Debts!$C$13/12),Debts!$D$13)+MIN(C16+0,I16*(1+Debts!$C$14/12))*0+MIN(I16*(1+Debts!$C$14/12),Debts!$D$14)+MIN(C16+0,J16*(1+Debts!$C$15/12))*0+MIN(J16*(1+Debts!$C$15/12),Debts!$D$15)))),0))) -> 17221.774 | G17: =IF(G16<=0,0,MAX(0,G16*(1+Debts!$C$12/12)-MIN(G16*(1+Debts!$C$12/12),Debts!$D$12)-IF(AND(G16>0,Debts!$E$12=MIN(IF(C16>0,Debts!$E$8,999),IF(D16>0,Debts!$E$9,999),IF(E16>0,Debts!$E$10,999),IF(F16>0,Debts!$E$11,999),IF(G16>0,Debts!$E$12,999),IF(H16>0,Debts!$E$13,999),IF(I16>0,Debts!$E$14,999),IF(J16>0,Debts!$E$15,999))),MAX(0,(B17-(MIN(C16+0,C16*(1+Debts!$C$8/12))*0+MIN(C16*(1+Debts!$C$8/12),Debts!$D$8)+MIN(C16+0,D16*(1+Debts!$C$9/12))*0+MIN(D16*(1+Debts!$C$9/12),Debts!$D$9)+MIN(C16+0,E16*(1+Debts!$C$10/12))*0+MIN(E16*(1+Debts!$C$10/12),Debts!$D$10)+MIN(C16+0,F16*(1+Debts!$C$11/12))*0+MIN(F16*(1+Debts!$C$11/12),Debts!$D$11)+MIN(C16+0,G16*(1+Debts!$C$12/12))*0+MIN(G16*(1+Debts!$C$12/12),Debts!$D$12)+MIN(C16+0,H16*(1+Debts!$C$13/12))*0+MIN(H16*(1+Debts!$C$13/12),Debts!$D$13)+MIN(C16+0,I16*(1+Debts!$C$14/12))*0+MIN(I16*(1+Debts!$C$14/12),Debts!$D$14)+MIN(C16+0,J16*(1+Debts!$C$15/12))*0+MIN(J16*(1+Debts!$C$15/12),Debts!$D$15)))),0))) -> 400 | H17: =IF(H16<=0,0,MAX(0,H16*(1+Debts!$C$13/12)-MIN(H16*(1+Debts!$C$13/12),Debts!$D$13)-IF(AND(H16>0,Debts!$E$13=MIN(IF(C16>0,Debts!$E$8,999),IF(D16>0,Debts!$E$9,999),IF(E16>0,Debts!$E$10,999),IF(F16>0,Debts!$E$11,999),IF(G16>0,Debts!$E$12,999),IF(H16>0,Debts!$E$13,999),IF(I16>0,Debts!$E$14,999),IF(J16>0,Debts!$E$15,999))),MAX(0,(B17-(MIN(C16+0,C16*(1+Debts!$C$8/12))*0+MIN(C16*(1+Debts!$C$8/12),Debts!$D$8)+MIN(C16+0,D16*(1+Debts!$C$9/12))*0+MIN(D16*(1+Debts!$C$9/12),Debts!$D$9)+MIN(C16+0,E16*(1+Debts!$C$10/12))*0+MIN(E16*(1+Debts!$C$10/12),Debts!$D$10)+MIN(C16+0,F16*(1+Debts!$C$11/12))*0+MIN(F16*(1+Debts!$C$11/12),Debts!$D$11)+MIN(C16+0,G16*(1+Debts!$C$12/12))*0+MIN(G16*(1+Debts!$C$12/12),Debts!$D$12)+MIN(C16+0,H16*(1+Debts!$C$13/12))*0+MIN(H16*(1+Debts!$C$13/12),Debts!$D$13)+MIN(C16+0,I16*(1+Debts!$C$14/12))*0+MIN(I16*(1+Debts!$C$14/12),Debts!$D$14)+MIN(C16+0,J16*(1+Debts!$C$15/12))*0+MIN(J16*(1+Debts!$C$15/12),Debts!$D$15)))),0))) -> 0 | I17: =IF(I16<=0,0,MAX(0,I16*(1+Debts!$C$14/12)-MIN(I16*(1+Debts!$C$14/12),Debts!$D$14)-IF(AND(I16>0,Debts!$E$14=MIN(IF(C16>0,Debts!$E$8,999),IF(D16>0,Debts!$E$9,999),IF(E16>0,Debts!$E$10,999),IF(F16>0,Debts!$E$11,999),IF(G16>0,Debts!$E$12,999),IF(H16>0,Debts!$E$13,999),IF(I16>0,Debts!$E$14,999),IF(J16>0,Debts!$E$15,999))),MAX(0,(B17-(MIN(C16+0,C16*(1+Debts!$C$8/12))*0+MIN(C16*(1+Debts!$C$8/12),Debts!$D$8)+MIN(C16+0,D16*(1+Debts!$C$9/12))*0+MIN(D16*(1+Debts!$C$9/12),Debts!$D$9)+MIN(C16+0,E16*(1+Debts!$C$10/12))*0+MIN(E16*(1+Debts!$C$10/12),Debts!$D$10)+MIN(C16+0,F16*(1+Debts!$C$11/12))*0+MIN(F16*(1+Debts!$C$11/12),Debts!$D$11)+MIN(C16+0,G16*(1+Debts!$C$12/12))*0+MIN(G16*(1+Debts!$C$12/12),Debts!$D$12)+MIN(C16+0,H16*(1+Debts!$C$13/12))*0+MIN(H16*(1+Debts!$C$13/12),Debts!$D$13)+MIN(C16+0,I16*(1+Debts!$C$14/12))*0+MIN(I16*(1+Debts!$C$14/12),Debts!$D$14)+MIN(C16+0,J16*(1+Debts!$C$15/12))*0+MIN(J16*(1+Debts!$C$15/12),Debts!$D$15)))),0))) -> 0 | J17: =IF(J16<=0,0,MAX(0,J16*(1+Debts!$C$15/12)-MIN(J16*(1+Debts!$C$15/12),Debts!$D$15)-IF(AND(J16>0,Debts!$E$15=MIN(IF(C16>0,Debts!$E$8,999),IF(D16>0,Debts!$E$9,999),IF(E16>0,Debts!$E$10,999),IF(F16>0,Debts!$E$11,999),IF(G16>0,Debts!$E$12,999),IF(H16>0,Debts!$E$13,999),IF(I16>0,Debts!$E$14,999),IF(J16>0,Debts!$E$15,999))),MAX(0,(B17-(MIN(C16+0,C16*(1+Debts!$C$8/12))*0+MIN(C16*(1+Debts!$C$8/12),Debts!$D$8)+MIN(C16+0,D16*(1+Debts!$C$9/12))*0+MIN(D16*(1+Debts!$C$9/12),Debts!$D$9)+MIN(C16+0,E16*(1+Debts!$C$10/12))*0+MIN(E16*(1+Debts!$C$10/12),Debts!$D$10)+MIN(C16+0,F16*(1+Debts!$C$11/12))*0+MIN(F16*(1+Debts!$C$11/12),Debts!$D$11)+MIN(C16+0,G16*(1+Debts!$C$12/12))*0+MIN(G16*(1+Debts!$C$12/12),Debts!$D$12)+MIN(C16+0,H16*(1+Debts!$C$13/12))*0+MIN(H16*(1+Debts!$C$13/12),Debts!$D$13)+MIN(C16+0,I16*(1+Debts!$C$14/12))*0+MIN(I16*(1+Debts!$C$14/12),Debts!$D$14)+MIN(C16+0,J16*(1+Debts!$C$15/12))*0+MIN(J16*(1+Debts!$C$15/12),Debts!$D$15)))),0))) -> 0 | K17: =IF(C16>0,C16*Debts!$C$8/12,0)+IF(D16>0,D16*Debts!$C$9/12,0)+IF(E16>0,E16*Debts!$C$10/12,0)+IF(F16>0,F16*Debts!$C$11/12,0)+IF(G16>0,G16*Debts!$C$12/12,0)+IF(H16>0,H16*Debts!$C$13/12,0)+IF(I16>0,I16*Debts!$C$14/12,0)+IF(J16>0,J16*Debts!$C$15/12,0) -> 214.93314 | L17: =SUM(C17:J17) -> 30513.284
A18: =11 -> 11 | B18: =IF(L17<=0,0,Debts!$D$16+Debts!$B$4) -> 1200 | C18: =IF(C17<=0,0,MAX(0,C17*(1+Debts!$C$8/12)-MIN(C17*(1+Debts!$C$8/12),Debts!$D$8)-IF(AND(C17>0,Debts!$E$8=MIN(IF(C17>0,Debts!$E$8,999),IF(D17>0,Debts!$E$9,999),IF(E17>0,Debts!$E$10,999),IF(F17>0,Debts!$E$11,999),IF(G17>0,Debts!$E$12,999),IF(H17>0,Debts!$E$13,999),IF(I17>0,Debts!$E$14,999),IF(J17>0,Debts!$E$15,999))),MAX(0,(B18-(MIN(C17+0,C17*(1+Debts!$C$8/12))*0+MIN(C17*(1+Debts!$C$8/12),Debts!$D$8)+MIN(C17+0,D17*(1+Debts!$C$9/12))*0+MIN(D17*(1+Debts!$C$9/12),Debts!$D$9)+MIN(C17+0,E17*(1+Debts!$C$10/12))*0+MIN(E17*(1+Debts!$C$10/12),Debts!$D$10)+MIN(C17+0,F17*(1+Debts!$C$11/12))*0+MIN(F17*(1+Debts!$C$11/12),Debts!$D$11)+MIN(C17+0,G17*(1+Debts!$C$12/12))*0+MIN(G17*(1+Debts!$C$12/12),Debts!$D$12)+MIN(C17+0,H17*(1+Debts!$C$13/12))*0+MIN(H17*(1+Debts!$C$13/12),Debts!$D$13)+MIN(C17+0,I17*(1+Debts!$C$14/12))*0+MIN(I17*(1+Debts!$C$14/12),Debts!$D$14)+MIN(C17+0,J17*(1+Debts!$C$15/12))*0+MIN(J17*(1+Debts!$C$15/12),Debts!$D$15)))),0))) -> 991.99468 | D18: =IF(D17<=0,0,MAX(0,D17*(1+Debts!$C$9/12)-MIN(D17*(1+Debts!$C$9/12),Debts!$D$9)-IF(AND(D17>0,Debts!$E$9=MIN(IF(C17>0,Debts!$E$8,999),IF(D17>0,Debts!$E$9,999),IF(E17>0,Debts!$E$10,999),IF(F17>0,Debts!$E$11,999),IF(G17>0,Debts!$E$12,999),IF(H17>0,Debts!$E$13,999),IF(I17>0,Debts!$E$14,999),IF(J17>0,Debts!$E$15,999))),MAX(0,(B18-(MIN(C17+0,C17*(1+Debts!$C$8/12))*0+MIN(C17*(1+Debts!$C$8/12),Debts!$D$8)+MIN(C17+0,D17*(1+Debts!$C$9/12))*0+MIN(D17*(1+Debts!$C$9/12),Debts!$D$9)+MIN(C17+0,E17*(1+Debts!$C$10/12))*0+MIN(E17*(1+Debts!$C$10/12),Debts!$D$10)+MIN(C17+0,F17*(1+Debts!$C$11/12))*0+MIN(F17*(1+Debts!$C$11/12),Debts!$D$11)+MIN(C17+0,G17*(1+Debts!$C$12/12))*0+MIN(G17*(1+Debts!$C$12/12),Debts!$D$12)+MIN(C17+0,H17*(1+Debts!$C$13/12))*0+MIN(H17*(1+Debts!$C$13/12),Debts!$D$13)+MIN(C17+0,I17*(1+Debts!$C$14/12))*0+MIN(I17*(1+Debts!$C$14/12),Debts!$D$14)+MIN(C17+0,J17*(1+Debts!$C$15/12))*0+MIN(J17*(1+Debts!$C$15/12),Debts!$D$15)))),0))) -> 2023.7042 | E18: =IF(E17<=0,0,MAX(0,E17*(1+Debts!$C$10/12)-MIN(E17*(1+Debts!$C$10/12),Debts!$D$10)-IF(AND(E17>0,Debts!$E$10=MIN(IF(C17>0,Debts!$E$8,999),IF(D17>0,Debts!$E$9,999),IF(E17>0,Debts!$E$10,999),IF(F17>0,Debts!$E$11,999),IF(G17>0,Debts!$E$12,999),IF(H17>0,Debts!$E$13,999),IF(I17>0,Debts!$E$14,999),IF(J17>0,Debts!$E$15,999))),MAX(0,(B18-(MIN(C17+0,C17*(1+Debts!$C$8/12))*0+MIN(C17*(1+Debts!$C$8/12),Debts!$D$8)+MIN(C17+0,D17*(1+Debts!$C$9/12))*0+MIN(D17*(1+Debts!$C$9/12),Debts!$D$9)+MIN(C17+0,E17*(1+Debts!$C$10/12))*0+MIN(E17*(1+Debts!$C$10/12),Debts!$D$10)+MIN(C17+0,F17*(1+Debts!$C$11/12))*0+MIN(F17*(1+Debts!$C$11/12),Debts!$D$11)+MIN(C17+0,G17*(1+Debts!$C$12/12))*0+MIN(G17*(1+Debts!$C$12/12),Debts!$D$12)+MIN(C17+0,H17*(1+Debts!$C$13/12))*0+MIN(H17*(1+Debts!$C$13/12),Debts!$D$13)+MIN(C17+0,I17*(1+Debts!$C$14/12))*0+MIN(I17*(1+Debts!$C$14/12),Debts!$D$14)+MIN(C17+0,J17*(1+Debts!$C$15/12))*0+MIN(J17*(1+Debts!$C$15/12),Debts!$D$15)))),0))) -> 9058.4337 | F18: =IF(F17<=0,0,MAX(0,F17*(1+Debts!$C$11/12)-MIN(F17*(1+Debts!$C$11/12),Debts!$D$11)-IF(AND(F17>0,Debts!$E$11=MIN(IF(C17>0,Debts!$E$8,999),IF(D17>0,Debts!$E$9,999),IF(E17>0,Debts!$E$10,999),IF(F17>0,Debts!$E$11,999),IF(G17>0,Debts!$E$12,999),IF(H17>0,Debts!$E$13,999),IF(I17>0,Debts!$E$14,999),IF(J17>0,Debts!$E$15,999))),MAX(0,(B18-(MIN(C17+0,C17*(1+Debts!$C$8/12))*0+MIN(C17*(1+Debts!$C$8/12),Debts!$D$8)+MIN(C17+0,D17*(1+Debts!$C$9/12))*0+MIN(D17*(1+Debts!$C$9/12),Debts!$D$9)+MIN(C17+0,E17*(1+Debts!$C$10/12))*0+MIN(E17*(1+Debts!$C$10/12),Debts!$D$10)+MIN(C17+0,F17*(1+Debts!$C$11/12))*0+MIN(F17*(1+Debts!$C$11/12),Debts!$D$11)+MIN(C17+0,G17*(1+Debts!$C$12/12))*0+MIN(G17*(1+Debts!$C$12/12),Debts!$D$12)+MIN(C17+0,H17*(1+Debts!$C$13/12))*0+MIN(H17*(1+Debts!$C$13/12),Debts!$D$13)+MIN(C17+0,I17*(1+Debts!$C$14/12))*0+MIN(I17*(1+Debts!$C$14/12),Debts!$D$14)+MIN(C17+0,J17*(1+Debts!$C$15/12))*0+MIN(J17*(1+Debts!$C$15/12),Debts!$D$15)))),0))) -> 17090.707 | G18: =IF(G17<=0,0,MAX(0,G17*(1+Debts!$C$12/12)-MIN(G17*(1+Debts!$C$12/12),Debts!$D$12)-IF(AND(G17>0,Debts!$E$12=MIN(IF(C17>0,Debts!$E$8,999),IF(D17>0,Debts!$E$9,999),IF(E17>0,Debts!$E$10,999),IF(F17>0,Debts!$E$11,999),IF(G17>0,Debts!$E$12,999),IF(H17>0,Debts!$E$13,999),IF(I17>0,Debts!$E$14,999),IF(J17>0,Debts!$E$15,999))),MAX(0,(B18-(MIN(C17+0,C17*(1+Debts!$C$8/12))*0+MIN(C17*(1+Debts!$C$8/12),Debts!$D$8)+MIN(C17+0,D17*(1+Debts!$C$9/12))*0+MIN(D17*(1+Debts!$C$9/12),Debts!$D$9)+MIN(C17+0,E17*(1+Debts!$C$10/12))*0+MIN(E17*(1+Debts!$C$10/12),Debts!$D$10)+MIN(C17+0,F17*(1+Debts!$C$11/12))*0+MIN(F17*(1+Debts!$C$11/12),Debts!$D$11)+MIN(C17+0,G17*(1+Debts!$C$12/12))*0+MIN(G17*(1+Debts!$C$12/12),Debts!$D$12)+MIN(C17+0,H17*(1+Debts!$C$13/12))*0+MIN(H17*(1+Debts!$C$13/12),Debts!$D$13)+MIN(C17+0,I17*(1+Debts!$C$14/12))*0+MIN(I17*(1+Debts!$C$14/12),Debts!$D$14)+MIN(C17+0,J17*(1+Debts!$C$15/12))*0+MIN(J17*(1+Debts!$C$15/12),Debts!$D$15)))),0))) -> 350 | H18: =IF(H17<=0,0,MAX(0,H17*(1+Debts!$C$13/12)-MIN(H17*(1+Debts!$C$13/12),Debts!$D$13)-IF(AND(H17>0,Debts!$E$13=MIN(IF(C17>0,Debts!$E$8,999),IF(D17>0,Debts!$E$9,999),IF(E17>0,Debts!$E$10,999),IF(F17>0,Debts!$E$11,999),IF(G17>0,Debts!$E$12,999),IF(H17>0,Debts!$E$13,999),IF(I17>0,Debts!$E$14,999),IF(J17>0,Debts!$E$15,999))),MAX(0,(B18-(MIN(C17+0,C17*(1+Debts!$C$8/12))*0+MIN(C17*(1+Debts!$C$8/12),Debts!$D$8)+MIN(C17+0,D17*(1+Debts!$C$9/12))*0+MIN(D17*(1+Debts!$C$9/12),Debts!$D$9)+MIN(C17+0,E17*(1+Debts!$C$10/12))*0+MIN(E17*(1+Debts!$C$10/12),Debts!$D$10)+MIN(C17+0,F17*(1+Debts!$C$11/12))*0+MIN(F17*(1+Debts!$C$11/12),Debts!$D$11)+MIN(C17+0,G17*(1+Debts!$C$12/12))*0+MIN(G17*(1+Debts!$C$12/12),Debts!$D$12)+MIN(C17+0,H17*(1+Debts!$C$13/12))*0+MIN(H17*(1+Debts!$C$13/12),Debts!$D$13)+MIN(C17+0,I17*(1+Debts!$C$14/12))*0+MIN(I17*(1+Debts!$C$14/12),Debts!$D$14)+MIN(C17+0,J17*(1+Debts!$C$15/12))*0+MIN(J17*(1+Debts!$C$15/12),Debts!$D$15)))),0))) -> 0 | I18: =IF(I17<=0,0,MAX(0,I17*(1+Debts!$C$14/12)-MIN(I17*(1+Debts!$C$14/12),Debts!$D$14)-IF(AND(I17>0,Debts!$E$14=MIN(IF(C17>0,Debts!$E$8,999),IF(D17>0,Debts!$E$9,999),IF(E17>0,Debts!$E$10,999),IF(F17>0,Debts!$E$11,999),IF(G17>0,Debts!$E$12,999),IF(H17>0,Debts!$E$13,999),IF(I17>0,Debts!$E$14,999),IF(J17>0,Debts!$E$15,999))),MAX(0,(B18-(MIN(C17+0,C17*(1+Debts!$C$8/12))*0+MIN(C17*(1+Debts!$C$8/12),Debts!$D$8)+MIN(C17+0,D17*(1+Debts!$C$9/12))*0+MIN(D17*(1+Debts!$C$9/12),Debts!$D$9)+MIN(C17+0,E17*(1+Debts!$C$10/12))*0+MIN(E17*(1+Debts!$C$10/12),Debts!$D$10)+MIN(C17+0,F17*(1+Debts!$C$11/12))*0+MIN(F17*(1+Debts!$C$11/12),Debts!$D$11)+MIN(C17+0,G17*(1+Debts!$C$12/12))*0+MIN(G17*(1+Debts!$C$12/12),Debts!$D$12)+MIN(C17+0,H17*(1+Debts!$C$13/12))*0+MIN(H17*(1+Debts!$C$13/12),Debts!$D$13)+MIN(C17+0,I17*(1+Debts!$C$14/12))*0+MIN(I17*(1+Debts!$C$14/12),Debts!$D$14)+MIN(C17+0,J17*(1+Debts!$C$15/12))*0+MIN(J17*(1+Debts!$C$15/12),Debts!$D$15)))),0))) -> 0 | J18: =IF(J17<=0,0,MAX(0,J17*(1+Debts!$C$15/12)-MIN(J17*(1+Debts!$C$15/12),Debts!$D$15)-IF(AND(J17>0,Debts!$E$15=MIN(IF(C17>0,Debts!$E$8,999),IF(D17>0,Debts!$E$9,999),IF(E17>0,Debts!$E$10,999),IF(F17>0,Debts!$E$11,999),IF(G17>0,Debts!$E$12,999),IF(H17>0,Debts!$E$13,999),IF(I17>0,Debts!$E$14,999),IF(J17>0,Debts!$E$15,999))),MAX(0,(B18-(MIN(C17+0,C17*(1+Debts!$C$8/12))*0+MIN(C17*(1+Debts!$C$8/12),Debts!$D$8)+MIN(C17+0,D17*(1+Debts!$C$9/12))*0+MIN(D17*(1+Debts!$C$9/12),Debts!$D$9)+MIN(C17+0,E17*(1+Debts!$C$10/12))*0+MIN(E17*(1+Debts!$C$10/12),Debts!$D$10)+MIN(C17+0,F17*(1+Debts!$C$11/12))*0+MIN(F17*(1+Debts!$C$11/12),Debts!$D$11)+MIN(C17+0,G17*(1+Debts!$C$12/12))*0+MIN(G17*(1+Debts!$C$12/12),Debts!$D$12)+MIN(C17+0,H17*(1+Debts!$C$13/12))*0+MIN(H17*(1+Debts!$C$13/12),Debts!$D$13)+MIN(C17+0,I17*(1+Debts!$C$14/12))*0+MIN(I17*(1+Debts!$C$14/12),Debts!$D$14)+MIN(C17+0,J17*(1+Debts!$C$15/12))*0+MIN(J17*(1+Debts!$C$15/12),Debts!$D$15)))),0))) -> 0 | K18: =IF(C17>0,C17*Debts!$C$8/12,0)+IF(D17>0,D17*Debts!$C$9/12,0)+IF(E17>0,E17*Debts!$C$10/12,0)+IF(F17>0,F17*Debts!$C$11/12,0)+IF(G17>0,G17*Debts!$C$12/12,0)+IF(H17>0,H17*Debts!$C$13/12,0)+IF(I17>0,I17*Debts!$C$14/12,0)+IF(J17>0,J17*Debts!$C$15/12,0) -> 201.55613 | L18: =SUM(C18:J18) -> 29514.84
A19: =12 -> 12 | B19: =IF(L18<=0,0,Debts!$D$16+Debts!$B$4) -> 1200 | C19: =IF(C18<=0,0,MAX(0,C18*(1+Debts!$C$8/12)-MIN(C18*(1+Debts!$C$8/12),Debts!$D$8)-IF(AND(C18>0,Debts!$E$8=MIN(IF(C18>0,Debts!$E$8,999),IF(D18>0,Debts!$E$9,999),IF(E18>0,Debts!$E$10,999),IF(F18>0,Debts!$E$11,999),IF(G18>0,Debts!$E$12,999),IF(H18>0,Debts!$E$13,999),IF(I18>0,Debts!$E$14,999),IF(J18>0,Debts!$E$15,999))),MAX(0,(B19-(MIN(C18+0,C18*(1+Debts!$C$8/12))*0+MIN(C18*(1+Debts!$C$8/12),Debts!$D$8)+MIN(C18+0,D18*(1+Debts!$C$9/12))*0+MIN(D18*(1+Debts!$C$9/12),Debts!$D$9)+MIN(C18+0,E18*(1+Debts!$C$10/12))*0+MIN(E18*(1+Debts!$C$10/12),Debts!$D$10)+MIN(C18+0,F18*(1+Debts!$C$11/12))*0+MIN(F18*(1+Debts!$C$11/12),Debts!$D$11)+MIN(C18+0,G18*(1+Debts!$C$12/12))*0+MIN(G18*(1+Debts!$C$12/12),Debts!$D$12)+MIN(C18+0,H18*(1+Debts!$C$13/12))*0+MIN(H18*(1+Debts!$C$13/12),Debts!$D$13)+MIN(C18+0,I18*(1+Debts!$C$14/12))*0+MIN(I18*(1+Debts!$C$14/12),Debts!$D$14)+MIN(C18+0,J18*(1+Debts!$C$15/12))*0+MIN(J18*(1+Debts!$C$15/12),Debts!$D$15)))),0))) -> 457.57857 | D19: =IF(D18<=0,0,MAX(0,D18*(1+Debts!$C$9/12)-MIN(D18*(1+Debts!$C$9/12),Debts!$D$9)-IF(AND(D18>0,Debts!$E$9=MIN(IF(C18>0,Debts!$E$8,999),IF(D18>0,Debts!$E$9,999),IF(E18>0,Debts!$E$10,999),IF(F18>0,Debts!$E$11,999),IF(G18>0,Debts!$E$12,999),IF(H18>0,Debts!$E$13,999),IF(I18>0,Debts!$E$14,999),IF(J18>0,Debts!$E$15,999))),MAX(0,(B19-(MIN(C18+0,C18*(1+Debts!$C$8/12))*0+MIN(C18*(1+Debts!$C$8/12),Debts!$D$8)+MIN(C18+0,D18*(1+Debts!$C$9/12))*0+MIN(D18*(1+Debts!$C$9/12),Debts!$D$9)+MIN(C18+0,E18*(1+Debts!$C$10/12))*0+MIN(E18*(1+Debts!$C$10/12),Debts!$D$10)+MIN(C18+0,F18*(1+Debts!$C$11/12))*0+MIN(F18*(1+Debts!$C$11/12),Debts!$D$11)+MIN(C18+0,G18*(1+Debts!$C$12/12))*0+MIN(G18*(1+Debts!$C$12/12),Debts!$D$12)+MIN(C18+0,H18*(1+Debts!$C$13/12))*0+MIN(H18*(1+Debts!$C$13/12),Debts!$D$13)+MIN(C18+0,I18*(1+Debts!$C$14/12))*0+MIN(I18*(1+Debts!$C$14/12),Debts!$D$14)+MIN(C18+0,J18*(1+Debts!$C$15/12))*0+MIN(J18*(1+Debts!$C$15/12),Debts!$D$15)))),0))) -> 1985.6368 | E19: =IF(E18<=0,0,MAX(0,E18*(1+Debts!$C$10/12)-MIN(E18*(1+Debts!$C$10/12),Debts!$D$10)-IF(AND(E18>0,Debts!$E$10=MIN(IF(C18>0,Debts!$E$8,999),IF(D18>0,Debts!$E$9,999),IF(E18>0,Debts!$E$10,999),IF(F18>0,Debts!$E$11,999),IF(G18>0,Debts!$E$12,999),IF(H18>0,Debts!$E$13,999),IF(I18>0,Debts!$E$14,999),IF(J18>0,Debts!$E$15,999))),MAX(0,(B19-(MIN(C18+0,C18*(1+Debts!$C$8/12))*0+MIN(C18*(1+Debts!$C$8/12),Debts!$D$8)+MIN(C18+0,D18*(1+Debts!$C$9/12))*0+MIN(D18*(1+Debts!$C$9/12),Debts!$D$9)+MIN(C18+0,E18*(1+Debts!$C$10/12))*0+MIN(E18*(1+Debts!$C$10/12),Debts!$D$10)+MIN(C18+0,F18*(1+Debts!$C$11/12))*0+MIN(F18*(1+Debts!$C$11/12),Debts!$D$11)+MIN(C18+0,G18*(1+Debts!$C$12/12))*0+MIN(G18*(1+Debts!$C$12/12),Debts!$D$12)+MIN(C18+0,H18*(1+Debts!$C$13/12))*0+MIN(H18*(1+Debts!$C$13/12),Debts!$D$13)+MIN(C18+0,I18*(1+Debts!$C$14/12))*0+MIN(I18*(1+Debts!$C$14/12),Debts!$D$14)+MIN(C18+0,J18*(1+Debts!$C$15/12))*0+MIN(J18*(1+Debts!$C$15/12),Debts!$D$15)))),0))) -> 8800.5197 | F19: =IF(F18<=0,0,MAX(0,F18*(1+Debts!$C$11/12)-MIN(F18*(1+Debts!$C$11/12),Debts!$D$11)-IF(AND(F18>0,Debts!$E$11=MIN(IF(C18>0,Debts!$E$8,999),IF(D18>0,Debts!$E$9,999),IF(E18>0,Debts!$E$10,999),IF(F18>0,Debts!$E$11,999),IF(G18>0,Debts!$E$12,999),IF(H18>0,Debts!$E$13,999),IF(I18>0,Debts!$E$14,999),IF(J18>0,Debts!$E$15,999))),MAX(0,(B19-(MIN(C18+0,C18*(1+Debts!$C$8/12))*0+MIN(C18*(1+Debts!$C$8/12),Debts!$D$8)+MIN(C18+0,D18*(1+Debts!$C$9/12))*0+MIN(D18*(1+Debts!$C$9/12),Debts!$D$9)+MIN(C18+0,E18*(1+Debts!$C$10/12))*0+MIN(E18*(1+Debts!$C$10/12),Debts!$D$10)+MIN(C18+0,F18*(1+Debts!$C$11/12))*0+MIN(F18*(1+Debts!$C$11/12),Debts!$D$11)+MIN(C18+0,G18*(1+Debts!$C$12/12))*0+MIN(G18*(1+Debts!$C$12/12),Debts!$D$12)+MIN(C18+0,H18*(1+Debts!$C$13/12))*0+MIN(H18*(1+Debts!$C$13/12),Debts!$D$13)+MIN(C18+0,I18*(1+Debts!$C$14/12))*0+MIN(I18*(1+Debts!$C$14/12),Debts!$D$14)+MIN(C18+0,J18*(1+Debts!$C$15/12))*0+MIN(J18*(1+Debts!$C$15/12),Debts!$D$15)))),0))) -> 16959.04 | G19: =IF(G18<=0,0,MAX(0,G18*(1+Debts!$C$12/12)-MIN(G18*(1+Debts!$C$12/12),Debts!$D$12)-IF(AND(G18>0,Debts!$E$12=MIN(IF(C18>0,Debts!$E$8,999),IF(D18>0,Debts!$E$9,999),IF(E18>0,Debts!$E$10,999),IF(F18>0,Debts!$E$11,999),IF(G18>0,Debts!$E$12,999),IF(H18>0,Debts!$E$13,999),IF(I18>0,Debts!$E$14,999),IF(J18>0,Debts!$E$15,999))),MAX(0,(B19-(MIN(C18+0,C18*(1+Debts!$C$8/12))*0+MIN(C18*(1+Debts!$C$8/12),Debts!$D$8)+MIN(C18+0,D18*(1+Debts!$C$9/12))*0+MIN(D18*(1+Debts!$C$9/12),Debts!$D$9)+MIN(C18+0,E18*(1+Debts!$C$10/12))*0+MIN(E18*(1+Debts!$C$10/12),Debts!$D$10)+MIN(C18+0,F18*(1+Debts!$C$11/12))*0+MIN(F18*(1+Debts!$C$11/12),Debts!$D$11)+MIN(C18+0,G18*(1+Debts!$C$12/12))*0+MIN(G18*(1+Debts!$C$12/12),Debts!$D$12)+MIN(C18+0,H18*(1+Debts!$C$13/12))*0+MIN(H18*(1+Debts!$C$13/12),Debts!$D$13)+MIN(C18+0,I18*(1+Debts!$C$14/12))*0+MIN(I18*(1+Debts!$C$14/12),Debts!$D$14)+MIN(C18+0,J18*(1+Debts!$C$15/12))*0+MIN(J18*(1+Debts!$C$15/12),Debts!$D$15)))),0))) -> 300 | H19: =IF(H18<=0,0,MAX(0,H18*(1+Debts!$C$13/12)-MIN(H18*(1+Debts!$C$13/12),Debts!$D$13)-IF(AND(H18>0,Debts!$E$13=MIN(IF(C18>0,Debts!$E$8,999),IF(D18>0,Debts!$E$9,999),IF(E18>0,Debts!$E$10,999),IF(F18>0,Debts!$E$11,999),IF(G18>0,Debts!$E$12,999),IF(H18>0,Debts!$E$13,999),IF(I18>0,Debts!$E$14,999),IF(J18>0,Debts!$E$15,999))),MAX(0,(B19-(MIN(C18+0,C18*(1+Debts!$C$8/12))*0+MIN(C18*(1+Debts!$C$8/12),Debts!$D$8)+MIN(C18+0,D18*(1+Debts!$C$9/12))*0+MIN(D18*(1+Debts!$C$9/12),Debts!$D$9)+MIN(C18+0,E18*(1+Debts!$C$10/12))*0+MIN(E18*(1+Debts!$C$10/12),Debts!$D$10)+MIN(C18+0,F18*(1+Debts!$C$11/12))*0+MIN(F18*(1+Debts!$C$11/12),Debts!$D$11)+MIN(C18+0,G18*(1+Debts!$C$12/12))*0+MIN(G18*(1+Debts!$C$12/12),Debts!$D$12)+MIN(C18+0,H18*(1+Debts!$C$13/12))*0+MIN(H18*(1+Debts!$C$13/12),Debts!$D$13)+MIN(C18+0,I18*(1+Debts!$C$14/12))*0+MIN(I18*(1+Debts!$C$14/12),Debts!$D$14)+MIN(C18+0,J18*(1+Debts!$C$15/12))*0+MIN(J18*(1+Debts!$C$15/12),Debts!$D$15)))),0))) -> 0 | I19: =IF(I18<=0,0,MAX(0,I18*(1+Debts!$C$14/12)-MIN(I18*(1+Debts!$C$14/12),Debts!$D$14)-IF(AND(I18>0,Debts!$E$14=MIN(IF(C18>0,Debts!$E$8,999),IF(D18>0,Debts!$E$9,999),IF(E18>0,Debts!$E$10,999),IF(F18>0,Debts!$E$11,999),IF(G18>0,Debts!$E$12,999),IF(H18>0,Debts!$E$13,999),IF(I18>0,Debts!$E$14,999),IF(J18>0,Debts!$E$15,999))),MAX(0,(B19-(MIN(C18+0,C18*(1+Debts!$C$8/12))*0+MIN(C18*(1+Debts!$C$8/12),Debts!$D$8)+MIN(C18+0,D18*(1+Debts!$C$9/12))*0+MIN(D18*(1+Debts!$C$9/12),Debts!$D$9)+MIN(C18+0,E18*(1+Debts!$C$10/12))*0+MIN(E18*(1+Debts!$C$10/12),Debts!$D$10)+MIN(C18+0,F18*(1+Debts!$C$11/12))*0+MIN(F18*(1+Debts!$C$11/12),Debts!$D$11)+MIN(C18+0,G18*(1+Debts!$C$12/12))*0+MIN(G18*(1+Debts!$C$12/12),Debts!$D$12)+MIN(C18+0,H18*(1+Debts!$C$13/12))*0+MIN(H18*(1+Debts!$C$13/12),Debts!$D$13)+MIN(C18+0,I18*(1+Debts!$C$14/12))*0+MIN(I18*(1+Debts!$C$14/12),Debts!$D$14)+MIN(C18+0,J18*(1+Debts!$C$15/12))*0+MIN(J18*(1+Debts!$C$15/12),Debts!$D$15)))),0))) -> 0 | J19: =IF(J18<=0,0,MAX(0,J18*(1+Debts!$C$15/12)-MIN(J18*(1+Debts!$C$15/12),Debts!$D$15)-IF(AND(J18>0,Debts!$E$15=MIN(IF(C18>0,Debts!$E$8,999),IF(D18>0,Debts!$E$9,999),IF(E18>0,Debts!$E$10,999),IF(F18>0,Debts!$E$11,999),IF(G18>0,Debts!$E$12,999),IF(H18>0,Debts!$E$13,999),IF(I18>0,Debts!$E$14,999),IF(J18>0,Debts!$E$15,999))),MAX(0,(B19-(MIN(C18+0,C18*(1+Debts!$C$8/12))*0+MIN(C18*(1+Debts!$C$8/12),Debts!$D$8)+MIN(C18+0,D18*(1+Debts!$C$9/12))*0+MIN(D18*(1+Debts!$C$9/12),Debts!$D$9)+MIN(C18+0,E18*(1+Debts!$C$10/12))*0+MIN(E18*(1+Debts!$C$10/12),Debts!$D$10)+MIN(C18+0,F18*(1+Debts!$C$11/12))*0+MIN(F18*(1+Debts!$C$11/12),Debts!$D$11)+MIN(C18+0,G18*(1+Debts!$C$12/12))*0+MIN(G18*(1+Debts!$C$12/12),Debts!$D$12)+MIN(C18+0,H18*(1+Debts!$C$13/12))*0+MIN(H18*(1+Debts!$C$13/12),Debts!$D$13)+MIN(C18+0,I18*(1+Debts!$C$14/12))*0+MIN(I18*(1+Debts!$C$14/12),Debts!$D$14)+MIN(C18+0,J18*(1+Debts!$C$15/12))*0+MIN(J18*(1+Debts!$C$15/12),Debts!$D$15)))),0))) -> 0 | K19: =IF(C18>0,C18*Debts!$C$8/12,0)+IF(D18>0,D18*Debts!$C$9/12,0)+IF(E18>0,E18*Debts!$C$10/12,0)+IF(F18>0,F18*Debts!$C$11/12,0)+IF(G18>0,G18*Debts!$C$12/12,0)+IF(H18>0,H18*Debts!$C$13/12,0)+IF(I18>0,I18*Debts!$C$14/12,0)+IF(J18>0,J18*Debts!$C$15/12,0) -> 187.93489 | L19: =SUM(C19:J19) -> 28502.775
A20: =13 -> 13 | B20: =IF(L19<=0,0,Debts!$D$16+Debts!$B$4) -> 1200 | C20: =IF(C19<=0,0,MAX(0,C19*(1+Debts!$C$8/12)-MIN(C19*(1+Debts!$C$8/12),Debts!$D$8)-IF(AND(C19>0,Debts!$E$8=MIN(IF(C19>0,Debts!$E$8,999),IF(D19>0,Debts!$E$9,999),IF(E19>0,Debts!$E$10,999),IF(F19>0,Debts!$E$11,999),IF(G19>0,Debts!$E$12,999),IF(H19>0,Debts!$E$13,999),IF(I19>0,Debts!$E$14,999),IF(J19>0,Debts!$E$15,999))),MAX(0,(B20-(MIN(C19+0,C19*(1+Debts!$C$8/12))*0+MIN(C19*(1+Debts!$C$8/12),Debts!$D$8)+MIN(C19+0,D19*(1+Debts!$C$9/12))*0+MIN(D19*(1+Debts!$C$9/12),Debts!$D$9)+MIN(C19+0,E19*(1+Debts!$C$10/12))*0+MIN(E19*(1+Debts!$C$10/12),Debts!$D$10)+MIN(C19+0,F19*(1+Debts!$C$11/12))*0+MIN(F19*(1+Debts!$C$11/12),Debts!$D$11)+MIN(C19+0,G19*(1+Debts!$C$12/12))*0+MIN(G19*(1+Debts!$C$12/12),Debts!$D$12)+MIN(C19+0,H19*(1+Debts!$C$13/12))*0+MIN(H19*(1+Debts!$C$13/12),Debts!$D$13)+MIN(C19+0,I19*(1+Debts!$C$14/12))*0+MIN(I19*(1+Debts!$C$14/12),Debts!$D$14)+MIN(C19+0,J19*(1+Debts!$C$15/12))*0+MIN(J19*(1+Debts!$C$15/12),Debts!$D$15)))),0))) -> 0 | D20: =IF(D19<=0,0,MAX(0,D19*(1+Debts!$C$9/12)-MIN(D19*(1+Debts!$C$9/12),Debts!$D$9)-IF(AND(D19>0,Debts!$E$9=MIN(IF(C19>0,Debts!$E$8,999),IF(D19>0,Debts!$E$9,999),IF(E19>0,Debts!$E$10,999),IF(F19>0,Debts!$E$11,999),IF(G19>0,Debts!$E$12,999),IF(H19>0,Debts!$E$13,999),IF(I19>0,Debts!$E$14,999),IF(J19>0,Debts!$E$15,999))),MAX(0,(B20-(MIN(C19+0,C19*(1+Debts!$C$8/12))*0+MIN(C19*(1+Debts!$C$8/12),Debts!$D$8)+MIN(C19+0,D19*(1+Debts!$C$9/12))*0+MIN(D19*(1+Debts!$C$9/12),Debts!$D$9)+MIN(C19+0,E19*(1+Debts!$C$10/12))*0+MIN(E19*(1+Debts!$C$10/12),Debts!$D$10)+MIN(C19+0,F19*(1+Debts!$C$11/12))*0+MIN(F19*(1+Debts!$C$11/12),Debts!$D$11)+MIN(C19+0,G19*(1+Debts!$C$12/12))*0+MIN(G19*(1+Debts!$C$12/12),Debts!$D$12)+MIN(C19+0,H19*(1+Debts!$C$13/12))*0+MIN(H19*(1+Debts!$C$13/12),Debts!$D$13)+MIN(C19+0,I19*(1+Debts!$C$14/12))*0+MIN(I19*(1+Debts!$C$14/12),Debts!$D$14)+MIN(C19+0,J19*(1+Debts!$C$15/12))*0+MIN(J19*(1+Debts!$C$15/12),Debts!$D$15)))),0))) -> 1946.8747 | E20: =IF(E19<=0,0,MAX(0,E19*(1+Debts!$C$10/12)-MIN(E19*(1+Debts!$C$10/12),Debts!$D$10)-IF(AND(E19>0,Debts!$E$10=MIN(IF(C19>0,Debts!$E$8,999),IF(D19>0,Debts!$E$9,999),IF(E19>0,Debts!$E$10,999),IF(F19>0,Debts!$E$11,999),IF(G19>0,Debts!$E$12,999),IF(H19>0,Debts!$E$13,999),IF(I19>0,Debts!$E$14,999),IF(J19>0,Debts!$E$15,999))),MAX(0,(B20-(MIN(C19+0,C19*(1+Debts!$C$8/12))*0+MIN(C19*(1+Debts!$C$8/12),Debts!$D$8)+MIN(C19+0,D19*(1+Debts!$C$9/12))*0+MIN(D19*(1+Debts!$C$9/12),Debts!$D$9)+MIN(C19+0,E19*(1+Debts!$C$10/12))*0+MIN(E19*(1+Debts!$C$10/12),Debts!$D$10)+MIN(C19+0,F19*(1+Debts!$C$11/12))*0+MIN(F19*(1+Debts!$C$11/12),Debts!$D$11)+MIN(C19+0,G19*(1+Debts!$C$12/12))*0+MIN(G19*(1+Debts!$C$12/12),Debts!$D$12)+MIN(C19+0,H19*(1+Debts!$C$13/12))*0+MIN(H19*(1+Debts!$C$13/12),Debts!$D$13)+MIN(C19+0,I19*(1+Debts!$C$14/12))*0+MIN(I19*(1+Debts!$C$14/12),Debts!$D$14)+MIN(C19+0,J19*(1+Debts!$C$15/12))*0+MIN(J19*(1+Debts!$C$15/12),Debts!$D$15)))),0))) -> 8541.1227 | F20: =IF(F19<=0,0,MAX(0,F19*(1+Debts!$C$11/12)-MIN(F19*(1+Debts!$C$11/12),Debts!$D$11)-IF(AND(F19>0,Debts!$E$11=MIN(IF(C19>0,Debts!$E$8,999),IF(D19>0,Debts!$E$9,999),IF(E19>0,Debts!$E$10,999),IF(F19>0,Debts!$E$11,999),IF(G19>0,Debts!$E$12,999),IF(H19>0,Debts!$E$13,999),IF(I19>0,Debts!$E$14,999),IF(J19>0,Debts!$E$15,999))),MAX(0,(B20-(MIN(C19+0,C19*(1+Debts!$C$8/12))*0+MIN(C19*(1+Debts!$C$8/12),Debts!$D$8)+MIN(C19+0,D19*(1+Debts!$C$9/12))*0+MIN(D19*(1+Debts!$C$9/12),Debts!$D$9)+MIN(C19+0,E19*(1+Debts!$C$10/12))*0+MIN(E19*(1+Debts!$C$10/12),Debts!$D$10)+MIN(C19+0,F19*(1+Debts!$C$11/12))*0+MIN(F19*(1+Debts!$C$11/12),Debts!$D$11)+MIN(C19+0,G19*(1+Debts!$C$12/12))*0+MIN(G19*(1+Debts!$C$12/12),Debts!$D$12)+MIN(C19+0,H19*(1+Debts!$C$13/12))*0+MIN(H19*(1+Debts!$C$13/12),Debts!$D$13)+MIN(C19+0,I19*(1+Debts!$C$14/12))*0+MIN(I19*(1+Debts!$C$14/12),Debts!$D$14)+MIN(C19+0,J19*(1+Debts!$C$15/12))*0+MIN(J19*(1+Debts!$C$15/12),Debts!$D$15)))),0))) -> 16826.769 | G20: =IF(G19<=0,0,MAX(0,G19*(1+Debts!$C$12/12)-MIN(G19*(1+Debts!$C$12/12),Debts!$D$12)-IF(AND(G19>0,Debts!$E$12=MIN(IF(C19>0,Debts!$E$8,999),IF(D19>0,Debts!$E$9,999),IF(E19>0,Debts!$E$10,999),IF(F19>0,Debts!$E$11,999),IF(G19>0,Debts!$E$12,999),IF(H19>0,Debts!$E$13,999),IF(I19>0,Debts!$E$14,999),IF(J19>0,Debts!$E$15,999))),MAX(0,(B20-(MIN(C19+0,C19*(1+Debts!$C$8/12))*0+MIN(C19*(1+Debts!$C$8/12),Debts!$D$8)+MIN(C19+0,D19*(1+Debts!$C$9/12))*0+MIN(D19*(1+Debts!$C$9/12),Debts!$D$9)+MIN(C19+0,E19*(1+Debts!$C$10/12))*0+MIN(E19*(1+Debts!$C$10/12),Debts!$D$10)+MIN(C19+0,F19*(1+Debts!$C$11/12))*0+MIN(F19*(1+Debts!$C$11/12),Debts!$D$11)+MIN(C19+0,G19*(1+Debts!$C$12/12))*0+MIN(G19*(1+Debts!$C$12/12),Debts!$D$12)+MIN(C19+0,H19*(1+Debts!$C$13/12))*0+MIN(H19*(1+Debts!$C$13/12),Debts!$D$13)+MIN(C19+0,I19*(1+Debts!$C$14/12))*0+MIN(I19*(1+Debts!$C$14/12),Debts!$D$14)+MIN(C19+0,J19*(1+Debts!$C$15/12))*0+MIN(J19*(1+Debts!$C$15/12),Debts!$D$15)))),0))) -> 250 | H20: =IF(H19<=0,0,MAX(0,H19*(1+Debts!$C$13/12)-MIN(H19*(1+Debts!$C$13/12),Debts!$D$13)-IF(AND(H19>0,Debts!$E$13=MIN(IF(C19>0,Debts!$E$8,999),IF(D19>0,Debts!$E$9,999),IF(E19>0,Debts!$E$10,999),IF(F19>0,Debts!$E$11,999),IF(G19>0,Debts!$E$12,999),IF(H19>0,Debts!$E$13,999),IF(I19>0,Debts!$E$14,999),IF(J19>0,Debts!$E$15,999))),MAX(0,(B20-(MIN(C19+0,C19*(1+Debts!$C$8/12))*0+MIN(C19*(1+Debts!$C$8/12),Debts!$D$8)+MIN(C19+0,D19*(1+Debts!$C$9/12))*0+MIN(D19*(1+Debts!$C$9/12),Debts!$D$9)+MIN(C19+0,E19*(1+Debts!$C$10/12))*0+MIN(E19*(1+Debts!$C$10/12),Debts!$D$10)+MIN(C19+0,F19*(1+Debts!$C$11/12))*0+MIN(F19*(1+Debts!$C$11/12),Debts!$D$11)+MIN(C19+0,G19*(1+Debts!$C$12/12))*0+MIN(G19*(1+Debts!$C$12/12),Debts!$D$12)+MIN(C19+0,H19*(1+Debts!$C$13/12))*0+MIN(H19*(1+Debts!$C$13/12),Debts!$D$13)+MIN(C19+0,I19*(1+Debts!$C$14/12))*0+MIN(I19*(1+Debts!$C$14/12),Debts!$D$14)+MIN(C19+0,J19*(1+Debts!$C$15/12))*0+MIN(J19*(1+Debts!$C$15/12),Debts!$D$15)))),0))) -> 0 | I20: =IF(I19<=0,0,MAX(0,I19*(1+Debts!$C$14/12)-MIN(I19*(1+Debts!$C$14/12),Debts!$D$14)-IF(AND(I19>0,Debts!$E$14=MIN(IF(C19>0,Debts!$E$8,999),IF(D19>0,Debts!$E$9,999),IF(E19>0,Debts!$E$10,999),IF(F19>0,Debts!$E$11,999),IF(G19>0,Debts!$E$12,999),IF(H19>0,Debts!$E$13,999),IF(I19>0,Debts!$E$14,999),IF(J19>0,Debts!$E$15,999))),MAX(0,(B20-(MIN(C19+0,C19*(1+Debts!$C$8/12))*0+MIN(C19*(1+Debts!$C$8/12),Debts!$D$8)+MIN(C19+0,D19*(1+Debts!$C$9/12))*0+MIN(D19*(1+Debts!$C$9/12),Debts!$D$9)+MIN(C19+0,E19*(1+Debts!$C$10/12))*0+MIN(E19*(1+Debts!$C$10/12),Debts!$D$10)+MIN(C19+0,F19*(1+Debts!$C$11/12))*0+MIN(F19*(1+Debts!$C$11/12),Debts!$D$11)+MIN(C19+0,G19*(1+Debts!$C$12/12))*0+MIN(G19*(1+Debts!$C$12/12),Debts!$D$12)+MIN(C19+0,H19*(1+Debts!$C$13/12))*0+MIN(H19*(1+Debts!$C$13/12),Debts!$D$13)+MIN(C19+0,I19*(1+Debts!$C$14/12))*0+MIN(I19*(1+Debts!$C$14/12),Debts!$D$14)+MIN(C19+0,J19*(1+Debts!$C$15/12))*0+MIN(J19*(1+Debts!$C$15/12),Debts!$D$15)))),0))) -> 0 | J20: =IF(J19<=0,0,MAX(0,J19*(1+Debts!$C$15/12)-MIN(J19*(1+Debts!$C$15/12),Debts!$D$15)-IF(AND(J19>0,Debts!$E$15=MIN(IF(C19>0,Debts!$E$8,999),IF(D19>0,Debts!$E$9,999),IF(E19>0,Debts!$E$10,999),IF(F19>0,Debts!$E$11,999),IF(G19>0,Debts!$E$12,999),IF(H19>0,Debts!$E$13,999),IF(I19>0,Debts!$E$14,999),IF(J19>0,Debts!$E$15,999))),MAX(0,(B20-(MIN(C19+0,C19*(1+Debts!$C$8/12))*0+MIN(C19*(1+Debts!$C$8/12),Debts!$D$8)+MIN(C19+0,D19*(1+Debts!$C$9/12))*0+MIN(D19*(1+Debts!$C$9/12),Debts!$D$9)+MIN(C19+0,E19*(1+Debts!$C$10/12))*0+MIN(E19*(1+Debts!$C$10/12),Debts!$D$10)+MIN(C19+0,F19*(1+Debts!$C$11/12))*0+MIN(F19*(1+Debts!$C$11/12),Debts!$D$11)+MIN(C19+0,G19*(1+Debts!$C$12/12))*0+MIN(G19*(1+Debts!$C$12/12),Debts!$D$12)+MIN(C19+0,H19*(1+Debts!$C$13/12))*0+MIN(H19*(1+Debts!$C$13/12),Debts!$D$13)+MIN(C19+0,I19*(1+Debts!$C$14/12))*0+MIN(I19*(1+Debts!$C$14/12),Debts!$D$14)+MIN(C19+0,J19*(1+Debts!$C$15/12))*0+MIN(J19*(1+Debts!$C$15/12),Debts!$D$15)))),0))) -> 0 | K20: =IF(C19>0,C19*Debts!$C$8/12,0)+IF(D19>0,D19*Debts!$C$9/12,0)+IF(E19>0,E19*Debts!$C$10/12,0)+IF(F19>0,F19*Debts!$C$11/12,0)+IF(G19>0,G19*Debts!$C$12/12,0)+IF(H19>0,H19*Debts!$C$13/12,0)+IF(I19>0,I19*Debts!$C$14/12,0)+IF(J19>0,J19*Debts!$C$15/12,0) -> 174.06455 | L20: =SUM(C20:J20) -> 27564.766
A21: =14 -> 14 | B21: =IF(L20<=0,0,Debts!$D$16+Debts!$B$4) -> 1200 | C21: =IF(C20<=0,0,MAX(0,C20*(1+Debts!$C$8/12)-MIN(C20*(1+Debts!$C$8/12),Debts!$D$8)-IF(AND(C20>0,Debts!$E$8=MIN(IF(C20>0,Debts!$E$8,999),IF(D20>0,Debts!$E$9,999),IF(E20>0,Debts!$E$10,999),IF(F20>0,Debts!$E$11,999),IF(G20>0,Debts!$E$12,999),IF(H20>0,Debts!$E$13,999),IF(I20>0,Debts!$E$14,999),IF(J20>0,Debts!$E$15,999))),MAX(0,(B21-(MIN(C20+0,C20*(1+Debts!$C$8/12))*0+MIN(C20*(1+Debts!$C$8/12),Debts!$D$8)+MIN(C20+0,D20*(1+Debts!$C$9/12))*0+MIN(D20*(1+Debts!$C$9/12),Debts!$D$9)+MIN(C20+0,E20*(1+Debts!$C$10/12))*0+MIN(E20*(1+Debts!$C$10/12),Debts!$D$10)+MIN(C20+0,F20*(1+Debts!$C$11/12))*0+MIN(F20*(1+Debts!$C$11/12),Debts!$D$11)+MIN(C20+0,G20*(1+Debts!$C$12/12))*0+MIN(G20*(1+Debts!$C$12/12),Debts!$D$12)+MIN(C20+0,H20*(1+Debts!$C$13/12))*0+MIN(H20*(1+Debts!$C$13/12),Debts!$D$13)+MIN(C20+0,I20*(1+Debts!$C$14/12))*0+MIN(I20*(1+Debts!$C$14/12),Debts!$D$14)+MIN(C20+0,J20*(1+Debts!$C$15/12))*0+MIN(J20*(1+Debts!$C$15/12),Debts!$D$15)))),0))) -> 0 | D21: =IF(D20<=0,0,MAX(0,D20*(1+Debts!$C$9/12)-MIN(D20*(1+Debts!$C$9/12),Debts!$D$9)-IF(AND(D20>0,Debts!$E$9=MIN(IF(C20>0,Debts!$E$8,999),IF(D20>0,Debts!$E$9,999),IF(E20>0,Debts!$E$10,999),IF(F20>0,Debts!$E$11,999),IF(G20>0,Debts!$E$12,999),IF(H20>0,Debts!$E$13,999),IF(I20>0,Debts!$E$14,999),IF(J20>0,Debts!$E$15,999))),MAX(0,(B21-(MIN(C20+0,C20*(1+Debts!$C$8/12))*0+MIN(C20*(1+Debts!$C$8/12),Debts!$D$8)+MIN(C20+0,D20*(1+Debts!$C$9/12))*0+MIN(D20*(1+Debts!$C$9/12),Debts!$D$9)+MIN(C20+0,E20*(1+Debts!$C$10/12))*0+MIN(E20*(1+Debts!$C$10/12),Debts!$D$10)+MIN(C20+0,F20*(1+Debts!$C$11/12))*0+MIN(F20*(1+Debts!$C$11/12),Debts!$D$11)+MIN(C20+0,G20*(1+Debts!$C$12/12))*0+MIN(G20*(1+Debts!$C$12/12),Debts!$D$12)+MIN(C20+0,H20*(1+Debts!$C$13/12))*0+MIN(H20*(1+Debts!$C$13/12),Debts!$D$13)+MIN(C20+0,I20*(1+Debts!$C$14/12))*0+MIN(I20*(1+Debts!$C$14/12),Debts!$D$14)+MIN(C20+0,J20*(1+Debts!$C$15/12))*0+MIN(J20*(1+Debts!$C$15/12),Debts!$D$15)))),0))) -> 1352.4051 | E21: =IF(E20<=0,0,MAX(0,E20*(1+Debts!$C$10/12)-MIN(E20*(1+Debts!$C$10/12),Debts!$D$10)-IF(AND(E20>0,Debts!$E$10=MIN(IF(C20>0,Debts!$E$8,999),IF(D20>0,Debts!$E$9,999),IF(E20>0,Debts!$E$10,999),IF(F20>0,Debts!$E$11,999),IF(G20>0,Debts!$E$12,999),IF(H20>0,Debts!$E$13,999),IF(I20>0,Debts!$E$14,999),IF(J20>0,Debts!$E$15,999))),MAX(0,(B21-(MIN(C20+0,C20*(1+Debts!$C$8/12))*0+MIN(C20*(1+Debts!$C$8/12),Debts!$D$8)+MIN(C20+0,D20*(1+Debts!$C$9/12))*0+MIN(D20*(1+Debts!$C$9/12),Debts!$D$9)+MIN(C20+0,E20*(1+Debts!$C$10/12))*0+MIN(E20*(1+Debts!$C$10/12),Debts!$D$10)+MIN(C20+0,F20*(1+Debts!$C$11/12))*0+MIN(F20*(1+Debts!$C$11/12),Debts!$D$11)+MIN(C20+0,G20*(1+Debts!$C$12/12))*0+MIN(G20*(1+Debts!$C$12/12),Debts!$D$12)+MIN(C20+0,H20*(1+Debts!$C$13/12))*0+MIN(H20*(1+Debts!$C$13/12),Debts!$D$13)+MIN(C20+0,I20*(1+Debts!$C$14/12))*0+MIN(I20*(1+Debts!$C$14/12),Debts!$D$14)+MIN(C20+0,J20*(1+Debts!$C$15/12))*0+MIN(J20*(1+Debts!$C$15/12),Debts!$D$15)))),0))) -> 8280.2342 | F21: =IF(F20<=0,0,MAX(0,F20*(1+Debts!$C$11/12)-MIN(F20*(1+Debts!$C$11/12),Debts!$D$11)-IF(AND(F20>0,Debts!$E$11=MIN(IF(C20>0,Debts!$E$8,999),IF(D20>0,Debts!$E$9,999),IF(E20>0,Debts!$E$10,999),IF(F20>0,Debts!$E$11,999),IF(G20>0,Debts!$E$12,999),IF(H20>0,Debts!$E$13,999),IF(I20>0,Debts!$E$14,999),IF(J20>0,Debts!$E$15,999))),MAX(0,(B21-(MIN(C20+0,C20*(1+Debts!$C$8/12))*0+MIN(C20*(1+Debts!$C$8/12),Debts!$D$8)+MIN(C20+0,D20*(1+Debts!$C$9/12))*0+MIN(D20*(1+Debts!$C$9/12),Debts!$D$9)+MIN(C20+0,E20*(1+Debts!$C$10/12))*0+MIN(E20*(1+Debts!$C$10/12),Debts!$D$10)+MIN(C20+0,F20*(1+Debts!$C$11/12))*0+MIN(F20*(1+Debts!$C$11/12),Debts!$D$11)+MIN(C20+0,G20*(1+Debts!$C$12/12))*0+MIN(G20*(1+Debts!$C$12/12),Debts!$D$12)+MIN(C20+0,H20*(1+Debts!$C$13/12))*0+MIN(H20*(1+Debts!$C$13/12),Debts!$D$13)+MIN(C20+0,I20*(1+Debts!$C$14/12))*0+MIN(I20*(1+Debts!$C$14/12),Debts!$D$14)+MIN(C20+0,J20*(1+Debts!$C$15/12))*0+MIN(J20*(1+Debts!$C$15/12),Debts!$D$15)))),0))) -> 16693.891 | G21: =IF(G20<=0,0,MAX(0,G20*(1+Debts!$C$12/12)-MIN(G20*(1+Debts!$C$12/12),Debts!$D$12)-IF(AND(G20>0,Debts!$E$12=MIN(IF(C20>0,Debts!$E$8,999),IF(D20>0,Debts!$E$9,999),IF(E20>0,Debts!$E$10,999),IF(F20>0,Debts!$E$11,999),IF(G20>0,Debts!$E$12,999),IF(H20>0,Debts!$E$13,999),IF(I20>0,Debts!$E$14,999),IF(J20>0,Debts!$E$15,999))),MAX(0,(B21-(MIN(C20+0,C20*(1+Debts!$C$8/12))*0+MIN(C20*(1+Debts!$C$8/12),Debts!$D$8)+MIN(C20+0,D20*(1+Debts!$C$9/12))*0+MIN(D20*(1+Debts!$C$9/12),Debts!$D$9)+MIN(C20+0,E20*(1+Debts!$C$10/12))*0+MIN(E20*(1+Debts!$C$10/12),Debts!$D$10)+MIN(C20+0,F20*(1+Debts!$C$11/12))*0+MIN(F20*(1+Debts!$C$11/12),Debts!$D$11)+MIN(C20+0,G20*(1+Debts!$C$12/12))*0+MIN(G20*(1+Debts!$C$12/12),Debts!$D$12)+MIN(C20+0,H20*(1+Debts!$C$13/12))*0+MIN(H20*(1+Debts!$C$13/12),Debts!$D$13)+MIN(C20+0,I20*(1+Debts!$C$14/12))*0+MIN(I20*(1+Debts!$C$14/12),Debts!$D$14)+MIN(C20+0,J20*(1+Debts!$C$15/12))*0+MIN(J20*(1+Debts!$C$15/12),Debts!$D$15)))),0))) -> 200 | H21: =IF(H20<=0,0,MAX(0,H20*(1+Debts!$C$13/12)-MIN(H20*(1+Debts!$C$13/12),Debts!$D$13)-IF(AND(H20>0,Debts!$E$13=MIN(IF(C20>0,Debts!$E$8,999),IF(D20>0,Debts!$E$9,999),IF(E20>0,Debts!$E$10,999),IF(F20>0,Debts!$E$11,999),IF(G20>0,Debts!$E$12,999),IF(H20>0,Debts!$E$13,999),IF(I20>0,Debts!$E$14,999),IF(J20>0,Debts!$E$15,999))),MAX(0,(B21-(MIN(C20+0,C20*(1+Debts!$C$8/12))*0+MIN(C20*(1+Debts!$C$8/12),Debts!$D$8)+MIN(C20+0,D20*(1+Debts!$C$9/12))*0+MIN(D20*(1+Debts!$C$9/12),Debts!$D$9)+MIN(C20+0,E20*(1+Debts!$C$10/12))*0+MIN(E20*(1+Debts!$C$10/12),Debts!$D$10)+MIN(C20+0,F20*(1+Debts!$C$11/12))*0+MIN(F20*(1+Debts!$C$11/12),Debts!$D$11)+MIN(C20+0,G20*(1+Debts!$C$12/12))*0+MIN(G20*(1+Debts!$C$12/12),Debts!$D$12)+MIN(C20+0,H20*(1+Debts!$C$13/12))*0+MIN(H20*(1+Debts!$C$13/12),Debts!$D$13)+MIN(C20+0,I20*(1+Debts!$C$14/12))*0+MIN(I20*(1+Debts!$C$14/12),Debts!$D$14)+MIN(C20+0,J20*(1+Debts!$C$15/12))*0+MIN(J20*(1+Debts!$C$15/12),Debts!$D$15)))),0))) -> 0 | I21: =IF(I20<=0,0,MAX(0,I20*(1+Debts!$C$14/12)-MIN(I20*(1+Debts!$C$14/12),Debts!$D$14)-IF(AND(I20>0,Debts!$E$14=MIN(IF(C20>0,Debts!$E$8,999),IF(D20>0,Debts!$E$9,999),IF(E20>0,Debts!$E$10,999),IF(F20>0,Debts!$E$11,999),IF(G20>0,Debts!$E$12,999),IF(H20>0,Debts!$E$13,999),IF(I20>0,Debts!$E$14,999),IF(J20>0,Debts!$E$15,999))),MAX(0,(B21-(MIN(C20+0,C20*(1+Debts!$C$8/12))*0+MIN(C20*(1+Debts!$C$8/12),Debts!$D$8)+MIN(C20+0,D20*(1+Debts!$C$9/12))*0+MIN(D20*(1+Debts!$C$9/12),Debts!$D$9)+MIN(C20+0,E20*(1+Debts!$C$10/12))*0+MIN(E20*(1+Debts!$C$10/12),Debts!$D$10)+MIN(C20+0,F20*(1+Debts!$C$11/12))*0+MIN(F20*(1+Debts!$C$11/12),Debts!$D$11)+MIN(C20+0,G20*(1+Debts!$C$12/12))*0+MIN(G20*(1+Debts!$C$12/12),Debts!$D$12)+MIN(C20+0,H20*(1+Debts!$C$13/12))*0+MIN(H20*(1+Debts!$C$13/12),Debts!$D$13)+MIN(C20+0,I20*(1+Debts!$C$14/12))*0+MIN(I20*(1+Debts!$C$14/12),Debts!$D$14)+MIN(C20+0,J20*(1+Debts!$C$15/12))*0+MIN(J20*(1+Debts!$C$15/12),Debts!$D$15)))),0))) -> 0 | J21: =IF(J20<=0,0,MAX(0,J20*(1+Debts!$C$15/12)-MIN(J20*(1+Debts!$C$15/12),Debts!$D$15)-IF(AND(J20>0,Debts!$E$15=MIN(IF(C20>0,Debts!$E$8,999),IF(D20>0,Debts!$E$9,999),IF(E20>0,Debts!$E$10,999),IF(F20>0,Debts!$E$11,999),IF(G20>0,Debts!$E$12,999),IF(H20>0,Debts!$E$13,999),IF(I20>0,Debts!$E$14,999),IF(J20>0,Debts!$E$15,999))),MAX(0,(B21-(MIN(C20+0,C20*(1+Debts!$C$8/12))*0+MIN(C20*(1+Debts!$C$8/12),Debts!$D$8)+MIN(C20+0,D20*(1+Debts!$C$9/12))*0+MIN(D20*(1+Debts!$C$9/12),Debts!$D$9)+MIN(C20+0,E20*(1+Debts!$C$10/12))*0+MIN(E20*(1+Debts!$C$10/12),Debts!$D$10)+MIN(C20+0,F20*(1+Debts!$C$11/12))*0+MIN(F20*(1+Debts!$C$11/12),Debts!$D$11)+MIN(C20+0,G20*(1+Debts!$C$12/12))*0+MIN(G20*(1+Debts!$C$12/12),Debts!$D$12)+MIN(C20+0,H20*(1+Debts!$C$13/12))*0+MIN(H20*(1+Debts!$C$13/12),Debts!$D$13)+MIN(C20+0,I20*(1+Debts!$C$14/12))*0+MIN(I20*(1+Debts!$C$14/12),Debts!$D$14)+MIN(C20+0,J20*(1+Debts!$C$15/12))*0+MIN(J20*(1+Debts!$C$15/12),Debts!$D$15)))),0))) -> 0 | K21: =IF(C20>0,C20*Debts!$C$8/12,0)+IF(D20>0,D20*Debts!$C$9/12,0)+IF(E20>0,E20*Debts!$C$10/12,0)+IF(F20>0,F20*Debts!$C$11/12,0)+IF(G20>0,G20*Debts!$C$12/12,0)+IF(H20>0,H20*Debts!$C$13/12,0)+IF(I20>0,I20*Debts!$C$14/12,0)+IF(J20>0,J20*Debts!$C$15/12,0) -> 161.76461 | L21: =SUM(C21:J21) -> 26526.531
A22: =15 -> 15 | B22: =IF(L21<=0,0,Debts!$D$16+Debts!$B$4) -> 1200 | C22: =IF(C21<=0,0,MAX(0,C21*(1+Debts!$C$8/12)-MIN(C21*(1+Debts!$C$8/12),Debts!$D$8)-IF(AND(C21>0,Debts!$E$8=MIN(IF(C21>0,Debts!$E$8,999),IF(D21>0,Debts!$E$9,999),IF(E21>0,Debts!$E$10,999),IF(F21>0,Debts!$E$11,999),IF(G21>0,Debts!$E$12,999),IF(H21>0,Debts!$E$13,999),IF(I21>0,Debts!$E$14,999),IF(J21>0,Debts!$E$15,999))),MAX(0,(B22-(MIN(C21+0,C21*(1+Debts!$C$8/12))*0+MIN(C21*(1+Debts!$C$8/12),Debts!$D$8)+MIN(C21+0,D21*(1+Debts!$C$9/12))*0+MIN(D21*(1+Debts!$C$9/12),Debts!$D$9)+MIN(C21+0,E21*(1+Debts!$C$10/12))*0+MIN(E21*(1+Debts!$C$10/12),Debts!$D$10)+MIN(C21+0,F21*(1+Debts!$C$11/12))*0+MIN(F21*(1+Debts!$C$11/12),Debts!$D$11)+MIN(C21+0,G21*(1+Debts!$C$12/12))*0+MIN(G21*(1+Debts!$C$12/12),Debts!$D$12)+MIN(C21+0,H21*(1+Debts!$C$13/12))*0+MIN(H21*(1+Debts!$C$13/12),Debts!$D$13)+MIN(C21+0,I21*(1+Debts!$C$14/12))*0+MIN(I21*(1+Debts!$C$14/12),Debts!$D$14)+MIN(C21+0,J21*(1+Debts!$C$15/12))*0+MIN(J21*(1+Debts!$C$15/12),Debts!$D$15)))),0))) -> 0 | D22: =IF(D21<=0,0,MAX(0,D21*(1+Debts!$C$9/12)-MIN(D21*(1+Debts!$C$9/12),Debts!$D$9)-IF(AND(D21>0,Debts!$E$9=MIN(IF(C21>0,Debts!$E$8,999),IF(D21>0,Debts!$E$9,999),IF(E21>0,Debts!$E$10,999),IF(F21>0,Debts!$E$11,999),IF(G21>0,Debts!$E$12,999),IF(H21>0,Debts!$E$13,999),IF(I21>0,Debts!$E$14,999),IF(J21>0,Debts!$E$15,999))),MAX(0,(B22-(MIN(C21+0,C21*(1+Debts!$C$8/12))*0+MIN(C21*(1+Debts!$C$8/12),Debts!$D$8)+MIN(C21+0,D21*(1+Debts!$C$9/12))*0+MIN(D21*(1+Debts!$C$9/12),Debts!$D$9)+MIN(C21+0,E21*(1+Debts!$C$10/12))*0+MIN(E21*(1+Debts!$C$10/12),Debts!$D$10)+MIN(C21+0,F21*(1+Debts!$C$11/12))*0+MIN(F21*(1+Debts!$C$11/12),Debts!$D$11)+MIN(C21+0,G21*(1+Debts!$C$12/12))*0+MIN(G21*(1+Debts!$C$12/12),Debts!$D$12)+MIN(C21+0,H21*(1+Debts!$C$13/12))*0+MIN(H21*(1+Debts!$C$13/12),Debts!$D$13)+MIN(C21+0,I21*(1+Debts!$C$14/12))*0+MIN(I21*(1+Debts!$C$14/12),Debts!$D$14)+MIN(C21+0,J21*(1+Debts!$C$15/12))*0+MIN(J21*(1+Debts!$C$15/12),Debts!$D$15)))),0))) -> 747.08651 | E22: =IF(E21<=0,0,MAX(0,E21*(1+Debts!$C$10/12)-MIN(E21*(1+Debts!$C$10/12),Debts!$D$10)-IF(AND(E21>0,Debts!$E$10=MIN(IF(C21>0,Debts!$E$8,999),IF(D21>0,Debts!$E$9,999),IF(E21>0,Debts!$E$10,999),IF(F21>0,Debts!$E$11,999),IF(G21>0,Debts!$E$12,999),IF(H21>0,Debts!$E$13,999),IF(I21>0,Debts!$E$14,999),IF(J21>0,Debts!$E$15,999))),MAX(0,(B22-(MIN(C21+0,C21*(1+Debts!$C$8/12))*0+MIN(C21*(1+Debts!$C$8/12),Debts!$D$8)+MIN(C21+0,D21*(1+Debts!$C$9/12))*0+MIN(D21*(1+Debts!$C$9/12),Debts!$D$9)+MIN(C21+0,E21*(1+Debts!$C$10/12))*0+MIN(E21*(1+Debts!$C$10/12),Debts!$D$10)+MIN(C21+0,F21*(1+Debts!$C$11/12))*0+MIN(F21*(1+Debts!$C$11/12),Debts!$D$11)+MIN(C21+0,G21*(1+Debts!$C$12/12))*0+MIN(G21*(1+Debts!$C$12/12),Debts!$D$12)+MIN(C21+0,H21*(1+Debts!$C$13/12))*0+MIN(H21*(1+Debts!$C$13/12),Debts!$D$13)+MIN(C21+0,I21*(1+Debts!$C$14/12))*0+MIN(I21*(1+Debts!$C$14/12),Debts!$D$14)+MIN(C21+0,J21*(1+Debts!$C$15/12))*0+MIN(J21*(1+Debts!$C$15/12),Debts!$D$15)))),0))) -> 8017.8455 | F22: =IF(F21<=0,0,MAX(0,F21*(1+Debts!$C$11/12)-MIN(F21*(1+Debts!$C$11/12),Debts!$D$11)-IF(AND(F21>0,Debts!$E$11=MIN(IF(C21>0,Debts!$E$8,999),IF(D21>0,Debts!$E$9,999),IF(E21>0,Debts!$E$10,999),IF(F21>0,Debts!$E$11,999),IF(G21>0,Debts!$E$12,999),IF(H21>0,Debts!$E$13,999),IF(I21>0,Debts!$E$14,999),IF(J21>0,Debts!$E$15,999))),MAX(0,(B22-(MIN(C21+0,C21*(1+Debts!$C$8/12))*0+MIN(C21*(1+Debts!$C$8/12),Debts!$D$8)+MIN(C21+0,D21*(1+Debts!$C$9/12))*0+MIN(D21*(1+Debts!$C$9/12),Debts!$D$9)+MIN(C21+0,E21*(1+Debts!$C$10/12))*0+MIN(E21*(1+Debts!$C$10/12),Debts!$D$10)+MIN(C21+0,F21*(1+Debts!$C$11/12))*0+MIN(F21*(1+Debts!$C$11/12),Debts!$D$11)+MIN(C21+0,G21*(1+Debts!$C$12/12))*0+MIN(G21*(1+Debts!$C$12/12),Debts!$D$12)+MIN(C21+0,H21*(1+Debts!$C$13/12))*0+MIN(H21*(1+Debts!$C$13/12),Debts!$D$13)+MIN(C21+0,I21*(1+Debts!$C$14/12))*0+MIN(I21*(1+Debts!$C$14/12),Debts!$D$14)+MIN(C21+0,J21*(1+Debts!$C$15/12))*0+MIN(J21*(1+Debts!$C$15/12),Debts!$D$15)))),0))) -> 16560.405 | G22: =IF(G21<=0,0,MAX(0,G21*(1+Debts!$C$12/12)-MIN(G21*(1+Debts!$C$12/12),Debts!$D$12)-IF(AND(G21>0,Debts!$E$12=MIN(IF(C21>0,Debts!$E$8,999),IF(D21>0,Debts!$E$9,999),IF(E21>0,Debts!$E$10,999),IF(F21>0,Debts!$E$11,999),IF(G21>0,Debts!$E$12,999),IF(H21>0,Debts!$E$13,999),IF(I21>0,Debts!$E$14,999),IF(J21>0,Debts!$E$15,999))),MAX(0,(B22-(MIN(C21+0,C21*(1+Debts!$C$8/12))*0+MIN(C21*(1+Debts!$C$8/12),Debts!$D$8)+MIN(C21+0,D21*(1+Debts!$C$9/12))*0+MIN(D21*(1+Debts!$C$9/12),Debts!$D$9)+MIN(C21+0,E21*(1+Debts!$C$10/12))*0+MIN(E21*(1+Debts!$C$10/12),Debts!$D$10)+MIN(C21+0,F21*(1+Debts!$C$11/12))*0+MIN(F21*(1+Debts!$C$11/12),Debts!$D$11)+MIN(C21+0,G21*(1+Debts!$C$12/12))*0+MIN(G21*(1+Debts!$C$12/12),Debts!$D$12)+MIN(C21+0,H21*(1+Debts!$C$13/12))*0+MIN(H21*(1+Debts!$C$13/12),Debts!$D$13)+MIN(C21+0,I21*(1+Debts!$C$14/12))*0+MIN(I21*(1+Debts!$C$14/12),Debts!$D$14)+MIN(C21+0,J21*(1+Debts!$C$15/12))*0+MIN(J21*(1+Debts!$C$15/12),Debts!$D$15)))),0))) -> 150 | H22: =IF(H21<=0,0,MAX(0,H21*(1+Debts!$C$13/12)-MIN(H21*(1+Debts!$C$13/12),Debts!$D$13)-IF(AND(H21>0,Debts!$E$13=MIN(IF(C21>0,Debts!$E$8,999),IF(D21>0,Debts!$E$9,999),IF(E21>0,Debts!$E$10,999),IF(F21>0,Debts!$E$11,999),IF(G21>0,Debts!$E$12,999),IF(H21>0,Debts!$E$13,999),IF(I21>0,Debts!$E$14,999),IF(J21>0,Debts!$E$15,999))),MAX(0,(B22-(MIN(C21+0,C21*(1+Debts!$C$8/12))*0+MIN(C21*(1+Debts!$C$8/12),Debts!$D$8)+MIN(C21+0,D21*(1+Debts!$C$9/12))*0+MIN(D21*(1+Debts!$C$9/12),Debts!$D$9)+MIN(C21+0,E21*(1+Debts!$C$10/12))*0+MIN(E21*(1+Debts!$C$10/12),Debts!$D$10)+MIN(C21+0,F21*(1+Debts!$C$11/12))*0+MIN(F21*(1+Debts!$C$11/12),Debts!$D$11)+MIN(C21+0,G21*(1+Debts!$C$12/12))*0+MIN(G21*(1+Debts!$C$12/12),Debts!$D$12)+MIN(C21+0,H21*(1+Debts!$C$13/12))*0+MIN(H21*(1+Debts!$C$13/12),Debts!$D$13)+MIN(C21+0,I21*(1+Debts!$C$14/12))*0+MIN(I21*(1+Debts!$C$14/12),Debts!$D$14)+MIN(C21+0,J21*(1+Debts!$C$15/12))*0+MIN(J21*(1+Debts!$C$15/12),Debts!$D$15)))),0))) -> 0 | I22: =IF(I21<=0,0,MAX(0,I21*(1+Debts!$C$14/12)-MIN(I21*(1+Debts!$C$14/12),Debts!$D$14)-IF(AND(I21>0,Debts!$E$14=MIN(IF(C21>0,Debts!$E$8,999),IF(D21>0,Debts!$E$9,999),IF(E21>0,Debts!$E$10,999),IF(F21>0,Debts!$E$11,999),IF(G21>0,Debts!$E$12,999),IF(H21>0,Debts!$E$13,999),IF(I21>0,Debts!$E$14,999),IF(J21>0,Debts!$E$15,999))),MAX(0,(B22-(MIN(C21+0,C21*(1+Debts!$C$8/12))*0+MIN(C21*(1+Debts!$C$8/12),Debts!$D$8)+MIN(C21+0,D21*(1+Debts!$C$9/12))*0+MIN(D21*(1+Debts!$C$9/12),Debts!$D$9)+MIN(C21+0,E21*(1+Debts!$C$10/12))*0+MIN(E21*(1+Debts!$C$10/12),Debts!$D$10)+MIN(C21+0,F21*(1+Debts!$C$11/12))*0+MIN(F21*(1+Debts!$C$11/12),Debts!$D$11)+MIN(C21+0,G21*(1+Debts!$C$12/12))*0+MIN(G21*(1+Debts!$C$12/12),Debts!$D$12)+MIN(C21+0,H21*(1+Debts!$C$13/12))*0+MIN(H21*(1+Debts!$C$13/12),Debts!$D$13)+MIN(C21+0,I21*(1+Debts!$C$14/12))*0+MIN(I21*(1+Debts!$C$14/12),Debts!$D$14)+MIN(C21+0,J21*(1+Debts!$C$15/12))*0+MIN(J21*(1+Debts!$C$15/12),Debts!$D$15)))),0))) -> 0 | J22: =IF(J21<=0,0,MAX(0,J21*(1+Debts!$C$15/12)-MIN(J21*(1+Debts!$C$15/12),Debts!$D$15)-IF(AND(J21>0,Debts!$E$15=MIN(IF(C21>0,Debts!$E$8,999),IF(D21>0,Debts!$E$9,999),IF(E21>0,Debts!$E$10,999),IF(F21>0,Debts!$E$11,999),IF(G21>0,Debts!$E$12,999),IF(H21>0,Debts!$E$13,999),IF(I21>0,Debts!$E$14,999),IF(J21>0,Debts!$E$15,999))),MAX(0,(B22-(MIN(C21+0,C21*(1+Debts!$C$8/12))*0+MIN(C21*(1+Debts!$C$8/12),Debts!$D$8)+MIN(C21+0,D21*(1+Debts!$C$9/12))*0+MIN(D21*(1+Debts!$C$9/12),Debts!$D$9)+MIN(C21+0,E21*(1+Debts!$C$10/12))*0+MIN(E21*(1+Debts!$C$10/12),Debts!$D$10)+MIN(C21+0,F21*(1+Debts!$C$11/12))*0+MIN(F21*(1+Debts!$C$11/12),Debts!$D$11)+MIN(C21+0,G21*(1+Debts!$C$12/12))*0+MIN(G21*(1+Debts!$C$12/12),Debts!$D$12)+MIN(C21+0,H21*(1+Debts!$C$13/12))*0+MIN(H21*(1+Debts!$C$13/12),Debts!$D$13)+MIN(C21+0,I21*(1+Debts!$C$14/12))*0+MIN(I21*(1+Debts!$C$14/12),Debts!$D$14)+MIN(C21+0,J21*(1+Debts!$C$15/12))*0+MIN(J21*(1+Debts!$C$15/12),Debts!$D$15)))),0))) -> 0 | K22: =IF(C21>0,C21*Debts!$C$8/12,0)+IF(D21>0,D21*Debts!$C$9/12,0)+IF(E21>0,E21*Debts!$C$10/12,0)+IF(F21>0,F21*Debts!$C$11/12,0)+IF(G21>0,G21*Debts!$C$12/12,0)+IF(H21>0,H21*Debts!$C$13/12,0)+IF(I21>0,I21*Debts!$C$14/12,0)+IF(J21>0,J21*Debts!$C$15/12,0) -> 148.80641 | L22: =SUM(C22:J22) -> 25475.337
A23: =16 -> 16 | B23: =IF(L22<=0,0,Debts!$D$16+Debts!$B$4) -> 1200 | C23: =IF(C22<=0,0,MAX(0,C22*(1+Debts!$C$8/12)-MIN(C22*(1+Debts!$C$8/12),Debts!$D$8)-IF(AND(C22>0,Debts!$E$8=MIN(IF(C22>0,Debts!$E$8,999),IF(D22>0,Debts!$E$9,999),IF(E22>0,Debts!$E$10,999),IF(F22>0,Debts!$E$11,999),IF(G22>0,Debts!$E$12,999),IF(H22>0,Debts!$E$13,999),IF(I22>0,Debts!$E$14,999),IF(J22>0,Debts!$E$15,999))),MAX(0,(B23-(MIN(C22+0,C22*(1+Debts!$C$8/12))*0+MIN(C22*(1+Debts!$C$8/12),Debts!$D$8)+MIN(C22+0,D22*(1+Debts!$C$9/12))*0+MIN(D22*(1+Debts!$C$9/12),Debts!$D$9)+MIN(C22+0,E22*(1+Debts!$C$10/12))*0+MIN(E22*(1+Debts!$C$10/12),Debts!$D$10)+MIN(C22+0,F22*(1+Debts!$C$11/12))*0+MIN(F22*(1+Debts!$C$11/12),Debts!$D$11)+MIN(C22+0,G22*(1+Debts!$C$12/12))*0+MIN(G22*(1+Debts!$C$12/12),Debts!$D$12)+MIN(C22+0,H22*(1+Debts!$C$13/12))*0+MIN(H22*(1+Debts!$C$13/12),Debts!$D$13)+MIN(C22+0,I22*(1+Debts!$C$14/12))*0+MIN(I22*(1+Debts!$C$14/12),Debts!$D$14)+MIN(C22+0,J22*(1+Debts!$C$15/12))*0+MIN(J22*(1+Debts!$C$15/12),Debts!$D$15)))),0))) -> 0 | D23: =IF(D22<=0,0,MAX(0,D22*(1+Debts!$C$9/12)-MIN(D22*(1+Debts!$C$9/12),Debts!$D$9)-IF(AND(D22>0,Debts!$E$9=MIN(IF(C22>0,Debts!$E$8,999),IF(D22>0,Debts!$E$9,999),IF(E22>0,Debts!$E$10,999),IF(F22>0,Debts!$E$11,999),IF(G22>0,Debts!$E$12,999),IF(H22>0,Debts!$E$13,999),IF(I22>0,Debts!$E$14,999),IF(J22>0,Debts!$E$15,999))),MAX(0,(B23-(MIN(C22+0,C22*(1+Debts!$C$8/12))*0+MIN(C22*(1+Debts!$C$8/12),Debts!$D$8)+MIN(C22+0,D22*(1+Debts!$C$9/12))*0+MIN(D22*(1+Debts!$C$9/12),Debts!$D$9)+MIN(C22+0,E22*(1+Debts!$C$10/12))*0+MIN(E22*(1+Debts!$C$10/12),Debts!$D$10)+MIN(C22+0,F22*(1+Debts!$C$11/12))*0+MIN(F22*(1+Debts!$C$11/12),Debts!$D$11)+MIN(C22+0,G22*(1+Debts!$C$12/12))*0+MIN(G22*(1+Debts!$C$12/12),Debts!$D$12)+MIN(C22+0,H22*(1+Debts!$C$13/12))*0+MIN(H22*(1+Debts!$C$13/12),Debts!$D$13)+MIN(C22+0,I22*(1+Debts!$C$14/12))*0+MIN(I22*(1+Debts!$C$14/12),Debts!$D$14)+MIN(C22+0,J22*(1+Debts!$C$15/12))*0+MIN(J22*(1+Debts!$C$15/12),Debts!$D$15)))),0))) -> 130.72084 | E23: =IF(E22<=0,0,MAX(0,E22*(1+Debts!$C$10/12)-MIN(E22*(1+Debts!$C$10/12),Debts!$D$10)-IF(AND(E22>0,Debts!$E$10=MIN(IF(C22>0,Debts!$E$8,999),IF(D22>0,Debts!$E$9,999),IF(E22>0,Debts!$E$10,999),IF(F22>0,Debts!$E$11,999),IF(G22>0,Debts!$E$12,999),IF(H22>0,Debts!$E$13,999),IF(I22>0,Debts!$E$14,999),IF(J22>0,Debts!$E$15,999))),MAX(0,(B23-(MIN(C22+0,C22*(1+Debts!$C$8/12))*0+MIN(C22*(1+Debts!$C$8/12),Debts!$D$8)+MIN(C22+0,D22*(1+Debts!$C$9/12))*0+MIN(D22*(1+Debts!$C$9/12),Debts!$D$9)+MIN(C22+0,E22*(1+Debts!$C$10/12))*0+MIN(E22*(1+Debts!$C$10/12),Debts!$D$10)+MIN(C22+0,F22*(1+Debts!$C$11/12))*0+MIN(F22*(1+Debts!$C$11/12),Debts!$D$11)+MIN(C22+0,G22*(1+Debts!$C$12/12))*0+MIN(G22*(1+Debts!$C$12/12),Debts!$D$12)+MIN(C22+0,H22*(1+Debts!$C$13/12))*0+MIN(H22*(1+Debts!$C$13/12),Debts!$D$13)+MIN(C22+0,I22*(1+Debts!$C$14/12))*0+MIN(I22*(1+Debts!$C$14/12),Debts!$D$14)+MIN(C22+0,J22*(1+Debts!$C$15/12))*0+MIN(J22*(1+Debts!$C$15/12),Debts!$D$15)))),0))) -> 7753.9481 | F23: =IF(F22<=0,0,MAX(0,F22*(1+Debts!$C$11/12)-MIN(F22*(1+Debts!$C$11/12),Debts!$D$11)-IF(AND(F22>0,Debts!$E$11=MIN(IF(C22>0,Debts!$E$8,999),IF(D22>0,Debts!$E$9,999),IF(E22>0,Debts!$E$10,999),IF(F22>0,Debts!$E$11,999),IF(G22>0,Debts!$E$12,999),IF(H22>0,Debts!$E$13,999),IF(I22>0,Debts!$E$14,999),IF(J22>0,Debts!$E$15,999))),MAX(0,(B23-(MIN(C22+0,C22*(1+Debts!$C$8/12))*0+MIN(C22*(1+Debts!$C$8/12),Debts!$D$8)+MIN(C22+0,D22*(1+Debts!$C$9/12))*0+MIN(D22*(1+Debts!$C$9/12),Debts!$D$9)+MIN(C22+0,E22*(1+Debts!$C$10/12))*0+MIN(E22*(1+Debts!$C$10/12),Debts!$D$10)+MIN(C22+0,F22*(1+Debts!$C$11/12))*0+MIN(F22*(1+Debts!$C$11/12),Debts!$D$11)+MIN(C22+0,G22*(1+Debts!$C$12/12))*0+MIN(G22*(1+Debts!$C$12/12),Debts!$D$12)+MIN(C22+0,H22*(1+Debts!$C$13/12))*0+MIN(H22*(1+Debts!$C$13/12),Debts!$D$13)+MIN(C22+0,I22*(1+Debts!$C$14/12))*0+MIN(I22*(1+Debts!$C$14/12),Debts!$D$14)+MIN(C22+0,J22*(1+Debts!$C$15/12))*0+MIN(J22*(1+Debts!$C$15/12),Debts!$D$15)))),0))) -> 16426.307 | G23: =IF(G22<=0,0,MAX(0,G22*(1+Debts!$C$12/12)-MIN(G22*(1+Debts!$C$12/12),Debts!$D$12)-IF(AND(G22>0,Debts!$E$12=MIN(IF(C22>0,Debts!$E$8,999),IF(D22>0,Debts!$E$9,999),IF(E22>0,Debts!$E$10,999),IF(F22>0,Debts!$E$11,999),IF(G22>0,Debts!$E$12,999),IF(H22>0,Debts!$E$13,999),IF(I22>0,Debts!$E$14,999),IF(J22>0,Debts!$E$15,999))),MAX(0,(B23-(MIN(C22+0,C22*(1+Debts!$C$8/12))*0+MIN(C22*(1+Debts!$C$8/12),Debts!$D$8)+MIN(C22+0,D22*(1+Debts!$C$9/12))*0+MIN(D22*(1+Debts!$C$9/12),Debts!$D$9)+MIN(C22+0,E22*(1+Debts!$C$10/12))*0+MIN(E22*(1+Debts!$C$10/12),Debts!$D$10)+MIN(C22+0,F22*(1+Debts!$C$11/12))*0+MIN(F22*(1+Debts!$C$11/12),Debts!$D$11)+MIN(C22+0,G22*(1+Debts!$C$12/12))*0+MIN(G22*(1+Debts!$C$12/12),Debts!$D$12)+MIN(C22+0,H22*(1+Debts!$C$13/12))*0+MIN(H22*(1+Debts!$C$13/12),Debts!$D$13)+MIN(C22+0,I22*(1+Debts!$C$14/12))*0+MIN(I22*(1+Debts!$C$14/12),Debts!$D$14)+MIN(C22+0,J22*(1+Debts!$C$15/12))*0+MIN(J22*(1+Debts!$C$15/12),Debts!$D$15)))),0))) -> 100 | H23: =IF(H22<=0,0,MAX(0,H22*(1+Debts!$C$13/12)-MIN(H22*(1+Debts!$C$13/12),Debts!$D$13)-IF(AND(H22>0,Debts!$E$13=MIN(IF(C22>0,Debts!$E$8,999),IF(D22>0,Debts!$E$9,999),IF(E22>0,Debts!$E$10,999),IF(F22>0,Debts!$E$11,999),IF(G22>0,Debts!$E$12,999),IF(H22>0,Debts!$E$13,999),IF(I22>0,Debts!$E$14,999),IF(J22>0,Debts!$E$15,999))),MAX(0,(B23-(MIN(C22+0,C22*(1+Debts!$C$8/12))*0+MIN(C22*(1+Debts!$C$8/12),Debts!$D$8)+MIN(C22+0,D22*(1+Debts!$C$9/12))*0+MIN(D22*(1+Debts!$C$9/12),Debts!$D$9)+MIN(C22+0,E22*(1+Debts!$C$10/12))*0+MIN(E22*(1+Debts!$C$10/12),Debts!$D$10)+MIN(C22+0,F22*(1+Debts!$C$11/12))*0+MIN(F22*(1+Debts!$C$11/12),Debts!$D$11)+MIN(C22+0,G22*(1+Debts!$C$12/12))*0+MIN(G22*(1+Debts!$C$12/12),Debts!$D$12)+MIN(C22+0,H22*(1+Debts!$C$13/12))*0+MIN(H22*(1+Debts!$C$13/12),Debts!$D$13)+MIN(C22+0,I22*(1+Debts!$C$14/12))*0+MIN(I22*(1+Debts!$C$14/12),Debts!$D$14)+MIN(C22+0,J22*(1+Debts!$C$15/12))*0+MIN(J22*(1+Debts!$C$15/12),Debts!$D$15)))),0))) -> 0 | I23: =IF(I22<=0,0,MAX(0,I22*(1+Debts!$C$14/12)-MIN(I22*(1+Debts!$C$14/12),Debts!$D$14)-IF(AND(I22>0,Debts!$E$14=MIN(IF(C22>0,Debts!$E$8,999),IF(D22>0,Debts!$E$9,999),IF(E22>0,Debts!$E$10,999),IF(F22>0,Debts!$E$11,999),IF(G22>0,Debts!$E$12,999),IF(H22>0,Debts!$E$13,999),IF(I22>0,Debts!$E$14,999),IF(J22>0,Debts!$E$15,999))),MAX(0,(B23-(MIN(C22+0,C22*(1+Debts!$C$8/12))*0+MIN(C22*(1+Debts!$C$8/12),Debts!$D$8)+MIN(C22+0,D22*(1+Debts!$C$9/12))*0+MIN(D22*(1+Debts!$C$9/12),Debts!$D$9)+MIN(C22+0,E22*(1+Debts!$C$10/12))*0+MIN(E22*(1+Debts!$C$10/12),Debts!$D$10)+MIN(C22+0,F22*(1+Debts!$C$11/12))*0+MIN(F22*(1+Debts!$C$11/12),Debts!$D$11)+MIN(C22+0,G22*(1+Debts!$C$12/12))*0+MIN(G22*(1+Debts!$C$12/12),Debts!$D$12)+MIN(C22+0,H22*(1+Debts!$C$13/12))*0+MIN(H22*(1+Debts!$C$13/12),Debts!$D$13)+MIN(C22+0,I22*(1+Debts!$C$14/12))*0+MIN(I22*(1+Debts!$C$14/12),Debts!$D$14)+MIN(C22+0,J22*(1+Debts!$C$15/12))*0+MIN(J22*(1+Debts!$C$15/12),Debts!$D$15)))),0))) -> 0 | J23: =IF(J22<=0,0,MAX(0,J22*(1+Debts!$C$15/12)-MIN(J22*(1+Debts!$C$15/12),Debts!$D$15)-IF(AND(J22>0,Debts!$E$15=MIN(IF(C22>0,Debts!$E$8,999),IF(D22>0,Debts!$E$9,999),IF(E22>0,Debts!$E$10,999),IF(F22>0,Debts!$E$11,999),IF(G22>0,Debts!$E$12,999),IF(H22>0,Debts!$E$13,999),IF(I22>0,Debts!$E$14,999),IF(J22>0,Debts!$E$15,999))),MAX(0,(B23-(MIN(C22+0,C22*(1+Debts!$C$8/12))*0+MIN(C22*(1+Debts!$C$8/12),Debts!$D$8)+MIN(C22+0,D22*(1+Debts!$C$9/12))*0+MIN(D22*(1+Debts!$C$9/12),Debts!$D$9)+MIN(C22+0,E22*(1+Debts!$C$10/12))*0+MIN(E22*(1+Debts!$C$10/12),Debts!$D$10)+MIN(C22+0,F22*(1+Debts!$C$11/12))*0+MIN(F22*(1+Debts!$C$11/12),Debts!$D$11)+MIN(C22+0,G22*(1+Debts!$C$12/12))*0+MIN(G22*(1+Debts!$C$12/12),Debts!$D$12)+MIN(C22+0,H22*(1+Debts!$C$13/12))*0+MIN(H22*(1+Debts!$C$13/12),Debts!$D$13)+MIN(C22+0,I22*(1+Debts!$C$14/12))*0+MIN(I22*(1+Debts!$C$14/12),Debts!$D$14)+MIN(C22+0,J22*(1+Debts!$C$15/12))*0+MIN(J22*(1+Debts!$C$15/12),Debts!$D$15)))),0))) -> 0 | K23: =IF(C22>0,C22*Debts!$C$8/12,0)+IF(D22>0,D22*Debts!$C$9/12,0)+IF(E22>0,E22*Debts!$C$10/12,0)+IF(F22>0,F22*Debts!$C$11/12,0)+IF(G22>0,G22*Debts!$C$12/12,0)+IF(H22>0,H22*Debts!$C$13/12,0)+IF(I22>0,I22*Debts!$C$14/12,0)+IF(J22>0,J22*Debts!$C$15/12,0) -> 135.6388 | L23: =SUM(C23:J23) -> 24410.976
A24: =17 -> 17 | B24: =IF(L23<=0,0,Debts!$D$16+Debts!$B$4) -> 1200 | C24: =IF(C23<=0,0,MAX(0,C23*(1+Debts!$C$8/12)-MIN(C23*(1+Debts!$C$8/12),Debts!$D$8)-IF(AND(C23>0,Debts!$E$8=MIN(IF(C23>0,Debts!$E$8,999),IF(D23>0,Debts!$E$9,999),IF(E23>0,Debts!$E$10,999),IF(F23>0,Debts!$E$11,999),IF(G23>0,Debts!$E$12,999),IF(H23>0,Debts!$E$13,999),IF(I23>0,Debts!$E$14,999),IF(J23>0,Debts!$E$15,999))),MAX(0,(B24-(MIN(C23+0,C23*(1+Debts!$C$8/12))*0+MIN(C23*(1+Debts!$C$8/12),Debts!$D$8)+MIN(C23+0,D23*(1+Debts!$C$9/12))*0+MIN(D23*(1+Debts!$C$9/12),Debts!$D$9)+MIN(C23+0,E23*(1+Debts!$C$10/12))*0+MIN(E23*(1+Debts!$C$10/12),Debts!$D$10)+MIN(C23+0,F23*(1+Debts!$C$11/12))*0+MIN(F23*(1+Debts!$C$11/12),Debts!$D$11)+MIN(C23+0,G23*(1+Debts!$C$12/12))*0+MIN(G23*(1+Debts!$C$12/12),Debts!$D$12)+MIN(C23+0,H23*(1+Debts!$C$13/12))*0+MIN(H23*(1+Debts!$C$13/12),Debts!$D$13)+MIN(C23+0,I23*(1+Debts!$C$14/12))*0+MIN(I23*(1+Debts!$C$14/12),Debts!$D$14)+MIN(C23+0,J23*(1+Debts!$C$15/12))*0+MIN(J23*(1+Debts!$C$15/12),Debts!$D$15)))),0))) -> 0 | D24: =IF(D23<=0,0,MAX(0,D23*(1+Debts!$C$9/12)-MIN(D23*(1+Debts!$C$9/12),Debts!$D$9)-IF(AND(D23>0,Debts!$E$9=MIN(IF(C23>0,Debts!$E$8,999),IF(D23>0,Debts!$E$9,999),IF(E23>0,Debts!$E$10,999),IF(F23>0,Debts!$E$11,999),IF(G23>0,Debts!$E$12,999),IF(H23>0,Debts!$E$13,999),IF(I23>0,Debts!$E$14,999),IF(J23>0,Debts!$E$15,999))),MAX(0,(B24-(MIN(C23+0,C23*(1+Debts!$C$8/12))*0+MIN(C23*(1+Debts!$C$8/12),Debts!$D$8)+MIN(C23+0,D23*(1+Debts!$C$9/12))*0+MIN(D23*(1+Debts!$C$9/12),Debts!$D$9)+MIN(C23+0,E23*(1+Debts!$C$10/12))*0+MIN(E23*(1+Debts!$C$10/12),Debts!$D$10)+MIN(C23+0,F23*(1+Debts!$C$11/12))*0+MIN(F23*(1+Debts!$C$11/12),Debts!$D$11)+MIN(C23+0,G23*(1+Debts!$C$12/12))*0+MIN(G23*(1+Debts!$C$12/12),Debts!$D$12)+MIN(C23+0,H23*(1+Debts!$C$13/12))*0+MIN(H23*(1+Debts!$C$13/12),Debts!$D$13)+MIN(C23+0,I23*(1+Debts!$C$14/12))*0+MIN(I23*(1+Debts!$C$14/12),Debts!$D$14)+MIN(C23+0,J23*(1+Debts!$C$15/12))*0+MIN(J23*(1+Debts!$C$15/12),Debts!$D$15)))),0))) -> 0 | E24: =IF(E23<=0,0,MAX(0,E23*(1+Debts!$C$10/12)-MIN(E23*(1+Debts!$C$10/12),Debts!$D$10)-IF(AND(E23>0,Debts!$E$10=MIN(IF(C23>0,Debts!$E$8,999),IF(D23>0,Debts!$E$9,999),IF(E23>0,Debts!$E$10,999),IF(F23>0,Debts!$E$11,999),IF(G23>0,Debts!$E$12,999),IF(H23>0,Debts!$E$13,999),IF(I23>0,Debts!$E$14,999),IF(J23>0,Debts!$E$15,999))),MAX(0,(B24-(MIN(C23+0,C23*(1+Debts!$C$8/12))*0+MIN(C23*(1+Debts!$C$8/12),Debts!$D$8)+MIN(C23+0,D23*(1+Debts!$C$9/12))*0+MIN(D23*(1+Debts!$C$9/12),Debts!$D$9)+MIN(C23+0,E23*(1+Debts!$C$10/12))*0+MIN(E23*(1+Debts!$C$10/12),Debts!$D$10)+MIN(C23+0,F23*(1+Debts!$C$11/12))*0+MIN(F23*(1+Debts!$C$11/12),Debts!$D$11)+MIN(C23+0,G23*(1+Debts!$C$12/12))*0+MIN(G23*(1+Debts!$C$12/12),Debts!$D$12)+MIN(C23+0,H23*(1+Debts!$C$13/12))*0+MIN(H23*(1+Debts!$C$13/12),Debts!$D$13)+MIN(C23+0,I23*(1+Debts!$C$14/12))*0+MIN(I23*(1+Debts!$C$14/12),Debts!$D$14)+MIN(C23+0,J23*(1+Debts!$C$15/12))*0+MIN(J23*(1+Debts!$C$15/12),Debts!$D$15)))),0))) -> 7488.5333 | F24: =IF(F23<=0,0,MAX(0,F23*(1+Debts!$C$11/12)-MIN(F23*(1+Debts!$C$11/12),Debts!$D$11)-IF(AND(F23>0,Debts!$E$11=MIN(IF(C23>0,Debts!$E$8,999),IF(D23>0,Debts!$E$9,999),IF(E23>0,Debts!$E$10,999),IF(F23>0,Debts!$E$11,999),IF(G23>0,Debts!$E$12,999),IF(H23>0,Debts!$E$13,999),IF(I23>0,Debts!$E$14,999),IF(J23>0,Debts!$E$15,999))),MAX(0,(B24-(MIN(C23+0,C23*(1+Debts!$C$8/12))*0+MIN(C23*(1+Debts!$C$8/12),Debts!$D$8)+MIN(C23+0,D23*(1+Debts!$C$9/12))*0+MIN(D23*(1+Debts!$C$9/12),Debts!$D$9)+MIN(C23+0,E23*(1+Debts!$C$10/12))*0+MIN(E23*(1+Debts!$C$10/12),Debts!$D$10)+MIN(C23+0,F23*(1+Debts!$C$11/12))*0+MIN(F23*(1+Debts!$C$11/12),Debts!$D$11)+MIN(C23+0,G23*(1+Debts!$C$12/12))*0+MIN(G23*(1+Debts!$C$12/12),Debts!$D$12)+MIN(C23+0,H23*(1+Debts!$C$13/12))*0+MIN(H23*(1+Debts!$C$13/12),Debts!$D$13)+MIN(C23+0,I23*(1+Debts!$C$14/12))*0+MIN(I23*(1+Debts!$C$14/12),Debts!$D$14)+MIN(C23+0,J23*(1+Debts!$C$15/12))*0+MIN(J23*(1+Debts!$C$15/12),Debts!$D$15)))),0))) -> 16291.594 | G24: =IF(G23<=0,0,MAX(0,G23*(1+Debts!$C$12/12)-MIN(G23*(1+Debts!$C$12/12),Debts!$D$12)-IF(AND(G23>0,Debts!$E$12=MIN(IF(C23>0,Debts!$E$8,999),IF(D23>0,Debts!$E$9,999),IF(E23>0,Debts!$E$10,999),IF(F23>0,Debts!$E$11,999),IF(G23>0,Debts!$E$12,999),IF(H23>0,Debts!$E$13,999),IF(I23>0,Debts!$E$14,999),IF(J23>0,Debts!$E$15,999))),MAX(0,(B24-(MIN(C23+0,C23*(1+Debts!$C$8/12))*0+MIN(C23*(1+Debts!$C$8/12),Debts!$D$8)+MIN(C23+0,D23*(1+Debts!$C$9/12))*0+MIN(D23*(1+Debts!$C$9/12),Debts!$D$9)+MIN(C23+0,E23*(1+Debts!$C$10/12))*0+MIN(E23*(1+Debts!$C$10/12),Debts!$D$10)+MIN(C23+0,F23*(1+Debts!$C$11/12))*0+MIN(F23*(1+Debts!$C$11/12),Debts!$D$11)+MIN(C23+0,G23*(1+Debts!$C$12/12))*0+MIN(G23*(1+Debts!$C$12/12),Debts!$D$12)+MIN(C23+0,H23*(1+Debts!$C$13/12))*0+MIN(H23*(1+Debts!$C$13/12),Debts!$D$13)+MIN(C23+0,I23*(1+Debts!$C$14/12))*0+MIN(I23*(1+Debts!$C$14/12),Debts!$D$14)+MIN(C23+0,J23*(1+Debts!$C$15/12))*0+MIN(J23*(1+Debts!$C$15/12),Debts!$D$15)))),0))) -> 50 | H24: =IF(H23<=0,0,MAX(0,H23*(1+Debts!$C$13/12)-MIN(H23*(1+Debts!$C$13/12),Debts!$D$13)-IF(AND(H23>0,Debts!$E$13=MIN(IF(C23>0,Debts!$E$8,999),IF(D23>0,Debts!$E$9,999),IF(E23>0,Debts!$E$10,999),IF(F23>0,Debts!$E$11,999),IF(G23>0,Debts!$E$12,999),IF(H23>0,Debts!$E$13,999),IF(I23>0,Debts!$E$14,999),IF(J23>0,Debts!$E$15,999))),MAX(0,(B24-(MIN(C23+0,C23*(1+Debts!$C$8/12))*0+MIN(C23*(1+Debts!$C$8/12),Debts!$D$8)+MIN(C23+0,D23*(1+Debts!$C$9/12))*0+MIN(D23*(1+Debts!$C$9/12),Debts!$D$9)+MIN(C23+0,E23*(1+Debts!$C$10/12))*0+MIN(E23*(1+Debts!$C$10/12),Debts!$D$10)+MIN(C23+0,F23*(1+Debts!$C$11/12))*0+MIN(F23*(1+Debts!$C$11/12),Debts!$D$11)+MIN(C23+0,G23*(1+Debts!$C$12/12))*0+MIN(G23*(1+Debts!$C$12/12),Debts!$D$12)+MIN(C23+0,H23*(1+Debts!$C$13/12))*0+MIN(H23*(1+Debts!$C$13/12),Debts!$D$13)+MIN(C23+0,I23*(1+Debts!$C$14/12))*0+MIN(I23*(1+Debts!$C$14/12),Debts!$D$14)+MIN(C23+0,J23*(1+Debts!$C$15/12))*0+MIN(J23*(1+Debts!$C$15/12),Debts!$D$15)))),0))) -> 0 | I24: =IF(I23<=0,0,MAX(0,I23*(1+Debts!$C$14/12)-MIN(I23*(1+Debts!$C$14/12),Debts!$D$14)-IF(AND(I23>0,Debts!$E$14=MIN(IF(C23>0,Debts!$E$8,999),IF(D23>0,Debts!$E$9,999),IF(E23>0,Debts!$E$10,999),IF(F23>0,Debts!$E$11,999),IF(G23>0,Debts!$E$12,999),IF(H23>0,Debts!$E$13,999),IF(I23>0,Debts!$E$14,999),IF(J23>0,Debts!$E$15,999))),MAX(0,(B24-(MIN(C23+0,C23*(1+Debts!$C$8/12))*0+MIN(C23*(1+Debts!$C$8/12),Debts!$D$8)+MIN(C23+0,D23*(1+Debts!$C$9/12))*0+MIN(D23*(1+Debts!$C$9/12),Debts!$D$9)+MIN(C23+0,E23*(1+Debts!$C$10/12))*0+MIN(E23*(1+Debts!$C$10/12),Debts!$D$10)+MIN(C23+0,F23*(1+Debts!$C$11/12))*0+MIN(F23*(1+Debts!$C$11/12),Debts!$D$11)+MIN(C23+0,G23*(1+Debts!$C$12/12))*0+MIN(G23*(1+Debts!$C$12/12),Debts!$D$12)+MIN(C23+0,H23*(1+Debts!$C$13/12))*0+MIN(H23*(1+Debts!$C$13/12),Debts!$D$13)+MIN(C23+0,I23*(1+Debts!$C$14/12))*0+MIN(I23*(1+Debts!$C$14/12),Debts!$D$14)+MIN(C23+0,J23*(1+Debts!$C$15/12))*0+MIN(J23*(1+Debts!$C$15/12),Debts!$D$15)))),0))) -> 0 | J24: =IF(J23<=0,0,MAX(0,J23*(1+Debts!$C$15/12)-MIN(J23*(1+Debts!$C$15/12),Debts!$D$15)-IF(AND(J23>0,Debts!$E$15=MIN(IF(C23>0,Debts!$E$8,999),IF(D23>0,Debts!$E$9,999),IF(E23>0,Debts!$E$10,999),IF(F23>0,Debts!$E$11,999),IF(G23>0,Debts!$E$12,999),IF(H23>0,Debts!$E$13,999),IF(I23>0,Debts!$E$14,999),IF(J23>0,Debts!$E$15,999))),MAX(0,(B24-(MIN(C23+0,C23*(1+Debts!$C$8/12))*0+MIN(C23*(1+Debts!$C$8/12),Debts!$D$8)+MIN(C23+0,D23*(1+Debts!$C$9/12))*0+MIN(D23*(1+Debts!$C$9/12),Debts!$D$9)+MIN(C23+0,E23*(1+Debts!$C$10/12))*0+MIN(E23*(1+Debts!$C$10/12),Debts!$D$10)+MIN(C23+0,F23*(1+Debts!$C$11/12))*0+MIN(F23*(1+Debts!$C$11/12),Debts!$D$11)+MIN(C23+0,G23*(1+Debts!$C$12/12))*0+MIN(G23*(1+Debts!$C$12/12),Debts!$D$12)+MIN(C23+0,H23*(1+Debts!$C$13/12))*0+MIN(H23*(1+Debts!$C$13/12),Debts!$D$13)+MIN(C23+0,I23*(1+Debts!$C$14/12))*0+MIN(I23*(1+Debts!$C$14/12),Debts!$D$14)+MIN(C23+0,J23*(1+Debts!$C$15/12))*0+MIN(J23*(1+Debts!$C$15/12),Debts!$D$15)))),0))) -> 0 | K24: =IF(C23>0,C23*Debts!$C$8/12,0)+IF(D23>0,D23*Debts!$C$9/12,0)+IF(E23>0,E23*Debts!$C$10/12,0)+IF(F23>0,F23*Debts!$C$11/12,0)+IF(G23>0,G23*Debts!$C$12/12,0)+IF(H23>0,H23*Debts!$C$13/12,0)+IF(I23>0,I23*Debts!$C$14/12,0)+IF(J23>0,J23*Debts!$C$15/12,0) -> 122.2581 | L24: =SUM(C24:J24) -> 23830.128
A25: =18 -> 18 | B25: =IF(L24<=0,0,Debts!$D$16+Debts!$B$4) -> 1200 | C25: =IF(C24<=0,0,MAX(0,C24*(1+Debts!$C$8/12)-MIN(C24*(1+Debts!$C$8/12),Debts!$D$8)-IF(AND(C24>0,Debts!$E$8=MIN(IF(C24>0,Debts!$E$8,999),IF(D24>0,Debts!$E$9,999),IF(E24>0,Debts!$E$10,999),IF(F24>0,Debts!$E$11,999),IF(G24>0,Debts!$E$12,999),IF(H24>0,Debts!$E$13,999),IF(I24>0,Debts!$E$14,999),IF(J24>0,Debts!$E$15,999))),MAX(0,(B25-(MIN(C24+0,C24*(1+Debts!$C$8/12))*0+MIN(C24*(1+Debts!$C$8/12),Debts!$D$8)+MIN(C24+0,D24*(1+Debts!$C$9/12))*0+MIN(D24*(1+Debts!$C$9/12),Debts!$D$9)+MIN(C24+0,E24*(1+Debts!$C$10/12))*0+MIN(E24*(1+Debts!$C$10/12),Debts!$D$10)+MIN(C24+0,F24*(1+Debts!$C$11/12))*0+MIN(F24*(1+Debts!$C$11/12),Debts!$D$11)+MIN(C24+0,G24*(1+Debts!$C$12/12))*0+MIN(G24*(1+Debts!$C$12/12),Debts!$D$12)+MIN(C24+0,H24*(1+Debts!$C$13/12))*0+MIN(H24*(1+Debts!$C$13/12),Debts!$D$13)+MIN(C24+0,I24*(1+Debts!$C$14/12))*0+MIN(I24*(1+Debts!$C$14/12),Debts!$D$14)+MIN(C24+0,J24*(1+Debts!$C$15/12))*0+MIN(J24*(1+Debts!$C$15/12),Debts!$D$15)))),0))) -> 0 | D25: =IF(D24<=0,0,MAX(0,D24*(1+Debts!$C$9/12)-MIN(D24*(1+Debts!$C$9/12),Debts!$D$9)-IF(AND(D24>0,Debts!$E$9=MIN(IF(C24>0,Debts!$E$8,999),IF(D24>0,Debts!$E$9,999),IF(E24>0,Debts!$E$10,999),IF(F24>0,Debts!$E$11,999),IF(G24>0,Debts!$E$12,999),IF(H24>0,Debts!$E$13,999),IF(I24>0,Debts!$E$14,999),IF(J24>0,Debts!$E$15,999))),MAX(0,(B25-(MIN(C24+0,C24*(1+Debts!$C$8/12))*0+MIN(C24*(1+Debts!$C$8/12),Debts!$D$8)+MIN(C24+0,D24*(1+Debts!$C$9/12))*0+MIN(D24*(1+Debts!$C$9/12),Debts!$D$9)+MIN(C24+0,E24*(1+Debts!$C$10/12))*0+MIN(E24*(1+Debts!$C$10/12),Debts!$D$10)+MIN(C24+0,F24*(1+Debts!$C$11/12))*0+MIN(F24*(1+Debts!$C$11/12),Debts!$D$11)+MIN(C24+0,G24*(1+Debts!$C$12/12))*0+MIN(G24*(1+Debts!$C$12/12),Debts!$D$12)+MIN(C24+0,H24*(1+Debts!$C$13/12))*0+MIN(H24*(1+Debts!$C$13/12),Debts!$D$13)+MIN(C24+0,I24*(1+Debts!$C$14/12))*0+MIN(I24*(1+Debts!$C$14/12),Debts!$D$14)+MIN(C24+0,J24*(1+Debts!$C$15/12))*0+MIN(J24*(1+Debts!$C$15/12),Debts!$D$15)))),0))) -> 0 | E25: =IF(E24<=0,0,MAX(0,E24*(1+Debts!$C$10/12)-MIN(E24*(1+Debts!$C$10/12),Debts!$D$10)-IF(AND(E24>0,Debts!$E$10=MIN(IF(C24>0,Debts!$E$8,999),IF(D24>0,Debts!$E$9,999),IF(E24>0,Debts!$E$10,999),IF(F24>0,Debts!$E$11,999),IF(G24>0,Debts!$E$12,999),IF(H24>0,Debts!$E$13,999),IF(I24>0,Debts!$E$14,999),IF(J24>0,Debts!$E$15,999))),MAX(0,(B25-(MIN(C24+0,C24*(1+Debts!$C$8/12))*0+MIN(C24*(1+Debts!$C$8/12),Debts!$D$8)+MIN(C24+0,D24*(1+Debts!$C$9/12))*0+MIN(D24*(1+Debts!$C$9/12),Debts!$D$9)+MIN(C24+0,E24*(1+Debts!$C$10/12))*0+MIN(E24*(1+Debts!$C$10/12),Debts!$D$10)+MIN(C24+0,F24*(1+Debts!$C$11/12))*0+MIN(F24*(1+Debts!$C$11/12),Debts!$D$11)+MIN(C24+0,G24*(1+Debts!$C$12/12))*0+MIN(G24*(1+Debts!$C$12/12),Debts!$D$12)+MIN(C24+0,H24*(1+Debts!$C$13/12))*0+MIN(H24*(1+Debts!$C$13/12),Debts!$D$13)+MIN(C24+0,I24*(1+Debts!$C$14/12))*0+MIN(I24*(1+Debts!$C$14/12),Debts!$D$14)+MIN(C24+0,J24*(1+Debts!$C$15/12))*0+MIN(J24*(1+Debts!$C$15/12),Debts!$D$15)))),0))) -> 6591.5924 | F25: =IF(F24<=0,0,MAX(0,F24*(1+Debts!$C$11/12)-MIN(F24*(1+Debts!$C$11/12),Debts!$D$11)-IF(AND(F24>0,Debts!$E$11=MIN(IF(C24>0,Debts!$E$8,999),IF(D24>0,Debts!$E$9,999),IF(E24>0,Debts!$E$10,999),IF(F24>0,Debts!$E$11,999),IF(G24>0,Debts!$E$12,999),IF(H24>0,Debts!$E$13,999),IF(I24>0,Debts!$E$14,999),IF(J24>0,Debts!$E$15,999))),MAX(0,(B25-(MIN(C24+0,C24*(1+Debts!$C$8/12))*0+MIN(C24*(1+Debts!$C$8/12),Debts!$D$8)+MIN(C24+0,D24*(1+Debts!$C$9/12))*0+MIN(D24*(1+Debts!$C$9/12),Debts!$D$9)+MIN(C24+0,E24*(1+Debts!$C$10/12))*0+MIN(E24*(1+Debts!$C$10/12),Debts!$D$10)+MIN(C24+0,F24*(1+Debts!$C$11/12))*0+MIN(F24*(1+Debts!$C$11/12),Debts!$D$11)+MIN(C24+0,G24*(1+Debts!$C$12/12))*0+MIN(G24*(1+Debts!$C$12/12),Debts!$D$12)+MIN(C24+0,H24*(1+Debts!$C$13/12))*0+MIN(H24*(1+Debts!$C$13/12),Debts!$D$13)+MIN(C24+0,I24*(1+Debts!$C$14/12))*0+MIN(I24*(1+Debts!$C$14/12),Debts!$D$14)+MIN(C24+0,J24*(1+Debts!$C$15/12))*0+MIN(J24*(1+Debts!$C$15/12),Debts!$D$15)))),0))) -> 16156.264 | G25: =IF(G24<=0,0,MAX(0,G24*(1+Debts!$C$12/12)-MIN(G24*(1+Debts!$C$12/12),Debts!$D$12)-IF(AND(G24>0,Debts!$E$12=MIN(IF(C24>0,Debts!$E$8,999),IF(D24>0,Debts!$E$9,999),IF(E24>0,Debts!$E$10,999),IF(F24>0,Debts!$E$11,999),IF(G24>0,Debts!$E$12,999),IF(H24>0,Debts!$E$13,999),IF(I24>0,Debts!$E$14,999),IF(J24>0,Debts!$E$15,999))),MAX(0,(B25-(MIN(C24+0,C24*(1+Debts!$C$8/12))*0+MIN(C24*(1+Debts!$C$8/12),Debts!$D$8)+MIN(C24+0,D24*(1+Debts!$C$9/12))*0+MIN(D24*(1+Debts!$C$9/12),Debts!$D$9)+MIN(C24+0,E24*(1+Debts!$C$10/12))*0+MIN(E24*(1+Debts!$C$10/12),Debts!$D$10)+MIN(C24+0,F24*(1+Debts!$C$11/12))*0+MIN(F24*(1+Debts!$C$11/12),Debts!$D$11)+MIN(C24+0,G24*(1+Debts!$C$12/12))*0+MIN(G24*(1+Debts!$C$12/12),Debts!$D$12)+MIN(C24+0,H24*(1+Debts!$C$13/12))*0+MIN(H24*(1+Debts!$C$13/12),Debts!$D$13)+MIN(C24+0,I24*(1+Debts!$C$14/12))*0+MIN(I24*(1+Debts!$C$14/12),Debts!$D$14)+MIN(C24+0,J24*(1+Debts!$C$15/12))*0+MIN(J24*(1+Debts!$C$15/12),Debts!$D$15)))),0))) -> 0 | H25: =IF(H24<=0,0,MAX(0,H24*(1+Debts!$C$13/12)-MIN(H24*(1+Debts!$C$13/12),Debts!$D$13)-IF(AND(H24>0,Debts!$E$13=MIN(IF(C24>0,Debts!$E$8,999),IF(D24>0,Debts!$E$9,999),IF(E24>0,Debts!$E$10,999),IF(F24>0,Debts!$E$11,999),IF(G24>0,Debts!$E$12,999),IF(H24>0,Debts!$E$13,999),IF(I24>0,Debts!$E$14,999),IF(J24>0,Debts!$E$15,999))),MAX(0,(B25-(MIN(C24+0,C24*(1+Debts!$C$8/12))*0+MIN(C24*(1+Debts!$C$8/12),Debts!$D$8)+MIN(C24+0,D24*(1+Debts!$C$9/12))*0+MIN(D24*(1+Debts!$C$9/12),Debts!$D$9)+MIN(C24+0,E24*(1+Debts!$C$10/12))*0+MIN(E24*(1+Debts!$C$10/12),Debts!$D$10)+MIN(C24+0,F24*(1+Debts!$C$11/12))*0+MIN(F24*(1+Debts!$C$11/12),Debts!$D$11)+MIN(C24+0,G24*(1+Debts!$C$12/12))*0+MIN(G24*(1+Debts!$C$12/12),Debts!$D$12)+MIN(C24+0,H24*(1+Debts!$C$13/12))*0+MIN(H24*(1+Debts!$C$13/12),Debts!$D$13)+MIN(C24+0,I24*(1+Debts!$C$14/12))*0+MIN(I24*(1+Debts!$C$14/12),Debts!$D$14)+MIN(C24+0,J24*(1+Debts!$C$15/12))*0+MIN(J24*(1+Debts!$C$15/12),Debts!$D$15)))),0))) -> 0 | I25: =IF(I24<=0,0,MAX(0,I24*(1+Debts!$C$14/12)-MIN(I24*(1+Debts!$C$14/12),Debts!$D$14)-IF(AND(I24>0,Debts!$E$14=MIN(IF(C24>0,Debts!$E$8,999),IF(D24>0,Debts!$E$9,999),IF(E24>0,Debts!$E$10,999),IF(F24>0,Debts!$E$11,999),IF(G24>0,Debts!$E$12,999),IF(H24>0,Debts!$E$13,999),IF(I24>0,Debts!$E$14,999),IF(J24>0,Debts!$E$15,999))),MAX(0,(B25-(MIN(C24+0,C24*(1+Debts!$C$8/12))*0+MIN(C24*(1+Debts!$C$8/12),Debts!$D$8)+MIN(C24+0,D24*(1+Debts!$C$9/12))*0+MIN(D24*(1+Debts!$C$9/12),Debts!$D$9)+MIN(C24+0,E24*(1+Debts!$C$10/12))*0+MIN(E24*(1+Debts!$C$10/12),Debts!$D$10)+MIN(C24+0,F24*(1+Debts!$C$11/12))*0+MIN(F24*(1+Debts!$C$11/12),Debts!$D$11)+MIN(C24+0,G24*(1+Debts!$C$12/12))*0+MIN(G24*(1+Debts!$C$12/12),Debts!$D$12)+MIN(C24+0,H24*(1+Debts!$C$13/12))*0+MIN(H24*(1+Debts!$C$13/12),Debts!$D$13)+MIN(C24+0,I24*(1+Debts!$C$14/12))*0+MIN(I24*(1+Debts!$C$14/12),Debts!$D$14)+MIN(C24+0,J24*(1+Debts!$C$15/12))*0+MIN(J24*(1+Debts!$C$15/12),Debts!$D$15)))),0))) -> 0 | J25: =IF(J24<=0,0,MAX(0,J24*(1+Debts!$C$15/12)-MIN(J24*(1+Debts!$C$15/12),Debts!$D$15)-IF(AND(J24>0,Debts!$E$15=MIN(IF(C24>0,Debts!$E$8,999),IF(D24>0,Debts!$E$9,999),IF(E24>0,Debts!$E$10,999),IF(F24>0,Debts!$E$11,999),IF(G24>0,Debts!$E$12,999),IF(H24>0,Debts!$E$13,999),IF(I24>0,Debts!$E$14,999),IF(J24>0,Debts!$E$15,999))),MAX(0,(B25-(MIN(C24+0,C24*(1+Debts!$C$8/12))*0+MIN(C24*(1+Debts!$C$8/12),Debts!$D$8)+MIN(C24+0,D24*(1+Debts!$C$9/12))*0+MIN(D24*(1+Debts!$C$9/12),Debts!$D$9)+MIN(C24+0,E24*(1+Debts!$C$10/12))*0+MIN(E24*(1+Debts!$C$10/12),Debts!$D$10)+MIN(C24+0,F24*(1+Debts!$C$11/12))*0+MIN(F24*(1+Debts!$C$11/12),Debts!$D$11)+MIN(C24+0,G24*(1+Debts!$C$12/12))*0+MIN(G24*(1+Debts!$C$12/12),Debts!$D$12)+MIN(C24+0,H24*(1+Debts!$C$13/12))*0+MIN(H24*(1+Debts!$C$13/12),Debts!$D$13)+MIN(C24+0,I24*(1+Debts!$C$14/12))*0+MIN(I24*(1+Debts!$C$14/12),Debts!$D$14)+MIN(C24+0,J24*(1+Debts!$C$15/12))*0+MIN(J24*(1+Debts!$C$15/12),Debts!$D$15)))),0))) -> 0 | K25: =IF(C24>0,C24*Debts!$C$8/12,0)+IF(D24>0,D24*Debts!$C$9/12,0)+IF(E24>0,E24*Debts!$C$10/12,0)+IF(F24>0,F24*Debts!$C$11/12,0)+IF(G24>0,G24*Debts!$C$12/12,0)+IF(H24>0,H24*Debts!$C$13/12,0)+IF(I24>0,I24*Debts!$C$14/12,0)+IF(J24>0,J24*Debts!$C$15/12,0) -> 117.72887 | L25: =SUM(C25:J25) -> 22747.856
A26: =19 -> 19 | B26: =IF(L25<=0,0,Debts!$D$16+Debts!$B$4) -> 1200 | C26: =IF(C25<=0,0,MAX(0,C25*(1+Debts!$C$8/12)-MIN(C25*(1+Debts!$C$8/12),Debts!$D$8)-IF(AND(C25>0,Debts!$E$8=MIN(IF(C25>0,Debts!$E$8,999),IF(D25>0,Debts!$E$9,999),IF(E25>0,Debts!$E$10,999),IF(F25>0,Debts!$E$11,999),IF(G25>0,Debts!$E$12,999),IF(H25>0,Debts!$E$13,999),IF(I25>0,Debts!$E$14,999),IF(J25>0,Debts!$E$15,999))),MAX(0,(B26-(MIN(C25+0,C25*(1+Debts!$C$8/12))*0+MIN(C25*(1+Debts!$C$8/12),Debts!$D$8)+MIN(C25+0,D25*(1+Debts!$C$9/12))*0+MIN(D25*(1+Debts!$C$9/12),Debts!$D$9)+MIN(C25+0,E25*(1+Debts!$C$10/12))*0+MIN(E25*(1+Debts!$C$10/12),Debts!$D$10)+MIN(C25+0,F25*(1+Debts!$C$11/12))*0+MIN(F25*(1+Debts!$C$11/12),Debts!$D$11)+MIN(C25+0,G25*(1+Debts!$C$12/12))*0+MIN(G25*(1+Debts!$C$12/12),Debts!$D$12)+MIN(C25+0,H25*(1+Debts!$C$13/12))*0+MIN(H25*(1+Debts!$C$13/12),Debts!$D$13)+MIN(C25+0,I25*(1+Debts!$C$14/12))*0+MIN(I25*(1+Debts!$C$14/12),Debts!$D$14)+MIN(C25+0,J25*(1+Debts!$C$15/12))*0+MIN(J25*(1+Debts!$C$15/12),Debts!$D$15)))),0))) -> 0 | D26: =IF(D25<=0,0,MAX(0,D25*(1+Debts!$C$9/12)-MIN(D25*(1+Debts!$C$9/12),Debts!$D$9)-IF(AND(D25>0,Debts!$E$9=MIN(IF(C25>0,Debts!$E$8,999),IF(D25>0,Debts!$E$9,999),IF(E25>0,Debts!$E$10,999),IF(F25>0,Debts!$E$11,999),IF(G25>0,Debts!$E$12,999),IF(H25>0,Debts!$E$13,999),IF(I25>0,Debts!$E$14,999),IF(J25>0,Debts!$E$15,999))),MAX(0,(B26-(MIN(C25+0,C25*(1+Debts!$C$8/12))*0+MIN(C25*(1+Debts!$C$8/12),Debts!$D$8)+MIN(C25+0,D25*(1+Debts!$C$9/12))*0+MIN(D25*(1+Debts!$C$9/12),Debts!$D$9)+MIN(C25+0,E25*(1+Debts!$C$10/12))*0+MIN(E25*(1+Debts!$C$10/12),Debts!$D$10)+MIN(C25+0,F25*(1+Debts!$C$11/12))*0+MIN(F25*(1+Debts!$C$11/12),Debts!$D$11)+MIN(C25+0,G25*(1+Debts!$C$12/12))*0+MIN(G25*(1+Debts!$C$12/12),Debts!$D$12)+MIN(C25+0,H25*(1+Debts!$C$13/12))*0+MIN(H25*(1+Debts!$C$13/12),Debts!$D$13)+MIN(C25+0,I25*(1+Debts!$C$14/12))*0+MIN(I25*(1+Debts!$C$14/12),Debts!$D$14)+MIN(C25+0,J25*(1+Debts!$C$15/12))*0+MIN(J25*(1+Debts!$C$15/12),Debts!$D$15)))),0))) -> 0 | E26: =IF(E25<=0,0,MAX(0,E25*(1+Debts!$C$10/12)-MIN(E25*(1+Debts!$C$10/12),Debts!$D$10)-IF(AND(E25>0,Debts!$E$10=MIN(IF(C25>0,Debts!$E$8,999),IF(D25>0,Debts!$E$9,999),IF(E25>0,Debts!$E$10,999),IF(F25>0,Debts!$E$11,999),IF(G25>0,Debts!$E$12,999),IF(H25>0,Debts!$E$13,999),IF(I25>0,Debts!$E$14,999),IF(J25>0,Debts!$E$15,999))),MAX(0,(B26-(MIN(C25+0,C25*(1+Debts!$C$8/12))*0+MIN(C25*(1+Debts!$C$8/12),Debts!$D$8)+MIN(C25+0,D25*(1+Debts!$C$9/12))*0+MIN(D25*(1+Debts!$C$9/12),Debts!$D$9)+MIN(C25+0,E25*(1+Debts!$C$10/12))*0+MIN(E25*(1+Debts!$C$10/12),Debts!$D$10)+MIN(C25+0,F25*(1+Debts!$C$11/12))*0+MIN(F25*(1+Debts!$C$11/12),Debts!$D$11)+MIN(C25+0,G25*(1+Debts!$C$12/12))*0+MIN(G25*(1+Debts!$C$12/12),Debts!$D$12)+MIN(C25+0,H25*(1+Debts!$C$13/12))*0+MIN(H25*(1+Debts!$C$13/12),Debts!$D$13)+MIN(C25+0,I25*(1+Debts!$C$14/12))*0+MIN(I25*(1+Debts!$C$14/12),Debts!$D$14)+MIN(C25+0,J25*(1+Debts!$C$15/12))*0+MIN(J25*(1+Debts!$C$15/12),Debts!$D$15)))),0))) -> 5639.4941 | F26: =IF(F25<=0,0,MAX(0,F25*(1+Debts!$C$11/12)-MIN(F25*(1+Debts!$C$11/12),Debts!$D$11)-IF(AND(F25>0,Debts!$E$11=MIN(IF(C25>0,Debts!$E$8,999),IF(D25>0,Debts!$E$9,999),IF(E25>0,Debts!$E$10,999),IF(F25>0,Debts!$E$11,999),IF(G25>0,Debts!$E$12,999),IF(H25>0,Debts!$E$13,999),IF(I25>0,Debts!$E$14,999),IF(J25>0,Debts!$E$15,999))),MAX(0,(B26-(MIN(C25+0,C25*(1+Debts!$C$8/12))*0+MIN(C25*(1+Debts!$C$8/12),Debts!$D$8)+MIN(C25+0,D25*(1+Debts!$C$9/12))*0+MIN(D25*(1+Debts!$C$9/12),Debts!$D$9)+MIN(C25+0,E25*(1+Debts!$C$10/12))*0+MIN(E25*(1+Debts!$C$10/12),Debts!$D$10)+MIN(C25+0,F25*(1+Debts!$C$11/12))*0+MIN(F25*(1+Debts!$C$11/12),Debts!$D$11)+MIN(C25+0,G25*(1+Debts!$C$12/12))*0+MIN(G25*(1+Debts!$C$12/12),Debts!$D$12)+MIN(C25+0,H25*(1+Debts!$C$13/12))*0+MIN(H25*(1+Debts!$C$13/12),Debts!$D$13)+MIN(C25+0,I25*(1+Debts!$C$14/12))*0+MIN(I25*(1+Debts!$C$14/12),Debts!$D$14)+MIN(C25+0,J25*(1+Debts!$C$15/12))*0+MIN(J25*(1+Debts!$C$15/12),Debts!$D$15)))),0))) -> 16020.314 | G26: =IF(G25<=0,0,MAX(0,G25*(1+Debts!$C$12/12)-MIN(G25*(1+Debts!$C$12/12),Debts!$D$12)-IF(AND(G25>0,Debts!$E$12=MIN(IF(C25>0,Debts!$E$8,999),IF(D25>0,Debts!$E$9,999),IF(E25>0,Debts!$E$10,999),IF(F25>0,Debts!$E$11,999),IF(G25>0,Debts!$E$12,999),IF(H25>0,Debts!$E$13,999),IF(I25>0,Debts!$E$14,999),IF(J25>0,Debts!$E$15,999))),MAX(0,(B26-(MIN(C25+0,C25*(1+Debts!$C$8/12))*0+MIN(C25*(1+Debts!$C$8/12),Debts!$D$8)+MIN(C25+0,D25*(1+Debts!$C$9/12))*0+MIN(D25*(1+Debts!$C$9/12),Debts!$D$9)+MIN(C25+0,E25*(1+Debts!$C$10/12))*0+MIN(E25*(1+Debts!$C$10/12),Debts!$D$10)+MIN(C25+0,F25*(1+Debts!$C$11/12))*0+MIN(F25*(1+Debts!$C$11/12),Debts!$D$11)+MIN(C25+0,G25*(1+Debts!$C$12/12))*0+MIN(G25*(1+Debts!$C$12/12),Debts!$D$12)+MIN(C25+0,H25*(1+Debts!$C$13/12))*0+MIN(H25*(1+Debts!$C$13/12),Debts!$D$13)+MIN(C25+0,I25*(1+Debts!$C$14/12))*0+MIN(I25*(1+Debts!$C$14/12),Debts!$D$14)+MIN(C25+0,J25*(1+Debts!$C$15/12))*0+MIN(J25*(1+Debts!$C$15/12),Debts!$D$15)))),0))) -> 0 | H26: =IF(H25<=0,0,MAX(0,H25*(1+Debts!$C$13/12)-MIN(H25*(1+Debts!$C$13/12),Debts!$D$13)-IF(AND(H25>0,Debts!$E$13=MIN(IF(C25>0,Debts!$E$8,999),IF(D25>0,Debts!$E$9,999),IF(E25>0,Debts!$E$10,999),IF(F25>0,Debts!$E$11,999),IF(G25>0,Debts!$E$12,999),IF(H25>0,Debts!$E$13,999),IF(I25>0,Debts!$E$14,999),IF(J25>0,Debts!$E$15,999))),MAX(0,(B26-(MIN(C25+0,C25*(1+Debts!$C$8/12))*0+MIN(C25*(1+Debts!$C$8/12),Debts!$D$8)+MIN(C25+0,D25*(1+Debts!$C$9/12))*0+MIN(D25*(1+Debts!$C$9/12),Debts!$D$9)+MIN(C25+0,E25*(1+Debts!$C$10/12))*0+MIN(E25*(1+Debts!$C$10/12),Debts!$D$10)+MIN(C25+0,F25*(1+Debts!$C$11/12))*0+MIN(F25*(1+Debts!$C$11/12),Debts!$D$11)+MIN(C25+0,G25*(1+Debts!$C$12/12))*0+MIN(G25*(1+Debts!$C$12/12),Debts!$D$12)+MIN(C25+0,H25*(1+Debts!$C$13/12))*0+MIN(H25*(1+Debts!$C$13/12),Debts!$D$13)+MIN(C25+0,I25*(1+Debts!$C$14/12))*0+MIN(I25*(1+Debts!$C$14/12),Debts!$D$14)+MIN(C25+0,J25*(1+Debts!$C$15/12))*0+MIN(J25*(1+Debts!$C$15/12),Debts!$D$15)))),0))) -> 0 | I26: =IF(I25<=0,0,MAX(0,I25*(1+Debts!$C$14/12)-MIN(I25*(1+Debts!$C$14/12),Debts!$D$14)-IF(AND(I25>0,Debts!$E$14=MIN(IF(C25>0,Debts!$E$8,999),IF(D25>0,Debts!$E$9,999),IF(E25>0,Debts!$E$10,999),IF(F25>0,Debts!$E$11,999),IF(G25>0,Debts!$E$12,999),IF(H25>0,Debts!$E$13,999),IF(I25>0,Debts!$E$14,999),IF(J25>0,Debts!$E$15,999))),MAX(0,(B26-(MIN(C25+0,C25*(1+Debts!$C$8/12))*0+MIN(C25*(1+Debts!$C$8/12),Debts!$D$8)+MIN(C25+0,D25*(1+Debts!$C$9/12))*0+MIN(D25*(1+Debts!$C$9/12),Debts!$D$9)+MIN(C25+0,E25*(1+Debts!$C$10/12))*0+MIN(E25*(1+Debts!$C$10/12),Debts!$D$10)+MIN(C25+0,F25*(1+Debts!$C$11/12))*0+MIN(F25*(1+Debts!$C$11/12),Debts!$D$11)+MIN(C25+0,G25*(1+Debts!$C$12/12))*0+MIN(G25*(1+Debts!$C$12/12),Debts!$D$12)+MIN(C25+0,H25*(1+Debts!$C$13/12))*0+MIN(H25*(1+Debts!$C$13/12),Debts!$D$13)+MIN(C25+0,I25*(1+Debts!$C$14/12))*0+MIN(I25*(1+Debts!$C$14/12),Debts!$D$14)+MIN(C25+0,J25*(1+Debts!$C$15/12))*0+MIN(J25*(1+Debts!$C$15/12),Debts!$D$15)))),0))) -> 0 | J26: =IF(J25<=0,0,MAX(0,J25*(1+Debts!$C$15/12)-MIN(J25*(1+Debts!$C$15/12),Debts!$D$15)-IF(AND(J25>0,Debts!$E$15=MIN(IF(C25>0,Debts!$E$8,999),IF(D25>0,Debts!$E$9,999),IF(E25>0,Debts!$E$10,999),IF(F25>0,Debts!$E$11,999),IF(G25>0,Debts!$E$12,999),IF(H25>0,Debts!$E$13,999),IF(I25>0,Debts!$E$14,999),IF(J25>0,Debts!$E$15,999))),MAX(0,(B26-(MIN(C25+0,C25*(1+Debts!$C$8/12))*0+MIN(C25*(1+Debts!$C$8/12),Debts!$D$8)+MIN(C25+0,D25*(1+Debts!$C$9/12))*0+MIN(D25*(1+Debts!$C$9/12),Debts!$D$9)+MIN(C25+0,E25*(1+Debts!$C$10/12))*0+MIN(E25*(1+Debts!$C$10/12),Debts!$D$10)+MIN(C25+0,F25*(1+Debts!$C$11/12))*0+MIN(F25*(1+Debts!$C$11/12),Debts!$D$11)+MIN(C25+0,G25*(1+Debts!$C$12/12))*0+MIN(G25*(1+Debts!$C$12/12),Debts!$D$12)+MIN(C25+0,H25*(1+Debts!$C$13/12))*0+MIN(H25*(1+Debts!$C$13/12),Debts!$D$13)+MIN(C25+0,I25*(1+Debts!$C$14/12))*0+MIN(I25*(1+Debts!$C$14/12),Debts!$D$14)+MIN(C25+0,J25*(1+Debts!$C$15/12))*0+MIN(J25*(1+Debts!$C$15/12),Debts!$D$15)))),0))) -> 0 | K26: =IF(C25>0,C25*Debts!$C$8/12,0)+IF(D25>0,D25*Debts!$C$9/12,0)+IF(E25>0,E25*Debts!$C$10/12,0)+IF(F25>0,F25*Debts!$C$11/12,0)+IF(G25>0,G25*Debts!$C$12/12,0)+IF(H25>0,H25*Debts!$C$13/12,0)+IF(I25>0,I25*Debts!$C$14/12,0)+IF(J25>0,J25*Debts!$C$15/12,0) -> 111.9512 | L26: =SUM(C26:J26) -> 21659.808
A27: =20 -> 20 | B27: =IF(L26<=0,0,Debts!$D$16+Debts!$B$4) -> 1200 | C27: =IF(C26<=0,0,MAX(0,C26*(1+Debts!$C$8/12)-MIN(C26*(1+Debts!$C$8/12),Debts!$D$8)-IF(AND(C26>0,Debts!$E$8=MIN(IF(C26>0,Debts!$E$8,999),IF(D26>0,Debts!$E$9,999),IF(E26>0,Debts!$E$10,999),IF(F26>0,Debts!$E$11,999),IF(G26>0,Debts!$E$12,999),IF(H26>0,Debts!$E$13,999),IF(I26>0,Debts!$E$14,999),IF(J26>0,Debts!$E$15,999))),MAX(0,(B27-(MIN(C26+0,C26*(1+Debts!$C$8/12))*0+MIN(C26*(1+Debts!$C$8/12),Debts!$D$8)+MIN(C26+0,D26*(1+Debts!$C$9/12))*0+MIN(D26*(1+Debts!$C$9/12),Debts!$D$9)+MIN(C26+0,E26*(1+Debts!$C$10/12))*0+MIN(E26*(1+Debts!$C$10/12),Debts!$D$10)+MIN(C26+0,F26*(1+Debts!$C$11/12))*0+MIN(F26*(1+Debts!$C$11/12),Debts!$D$11)+MIN(C26+0,G26*(1+Debts!$C$12/12))*0+MIN(G26*(1+Debts!$C$12/12),Debts!$D$12)+MIN(C26+0,H26*(1+Debts!$C$13/12))*0+MIN(H26*(1+Debts!$C$13/12),Debts!$D$13)+MIN(C26+0,I26*(1+Debts!$C$14/12))*0+MIN(I26*(1+Debts!$C$14/12),Debts!$D$14)+MIN(C26+0,J26*(1+Debts!$C$15/12))*0+MIN(J26*(1+Debts!$C$15/12),Debts!$D$15)))),0))) -> 0 | D27: =IF(D26<=0,0,MAX(0,D26*(1+Debts!$C$9/12)-MIN(D26*(1+Debts!$C$9/12),Debts!$D$9)-IF(AND(D26>0,Debts!$E$9=MIN(IF(C26>0,Debts!$E$8,999),IF(D26>0,Debts!$E$9,999),IF(E26>0,Debts!$E$10,999),IF(F26>0,Debts!$E$11,999),IF(G26>0,Debts!$E$12,999),IF(H26>0,Debts!$E$13,999),IF(I26>0,Debts!$E$14,999),IF(J26>0,Debts!$E$15,999))),MAX(0,(B27-(MIN(C26+0,C26*(1+Debts!$C$8/12))*0+MIN(C26*(1+Debts!$C$8/12),Debts!$D$8)+MIN(C26+0,D26*(1+Debts!$C$9/12))*0+MIN(D26*(1+Debts!$C$9/12),Debts!$D$9)+MIN(C26+0,E26*(1+Debts!$C$10/12))*0+MIN(E26*(1+Debts!$C$10/12),Debts!$D$10)+MIN(C26+0,F26*(1+Debts!$C$11/12))*0+MIN(F26*(1+Debts!$C$11/12),Debts!$D$11)+MIN(C26+0,G26*(1+Debts!$C$12/12))*0+MIN(G26*(1+Debts!$C$12/12),Debts!$D$12)+MIN(C26+0,H26*(1+Debts!$C$13/12))*0+MIN(H26*(1+Debts!$C$13/12),Debts!$D$13)+MIN(C26+0,I26*(1+Debts!$C$14/12))*0+MIN(I26*(1+Debts!$C$14/12),Debts!$D$14)+MIN(C26+0,J26*(1+Debts!$C$15/12))*0+MIN(J26*(1+Debts!$C$15/12),Debts!$D$15)))),0))) -> 0 | E27: =IF(E26<=0,0,MAX(0,E26*(1+Debts!$C$10/12)-MIN(E26*(1+Debts!$C$10/12),Debts!$D$10)-IF(AND(E26>0,Debts!$E$10=MIN(IF(C26>0,Debts!$E$8,999),IF(D26>0,Debts!$E$9,999),IF(E26>0,Debts!$E$10,999),IF(F26>0,Debts!$E$11,999),IF(G26>0,Debts!$E$12,999),IF(H26>0,Debts!$E$13,999),IF(I26>0,Debts!$E$14,999),IF(J26>0,Debts!$E$15,999))),MAX(0,(B27-(MIN(C26+0,C26*(1+Debts!$C$8/12))*0+MIN(C26*(1+Debts!$C$8/12),Debts!$D$8)+MIN(C26+0,D26*(1+Debts!$C$9/12))*0+MIN(D26*(1+Debts!$C$9/12),Debts!$D$9)+MIN(C26+0,E26*(1+Debts!$C$10/12))*0+MIN(E26*(1+Debts!$C$10/12),Debts!$D$10)+MIN(C26+0,F26*(1+Debts!$C$11/12))*0+MIN(F26*(1+Debts!$C$11/12),Debts!$D$11)+MIN(C26+0,G26*(1+Debts!$C$12/12))*0+MIN(G26*(1+Debts!$C$12/12),Debts!$D$12)+MIN(C26+0,H26*(1+Debts!$C$13/12))*0+MIN(H26*(1+Debts!$C$13/12),Debts!$D$13)+MIN(C26+0,I26*(1+Debts!$C$14/12))*0+MIN(I26*(1+Debts!$C$14/12),Debts!$D$14)+MIN(C26+0,J26*(1+Debts!$C$15/12))*0+MIN(J26*(1+Debts!$C$15/12),Debts!$D$15)))),0))) -> 4681.9212 | F27: =IF(F26<=0,0,MAX(0,F26*(1+Debts!$C$11/12)-MIN(F26*(1+Debts!$C$11/12),Debts!$D$11)-IF(AND(F26>0,Debts!$E$11=MIN(IF(C26>0,Debts!$E$8,999),IF(D26>0,Debts!$E$9,999),IF(E26>0,Debts!$E$10,999),IF(F26>0,Debts!$E$11,999),IF(G26>0,Debts!$E$12,999),IF(H26>0,Debts!$E$13,999),IF(I26>0,Debts!$E$14,999),IF(J26>0,Debts!$E$15,999))),MAX(0,(B27-(MIN(C26+0,C26*(1+Debts!$C$8/12))*0+MIN(C26*(1+Debts!$C$8/12),Debts!$D$8)+MIN(C26+0,D26*(1+Debts!$C$9/12))*0+MIN(D26*(1+Debts!$C$9/12),Debts!$D$9)+MIN(C26+0,E26*(1+Debts!$C$10/12))*0+MIN(E26*(1+Debts!$C$10/12),Debts!$D$10)+MIN(C26+0,F26*(1+Debts!$C$11/12))*0+MIN(F26*(1+Debts!$C$11/12),Debts!$D$11)+MIN(C26+0,G26*(1+Debts!$C$12/12))*0+MIN(G26*(1+Debts!$C$12/12),Debts!$D$12)+MIN(C26+0,H26*(1+Debts!$C$13/12))*0+MIN(H26*(1+Debts!$C$13/12),Debts!$D$13)+MIN(C26+0,I26*(1+Debts!$C$14/12))*0+MIN(I26*(1+Debts!$C$14/12),Debts!$D$14)+MIN(C26+0,J26*(1+Debts!$C$15/12))*0+MIN(J26*(1+Debts!$C$15/12),Debts!$D$15)))),0))) -> 15883.74 | G27: =IF(G26<=0,0,MAX(0,G26*(1+Debts!$C$12/12)-MIN(G26*(1+Debts!$C$12/12),Debts!$D$12)-IF(AND(G26>0,Debts!$E$12=MIN(IF(C26>0,Debts!$E$8,999),IF(D26>0,Debts!$E$9,999),IF(E26>0,Debts!$E$10,999),IF(F26>0,Debts!$E$11,999),IF(G26>0,Debts!$E$12,999),IF(H26>0,Debts!$E$13,999),IF(I26>0,Debts!$E$14,999),IF(J26>0,Debts!$E$15,999))),MAX(0,(B27-(MIN(C26+0,C26*(1+Debts!$C$8/12))*0+MIN(C26*(1+Debts!$C$8/12),Debts!$D$8)+MIN(C26+0,D26*(1+Debts!$C$9/12))*0+MIN(D26*(1+Debts!$C$9/12),Debts!$D$9)+MIN(C26+0,E26*(1+Debts!$C$10/12))*0+MIN(E26*(1+Debts!$C$10/12),Debts!$D$10)+MIN(C26+0,F26*(1+Debts!$C$11/12))*0+MIN(F26*(1+Debts!$C$11/12),Debts!$D$11)+MIN(C26+0,G26*(1+Debts!$C$12/12))*0+MIN(G26*(1+Debts!$C$12/12),Debts!$D$12)+MIN(C26+0,H26*(1+Debts!$C$13/12))*0+MIN(H26*(1+Debts!$C$13/12),Debts!$D$13)+MIN(C26+0,I26*(1+Debts!$C$14/12))*0+MIN(I26*(1+Debts!$C$14/12),Debts!$D$14)+MIN(C26+0,J26*(1+Debts!$C$15/12))*0+MIN(J26*(1+Debts!$C$15/12),Debts!$D$15)))),0))) -> 0 | H27: =IF(H26<=0,0,MAX(0,H26*(1+Debts!$C$13/12)-MIN(H26*(1+Debts!$C$13/12),Debts!$D$13)-IF(AND(H26>0,Debts!$E$13=MIN(IF(C26>0,Debts!$E$8,999),IF(D26>0,Debts!$E$9,999),IF(E26>0,Debts!$E$10,999),IF(F26>0,Debts!$E$11,999),IF(G26>0,Debts!$E$12,999),IF(H26>0,Debts!$E$13,999),IF(I26>0,Debts!$E$14,999),IF(J26>0,Debts!$E$15,999))),MAX(0,(B27-(MIN(C26+0,C26*(1+Debts!$C$8/12))*0+MIN(C26*(1+Debts!$C$8/12),Debts!$D$8)+MIN(C26+0,D26*(1+Debts!$C$9/12))*0+MIN(D26*(1+Debts!$C$9/12),Debts!$D$9)+MIN(C26+0,E26*(1+Debts!$C$10/12))*0+MIN(E26*(1+Debts!$C$10/12),Debts!$D$10)+MIN(C26+0,F26*(1+Debts!$C$11/12))*0+MIN(F26*(1+Debts!$C$11/12),Debts!$D$11)+MIN(C26+0,G26*(1+Debts!$C$12/12))*0+MIN(G26*(1+Debts!$C$12/12),Debts!$D$12)+MIN(C26+0,H26*(1+Debts!$C$13/12))*0+MIN(H26*(1+Debts!$C$13/12),Debts!$D$13)+MIN(C26+0,I26*(1+Debts!$C$14/12))*0+MIN(I26*(1+Debts!$C$14/12),Debts!$D$14)+MIN(C26+0,J26*(1+Debts!$C$15/12))*0+MIN(J26*(1+Debts!$C$15/12),Debts!$D$15)))),0))) -> 0 | I27: =IF(I26<=0,0,MAX(0,I26*(1+Debts!$C$14/12)-MIN(I26*(1+Debts!$C$14/12),Debts!$D$14)-IF(AND(I26>0,Debts!$E$14=MIN(IF(C26>0,Debts!$E$8,999),IF(D26>0,Debts!$E$9,999),IF(E26>0,Debts!$E$10,999),IF(F26>0,Debts!$E$11,999),IF(G26>0,Debts!$E$12,999),IF(H26>0,Debts!$E$13,999),IF(I26>0,Debts!$E$14,999),IF(J26>0,Debts!$E$15,999))),MAX(0,(B27-(MIN(C26+0,C26*(1+Debts!$C$8/12))*0+MIN(C26*(1+Debts!$C$8/12),Debts!$D$8)+MIN(C26+0,D26*(1+Debts!$C$9/12))*0+MIN(D26*(1+Debts!$C$9/12),Debts!$D$9)+MIN(C26+0,E26*(1+Debts!$C$10/12))*0+MIN(E26*(1+Debts!$C$10/12),Debts!$D$10)+MIN(C26+0,F26*(1+Debts!$C$11/12))*0+MIN(F26*(1+Debts!$C$11/12),Debts!$D$11)+MIN(C26+0,G26*(1+Debts!$C$12/12))*0+MIN(G26*(1+Debts!$C$12/12),Debts!$D$12)+MIN(C26+0,H26*(1+Debts!$C$13/12))*0+MIN(H26*(1+Debts!$C$13/12),Debts!$D$13)+MIN(C26+0,I26*(1+Debts!$C$14/12))*0+MIN(I26*(1+Debts!$C$14/12),Debts!$D$14)+MIN(C26+0,J26*(1+Debts!$C$15/12))*0+MIN(J26*(1+Debts!$C$15/12),Debts!$D$15)))),0))) -> 0 | J27: =IF(J26<=0,0,MAX(0,J26*(1+Debts!$C$15/12)-MIN(J26*(1+Debts!$C$15/12),Debts!$D$15)-IF(AND(J26>0,Debts!$E$15=MIN(IF(C26>0,Debts!$E$8,999),IF(D26>0,Debts!$E$9,999),IF(E26>0,Debts!$E$10,999),IF(F26>0,Debts!$E$11,999),IF(G26>0,Debts!$E$12,999),IF(H26>0,Debts!$E$13,999),IF(I26>0,Debts!$E$14,999),IF(J26>0,Debts!$E$15,999))),MAX(0,(B27-(MIN(C26+0,C26*(1+Debts!$C$8/12))*0+MIN(C26*(1+Debts!$C$8/12),Debts!$D$8)+MIN(C26+0,D26*(1+Debts!$C$9/12))*0+MIN(D26*(1+Debts!$C$9/12),Debts!$D$9)+MIN(C26+0,E26*(1+Debts!$C$10/12))*0+MIN(E26*(1+Debts!$C$10/12),Debts!$D$10)+MIN(C26+0,F26*(1+Debts!$C$11/12))*0+MIN(F26*(1+Debts!$C$11/12),Debts!$D$11)+MIN(C26+0,G26*(1+Debts!$C$12/12))*0+MIN(G26*(1+Debts!$C$12/12),Debts!$D$12)+MIN(C26+0,H26*(1+Debts!$C$13/12))*0+MIN(H26*(1+Debts!$C$13/12),Debts!$D$13)+MIN(C26+0,I26*(1+Debts!$C$14/12))*0+MIN(I26*(1+Debts!$C$14/12),Debts!$D$14)+MIN(C26+0,J26*(1+Debts!$C$15/12))*0+MIN(J26*(1+Debts!$C$15/12),Debts!$D$15)))),0))) -> 0 | K27: =IF(C26>0,C26*Debts!$C$8/12,0)+IF(D26>0,D26*Debts!$C$9/12,0)+IF(E26>0,E26*Debts!$C$10/12,0)+IF(F26>0,F26*Debts!$C$11/12,0)+IF(G26>0,G26*Debts!$C$12/12,0)+IF(H26>0,H26*Debts!$C$13/12,0)+IF(I26>0,I26*Debts!$C$14/12,0)+IF(J26>0,J26*Debts!$C$15/12,0) -> 105.85353 | L27: =SUM(C27:J27) -> 20565.661
A28: =21 -> 21 | B28: =IF(L27<=0,0,Debts!$D$16+Debts!$B$4) -> 1200 | C28: =IF(C27<=0,0,MAX(0,C27*(1+Debts!$C$8/12)-MIN(C27*(1+Debts!$C$8/12),Debts!$D$8)-IF(AND(C27>0,Debts!$E$8=MIN(IF(C27>0,Debts!$E$8,999),IF(D27>0,Debts!$E$9,999),IF(E27>0,Debts!$E$10,999),IF(F27>0,Debts!$E$11,999),IF(G27>0,Debts!$E$12,999),IF(H27>0,Debts!$E$13,999),IF(I27>0,Debts!$E$14,999),IF(J27>0,Debts!$E$15,999))),MAX(0,(B28-(MIN(C27+0,C27*(1+Debts!$C$8/12))*0+MIN(C27*(1+Debts!$C$8/12),Debts!$D$8)+MIN(C27+0,D27*(1+Debts!$C$9/12))*0+MIN(D27*(1+Debts!$C$9/12),Debts!$D$9)+MIN(C27+0,E27*(1+Debts!$C$10/12))*0+MIN(E27*(1+Debts!$C$10/12),Debts!$D$10)+MIN(C27+0,F27*(1+Debts!$C$11/12))*0+MIN(F27*(1+Debts!$C$11/12),Debts!$D$11)+MIN(C27+0,G27*(1+Debts!$C$12/12))*0+MIN(G27*(1+Debts!$C$12/12),Debts!$D$12)+MIN(C27+0,H27*(1+Debts!$C$13/12))*0+MIN(H27*(1+Debts!$C$13/12),Debts!$D$13)+MIN(C27+0,I27*(1+Debts!$C$14/12))*0+MIN(I27*(1+Debts!$C$14/12),Debts!$D$14)+MIN(C27+0,J27*(1+Debts!$C$15/12))*0+MIN(J27*(1+Debts!$C$15/12),Debts!$D$15)))),0))) -> 0 | D28: =IF(D27<=0,0,MAX(0,D27*(1+Debts!$C$9/12)-MIN(D27*(1+Debts!$C$9/12),Debts!$D$9)-IF(AND(D27>0,Debts!$E$9=MIN(IF(C27>0,Debts!$E$8,999),IF(D27>0,Debts!$E$9,999),IF(E27>0,Debts!$E$10,999),IF(F27>0,Debts!$E$11,999),IF(G27>0,Debts!$E$12,999),IF(H27>0,Debts!$E$13,999),IF(I27>0,Debts!$E$14,999),IF(J27>0,Debts!$E$15,999))),MAX(0,(B28-(MIN(C27+0,C27*(1+Debts!$C$8/12))*0+MIN(C27*(1+Debts!$C$8/12),Debts!$D$8)+MIN(C27+0,D27*(1+Debts!$C$9/12))*0+MIN(D27*(1+Debts!$C$9/12),Debts!$D$9)+MIN(C27+0,E27*(1+Debts!$C$10/12))*0+MIN(E27*(1+Debts!$C$10/12),Debts!$D$10)+MIN(C27+0,F27*(1+Debts!$C$11/12))*0+MIN(F27*(1+Debts!$C$11/12),Debts!$D$11)+MIN(C27+0,G27*(1+Debts!$C$12/12))*0+MIN(G27*(1+Debts!$C$12/12),Debts!$D$12)+MIN(C27+0,H27*(1+Debts!$C$13/12))*0+MIN(H27*(1+Debts!$C$13/12),Debts!$D$13)+MIN(C27+0,I27*(1+Debts!$C$14/12))*0+MIN(I27*(1+Debts!$C$14/12),Debts!$D$14)+MIN(C27+0,J27*(1+Debts!$C$15/12))*0+MIN(J27*(1+Debts!$C$15/12),Debts!$D$15)))),0))) -> 0 | E28: =IF(E27<=0,0,MAX(0,E27*(1+Debts!$C$10/12)-MIN(E27*(1+Debts!$C$10/12),Debts!$D$10)-IF(AND(E27>0,Debts!$E$10=MIN(IF(C27>0,Debts!$E$8,999),IF(D27>0,Debts!$E$9,999),IF(E27>0,Debts!$E$10,999),IF(F27>0,Debts!$E$11,999),IF(G27>0,Debts!$E$12,999),IF(H27>0,Debts!$E$13,999),IF(I27>0,Debts!$E$14,999),IF(J27>0,Debts!$E$15,999))),MAX(0,(B28-(MIN(C27+0,C27*(1+Debts!$C$8/12))*0+MIN(C27*(1+Debts!$C$8/12),Debts!$D$8)+MIN(C27+0,D27*(1+Debts!$C$9/12))*0+MIN(D27*(1+Debts!$C$9/12),Debts!$D$9)+MIN(C27+0,E27*(1+Debts!$C$10/12))*0+MIN(E27*(1+Debts!$C$10/12),Debts!$D$10)+MIN(C27+0,F27*(1+Debts!$C$11/12))*0+MIN(F27*(1+Debts!$C$11/12),Debts!$D$11)+MIN(C27+0,G27*(1+Debts!$C$12/12))*0+MIN(G27*(1+Debts!$C$12/12),Debts!$D$12)+MIN(C27+0,H27*(1+Debts!$C$13/12))*0+MIN(H27*(1+Debts!$C$13/12),Debts!$D$13)+MIN(C27+0,I27*(1+Debts!$C$14/12))*0+MIN(I27*(1+Debts!$C$14/12),Debts!$D$14)+MIN(C27+0,J27*(1+Debts!$C$15/12))*0+MIN(J27*(1+Debts!$C$15/12),Debts!$D$15)))),0))) -> 3718.8422 | F28: =IF(F27<=0,0,MAX(0,F27*(1+Debts!$C$11/12)-MIN(F27*(1+Debts!$C$11/12),Debts!$D$11)-IF(AND(F27>0,Debts!$E$11=MIN(IF(C27>0,Debts!$E$8,999),IF(D27>0,Debts!$E$9,999),IF(E27>0,Debts!$E$10,999),IF(F27>0,Debts!$E$11,999),IF(G27>0,Debts!$E$12,999),IF(H27>0,Debts!$E$13,999),IF(I27>0,Debts!$E$14,999),IF(J27>0,Debts!$E$15,999))),MAX(0,(B28-(MIN(C27+0,C27*(1+Debts!$C$8/12))*0+MIN(C27*(1+Debts!$C$8/12),Debts!$D$8)+MIN(C27+0,D27*(1+Debts!$C$9/12))*0+MIN(D27*(1+Debts!$C$9/12),Debts!$D$9)+MIN(C27+0,E27*(1+Debts!$C$10/12))*0+MIN(E27*(1+Debts!$C$10/12),Debts!$D$10)+MIN(C27+0,F27*(1+Debts!$C$11/12))*0+MIN(F27*(1+Debts!$C$11/12),Debts!$D$11)+MIN(C27+0,G27*(1+Debts!$C$12/12))*0+MIN(G27*(1+Debts!$C$12/12),Debts!$D$12)+MIN(C27+0,H27*(1+Debts!$C$13/12))*0+MIN(H27*(1+Debts!$C$13/12),Debts!$D$13)+MIN(C27+0,I27*(1+Debts!$C$14/12))*0+MIN(I27*(1+Debts!$C$14/12),Debts!$D$14)+MIN(C27+0,J27*(1+Debts!$C$15/12))*0+MIN(J27*(1+Debts!$C$15/12),Debts!$D$15)))),0))) -> 15746.54 | G28: =IF(G27<=0,0,MAX(0,G27*(1+Debts!$C$12/12)-MIN(G27*(1+Debts!$C$12/12),Debts!$D$12)-IF(AND(G27>0,Debts!$E$12=MIN(IF(C27>0,Debts!$E$8,999),IF(D27>0,Debts!$E$9,999),IF(E27>0,Debts!$E$10,999),IF(F27>0,Debts!$E$11,999),IF(G27>0,Debts!$E$12,999),IF(H27>0,Debts!$E$13,999),IF(I27>0,Debts!$E$14,999),IF(J27>0,Debts!$E$15,999))),MAX(0,(B28-(MIN(C27+0,C27*(1+Debts!$C$8/12))*0+MIN(C27*(1+Debts!$C$8/12),Debts!$D$8)+MIN(C27+0,D27*(1+Debts!$C$9/12))*0+MIN(D27*(1+Debts!$C$9/12),Debts!$D$9)+MIN(C27+0,E27*(1+Debts!$C$10/12))*0+MIN(E27*(1+Debts!$C$10/12),Debts!$D$10)+MIN(C27+0,F27*(1+Debts!$C$11/12))*0+MIN(F27*(1+Debts!$C$11/12),Debts!$D$11)+MIN(C27+0,G27*(1+Debts!$C$12/12))*0+MIN(G27*(1+Debts!$C$12/12),Debts!$D$12)+MIN(C27+0,H27*(1+Debts!$C$13/12))*0+MIN(H27*(1+Debts!$C$13/12),Debts!$D$13)+MIN(C27+0,I27*(1+Debts!$C$14/12))*0+MIN(I27*(1+Debts!$C$14/12),Debts!$D$14)+MIN(C27+0,J27*(1+Debts!$C$15/12))*0+MIN(J27*(1+Debts!$C$15/12),Debts!$D$15)))),0))) -> 0 | H28: =IF(H27<=0,0,MAX(0,H27*(1+Debts!$C$13/12)-MIN(H27*(1+Debts!$C$13/12),Debts!$D$13)-IF(AND(H27>0,Debts!$E$13=MIN(IF(C27>0,Debts!$E$8,999),IF(D27>0,Debts!$E$9,999),IF(E27>0,Debts!$E$10,999),IF(F27>0,Debts!$E$11,999),IF(G27>0,Debts!$E$12,999),IF(H27>0,Debts!$E$13,999),IF(I27>0,Debts!$E$14,999),IF(J27>0,Debts!$E$15,999))),MAX(0,(B28-(MIN(C27+0,C27*(1+Debts!$C$8/12))*0+MIN(C27*(1+Debts!$C$8/12),Debts!$D$8)+MIN(C27+0,D27*(1+Debts!$C$9/12))*0+MIN(D27*(1+Debts!$C$9/12),Debts!$D$9)+MIN(C27+0,E27*(1+Debts!$C$10/12))*0+MIN(E27*(1+Debts!$C$10/12),Debts!$D$10)+MIN(C27+0,F27*(1+Debts!$C$11/12))*0+MIN(F27*(1+Debts!$C$11/12),Debts!$D$11)+MIN(C27+0,G27*(1+Debts!$C$12/12))*0+MIN(G27*(1+Debts!$C$12/12),Debts!$D$12)+MIN(C27+0,H27*(1+Debts!$C$13/12))*0+MIN(H27*(1+Debts!$C$13/12),Debts!$D$13)+MIN(C27+0,I27*(1+Debts!$C$14/12))*0+MIN(I27*(1+Debts!$C$14/12),Debts!$D$14)+MIN(C27+0,J27*(1+Debts!$C$15/12))*0+MIN(J27*(1+Debts!$C$15/12),Debts!$D$15)))),0))) -> 0 | I28: =IF(I27<=0,0,MAX(0,I27*(1+Debts!$C$14/12)-MIN(I27*(1+Debts!$C$14/12),Debts!$D$14)-IF(AND(I27>0,Debts!$E$14=MIN(IF(C27>0,Debts!$E$8,999),IF(D27>0,Debts!$E$9,999),IF(E27>0,Debts!$E$10,999),IF(F27>0,Debts!$E$11,999),IF(G27>0,Debts!$E$12,999),IF(H27>0,Debts!$E$13,999),IF(I27>0,Debts!$E$14,999),IF(J27>0,Debts!$E$15,999))),MAX(0,(B28-(MIN(C27+0,C27*(1+Debts!$C$8/12))*0+MIN(C27*(1+Debts!$C$8/12),Debts!$D$8)+MIN(C27+0,D27*(1+Debts!$C$9/12))*0+MIN(D27*(1+Debts!$C$9/12),Debts!$D$9)+MIN(C27+0,E27*(1+Debts!$C$10/12))*0+MIN(E27*(1+Debts!$C$10/12),Debts!$D$10)+MIN(C27+0,F27*(1+Debts!$C$11/12))*0+MIN(F27*(1+Debts!$C$11/12),Debts!$D$11)+MIN(C27+0,G27*(1+Debts!$C$12/12))*0+MIN(G27*(1+Debts!$C$12/12),Debts!$D$12)+MIN(C27+0,H27*(1+Debts!$C$13/12))*0+MIN(H27*(1+Debts!$C$13/12),Debts!$D$13)+MIN(C27+0,I27*(1+Debts!$C$14/12))*0+MIN(I27*(1+Debts!$C$14/12),Debts!$D$14)+MIN(C27+0,J27*(1+Debts!$C$15/12))*0+MIN(J27*(1+Debts!$C$15/12),Debts!$D$15)))),0))) -> 0 | J28: =IF(J27<=0,0,MAX(0,J27*(1+Debts!$C$15/12)-MIN(J27*(1+Debts!$C$15/12),Debts!$D$15)-IF(AND(J27>0,Debts!$E$15=MIN(IF(C27>0,Debts!$E$8,999),IF(D27>0,Debts!$E$9,999),IF(E27>0,Debts!$E$10,999),IF(F27>0,Debts!$E$11,999),IF(G27>0,Debts!$E$12,999),IF(H27>0,Debts!$E$13,999),IF(I27>0,Debts!$E$14,999),IF(J27>0,Debts!$E$15,999))),MAX(0,(B28-(MIN(C27+0,C27*(1+Debts!$C$8/12))*0+MIN(C27*(1+Debts!$C$8/12),Debts!$D$8)+MIN(C27+0,D27*(1+Debts!$C$9/12))*0+MIN(D27*(1+Debts!$C$9/12),Debts!$D$9)+MIN(C27+0,E27*(1+Debts!$C$10/12))*0+MIN(E27*(1+Debts!$C$10/12),Debts!$D$10)+MIN(C27+0,F27*(1+Debts!$C$11/12))*0+MIN(F27*(1+Debts!$C$11/12),Debts!$D$11)+MIN(C27+0,G27*(1+Debts!$C$12/12))*0+MIN(G27*(1+Debts!$C$12/12),Debts!$D$12)+MIN(C27+0,H27*(1+Debts!$C$13/12))*0+MIN(H27*(1+Debts!$C$13/12),Debts!$D$13)+MIN(C27+0,I27*(1+Debts!$C$14/12))*0+MIN(I27*(1+Debts!$C$14/12),Debts!$D$14)+MIN(C27+0,J27*(1+Debts!$C$15/12))*0+MIN(J27*(1+Debts!$C$15/12),Debts!$D$15)))),0))) -> 0 | K28: =IF(C27>0,C27*Debts!$C$8/12,0)+IF(D27>0,D27*Debts!$C$9/12,0)+IF(E27>0,E27*Debts!$C$10/12,0)+IF(F27>0,F27*Debts!$C$11/12,0)+IF(G27>0,G27*Debts!$C$12/12,0)+IF(H27>0,H27*Debts!$C$13/12,0)+IF(I27>0,I27*Debts!$C$14/12,0)+IF(J27>0,J27*Debts!$C$15/12,0) -> 99.721522 | L28: =SUM(C28:J28) -> 19465.383
A29: =22 -> 22 | B29: =IF(L28<=0,0,Debts!$D$16+Debts!$B$4) -> 1200 | C29: =IF(C28<=0,0,MAX(0,C28*(1+Debts!$C$8/12)-MIN(C28*(1+Debts!$C$8/12),Debts!$D$8)-IF(AND(C28>0,Debts!$E$8=MIN(IF(C28>0,Debts!$E$8,999),IF(D28>0,Debts!$E$9,999),IF(E28>0,Debts!$E$10,999),IF(F28>0,Debts!$E$11,999),IF(G28>0,Debts!$E$12,999),IF(H28>0,Debts!$E$13,999),IF(I28>0,Debts!$E$14,999),IF(J28>0,Debts!$E$15,999))),MAX(0,(B29-(MIN(C28+0,C28*(1+Debts!$C$8/12))*0+MIN(C28*(1+Debts!$C$8/12),Debts!$D$8)+MIN(C28+0,D28*(1+Debts!$C$9/12))*0+MIN(D28*(1+Debts!$C$9/12),Debts!$D$9)+MIN(C28+0,E28*(1+Debts!$C$10/12))*0+MIN(E28*(1+Debts!$C$10/12),Debts!$D$10)+MIN(C28+0,F28*(1+Debts!$C$11/12))*0+MIN(F28*(1+Debts!$C$11/12),Debts!$D$11)+MIN(C28+0,G28*(1+Debts!$C$12/12))*0+MIN(G28*(1+Debts!$C$12/12),Debts!$D$12)+MIN(C28+0,H28*(1+Debts!$C$13/12))*0+MIN(H28*(1+Debts!$C$13/12),Debts!$D$13)+MIN(C28+0,I28*(1+Debts!$C$14/12))*0+MIN(I28*(1+Debts!$C$14/12),Debts!$D$14)+MIN(C28+0,J28*(1+Debts!$C$15/12))*0+MIN(J28*(1+Debts!$C$15/12),Debts!$D$15)))),0))) -> 0 | D29: =IF(D28<=0,0,MAX(0,D28*(1+Debts!$C$9/12)-MIN(D28*(1+Debts!$C$9/12),Debts!$D$9)-IF(AND(D28>0,Debts!$E$9=MIN(IF(C28>0,Debts!$E$8,999),IF(D28>0,Debts!$E$9,999),IF(E28>0,Debts!$E$10,999),IF(F28>0,Debts!$E$11,999),IF(G28>0,Debts!$E$12,999),IF(H28>0,Debts!$E$13,999),IF(I28>0,Debts!$E$14,999),IF(J28>0,Debts!$E$15,999))),MAX(0,(B29-(MIN(C28+0,C28*(1+Debts!$C$8/12))*0+MIN(C28*(1+Debts!$C$8/12),Debts!$D$8)+MIN(C28+0,D28*(1+Debts!$C$9/12))*0+MIN(D28*(1+Debts!$C$9/12),Debts!$D$9)+MIN(C28+0,E28*(1+Debts!$C$10/12))*0+MIN(E28*(1+Debts!$C$10/12),Debts!$D$10)+MIN(C28+0,F28*(1+Debts!$C$11/12))*0+MIN(F28*(1+Debts!$C$11/12),Debts!$D$11)+MIN(C28+0,G28*(1+Debts!$C$12/12))*0+MIN(G28*(1+Debts!$C$12/12),Debts!$D$12)+MIN(C28+0,H28*(1+Debts!$C$13/12))*0+MIN(H28*(1+Debts!$C$13/12),Debts!$D$13)+MIN(C28+0,I28*(1+Debts!$C$14/12))*0+MIN(I28*(1+Debts!$C$14/12),Debts!$D$14)+MIN(C28+0,J28*(1+Debts!$C$15/12))*0+MIN(J28*(1+Debts!$C$15/12),Debts!$D$15)))),0))) -> 0 | E29: =IF(E28<=0,0,MAX(0,E28*(1+Debts!$C$10/12)-MIN(E28*(1+Debts!$C$10/12),Debts!$D$10)-IF(AND(E28>0,Debts!$E$10=MIN(IF(C28>0,Debts!$E$8,999),IF(D28>0,Debts!$E$9,999),IF(E28>0,Debts!$E$10,999),IF(F28>0,Debts!$E$11,999),IF(G28>0,Debts!$E$12,999),IF(H28>0,Debts!$E$13,999),IF(I28>0,Debts!$E$14,999),IF(J28>0,Debts!$E$15,999))),MAX(0,(B29-(MIN(C28+0,C28*(1+Debts!$C$8/12))*0+MIN(C28*(1+Debts!$C$8/12),Debts!$D$8)+MIN(C28+0,D28*(1+Debts!$C$9/12))*0+MIN(D28*(1+Debts!$C$9/12),Debts!$D$9)+MIN(C28+0,E28*(1+Debts!$C$10/12))*0+MIN(E28*(1+Debts!$C$10/12),Debts!$D$10)+MIN(C28+0,F28*(1+Debts!$C$11/12))*0+MIN(F28*(1+Debts!$C$11/12),Debts!$D$11)+MIN(C28+0,G28*(1+Debts!$C$12/12))*0+MIN(G28*(1+Debts!$C$12/12),Debts!$D$12)+MIN(C28+0,H28*(1+Debts!$C$13/12))*0+MIN(H28*(1+Debts!$C$13/12),Debts!$D$13)+MIN(C28+0,I28*(1+Debts!$C$14/12))*0+MIN(I28*(1+Debts!$C$14/12),Debts!$D$14)+MIN(C28+0,J28*(1+Debts!$C$15/12))*0+MIN(J28*(1+Debts!$C$15/12),Debts!$D$15)))),0))) -> 2750.2255 | F29: =IF(F28<=0,0,MAX(0,F28*(1+Debts!$C$11/12)-MIN(F28*(1+Debts!$C$11/12),Debts!$D$11)-IF(AND(F28>0,Debts!$E$11=MIN(IF(C28>0,Debts!$E$8,999),IF(D28>0,Debts!$E$9,999),IF(E28>0,Debts!$E$10,999),IF(F28>0,Debts!$E$11,999),IF(G28>0,Debts!$E$12,999),IF(H28>0,Debts!$E$13,999),IF(I28>0,Debts!$E$14,999),IF(J28>0,Debts!$E$15,999))),MAX(0,(B29-(MIN(C28+0,C28*(1+Debts!$C$8/12))*0+MIN(C28*(1+Debts!$C$8/12),Debts!$D$8)+MIN(C28+0,D28*(1+Debts!$C$9/12))*0+MIN(D28*(1+Debts!$C$9/12),Debts!$D$9)+MIN(C28+0,E28*(1+Debts!$C$10/12))*0+MIN(E28*(1+Debts!$C$10/12),Debts!$D$10)+MIN(C28+0,F28*(1+Debts!$C$11/12))*0+MIN(F28*(1+Debts!$C$11/12),Debts!$D$11)+MIN(C28+0,G28*(1+Debts!$C$12/12))*0+MIN(G28*(1+Debts!$C$12/12),Debts!$D$12)+MIN(C28+0,H28*(1+Debts!$C$13/12))*0+MIN(H28*(1+Debts!$C$13/12),Debts!$D$13)+MIN(C28+0,I28*(1+Debts!$C$14/12))*0+MIN(I28*(1+Debts!$C$14/12),Debts!$D$14)+MIN(C28+0,J28*(1+Debts!$C$15/12))*0+MIN(J28*(1+Debts!$C$15/12),Debts!$D$15)))),0))) -> 15608.712 | G29: =IF(G28<=0,0,MAX(0,G28*(1+Debts!$C$12/12)-MIN(G28*(1+Debts!$C$12/12),Debts!$D$12)-IF(AND(G28>0,Debts!$E$12=MIN(IF(C28>0,Debts!$E$8,999),IF(D28>0,Debts!$E$9,999),IF(E28>0,Debts!$E$10,999),IF(F28>0,Debts!$E$11,999),IF(G28>0,Debts!$E$12,999),IF(H28>0,Debts!$E$13,999),IF(I28>0,Debts!$E$14,999),IF(J28>0,Debts!$E$15,999))),MAX(0,(B29-(MIN(C28+0,C28*(1+Debts!$C$8/12))*0+MIN(C28*(1+Debts!$C$8/12),Debts!$D$8)+MIN(C28+0,D28*(1+Debts!$C$9/12))*0+MIN(D28*(1+Debts!$C$9/12),Debts!$D$9)+MIN(C28+0,E28*(1+Debts!$C$10/12))*0+MIN(E28*(1+Debts!$C$10/12),Debts!$D$10)+MIN(C28+0,F28*(1+Debts!$C$11/12))*0+MIN(F28*(1+Debts!$C$11/12),Debts!$D$11)+MIN(C28+0,G28*(1+Debts!$C$12/12))*0+MIN(G28*(1+Debts!$C$12/12),Debts!$D$12)+MIN(C28+0,H28*(1+Debts!$C$13/12))*0+MIN(H28*(1+Debts!$C$13/12),Debts!$D$13)+MIN(C28+0,I28*(1+Debts!$C$14/12))*0+MIN(I28*(1+Debts!$C$14/12),Debts!$D$14)+MIN(C28+0,J28*(1+Debts!$C$15/12))*0+MIN(J28*(1+Debts!$C$15/12),Debts!$D$15)))),0))) -> 0 | H29: =IF(H28<=0,0,MAX(0,H28*(1+Debts!$C$13/12)-MIN(H28*(1+Debts!$C$13/12),Debts!$D$13)-IF(AND(H28>0,Debts!$E$13=MIN(IF(C28>0,Debts!$E$8,999),IF(D28>0,Debts!$E$9,999),IF(E28>0,Debts!$E$10,999),IF(F28>0,Debts!$E$11,999),IF(G28>0,Debts!$E$12,999),IF(H28>0,Debts!$E$13,999),IF(I28>0,Debts!$E$14,999),IF(J28>0,Debts!$E$15,999))),MAX(0,(B29-(MIN(C28+0,C28*(1+Debts!$C$8/12))*0+MIN(C28*(1+Debts!$C$8/12),Debts!$D$8)+MIN(C28+0,D28*(1+Debts!$C$9/12))*0+MIN(D28*(1+Debts!$C$9/12),Debts!$D$9)+MIN(C28+0,E28*(1+Debts!$C$10/12))*0+MIN(E28*(1+Debts!$C$10/12),Debts!$D$10)+MIN(C28+0,F28*(1+Debts!$C$11/12))*0+MIN(F28*(1+Debts!$C$11/12),Debts!$D$11)+MIN(C28+0,G28*(1+Debts!$C$12/12))*0+MIN(G28*(1+Debts!$C$12/12),Debts!$D$12)+MIN(C28+0,H28*(1+Debts!$C$13/12))*0+MIN(H28*(1+Debts!$C$13/12),Debts!$D$13)+MIN(C28+0,I28*(1+Debts!$C$14/12))*0+MIN(I28*(1+Debts!$C$14/12),Debts!$D$14)+MIN(C28+0,J28*(1+Debts!$C$15/12))*0+MIN(J28*(1+Debts!$C$15/12),Debts!$D$15)))),0))) -> 0 | I29: =IF(I28<=0,0,MAX(0,I28*(1+Debts!$C$14/12)-MIN(I28*(1+Debts!$C$14/12),Debts!$D$14)-IF(AND(I28>0,Debts!$E$14=MIN(IF(C28>0,Debts!$E$8,999),IF(D28>0,Debts!$E$9,999),IF(E28>0,Debts!$E$10,999),IF(F28>0,Debts!$E$11,999),IF(G28>0,Debts!$E$12,999),IF(H28>0,Debts!$E$13,999),IF(I28>0,Debts!$E$14,999),IF(J28>0,Debts!$E$15,999))),MAX(0,(B29-(MIN(C28+0,C28*(1+Debts!$C$8/12))*0+MIN(C28*(1+Debts!$C$8/12),Debts!$D$8)+MIN(C28+0,D28*(1+Debts!$C$9/12))*0+MIN(D28*(1+Debts!$C$9/12),Debts!$D$9)+MIN(C28+0,E28*(1+Debts!$C$10/12))*0+MIN(E28*(1+Debts!$C$10/12),Debts!$D$10)+MIN(C28+0,F28*(1+Debts!$C$11/12))*0+MIN(F28*(1+Debts!$C$11/12),Debts!$D$11)+MIN(C28+0,G28*(1+Debts!$C$12/12))*0+MIN(G28*(1+Debts!$C$12/12),Debts!$D$12)+MIN(C28+0,H28*(1+Debts!$C$13/12))*0+MIN(H28*(1+Debts!$C$13/12),Debts!$D$13)+MIN(C28+0,I28*(1+Debts!$C$14/12))*0+MIN(I28*(1+Debts!$C$14/12),Debts!$D$14)+MIN(C28+0,J28*(1+Debts!$C$15/12))*0+MIN(J28*(1+Debts!$C$15/12),Debts!$D$15)))),0))) -> 0 | J29: =IF(J28<=0,0,MAX(0,J28*(1+Debts!$C$15/12)-MIN(J28*(1+Debts!$C$15/12),Debts!$D$15)-IF(AND(J28>0,Debts!$E$15=MIN(IF(C28>0,Debts!$E$8,999),IF(D28>0,Debts!$E$9,999),IF(E28>0,Debts!$E$10,999),IF(F28>0,Debts!$E$11,999),IF(G28>0,Debts!$E$12,999),IF(H28>0,Debts!$E$13,999),IF(I28>0,Debts!$E$14,999),IF(J28>0,Debts!$E$15,999))),MAX(0,(B29-(MIN(C28+0,C28*(1+Debts!$C$8/12))*0+MIN(C28*(1+Debts!$C$8/12),Debts!$D$8)+MIN(C28+0,D28*(1+Debts!$C$9/12))*0+MIN(D28*(1+Debts!$C$9/12),Debts!$D$9)+MIN(C28+0,E28*(1+Debts!$C$10/12))*0+MIN(E28*(1+Debts!$C$10/12),Debts!$D$10)+MIN(C28+0,F28*(1+Debts!$C$11/12))*0+MIN(F28*(1+Debts!$C$11/12),Debts!$D$11)+MIN(C28+0,G28*(1+Debts!$C$12/12))*0+MIN(G28*(1+Debts!$C$12/12),Debts!$D$12)+MIN(C28+0,H28*(1+Debts!$C$13/12))*0+MIN(H28*(1+Debts!$C$13/12),Debts!$D$13)+MIN(C28+0,I28*(1+Debts!$C$14/12))*0+MIN(I28*(1+Debts!$C$14/12),Debts!$D$14)+MIN(C28+0,J28*(1+Debts!$C$15/12))*0+MIN(J28*(1+Debts!$C$15/12),Debts!$D$15)))),0))) -> 0 | K29: =IF(C28>0,C28*Debts!$C$8/12,0)+IF(D28>0,D28*Debts!$C$9/12,0)+IF(E28>0,E28*Debts!$C$10/12,0)+IF(F28>0,F28*Debts!$C$11/12,0)+IF(G28>0,G28*Debts!$C$12/12,0)+IF(H28>0,H28*Debts!$C$13/12,0)+IF(I28>0,I28*Debts!$C$14/12,0)+IF(J28>0,J28*Debts!$C$15/12,0) -> 93.554986 | L29: =SUM(C29:J29) -> 18358.938
A30: =23 -> 23 | B30: =IF(L29<=0,0,Debts!$D$16+Debts!$B$4) -> 1200 | C30: =IF(C29<=0,0,MAX(0,C29*(1+Debts!$C$8/12)-MIN(C29*(1+Debts!$C$8/12),Debts!$D$8)-IF(AND(C29>0,Debts!$E$8=MIN(IF(C29>0,Debts!$E$8,999),IF(D29>0,Debts!$E$9,999),IF(E29>0,Debts!$E$10,999),IF(F29>0,Debts!$E$11,999),IF(G29>0,Debts!$E$12,999),IF(H29>0,Debts!$E$13,999),IF(I29>0,Debts!$E$14,999),IF(J29>0,Debts!$E$15,999))),MAX(0,(B30-(MIN(C29+0,C29*(1+Debts!$C$8/12))*0+MIN(C29*(1+Debts!$C$8/12),Debts!$D$8)+MIN(C29+0,D29*(1+Debts!$C$9/12))*0+MIN(D29*(1+Debts!$C$9/12),Debts!$D$9)+MIN(C29+0,E29*(1+Debts!$C$10/12))*0+MIN(E29*(1+Debts!$C$10/12),Debts!$D$10)+MIN(C29+0,F29*(1+Debts!$C$11/12))*0+MIN(F29*(1+Debts!$C$11/12),Debts!$D$11)+MIN(C29+0,G29*(1+Debts!$C$12/12))*0+MIN(G29*(1+Debts!$C$12/12),Debts!$D$12)+MIN(C29+0,H29*(1+Debts!$C$13/12))*0+MIN(H29*(1+Debts!$C$13/12),Debts!$D$13)+MIN(C29+0,I29*(1+Debts!$C$14/12))*0+MIN(I29*(1+Debts!$C$14/12),Debts!$D$14)+MIN(C29+0,J29*(1+Debts!$C$15/12))*0+MIN(J29*(1+Debts!$C$15/12),Debts!$D$15)))),0))) -> 0 | D30: =IF(D29<=0,0,MAX(0,D29*(1+Debts!$C$9/12)-MIN(D29*(1+Debts!$C$9/12),Debts!$D$9)-IF(AND(D29>0,Debts!$E$9=MIN(IF(C29>0,Debts!$E$8,999),IF(D29>0,Debts!$E$9,999),IF(E29>0,Debts!$E$10,999),IF(F29>0,Debts!$E$11,999),IF(G29>0,Debts!$E$12,999),IF(H29>0,Debts!$E$13,999),IF(I29>0,Debts!$E$14,999),IF(J29>0,Debts!$E$15,999))),MAX(0,(B30-(MIN(C29+0,C29*(1+Debts!$C$8/12))*0+MIN(C29*(1+Debts!$C$8/12),Debts!$D$8)+MIN(C29+0,D29*(1+Debts!$C$9/12))*0+MIN(D29*(1+Debts!$C$9/12),Debts!$D$9)+MIN(C29+0,E29*(1+Debts!$C$10/12))*0+MIN(E29*(1+Debts!$C$10/12),Debts!$D$10)+MIN(C29+0,F29*(1+Debts!$C$11/12))*0+MIN(F29*(1+Debts!$C$11/12),Debts!$D$11)+MIN(C29+0,G29*(1+Debts!$C$12/12))*0+MIN(G29*(1+Debts!$C$12/12),Debts!$D$12)+MIN(C29+0,H29*(1+Debts!$C$13/12))*0+MIN(H29*(1+Debts!$C$13/12),Debts!$D$13)+MIN(C29+0,I29*(1+Debts!$C$14/12))*0+MIN(I29*(1+Debts!$C$14/12),Debts!$D$14)+MIN(C29+0,J29*(1+Debts!$C$15/12))*0+MIN(J29*(1+Debts!$C$15/12),Debts!$D$15)))),0))) -> 0 | E30: =IF(E29<=0,0,MAX(0,E29*(1+Debts!$C$10/12)-MIN(E29*(1+Debts!$C$10/12),Debts!$D$10)-IF(AND(E29>0,Debts!$E$10=MIN(IF(C29>0,Debts!$E$8,999),IF(D29>0,Debts!$E$9,999),IF(E29>0,Debts!$E$10,999),IF(F29>0,Debts!$E$11,999),IF(G29>0,Debts!$E$12,999),IF(H29>0,Debts!$E$13,999),IF(I29>0,Debts!$E$14,999),IF(J29>0,Debts!$E$15,999))),MAX(0,(B30-(MIN(C29+0,C29*(1+Debts!$C$8/12))*0+MIN(C29*(1+Debts!$C$8/12),Debts!$D$8)+MIN(C29+0,D29*(1+Debts!$C$9/12))*0+MIN(D29*(1+Debts!$C$9/12),Debts!$D$9)+MIN(C29+0,E29*(1+Debts!$C$10/12))*0+MIN(E29*(1+Debts!$C$10/12),Debts!$D$10)+MIN(C29+0,F29*(1+Debts!$C$11/12))*0+MIN(F29*(1+Debts!$C$11/12),Debts!$D$11)+MIN(C29+0,G29*(1+Debts!$C$12/12))*0+MIN(G29*(1+Debts!$C$12/12),Debts!$D$12)+MIN(C29+0,H29*(1+Debts!$C$13/12))*0+MIN(H29*(1+Debts!$C$13/12),Debts!$D$13)+MIN(C29+0,I29*(1+Debts!$C$14/12))*0+MIN(I29*(1+Debts!$C$14/12),Debts!$D$14)+MIN(C29+0,J29*(1+Debts!$C$15/12))*0+MIN(J29*(1+Debts!$C$15/12),Debts!$D$15)))),0))) -> 1776.0393 | F30: =IF(F29<=0,0,MAX(0,F29*(1+Debts!$C$11/12)-MIN(F29*(1+Debts!$C$11/12),Debts!$D$11)-IF(AND(F29>0,Debts!$E$11=MIN(IF(C29>0,Debts!$E$8,999),IF(D29>0,Debts!$E$9,999),IF(E29>0,Debts!$E$10,999),IF(F29>0,Debts!$E$11,999),IF(G29>0,Debts!$E$12,999),IF(H29>0,Debts!$E$13,999),IF(I29>0,Debts!$E$14,999),IF(J29>0,Debts!$E$15,999))),MAX(0,(B30-(MIN(C29+0,C29*(1+Debts!$C$8/12))*0+MIN(C29*(1+Debts!$C$8/12),Debts!$D$8)+MIN(C29+0,D29*(1+Debts!$C$9/12))*0+MIN(D29*(1+Debts!$C$9/12),Debts!$D$9)+MIN(C29+0,E29*(1+Debts!$C$10/12))*0+MIN(E29*(1+Debts!$C$10/12),Debts!$D$10)+MIN(C29+0,F29*(1+Debts!$C$11/12))*0+MIN(F29*(1+Debts!$C$11/12),Debts!$D$11)+MIN(C29+0,G29*(1+Debts!$C$12/12))*0+MIN(G29*(1+Debts!$C$12/12),Debts!$D$12)+MIN(C29+0,H29*(1+Debts!$C$13/12))*0+MIN(H29*(1+Debts!$C$13/12),Debts!$D$13)+MIN(C29+0,I29*(1+Debts!$C$14/12))*0+MIN(I29*(1+Debts!$C$14/12),Debts!$D$14)+MIN(C29+0,J29*(1+Debts!$C$15/12))*0+MIN(J29*(1+Debts!$C$15/12),Debts!$D$15)))),0))) -> 15470.252 | G30: =IF(G29<=0,0,MAX(0,G29*(1+Debts!$C$12/12)-MIN(G29*(1+Debts!$C$12/12),Debts!$D$12)-IF(AND(G29>0,Debts!$E$12=MIN(IF(C29>0,Debts!$E$8,999),IF(D29>0,Debts!$E$9,999),IF(E29>0,Debts!$E$10,999),IF(F29>0,Debts!$E$11,999),IF(G29>0,Debts!$E$12,999),IF(H29>0,Debts!$E$13,999),IF(I29>0,Debts!$E$14,999),IF(J29>0,Debts!$E$15,999))),MAX(0,(B30-(MIN(C29+0,C29*(1+Debts!$C$8/12))*0+MIN(C29*(1+Debts!$C$8/12),Debts!$D$8)+MIN(C29+0,D29*(1+Debts!$C$9/12))*0+MIN(D29*(1+Debts!$C$9/12),Debts!$D$9)+MIN(C29+0,E29*(1+Debts!$C$10/12))*0+MIN(E29*(1+Debts!$C$10/12),Debts!$D$10)+MIN(C29+0,F29*(1+Debts!$C$11/12))*0+MIN(F29*(1+Debts!$C$11/12),Debts!$D$11)+MIN(C29+0,G29*(1+Debts!$C$12/12))*0+MIN(G29*(1+Debts!$C$12/12),Debts!$D$12)+MIN(C29+0,H29*(1+Debts!$C$13/12))*0+MIN(H29*(1+Debts!$C$13/12),Debts!$D$13)+MIN(C29+0,I29*(1+Debts!$C$14/12))*0+MIN(I29*(1+Debts!$C$14/12),Debts!$D$14)+MIN(C29+0,J29*(1+Debts!$C$15/12))*0+MIN(J29*(1+Debts!$C$15/12),Debts!$D$15)))),0))) -> 0 | H30: =IF(H29<=0,0,MAX(0,H29*(1+Debts!$C$13/12)-MIN(H29*(1+Debts!$C$13/12),Debts!$D$13)-IF(AND(H29>0,Debts!$E$13=MIN(IF(C29>0,Debts!$E$8,999),IF(D29>0,Debts!$E$9,999),IF(E29>0,Debts!$E$10,999),IF(F29>0,Debts!$E$11,999),IF(G29>0,Debts!$E$12,999),IF(H29>0,Debts!$E$13,999),IF(I29>0,Debts!$E$14,999),IF(J29>0,Debts!$E$15,999))),MAX(0,(B30-(MIN(C29+0,C29*(1+Debts!$C$8/12))*0+MIN(C29*(1+Debts!$C$8/12),Debts!$D$8)+MIN(C29+0,D29*(1+Debts!$C$9/12))*0+MIN(D29*(1+Debts!$C$9/12),Debts!$D$9)+MIN(C29+0,E29*(1+Debts!$C$10/12))*0+MIN(E29*(1+Debts!$C$10/12),Debts!$D$10)+MIN(C29+0,F29*(1+Debts!$C$11/12))*0+MIN(F29*(1+Debts!$C$11/12),Debts!$D$11)+MIN(C29+0,G29*(1+Debts!$C$12/12))*0+MIN(G29*(1+Debts!$C$12/12),Debts!$D$12)+MIN(C29+0,H29*(1+Debts!$C$13/12))*0+MIN(H29*(1+Debts!$C$13/12),Debts!$D$13)+MIN(C29+0,I29*(1+Debts!$C$14/12))*0+MIN(I29*(1+Debts!$C$14/12),Debts!$D$14)+MIN(C29+0,J29*(1+Debts!$C$15/12))*0+MIN(J29*(1+Debts!$C$15/12),Debts!$D$15)))),0))) -> 0 | I30: =IF(I29<=0,0,MAX(0,I29*(1+Debts!$C$14/12)-MIN(I29*(1+Debts!$C$14/12),Debts!$D$14)-IF(AND(I29>0,Debts!$E$14=MIN(IF(C29>0,Debts!$E$8,999),IF(D29>0,Debts!$E$9,999),IF(E29>0,Debts!$E$10,999),IF(F29>0,Debts!$E$11,999),IF(G29>0,Debts!$E$12,999),IF(H29>0,Debts!$E$13,999),IF(I29>0,Debts!$E$14,999),IF(J29>0,Debts!$E$15,999))),MAX(0,(B30-(MIN(C29+0,C29*(1+Debts!$C$8/12))*0+MIN(C29*(1+Debts!$C$8/12),Debts!$D$8)+MIN(C29+0,D29*(1+Debts!$C$9/12))*0+MIN(D29*(1+Debts!$C$9/12),Debts!$D$9)+MIN(C29+0,E29*(1+Debts!$C$10/12))*0+MIN(E29*(1+Debts!$C$10/12),Debts!$D$10)+MIN(C29+0,F29*(1+Debts!$C$11/12))*0+MIN(F29*(1+Debts!$C$11/12),Debts!$D$11)+MIN(C29+0,G29*(1+Debts!$C$12/12))*0+MIN(G29*(1+Debts!$C$12/12),Debts!$D$12)+MIN(C29+0,H29*(1+Debts!$C$13/12))*0+MIN(H29*(1+Debts!$C$13/12),Debts!$D$13)+MIN(C29+0,I29*(1+Debts!$C$14/12))*0+MIN(I29*(1+Debts!$C$14/12),Debts!$D$14)+MIN(C29+0,J29*(1+Debts!$C$15/12))*0+MIN(J29*(1+Debts!$C$15/12),Debts!$D$15)))),0))) -> 0 | J30: =IF(J29<=0,0,MAX(0,J29*(1+Debts!$C$15/12)-MIN(J29*(1+Debts!$C$15/12),Debts!$D$15)-IF(AND(J29>0,Debts!$E$15=MIN(IF(C29>0,Debts!$E$8,999),IF(D29>0,Debts!$E$9,999),IF(E29>0,Debts!$E$10,999),IF(F29>0,Debts!$E$11,999),IF(G29>0,Debts!$E$12,999),IF(H29>0,Debts!$E$13,999),IF(I29>0,Debts!$E$14,999),IF(J29>0,Debts!$E$15,999))),MAX(0,(B30-(MIN(C29+0,C29*(1+Debts!$C$8/12))*0+MIN(C29*(1+Debts!$C$8/12),Debts!$D$8)+MIN(C29+0,D29*(1+Debts!$C$9/12))*0+MIN(D29*(1+Debts!$C$9/12),Debts!$D$9)+MIN(C29+0,E29*(1+Debts!$C$10/12))*0+MIN(E29*(1+Debts!$C$10/12),Debts!$D$10)+MIN(C29+0,F29*(1+Debts!$C$11/12))*0+MIN(F29*(1+Debts!$C$11/12),Debts!$D$11)+MIN(C29+0,G29*(1+Debts!$C$12/12))*0+MIN(G29*(1+Debts!$C$12/12),Debts!$D$12)+MIN(C29+0,H29*(1+Debts!$C$13/12))*0+MIN(H29*(1+Debts!$C$13/12),Debts!$D$13)+MIN(C29+0,I29*(1+Debts!$C$14/12))*0+MIN(I29*(1+Debts!$C$14/12),Debts!$D$14)+MIN(C29+0,J29*(1+Debts!$C$15/12))*0+MIN(J29*(1+Debts!$C$15/12),Debts!$D$15)))),0))) -> 0 | K30: =IF(C29>0,C29*Debts!$C$8/12,0)+IF(D29>0,D29*Debts!$C$9/12,0)+IF(E29>0,E29*Debts!$C$10/12,0)+IF(F29>0,F29*Debts!$C$11/12,0)+IF(G29>0,G29*Debts!$C$12/12,0)+IF(H29>0,H29*Debts!$C$13/12,0)+IF(I29>0,I29*Debts!$C$14/12,0)+IF(J29>0,J29*Debts!$C$15/12,0) -> 87.353727 | L30: =SUM(C30:J30) -> 17246.291
A31: =24 -> 24 | B31: =IF(L30<=0,0,Debts!$D$16+Debts!$B$4) -> 1200 | C31: =IF(C30<=0,0,MAX(0,C30*(1+Debts!$C$8/12)-MIN(C30*(1+Debts!$C$8/12),Debts!$D$8)-IF(AND(C30>0,Debts!$E$8=MIN(IF(C30>0,Debts!$E$8,999),IF(D30>0,Debts!$E$9,999),IF(E30>0,Debts!$E$10,999),IF(F30>0,Debts!$E$11,999),IF(G30>0,Debts!$E$12,999),IF(H30>0,Debts!$E$13,999),IF(I30>0,Debts!$E$14,999),IF(J30>0,Debts!$E$15,999))),MAX(0,(B31-(MIN(C30+0,C30*(1+Debts!$C$8/12))*0+MIN(C30*(1+Debts!$C$8/12),Debts!$D$8)+MIN(C30+0,D30*(1+Debts!$C$9/12))*0+MIN(D30*(1+Debts!$C$9/12),Debts!$D$9)+MIN(C30+0,E30*(1+Debts!$C$10/12))*0+MIN(E30*(1+Debts!$C$10/12),Debts!$D$10)+MIN(C30+0,F30*(1+Debts!$C$11/12))*0+MIN(F30*(1+Debts!$C$11/12),Debts!$D$11)+MIN(C30+0,G30*(1+Debts!$C$12/12))*0+MIN(G30*(1+Debts!$C$12/12),Debts!$D$12)+MIN(C30+0,H30*(1+Debts!$C$13/12))*0+MIN(H30*(1+Debts!$C$13/12),Debts!$D$13)+MIN(C30+0,I30*(1+Debts!$C$14/12))*0+MIN(I30*(1+Debts!$C$14/12),Debts!$D$14)+MIN(C30+0,J30*(1+Debts!$C$15/12))*0+MIN(J30*(1+Debts!$C$15/12),Debts!$D$15)))),0))) -> 0 | D31: =IF(D30<=0,0,MAX(0,D30*(1+Debts!$C$9/12)-MIN(D30*(1+Debts!$C$9/12),Debts!$D$9)-IF(AND(D30>0,Debts!$E$9=MIN(IF(C30>0,Debts!$E$8,999),IF(D30>0,Debts!$E$9,999),IF(E30>0,Debts!$E$10,999),IF(F30>0,Debts!$E$11,999),IF(G30>0,Debts!$E$12,999),IF(H30>0,Debts!$E$13,999),IF(I30>0,Debts!$E$14,999),IF(J30>0,Debts!$E$15,999))),MAX(0,(B31-(MIN(C30+0,C30*(1+Debts!$C$8/12))*0+MIN(C30*(1+Debts!$C$8/12),Debts!$D$8)+MIN(C30+0,D30*(1+Debts!$C$9/12))*0+MIN(D30*(1+Debts!$C$9/12),Debts!$D$9)+MIN(C30+0,E30*(1+Debts!$C$10/12))*0+MIN(E30*(1+Debts!$C$10/12),Debts!$D$10)+MIN(C30+0,F30*(1+Debts!$C$11/12))*0+MIN(F30*(1+Debts!$C$11/12),Debts!$D$11)+MIN(C30+0,G30*(1+Debts!$C$12/12))*0+MIN(G30*(1+Debts!$C$12/12),Debts!$D$12)+MIN(C30+0,H30*(1+Debts!$C$13/12))*0+MIN(H30*(1+Debts!$C$13/12),Debts!$D$13)+MIN(C30+0,I30*(1+Debts!$C$14/12))*0+MIN(I30*(1+Debts!$C$14/12),Debts!$D$14)+MIN(C30+0,J30*(1+Debts!$C$15/12))*0+MIN(J30*(1+Debts!$C$15/12),Debts!$D$15)))),0))) -> 0 | E31: =IF(E30<=0,0,MAX(0,E30*(1+Debts!$C$10/12)-MIN(E30*(1+Debts!$C$10/12),Debts!$D$10)-IF(AND(E30>0,Debts!$E$10=MIN(IF(C30>0,Debts!$E$8,999),IF(D30>0,Debts!$E$9,999),IF(E30>0,Debts!$E$10,999),IF(F30>0,Debts!$E$11,999),IF(G30>0,Debts!$E$12,999),IF(H30>0,Debts!$E$13,999),IF(I30>0,Debts!$E$14,999),IF(J30>0,Debts!$E$15,999))),MAX(0,(B31-(MIN(C30+0,C30*(1+Debts!$C$8/12))*0+MIN(C30*(1+Debts!$C$8/12),Debts!$D$8)+MIN(C30+0,D30*(1+Debts!$C$9/12))*0+MIN(D30*(1+Debts!$C$9/12),Debts!$D$9)+MIN(C30+0,E30*(1+Debts!$C$10/12))*0+MIN(E30*(1+Debts!$C$10/12),Debts!$D$10)+MIN(C30+0,F30*(1+Debts!$C$11/12))*0+MIN(F30*(1+Debts!$C$11/12),Debts!$D$11)+MIN(C30+0,G30*(1+Debts!$C$12/12))*0+MIN(G30*(1+Debts!$C$12/12),Debts!$D$12)+MIN(C30+0,H30*(1+Debts!$C$13/12))*0+MIN(H30*(1+Debts!$C$13/12),Debts!$D$13)+MIN(C30+0,I30*(1+Debts!$C$14/12))*0+MIN(I30*(1+Debts!$C$14/12),Debts!$D$14)+MIN(C30+0,J30*(1+Debts!$C$15/12))*0+MIN(J30*(1+Debts!$C$15/12),Debts!$D$15)))),0))) -> 796.25157 | F31: =IF(F30<=0,0,MAX(0,F30*(1+Debts!$C$11/12)-MIN(F30*(1+Debts!$C$11/12),Debts!$D$11)-IF(AND(F30>0,Debts!$E$11=MIN(IF(C30>0,Debts!$E$8,999),IF(D30>0,Debts!$E$9,999),IF(E30>0,Debts!$E$10,999),IF(F30>0,Debts!$E$11,999),IF(G30>0,Debts!$E$12,999),IF(H30>0,Debts!$E$13,999),IF(I30>0,Debts!$E$14,999),IF(J30>0,Debts!$E$15,999))),MAX(0,(B31-(MIN(C30+0,C30*(1+Debts!$C$8/12))*0+MIN(C30*(1+Debts!$C$8/12),Debts!$D$8)+MIN(C30+0,D30*(1+Debts!$C$9/12))*0+MIN(D30*(1+Debts!$C$9/12),Debts!$D$9)+MIN(C30+0,E30*(1+Debts!$C$10/12))*0+MIN(E30*(1+Debts!$C$10/12),Debts!$D$10)+MIN(C30+0,F30*(1+Debts!$C$11/12))*0+MIN(F30*(1+Debts!$C$11/12),Debts!$D$11)+MIN(C30+0,G30*(1+Debts!$C$12/12))*0+MIN(G30*(1+Debts!$C$12/12),Debts!$D$12)+MIN(C30+0,H30*(1+Debts!$C$13/12))*0+MIN(H30*(1+Debts!$C$13/12),Debts!$D$13)+MIN(C30+0,I30*(1+Debts!$C$14/12))*0+MIN(I30*(1+Debts!$C$14/12),Debts!$D$14)+MIN(C30+0,J30*(1+Debts!$C$15/12))*0+MIN(J30*(1+Debts!$C$15/12),Debts!$D$15)))),0))) -> 15331.157 | G31: =IF(G30<=0,0,MAX(0,G30*(1+Debts!$C$12/12)-MIN(G30*(1+Debts!$C$12/12),Debts!$D$12)-IF(AND(G30>0,Debts!$E$12=MIN(IF(C30>0,Debts!$E$8,999),IF(D30>0,Debts!$E$9,999),IF(E30>0,Debts!$E$10,999),IF(F30>0,Debts!$E$11,999),IF(G30>0,Debts!$E$12,999),IF(H30>0,Debts!$E$13,999),IF(I30>0,Debts!$E$14,999),IF(J30>0,Debts!$E$15,999))),MAX(0,(B31-(MIN(C30+0,C30*(1+Debts!$C$8/12))*0+MIN(C30*(1+Debts!$C$8/12),Debts!$D$8)+MIN(C30+0,D30*(1+Debts!$C$9/12))*0+MIN(D30*(1+Debts!$C$9/12),Debts!$D$9)+MIN(C30+0,E30*(1+Debts!$C$10/12))*0+MIN(E30*(1+Debts!$C$10/12),Debts!$D$10)+MIN(C30+0,F30*(1+Debts!$C$11/12))*0+MIN(F30*(1+Debts!$C$11/12),Debts!$D$11)+MIN(C30+0,G30*(1+Debts!$C$12/12))*0+MIN(G30*(1+Debts!$C$12/12),Debts!$D$12)+MIN(C30+0,H30*(1+Debts!$C$13/12))*0+MIN(H30*(1+Debts!$C$13/12),Debts!$D$13)+MIN(C30+0,I30*(1+Debts!$C$14/12))*0+MIN(I30*(1+Debts!$C$14/12),Debts!$D$14)+MIN(C30+0,J30*(1+Debts!$C$15/12))*0+MIN(J30*(1+Debts!$C$15/12),Debts!$D$15)))),0))) -> 0 | H31: =IF(H30<=0,0,MAX(0,H30*(1+Debts!$C$13/12)-MIN(H30*(1+Debts!$C$13/12),Debts!$D$13)-IF(AND(H30>0,Debts!$E$13=MIN(IF(C30>0,Debts!$E$8,999),IF(D30>0,Debts!$E$9,999),IF(E30>0,Debts!$E$10,999),IF(F30>0,Debts!$E$11,999),IF(G30>0,Debts!$E$12,999),IF(H30>0,Debts!$E$13,999),IF(I30>0,Debts!$E$14,999),IF(J30>0,Debts!$E$15,999))),MAX(0,(B31-(MIN(C30+0,C30*(1+Debts!$C$8/12))*0+MIN(C30*(1+Debts!$C$8/12),Debts!$D$8)+MIN(C30+0,D30*(1+Debts!$C$9/12))*0+MIN(D30*(1+Debts!$C$9/12),Debts!$D$9)+MIN(C30+0,E30*(1+Debts!$C$10/12))*0+MIN(E30*(1+Debts!$C$10/12),Debts!$D$10)+MIN(C30+0,F30*(1+Debts!$C$11/12))*0+MIN(F30*(1+Debts!$C$11/12),Debts!$D$11)+MIN(C30+0,G30*(1+Debts!$C$12/12))*0+MIN(G30*(1+Debts!$C$12/12),Debts!$D$12)+MIN(C30+0,H30*(1+Debts!$C$13/12))*0+MIN(H30*(1+Debts!$C$13/12),Debts!$D$13)+MIN(C30+0,I30*(1+Debts!$C$14/12))*0+MIN(I30*(1+Debts!$C$14/12),Debts!$D$14)+MIN(C30+0,J30*(1+Debts!$C$15/12))*0+MIN(J30*(1+Debts!$C$15/12),Debts!$D$15)))),0))) -> 0 | I31: =IF(I30<=0,0,MAX(0,I30*(1+Debts!$C$14/12)-MIN(I30*(1+Debts!$C$14/12),Debts!$D$14)-IF(AND(I30>0,Debts!$E$14=MIN(IF(C30>0,Debts!$E$8,999),IF(D30>0,Debts!$E$9,999),IF(E30>0,Debts!$E$10,999),IF(F30>0,Debts!$E$11,999),IF(G30>0,Debts!$E$12,999),IF(H30>0,Debts!$E$13,999),IF(I30>0,Debts!$E$14,999),IF(J30>0,Debts!$E$15,999))),MAX(0,(B31-(MIN(C30+0,C30*(1+Debts!$C$8/12))*0+MIN(C30*(1+Debts!$C$8/12),Debts!$D$8)+MIN(C30+0,D30*(1+Debts!$C$9/12))*0+MIN(D30*(1+Debts!$C$9/12),Debts!$D$9)+MIN(C30+0,E30*(1+Debts!$C$10/12))*0+MIN(E30*(1+Debts!$C$10/12),Debts!$D$10)+MIN(C30+0,F30*(1+Debts!$C$11/12))*0+MIN(F30*(1+Debts!$C$11/12),Debts!$D$11)+MIN(C30+0,G30*(1+Debts!$C$12/12))*0+MIN(G30*(1+Debts!$C$12/12),Debts!$D$12)+MIN(C30+0,H30*(1+Debts!$C$13/12))*0+MIN(H30*(1+Debts!$C$13/12),Debts!$D$13)+MIN(C30+0,I30*(1+Debts!$C$14/12))*0+MIN(I30*(1+Debts!$C$14/12),Debts!$D$14)+MIN(C30+0,J30*(1+Debts!$C$15/12))*0+MIN(J30*(1+Debts!$C$15/12),Debts!$D$15)))),0))) -> 0 | J31: =IF(J30<=0,0,MAX(0,J30*(1+Debts!$C$15/12)-MIN(J30*(1+Debts!$C$15/12),Debts!$D$15)-IF(AND(J30>0,Debts!$E$15=MIN(IF(C30>0,Debts!$E$8,999),IF(D30>0,Debts!$E$9,999),IF(E30>0,Debts!$E$10,999),IF(F30>0,Debts!$E$11,999),IF(G30>0,Debts!$E$12,999),IF(H30>0,Debts!$E$13,999),IF(I30>0,Debts!$E$14,999),IF(J30>0,Debts!$E$15,999))),MAX(0,(B31-(MIN(C30+0,C30*(1+Debts!$C$8/12))*0+MIN(C30*(1+Debts!$C$8/12),Debts!$D$8)+MIN(C30+0,D30*(1+Debts!$C$9/12))*0+MIN(D30*(1+Debts!$C$9/12),Debts!$D$9)+MIN(C30+0,E30*(1+Debts!$C$10/12))*0+MIN(E30*(1+Debts!$C$10/12),Debts!$D$10)+MIN(C30+0,F30*(1+Debts!$C$11/12))*0+MIN(F30*(1+Debts!$C$11/12),Debts!$D$11)+MIN(C30+0,G30*(1+Debts!$C$12/12))*0+MIN(G30*(1+Debts!$C$12/12),Debts!$D$12)+MIN(C30+0,H30*(1+Debts!$C$13/12))*0+MIN(H30*(1+Debts!$C$13/12),Debts!$D$13)+MIN(C30+0,I30*(1+Debts!$C$14/12))*0+MIN(I30*(1+Debts!$C$14/12),Debts!$D$14)+MIN(C30+0,J30*(1+Debts!$C$15/12))*0+MIN(J30*(1+Debts!$C$15/12),Debts!$D$15)))),0))) -> 0 | K31: =IF(C30>0,C30*Debts!$C$8/12,0)+IF(D30>0,D30*Debts!$C$9/12,0)+IF(E30>0,E30*Debts!$C$10/12,0)+IF(F30>0,F30*Debts!$C$11/12,0)+IF(G30>0,G30*Debts!$C$12/12,0)+IF(H30>0,H30*Debts!$C$13/12,0)+IF(I30>0,I30*Debts!$C$14/12,0)+IF(J30>0,J30*Debts!$C$15/12,0) -> 81.117548 | L31: =SUM(C31:J31) -> 16127.409
