Workbook

Sheet Start Here
A1: Savings Goals & Sinking Funds Tracker
A2: Simple Sheets Co. — Excel + Google Sheets
A4: Setup
A5: 1. One row per goal: target amount, target date, and what you've saved so far.
A6: 2. Monthly amount needed to hit each date calculates, plus a progress bar and on-track status.
A7: 3. Log deposits on the Deposits tab; balances update automatically.
A9: Conventions
A10: • Yellow cells with blue text are inputs. Type over the sample numbers.
A11: • Black text is a formula. Leave it alone unless you know what you're changing.
A12: • Green text pulls from another tab.
A13: • Works in Excel 2016+ and Google Sheets (File > Import > Upload > Replace). No macros.
A15: For planning and educational use only. Not financial, legal, or tax advice. Every number is an estimate you should verify for your own business.

Sheet Dashboard
B2: Savings Dashboard
B3: Every goal, how far along, and what it takes each month.
B5: TOTAL SAVED | E5: TOTAL TARGET | H5: STILL TO SAVE | K5: NEEDED PER MONTH (ALL GOALS)
B6: =Goals!F20 -> 7350 | E6: =Goals!B20 -> 23500 | H6: =Goals!G20 -> 16150 | K6: =Goals!I20 -> 2231.7055
B9: OVERALL PROGRESS | E9: GOALS COMPLETE
B10: =IF(Goals!B20=0,0,Goals!F20/Goals!B20) -> 0.31276596 | E10: =COUNTIF(Goals!K5:K19,"DONE")&" of "&COUNTA(Goals!A5:A19) -> 0 of 5
B13: Overall progress
B14: =REPT("█",ROUND(MIN(1,MAX(0,IF(Goals!B20=0,0,Goals!F20/Goals!B20)))*40,0))&REPT("░",40-ROUND(MIN(1,MAX(0,IF(Goals!B20=0,0,Goals!F20/Goals!B20)))*40,0))&" "&TEXT(IF(Goals!B20=0,0,Goals!F20/Goals!B20),"0%") -> █████████████░░░░░░░░░░░░░░░░░░░░░░░░░░░ 31%

Sheet Goals
A1: Savings Goals
A3: How to use: type your numbers in the yellow cells (blue text). Everything else calculates.
A4: Goal | B4: Target amount | C4: Target date | D4: Starting balance | E4: Deposits logged | F4: Current balance | G4: Remaining | H4: Months left | I4: Needed per month | J4: Progress | K4: Status
A5: Emergency fund | B5: 10000 | C5: 2027-06-30 | D5: 3200 | E5: =SUMIF(Deposits!$B$6:$B$500,A5,Deposits!$C$6:$C$500) -> 800 | F5: =D5+E5 -> 4000 | G5: =MAX(0,B5-F5) -> 6000 | H5: =MAX(0,ROUND((DATEVALUE(C5)-TODAY())/30.4,1)) -> 9.4 | I5: =IF(H5<=0,G5,G5/H5) -> 638.29787 | J5: =REPT("█",ROUND(MIN(1,IF(B5=0,0,F5/B5))*20,0))&" "&TEXT(IF(B5=0,0,F5/B5),"0%") -> ████████ 40% | K5: =IF(G5=0,"DONE",IF(H5=0,"Past due","On track")) -> On track
A6: Vacation — Japan | B6: 4500 | C6: 2027-03-01 | D6: 900 | E6: =SUMIF(Deposits!$B$6:$B$500,A6,Deposits!$C$6:$C$500) -> 200 | F6: =D6+E6 -> 1100 | G6: =MAX(0,B6-F6) -> 3400 | H6: =MAX(0,ROUND((DATEVALUE(C6)-TODAY())/30.4,1)) -> 5.4 | I6: =IF(H6<=0,G6,G6/H6) -> 629.62963 | J6: =REPT("█",ROUND(MIN(1,IF(B6=0,0,F6/B6))*20,0))&" "&TEXT(IF(B6=0,0,F6/B6),"0%") -> █████ 24% | K6: =IF(G6=0,"DONE",IF(H6=0,"Past due","On track")) -> On track
A7: New laptop | B7: 1800 | C7: 2026-12-15 | D7: 1100 | E7: =SUMIF(Deposits!$B$6:$B$500,A7,Deposits!$C$6:$C$500) -> 150 | F7: =D7+E7 -> 1250 | G7: =MAX(0,B7-F7) -> 550 | H7: =MAX(0,ROUND((DATEVALUE(C7)-TODAY())/30.4,1)) -> 2.9 | I7: =IF(H7<=0,G7,G7/H7) -> 189.65517 | J7: =REPT("█",ROUND(MIN(1,IF(B7=0,0,F7/B7))*20,0))&" "&TEXT(IF(B7=0,0,F7/B7),"0%") -> ██████████████ 69% | K7: =IF(G7=0,"DONE",IF(H7=0,"Past due","On track")) -> On track
A8: Car down payment | B8: 6000 | C8: 2027-09-01 | D8: 500 | E8: =SUMIF(Deposits!$B$6:$B$500,A8,Deposits!$C$6:$C$500) -> 0 | F8: =D8+E8 -> 500 | G8: =MAX(0,B8-F8) -> 5500 | H8: =MAX(0,ROUND((DATEVALUE(C8)-TODAY())/30.4,1)) -> 11.4 | I8: =IF(H8<=0,G8,G8/H8) -> 482.45614 | J8: =REPT("█",ROUND(MIN(1,IF(B8=0,0,F8/B8))*20,0))&" "&TEXT(IF(B8=0,0,F8/B8),"0%") -> ██ 8% | K8: =IF(G8=0,"DONE",IF(H8=0,"Past due","On track")) -> On track
A9: Holiday gifts | B9: 1200 | C9: 2026-12-01 | D9: 400 | E9: =SUMIF(Deposits!$B$6:$B$500,A9,Deposits!$C$6:$C$500) -> 100 | F9: =D9+E9 -> 500 | G9: =MAX(0,B9-F9) -> 700 | H9: =MAX(0,ROUND((DATEVALUE(C9)-TODAY())/30.4,1)) -> 2.4 | I9: =IF(H9<=0,G9,G9/H9) -> 291.66667 | J9: =REPT("█",ROUND(MIN(1,IF(B9=0,0,F9/B9))*20,0))&" "&TEXT(IF(B9=0,0,F9/B9),"0%") -> ████████ 42% | K9: =IF(G9=0,"DONE",IF(H9=0,"Past due","On track")) -> On track
E10: =IF(A10="","",SUMIF(Deposits!$B$6:$B$500,A10,Deposits!$C$6:$C$500)) | F10: =IF(A10="","",D10+E10) | G10: =IF(A10="","",MAX(0,B10-F10)) | H10: =IF(A10="","",MAX(0,ROUND((DATEVALUE(C10)-TODAY())/30.4,1))) | I10: =IF(A10="","",IF(H10<=0,G10,G10/H10)) | J10: =IF(A10="","",REPT("█",ROUND(MIN(1,IF(B10=0,0,F10/B10))*20,0))&" "&TEXT(IF(B10=0,0,F10/B10),"0%")) | K10: =IF(A10="","",IF(G10=0,"DONE",IF(H10=0,"Past due","On track")))
E11: =IF(A11="","",SUMIF(Deposits!$B$6:$B$500,A11,Deposits!$C$6:$C$500)) | F11: =IF(A11="","",D11+E11) | G11: =IF(A11="","",MAX(0,B11-F11)) | H11: =IF(A11="","",MAX(0,ROUND((DATEVALUE(C11)-TODAY())/30.4,1))) | I11: =IF(A11="","",IF(H11<=0,G11,G11/H11)) | J11: =IF(A11="","",REPT("█",ROUND(MIN(1,IF(B11=0,0,F11/B11))*20,0))&" "&TEXT(IF(B11=0,0,F11/B11),"0%")) | K11: =IF(A11="","",IF(G11=0,"DONE",IF(H11=0,"Past due","On track")))
E12: =IF(A12="","",SUMIF(Deposits!$B$6:$B$500,A12,Deposits!$C$6:$C$500)) | F12: =IF(A12="","",D12+E12) | G12: =IF(A12="","",MAX(0,B12-F12)) | H12: =IF(A12="","",MAX(0,ROUND((DATEVALUE(C12)-TODAY())/30.4,1))) | I12: =IF(A12="","",IF(H12<=0,G12,G12/H12)) | J12: =IF(A12="","",REPT("█",ROUND(MIN(1,IF(B12=0,0,F12/B12))*20,0))&" "&TEXT(IF(B12=0,0,F12/B12),"0%")) | K12: =IF(A12="","",IF(G12=0,"DONE",IF(H12=0,"Past due","On track")))
E13: =IF(A13="","",SUMIF(Deposits!$B$6:$B$500,A13,Deposits!$C$6:$C$500)) | F13: =IF(A13="","",D13+E13) | G13: =IF(A13="","",MAX(0,B13-F13)) | H13: =IF(A13="","",MAX(0,ROUND((DATEVALUE(C13)-TODAY())/30.4,1))) | I13: =IF(A13="","",IF(H13<=0,G13,G13/H13)) | J13: =IF(A13="","",REPT("█",ROUND(MIN(1,IF(B13=0,0,F13/B13))*20,0))&" "&TEXT(IF(B13=0,0,F13/B13),"0%")) | K13: =IF(A13="","",IF(G13=0,"DONE",IF(H13=0,"Past due","On track")))
E14: =IF(A14="","",SUMIF(Deposits!$B$6:$B$500,A14,Deposits!$C$6:$C$500)) | F14: =IF(A14="","",D14+E14) | G14: =IF(A14="","",MAX(0,B14-F14)) | H14: =IF(A14="","",MAX(0,ROUND((DATEVALUE(C14)-TODAY())/30.4,1))) | I14: =IF(A14="","",IF(H14<=0,G14,G14/H14)) | J14: =IF(A14="","",REPT("█",ROUND(MIN(1,IF(B14=0,0,F14/B14))*20,0))&" "&TEXT(IF(B14=0,0,F14/B14),"0%")) | K14: =IF(A14="","",IF(G14=0,"DONE",IF(H14=0,"Past due","On track")))
E15: =IF(A15="","",SUMIF(Deposits!$B$6:$B$500,A15,Deposits!$C$6:$C$500)) | F15: =IF(A15="","",D15+E15) | G15: =IF(A15="","",MAX(0,B15-F15)) | H15: =IF(A15="","",MAX(0,ROUND((DATEVALUE(C15)-TODAY())/30.4,1))) | I15: =IF(A15="","",IF(H15<=0,G15,G15/H15)) | J15: =IF(A15="","",REPT("█",ROUND(MIN(1,IF(B15=0,0,F15/B15))*20,0))&" "&TEXT(IF(B15=0,0,F15/B15),"0%")) | K15: =IF(A15="","",IF(G15=0,"DONE",IF(H15=0,"Past due","On track")))
E16: =IF(A16="","",SUMIF(Deposits!$B$6:$B$500,A16,Deposits!$C$6:$C$500)) | F16: =IF(A16="","",D16+E16) | G16: =IF(A16="","",MAX(0,B16-F16)) | H16: =IF(A16="","",MAX(0,ROUND((DATEVALUE(C16)-TODAY())/30.4,1))) | I16: =IF(A16="","",IF(H16<=0,G16,G16/H16)) | J16: =IF(A16="","",REPT("█",ROUND(MIN(1,IF(B16=0,0,F16/B16))*20,0))&" "&TEXT(IF(B16=0,0,F16/B16),"0%")) | K16: =IF(A16="","",IF(G16=0,"DONE",IF(H16=0,"Past due","On track")))
E17: =IF(A17="","",SUMIF(Deposits!$B$6:$B$500,A17,Deposits!$C$6:$C$500)) | F17: =IF(A17="","",D17+E17) | G17: =IF(A17="","",MAX(0,B17-F17)) | H17: =IF(A17="","",MAX(0,ROUND((DATEVALUE(C17)-TODAY())/30.4,1))) | I17: =IF(A17="","",IF(H17<=0,G17,G17/H17)) | J17: =IF(A17="","",REPT("█",ROUND(MIN(1,IF(B17=0,0,F17/B17))*20,0))&" "&TEXT(IF(B17=0,0,F17/B17),"0%")) | K17: =IF(A17="","",IF(G17=0,"DONE",IF(H17=0,"Past due","On track")))
E18: =IF(A18="","",SUMIF(Deposits!$B$6:$B$500,A18,Deposits!$C$6:$C$500)) | F18: =IF(A18="","",D18+E18) | G18: =IF(A18="","",MAX(0,B18-F18)) | H18: =IF(A18="","",MAX(0,ROUND((DATEVALUE(C18)-TODAY())/30.4,1))) | I18: =IF(A18="","",IF(H18<=0,G18,G18/H18)) | J18: =IF(A18="","",REPT("█",ROUND(MIN(1,IF(B18=0,0,F18/B18))*20,0))&" "&TEXT(IF(B18=0,0,F18/B18),"0%")) | K18: =IF(A18="","",IF(G18=0,"DONE",IF(H18=0,"Past due","On track")))
E19: =IF(A19="","",SUMIF(Deposits!$B$6:$B$500,A19,Deposits!$C$6:$C$500)) | F19: =IF(A19="","",D19+E19) | G19: =IF(A19="","",MAX(0,B19-F19)) | H19: =IF(A19="","",MAX(0,ROUND((DATEVALUE(C19)-TODAY())/30.4,1))) | I19: =IF(A19="","",IF(H19<=0,G19,G19/H19)) | J19: =IF(A19="","",REPT("█",ROUND(MIN(1,IF(B19=0,0,F19/B19))*20,0))&" "&TEXT(IF(B19=0,0,F19/B19),"0%")) | K19: =IF(A19="","",IF(G19=0,"DONE",IF(H19=0,"Past due","On track")))
A20: TOTAL | B20: =SUM(B5:B19) -> 23500 | F20: =SUM(F5:F19) -> 7350 | G20: =SUM(G5:G19) -> 16150 | I20: =SUM(I5:I19) -> 2231.7055

Sheet Deposits
A1: Deposit Log
A2: Goal name must match the Goals tab exactly.
A4: How to use: type your numbers in the yellow cells (blue text). Everything else calculates.
A5: Date | B5: Goal | C5: Amount | D5: Note
A6: 2026-08-01 | B6: Emergency fund | C6: 400
A7: 2026-08-15 | B7: Vacation — Japan | C7: 200
A8: 2026-09-01 | B8: Emergency fund | C8: 400
A9: 2026-09-01 | B9: New laptop | C9: 150
A10: 2026-09-15 | B10: Holiday gifts | C10: 100
