Workbook

Sheet Start Here
A1: Monthly Bill Tracker & Payment Calendar
A2: Simple Sheets Co. — Excel + Google Sheets
A4: Setup
A5: 1. List every recurring bill once with amount, due day, and how it's paid.
A6: 2. Each month, mark bills paid in the month column. Unpaid totals and what's due this week show at the top.
A7: 3. The Calendar view shows the amount due on each day of the month.
A9: Conventions
A10: • Yellow cells with blue text are inputs. Type over the sample numbers.
A11: • Black text is a formula. Leave it alone unless you know what you're changing.
A12: • Green text pulls from another tab.
A13: • Works in Excel 2016+ and Google Sheets (File > Import > Upload > Replace). No macros.
A15: For planning and educational use only. Not financial, legal, or tax advice. Every number is an estimate you should verify for your own business.

Sheet Dashboard
B2: Bills Dashboard
B3: This month at a glance.
B5: MONTHLY BILLS | E5: PAID THIS MONTH | H5: STILL UNPAID | K5: DUE IN 7 DAYS
B6: =Bills!B34 -> 3127 | E6: =Bills!B35 -> 2555 | H6: =Bills!B36 -> 572 | K6: =Bills!B37 -> 362
B9: OVERDUE | E9: PAID
B10: =Bills!B38 -> 0 | E10: =IF(Bills!B34=0,0,Bills!B35/Bills!B34) -> 0.81707707
B13: Paid this month
B14: =REPT("█",ROUND(MIN(1,MAX(0,IF(Bills!B34=0,0,Bills!B35/Bills!B34)))*40,0))&REPT("░",40-ROUND(MIN(1,MAX(0,IF(Bills!B34=0,0,Bills!B35/Bills!B34)))*40,0))&" "&TEXT(IF(Bills!B34=0,0,Bills!B35/Bills!B34),"0%") -> █████████████████████████████████░░░░░░░ 82%

Sheet Calendar
A1: Payment Calendar
A2: Amount due each day of the month. | B2: Amount due
A4: Day | B4: Amount due | C4: Bills
A5: 1 | B5: =SUMIF(Bills!$C$8:$C$33,A5,Bills!$B$8:$B$33) -> 1850 | C5: =IF(B5=0,"",IFERROR(INDEX(Bills!$A$8:$A$33,MATCH(A5,Bills!$C$8:$C$33,0)),"")&IF(COUNTIF(Bills!$C$8:$C$33,A5)>1," +"&(COUNTIF(Bills!$C$8:$C$33,A5)-1)&" more","")) -> Rent
A6: 2 | B6: =SUMIF(Bills!$C$8:$C$33,A6,Bills!$B$8:$B$33) -> 0 | C6: =IF(B6=0,"",IFERROR(INDEX(Bills!$A$8:$A$33,MATCH(A6,Bills!$C$8:$C$33,0)),"")&IF(COUNTIF(Bills!$C$8:$C$33,A6)>1," +"&(COUNTIF(Bills!$C$8:$C$33,A6)-1)&" more",""))
A7: 3 | B7: =SUMIF(Bills!$C$8:$C$33,A7,Bills!$B$8:$B$33) -> 45 | C7: =IF(B7=0,"",IFERROR(INDEX(Bills!$A$8:$A$33,MATCH(A7,Bills!$C$8:$C$33,0)),"")&IF(COUNTIF(Bills!$C$8:$C$33,A7)>1," +"&(COUNTIF(Bills!$C$8:$C$33,A7)-1)&" more","")) -> Gym
A8: 4 | B8: =SUMIF(Bills!$C$8:$C$33,A8,Bills!$B$8:$B$33) -> 0 | C8: =IF(B8=0,"",IFERROR(INDEX(Bills!$A$8:$A$33,MATCH(A8,Bills!$C$8:$C$33,0)),"")&IF(COUNTIF(Bills!$C$8:$C$33,A8)>1," +"&(COUNTIF(Bills!$C$8:$C$33,A8)-1)&" more",""))
A9: 5 | B9: =SUMIF(Bills!$C$8:$C$33,A9,Bills!$B$8:$B$33) -> 310 | C9: =IF(B9=0,"",IFERROR(INDEX(Bills!$A$8:$A$33,MATCH(A9,Bills!$C$8:$C$33,0)),"")&IF(COUNTIF(Bills!$C$8:$C$33,A9)>1," +"&(COUNTIF(Bills!$C$8:$C$33,A9)-1)&" more","")) -> Car payment
A10: 6 | B10: =SUMIF(Bills!$C$8:$C$33,A10,Bills!$B$8:$B$33) -> 0 | C10: =IF(B10=0,"",IFERROR(INDEX(Bills!$A$8:$A$33,MATCH(A10,Bills!$C$8:$C$33,0)),"")&IF(COUNTIF(Bills!$C$8:$C$33,A10)>1," +"&(COUNTIF(Bills!$C$8:$C$33,A10)-1)&" more",""))
A11: 7 | B11: =SUMIF(Bills!$C$8:$C$33,A11,Bills!$B$8:$B$33) -> 0 | C11: =IF(B11=0,"",IFERROR(INDEX(Bills!$A$8:$A$33,MATCH(A11,Bills!$C$8:$C$33,0)),"")&IF(COUNTIF(Bills!$C$8:$C$33,A11)>1," +"&(COUNTIF(Bills!$C$8:$C$33,A11)-1)&" more",""))
A12: 8 | B12: =SUMIF(Bills!$C$8:$C$33,A12,Bills!$B$8:$B$33) -> 145 | C12: =IF(B12=0,"",IFERROR(INDEX(Bills!$A$8:$A$33,MATCH(A12,Bills!$C$8:$C$33,0)),"")&IF(COUNTIF(Bills!$C$8:$C$33,A12)>1," +"&(COUNTIF(Bills!$C$8:$C$33,A12)-1)&" more","")) -> Car insurance
A13: 9 | B13: =SUMIF(Bills!$C$8:$C$33,A13,Bills!$B$8:$B$33) -> 0 | C13: =IF(B13=0,"",IFERROR(INDEX(Bills!$A$8:$A$33,MATCH(A13,Bills!$C$8:$C$33,0)),"")&IF(COUNTIF(Bills!$C$8:$C$33,A13)>1," +"&(COUNTIF(Bills!$C$8:$C$33,A13)-1)&" more",""))
A14: 10 | B14: =SUMIF(Bills!$C$8:$C$33,A14,Bills!$B$8:$B$33) -> 0 | C14: =IF(B14=0,"",IFERROR(INDEX(Bills!$A$8:$A$33,MATCH(A14,Bills!$C$8:$C$33,0)),"")&IF(COUNTIF(Bills!$C$8:$C$33,A14)>1," +"&(COUNTIF(Bills!$C$8:$C$33,A14)-1)&" more",""))
A15: 11 | B15: =SUMIF(Bills!$C$8:$C$33,A15,Bills!$B$8:$B$33) -> 0 | C15: =IF(B15=0,"",IFERROR(INDEX(Bills!$A$8:$A$33,MATCH(A15,Bills!$C$8:$C$33,0)),"")&IF(COUNTIF(Bills!$C$8:$C$33,A15)>1," +"&(COUNTIF(Bills!$C$8:$C$33,A15)-1)&" more",""))
A16: 12 | B16: =SUMIF(Bills!$C$8:$C$33,A16,Bills!$B$8:$B$33) -> 140 | C16: =IF(B16=0,"",IFERROR(INDEX(Bills!$A$8:$A$33,MATCH(A16,Bills!$C$8:$C$33,0)),"")&IF(COUNTIF(Bills!$C$8:$C$33,A16)>1," +"&(COUNTIF(Bills!$C$8:$C$33,A16)-1)&" more","")) -> Electric
... A35: 31 | B35: =SUMIF(Bills!$C$8:$C$33,A35,Bills!$B$8:$B$33) -> 0 | C35: =IF(B35=0,"",IFERROR(INDEX(Bills!$A$8:$A$33,MATCH(A35,Bills!$C$8:$C$33,0)),"")&IF(COUNTIF(Bills!$C$8:$C$33,A35)>1," +"&(COUNTIF(Bills!$C$8:$C$33,A35)-1)&" more",""))

Sheet Bills
A1: Bills
A3: How to use: type your numbers in the yellow cells (blue text). Everything else calculates.
A4: Current month (1–12) | B4: 9
A5: Today's day of month | B5: =DAY(TODAY()) -> 18
A7: Bill | B7: Amount | C7: Due day | D7: Auto-pay? | E7: Account / method | F7: Jan | G7: Feb | H7: Mar | I7: Apr | J7: May | K7: Jun | L7: Jul | M7: Aug | N7: Sep | O7: Oct | P7: Nov | Q7: Dec
A8: Rent | B8: 1850 | C8: 1 | D8: N | E8: Checking | F8: Y | G8: Y | H8: Y | I8: Y | J8: Y | K8: Y | L8: Y | M8: Y | N8: Y
A9: Electric | B9: 140 | C9: 12 | D9: Y | E9: Visa 4417 | F9: Y | G9: Y | H9: Y | I9: Y | J9: Y | K9: Y | L9: Y | M9: Y | N9: Y
A10: Water/trash | B10: 65 | C10: 15 | D10: Y | E10: Checking | F10: Y | G10: Y | H10: Y | I10: Y | J10: Y | K10: Y | L10: Y | M10: Y | N10: Y
A11: Internet | B11: 80 | C11: 18 | D11: Y | E11: Visa 4417 | F11: Y | G11: Y | H11: Y | I11: Y | J11: Y | K11: Y | L11: Y | M11: Y
A12: Phone | B12: 95 | C12: 20 | D12: Y | E12: Visa 4417 | F12: Y | G12: Y | H12: Y | I12: Y | J12: Y | K12: Y | L12: Y | M12: Y
A13: Car payment | B13: 310 | C13: 5 | D13: Y | E13: Checking | F13: Y | G13: Y | H13: Y | I13: Y | J13: Y | K13: Y | L13: Y | M13: Y | N13: Y
A14: Car insurance | B14: 145 | C14: 8 | D14: Y | E14: Checking | F14: Y | G14: Y | H14: Y | I14: Y | J14: Y | K14: Y | L14: Y | M14: Y | N14: Y
A15: Streaming | B15: 32 | C15: 22 | D15: Y | E15: Visa 4417 | F15: Y | G15: Y | H15: Y | I15: Y | J15: Y | K15: Y | L15: Y | M15: Y
A16: Gym | B16: 45 | C16: 3 | D16: Y | E16: Visa 4417 | F16: Y | G16: Y | H16: Y | I16: Y | J16: Y | K16: Y | L16: Y | M16: Y | N16: Y
A17: Credit card min | B17: 155 | C17: 25 | D17: N | E17: Checking | F17: Y | G17: Y | H17: Y | I17: Y | J17: Y | K17: Y | L17: Y | M17: Y
A18: Student loan | B18: 210 | C18: 28 | D18: N | E18: Checking | F18: Y | G18: Y | H18: Y | I18: Y | J18: Y | K18: Y | L18: Y | M18: Y
A34: TOTAL monthly bills | B34: =SUM(B8:B33) -> 3127
A35: Paid this month | B35: =SUMPRODUCT((INDEX(F8:Q33,0,$B$4)="Y")*B8:B33) -> 2555
A36: Still unpaid this month | B36: =B34-B35 -> 572
A37: Due in the next 7 days (unpaid) | B37: =SUMPRODUCT((INDEX(F8:Q33,0,$B$4)<>"Y")*(C8:C33>=$B$5)*(C8:C33<=$B$5+7)*B8:B33) -> 362
A38: Overdue (unpaid, due day passed) | B38: =SUMPRODUCT((INDEX(F8:Q33,0,$B$4)<>"Y")*(C8:C33<$B$5)*B8:B33) -> 0
