Workbook

Sheet Start Here
A1: Freelancer Income, Expense & Quarterly Tax Tracker
A2: Simple Sheets Co. — Excel + Google Sheets
A4: Setup
A5: 1. Income tab: every invoice or payout (client, amount, date, paid?).
A6: 2. Expenses tab: deductible business costs by category.
A7: 3. Quarterly tab: net profit per US quarter, self-employment tax estimate, and an income-tax set-aside using your rate. Federal quarterly due dates are listed.
A9: Conventions
A10: • Yellow cells with blue text are inputs. Type over the sample numbers.
A11: • Black text is a formula. Leave it alone unless you know what you're changing.
A12: • Green text pulls from another tab.
A13: • Works in Excel 2016+ and Google Sheets (File > Import > Upload > Replace). No macros.
A14: • Self-employment tax uses 15.3% on 92.35% of net profit (2026 rules may differ; this is an estimate for set-aside, not a tax return).
A16: For planning and educational use only. Not financial, legal, or tax advice. Every number is an estimate you should verify for your own business.

Sheet Dashboard
B2: Freelance Dashboard
B3: Income, expenses and what to set aside for taxes.
B5: INCOME (PAID, YTD) | E5: UNPAID INVOICES | H5: EXPENSES (YTD) | K5: NET PROFIT (YTD)
B6: =Quarterly!C9 -> 29000 | E6: =Quarterly!D9 -> 3950 | H6: =Quarterly!E9 -> 3323 | K6: =Quarterly!F9 -> 25677
B9: SET ASIDE FOR TAXES | E9: SET-ASIDE RATE | H9: PROFIT MARGIN
B10: =Quarterly!I9 -> 9355.1592 | E10: =Quarterly!J9 -> 0.36434004 | H10: =IF(Quarterly!C9=0,0,Quarterly!F9/Quarterly!C9) -> 0.88541379

Sheet Quarterly
A1: Quarterly Summary & Tax Set-Aside
A2: Estimates only.
A4: Quarter | B4: Federal est. payment due | C4: Income (paid) | D4: Income (unpaid) | E4: Expenses | F4: Net profit | G4: SE tax est. | H4: Income tax set-aside | I4: Total set-aside | J4: Set-aside % of net
A5: Q1 | B5: April 15 | C5: =SUMIFS(Income!$D$5:$D$154,Income!$F$5:$F$154,A5,Income!$E$5:$E$154,"Y") -> 11000 | D5: =SUMIFS(Income!$D$5:$D$154,Income!$F$5:$F$154,A5)-C5 -> 0 | E5: =SUMIF(Expenses!$E$5:$E$142,A5,Expenses!$D$5:$D$142) -> 1618 | F5: =C5-E5 -> 9382 | G5: =MAX(0,F5)*Settings!$B$6*Settings!$B$5 -> 1325.6344 | H5: =MAX(0,F5-G5/2)*Settings!$B$4 -> 2092.6039 | I5: =G5+H5 -> 3418.2383 | J5: =IF(F5<=0,0,I5/F5) -> 0.36434004
A6: Q2 | B6: June 15 | C6: =SUMIFS(Income!$D$5:$D$154,Income!$F$5:$F$154,A6,Income!$E$5:$E$154,"Y") -> 9100 | D6: =SUMIFS(Income!$D$5:$D$154,Income!$F$5:$F$154,A6)-C6 -> 0 | E6: =SUMIF(Expenses!$E$5:$E$142,A6,Expenses!$D$5:$D$142) -> 1318 | F6: =C6-E6 -> 7782 | G6: =MAX(0,F6)*Settings!$B$6*Settings!$B$5 -> 1099.5616 | H6: =MAX(0,F6-G6/2)*Settings!$B$4 -> 1735.7326 | I6: =G6+H6 -> 2835.2942 | J6: =IF(F6<=0,0,I6/F6) -> 0.36434004
A7: Q3 | B7: September 15 | C7: =SUMIFS(Income!$D$5:$D$154,Income!$F$5:$F$154,A7,Income!$E$5:$E$154,"Y") -> 8900 | D7: =SUMIFS(Income!$D$5:$D$154,Income!$F$5:$F$154,A7)-C7 -> 2750 | E7: =SUMIF(Expenses!$E$5:$E$142,A7,Expenses!$D$5:$D$142) -> 387 | F7: =C7-E7 -> 8513 | G7: =MAX(0,F7)*Settings!$B$6*Settings!$B$5 -> 1202.8486 | H7: =MAX(0,F7-G7/2)*Settings!$B$4 -> 1898.7782 | I7: =G7+H7 -> 3101.6268 | J7: =IF(F7<=0,0,I7/F7) -> 0.36434004
A8: Q4 | B8: January 15 (next yr) | C8: =SUMIFS(Income!$D$5:$D$154,Income!$F$5:$F$154,A8,Income!$E$5:$E$154,"Y") -> 0 | D8: =SUMIFS(Income!$D$5:$D$154,Income!$F$5:$F$154,A8)-C8 -> 1200 | E8: =SUMIF(Expenses!$E$5:$E$142,A8,Expenses!$D$5:$D$142) -> 0 | F8: =C8-E8 -> 0 | G8: =MAX(0,F8)*Settings!$B$6*Settings!$B$5 -> 0 | H8: =MAX(0,F8-G8/2)*Settings!$B$4 -> 0 | I8: =G8+H8 -> 0 | J8: =IF(F8<=0,0,I8/F8) -> 0
A9: YEAR | C9: =SUM(C5:C8) -> 29000 | D9: =SUM(D5:D8) -> 3950 | E9: =SUM(E5:E8) -> 3323 | F9: =SUM(F5:F8) -> 25677 | G9: =SUM(G5:G8) -> 3628.0446 | H9: =SUM(H5:H8) -> 5727.1147 | I9: =SUM(I5:I8) -> 9355.1592 | J9: =IF(F9<=0,0,I9/F9) -> 0.36434004
A11: Income tax set-aside applies your rate to net profit minus half of SE tax (the deductible half). Talk to a tax professional for actual estimated payments.

Sheet Settings
A1: Settings
A3: How to use: type your numbers in the yellow cells (blue text). Everything else calculates.
A4: Federal + state income tax rate (marginal, for set-aside) | B4: 0.24
A5: Self-employment tax rate | B5: 0.153
A6: Portion of profit subject to SE tax | B6: 0.9235

Sheet Income
A1: Income
A3: How to use: type your numbers in the yellow cells (blue text). Everything else calculates.
A4: Date | B4: Client | C4: Description | D4: Amount | E4: Paid? (Y) | F4: Quarter
A5: 2026-01-16 | B5: Acme Co. | C5: Invoice 1040 | D5: 1200 | E5: Y | F5: =IF(A5="","","Q"&ROUNDUP(MONTH(DATEVALUE(A5))/3,0)) -> Q1
A6: 2026-01-26 | B6: Bluebird Studio | C6: Invoice 1041 | D6: 800 | E6: Y | F6: =IF(A6="","","Q"&ROUNDUP(MONTH(DATEVALUE(A6))/3,0)) -> Q1
A7: 2026-02-07 | B7: Acme Co. | C7: Invoice 1042 | D7: 1500 | E7: Y | F7: =IF(A7="","","Q"&ROUNDUP(MONTH(DATEVALUE(A7))/3,0)) -> Q1
A8: 2026-02-13 | B8: Bluebird Studio | C8: Invoice 1043 | D8: 800 | E8: Y | F8: =IF(A8="","","Q"&ROUNDUP(MONTH(DATEVALUE(A8))/3,0)) -> Q1
A9: 2026-02-24 | B9: Acme Co. | C9: Invoice 1044 | D9: 1500 | E9: Y | F9: =IF(A9="","","Q"&ROUNDUP(MONTH(DATEVALUE(A9))/3,0)) -> Q1
A10: 2026-03-07 | B10: Northwind | C10: Invoice 1045 | D10: 2200 | E10: Y | F10: =IF(A10="","","Q"&ROUNDUP(MONTH(DATEVALUE(A10))/3,0)) -> Q1
A11: 2026-03-15 | B11: Northwind | C11: Invoice 1046 | D11: 2200 | E11: Y | F11: =IF(A11="","","Q"&ROUNDUP(MONTH(DATEVALUE(A11))/3,0)) -> Q1
A12: 2026-03-23 | B12: Northwind | C12: Invoice 1047 | D12: 800 | E12: Y | F12: =IF(A12="","","Q"&ROUNDUP(MONTH(DATEVALUE(A12))/3,0)) -> Q1
A13: 2026-04-02 | B13: Northwind | C13: Invoice 1048 | D13: 1200 | E13: Y | F13: =IF(A13="","","Q"&ROUNDUP(MONTH(DATEVALUE(A13))/3,0)) -> Q2
A14: 2026-04-12 | B14: Northwind | C14: Invoice 1049 | D14: 800 | E14: Y | F14: =IF(A14="","","Q"&ROUNDUP(MONTH(DATEVALUE(A14))/3,0)) -> Q2
A15: 2026-04-20 | B15: Acme Co. | C15: Invoice 1050 | D15: 800 | E15: Y | F15: =IF(A15="","","Q"&ROUNDUP(MONTH(DATEVALUE(A15))/3,0)) -> Q2
A16: 2026-04-28 | B16: Northwind | C16: Invoice 1051 | D16: 450 | E16: Y | F16: =IF(A16="","","Q"&ROUNDUP(MONTH(DATEVALUE(A16))/3,0)) -> Q2
... A30: 2026-08-22 | B30: Riverside Dental | C30: Invoice 1065 | D30: 1500 | E30: Y | F30: =IF(A30="","","Q"&ROUNDUP(MONTH(DATEVALUE(A30))/3,0)) -> Q3
A31: 2026-09-01 | B31: Riverside Dental | C31: Invoice 1066 | D31: 800 | F31: =IF(A31="","","Q"&ROUNDUP(MONTH(DATEVALUE(A31))/3,0)) -> Q3
A32: 2026-09-11 | B32: Acme Co. | C32: Invoice 1067 | D32: 450 | F32: =IF(A32="","","Q"&ROUNDUP(MONTH(DATEVALUE(A32))/3,0)) -> Q3
A33: 2026-09-19 | B33: Northwind | C33: Invoice 1068 | D33: 1500 | F33: =IF(A33="","","Q"&ROUNDUP(MONTH(DATEVALUE(A33))/3,0)) -> Q3
A34: 2026-10-01 | B34: Bluebird Studio | C34: Invoice 1069 | D34: 1200 | F34: =IF(A34="","","Q"&ROUNDUP(MONTH(DATEVALUE(A34))/3,0)) -> Q4
F35: =IF(A35="","","Q"&ROUNDUP(MONTH(DATEVALUE(A35))/3,0))
F36: =IF(A36="","","Q"&ROUNDUP(MONTH(DATEVALUE(A36))/3,0))
F37: =IF(A37="","","Q"&ROUNDUP(MONTH(DATEVALUE(A37))/3,0))
F38: =IF(A38="","","Q"&ROUNDUP(MONTH(DATEVALUE(A38))/3,0))
F39: =IF(A39="","","Q"&ROUNDUP(MONTH(DATEVALUE(A39))/3,0))
F40: =IF(A40="","","Q"&ROUNDUP(MONTH(DATEVALUE(A40))/3,0))
F41: =IF(A41="","","Q"&ROUNDUP(MONTH(DATEVALUE(A41))/3,0))
F42: =IF(A42="","","Q"&ROUNDUP(MONTH(DATEVALUE(A42))/3,0))
F43: =IF(A43="","","Q"&ROUNDUP(MONTH(DATEVALUE(A43))/3,0))
F44: =IF(A44="","","Q"&ROUNDUP(MONTH(DATEVALUE(A44))/3,0))
F45: =IF(A45="","","Q"&ROUNDUP(MONTH(DATEVALUE(A45))/3,0))
F46: =IF(A46="","","Q"&ROUNDUP(MONTH(DATEVALUE(A46))/3,0))
... F154: =IF(A154="","","Q"&ROUNDUP(MONTH(DATEVALUE(A154))/3,0))

Sheet Expenses
A1: Expenses
A3: How to use: type your numbers in the yellow cells (blue text). Everything else calculates.
A4: Date | B4: Category | C4: Description | D4: Amount | E4: Quarter
A5: 2026-01-01 | B5: Travel | C5: Expense 1 | D5: 29 | E5: =IF(A5="","","Q"&ROUNDUP(MONTH(DATEVALUE(A5))/3,0)) -> Q1
A6: 2026-01-08 | B6: Marketing | C6: Expense 2 | D6: 29 | E6: =IF(A6="","","Q"&ROUNDUP(MONTH(DATEVALUE(A6))/3,0)) -> Q1
A7: 2026-01-15 | B7: Software | C7: Expense 3 | D7: 240 | E7: =IF(A7="","","Q"&ROUNDUP(MONTH(DATEVALUE(A7))/3,0)) -> Q1
A8: 2026-02-22 | B8: Software | C8: Expense 4 | D8: 60 | E8: =IF(A8="","","Q"&ROUNDUP(MONTH(DATEVALUE(A8))/3,0)) -> Q1
A9: 2026-02-02 | B9: Software | C9: Expense 5 | D9: 900 | E9: =IF(A9="","","Q"&ROUNDUP(MONTH(DATEVALUE(A9))/3,0)) -> Q1
A10: 2026-03-09 | B10: Professional services | C10: Expense 6 | D10: 120 | E10: =IF(A10="","","Q"&ROUNDUP(MONTH(DATEVALUE(A10))/3,0)) -> Q1
A11: 2026-03-16 | B11: Marketing | C11: Expense 7 | D11: 240 | E11: =IF(A11="","","Q"&ROUNDUP(MONTH(DATEVALUE(A11))/3,0)) -> Q1
A12: 2026-04-23 | B12: Home office | C12: Expense 8 | D12: 240 | E12: =IF(A12="","","Q"&ROUNDUP(MONTH(DATEVALUE(A12))/3,0)) -> Q2
A13: 2026-04-03 | B13: Marketing | C13: Expense 9 | D13: 60 | E13: =IF(A13="","","Q"&ROUNDUP(MONTH(DATEVALUE(A13))/3,0)) -> Q2
A14: 2026-05-10 | B14: Equipment | C14: Expense 10 | D14: 60 | E14: =IF(A14="","","Q"&ROUNDUP(MONTH(DATEVALUE(A14))/3,0)) -> Q2
A15: 2026-05-17 | B15: Software | C15: Expense 11 | D15: 900 | E15: =IF(A15="","","Q"&ROUNDUP(MONTH(DATEVALUE(A15))/3,0)) -> Q2
A16: 2026-06-24 | B16: Professional services | C16: Expense 12 | D16: 29 | E16: =IF(A16="","","Q"&ROUNDUP(MONTH(DATEVALUE(A16))/3,0)) -> Q2
... A22: 2026-09-12 | B22: Professional services | C22: Expense 18 | D22: 29 | E22: =IF(A22="","","Q"&ROUNDUP(MONTH(DATEVALUE(A22))/3,0)) -> Q3
E23: =IF(A23="","","Q"&ROUNDUP(MONTH(DATEVALUE(A23))/3,0))
E24: =IF(A24="","","Q"&ROUNDUP(MONTH(DATEVALUE(A24))/3,0))
E25: =IF(A25="","","Q"&ROUNDUP(MONTH(DATEVALUE(A25))/3,0))
E26: =IF(A26="","","Q"&ROUNDUP(MONTH(DATEVALUE(A26))/3,0))
E27: =IF(A27="","","Q"&ROUNDUP(MONTH(DATEVALUE(A27))/3,0))
E28: =IF(A28="","","Q"&ROUNDUP(MONTH(DATEVALUE(A28))/3,0))
E29: =IF(A29="","","Q"&ROUNDUP(MONTH(DATEVALUE(A29))/3,0))
E30: =IF(A30="","","Q"&ROUNDUP(MONTH(DATEVALUE(A30))/3,0))
E31: =IF(A31="","","Q"&ROUNDUP(MONTH(DATEVALUE(A31))/3,0))
E32: =IF(A32="","","Q"&ROUNDUP(MONTH(DATEVALUE(A32))/3,0))
E33: =IF(A33="","","Q"&ROUNDUP(MONTH(DATEVALUE(A33))/3,0))
E34: =IF(A34="","","Q"&ROUNDUP(MONTH(DATEVALUE(A34))/3,0))
... E142: =IF(A142="","","Q"&ROUNDUP(MONTH(DATEVALUE(A142))/3,0))
