Workbook

Sheet Start Here
A1: Net Worth Tracker & Annual Money Dashboard
A2: Simple Sheets Co. — Excel + Google Sheets
A4: Setup
A5: 1. Once a month, enter the balance of every account (cash, investments, property, and debts) in that month's column.
A6: 2. Net worth, month-over-month change, and the split between liquid and long-term assets calculate.
A7: 3. The Dashboard shows the year's trend and your debt-to-asset ratio.
A9: Conventions
A10: • Yellow cells with blue text are inputs. Type over the sample numbers.
A11: • Black text is a formula. Leave it alone unless you know what you're changing.
A12: • Green text pulls from another tab.
A13: • Works in Excel 2016+ and Google Sheets (File > Import > Upload > Replace). No macros.
A15: For planning and educational use only. Not financial, legal, or tax advice. Every number is an estimate you should verify for your own business.

Sheet Dashboard
B2: Net Worth Dashboard
B3: Where you stand, and which way it's moving.
B5: NET WORTH (LATEST) | E5: CHANGE THIS YEAR | H5: CHANGE THIS YEAR % | K5: MONTHS OF EXPENSES IN CASH
B6: =Details!B3 -> 211124 | E6: =Details!B5 -> 65124 | H6: =Details!B6 -> 0.44605479 | K6: =Details!B8 -> 3.3985714
B9: CASH SHARE OF ASSETS | E9: STARTED THE YEAR AT
B10: =Details!B7 -> 0.028205584 | E10: =Details!B4 -> 146000
N13: Mix
N14: Cash | O14: =LOOKUP(2,1/(Balances!C23:N23<>0),Balances!C23:N23) -> 14274
N15: Investments | O15: =LOOKUP(2,1/(Balances!C24:N24<>0),Balances!C24:N24) -> 72108
N16: Property | O16: =LOOKUP(2,1/(Balances!C25:N25<>0),Balances!C25:N25) -> 419688

Sheet Details
A1: Year Dashboard
A3: Latest net worth | B3: =LOOKUP(2,1/(Balances!C27:N27<>""),Balances!C27:N27) -> 211124
A4: Net worth in January | B4: =Balances!C27 -> 146000
A5: Change this year | B5: =IF(B3="","",B3-B4) -> 65124
A6: Change this year % | B6: =IF(OR(B4="",B4=0),"",B5/B4) -> 0.44605479
A7: Liquid (cash) share of assets | B7: =LOOKUP(2,1/(Balances!C23:N23<>0),Balances!C23:N23)/(LOOKUP(2,1/(Balances!C23:N23<>0),Balances!C23:N23)+LOOKUP(2,1/(Balances!C24:N24<>0),Balances!C24:N24)+LOOKUP(2,1/(Balances!C25:N25<>0),Balances!C25:N25)) -> 0.028205584
A8: Months of expenses in cash (enter monthly expenses →) | B8: =IF(C8=0,0,LOOKUP(2,1/(Balances!C23:N23<>0),Balances!C23:N23)/C8) -> 3.3985714 | C8: 4200
A10: Month | B10: Net worth | C10: Change
A11: Jan | B11: =Balances!C27 -> 146000 | C11: =""
A12: Feb | B12: =Balances!D27 -> 151920 | C12: =Balances!D28 -> 5920
A13: Mar | B13: =Balances!E27 -> 157841 | C13: =Balances!E28 -> 5921
A14: Apr | B14: =Balances!F27 -> 163761 | C14: =Balances!F28 -> 5920
A15: May | B15: =Balances!G27 -> 169682 | C15: =Balances!G28 -> 5921
A16: Jun | B16: =Balances!H27 -> 175602 | C16: =Balances!H28 -> 5920
A17: Jul | B17: =Balances!I27 -> 181522 | C17: =Balances!I28 -> 5920
A18: Aug | B18: =Balances!J27 -> 187443 | C18: =Balances!J28 -> 5921
A19: Sep | B19: =Balances!K27 -> 193363 | C19: =Balances!K28 -> 5920
A20: Oct | B20: =Balances!L27 -> 199284 | C20: =Balances!L28 -> 5921
A21: Nov | B21: =Balances!M27 -> 205204 | C21: =Balances!M28 -> 5920
A22: Dec | B22: =Balances!N27 -> 211124 | C22: =Balances!N28 -> 5920

Sheet Balances
A1: Monthly Balances
A2: Enter end-of-month balances.
A4: How to use: type your numbers in the yellow cells (blue text). Everything else calculates.
A5: Account | B5: Type | C5: Jan | D5: Feb | E5: Mar | F5: Apr | G5: May | H5: Jun | I5: Jul | J5: Aug | K5: Sep | L5: Oct | M5: Nov | N5: Dec
A6: Checking | B6: Cash | C6: 3200 | D6: 3264 | E6: 3328 | F6: 3392 | G6: 3456 | H6: 3520 | I6: 3584 | J6: 3648 | K6: 3712 | L6: 3776 | M6: 3840 | N6: 3904
A7: Savings / emergency | B7: Cash | C7: 8500 | D7: 8670 | E7: 8840 | F7: 9010 | G7: 9180 | H7: 9350 | I7: 9520 | J7: 9690 | K7: 9860 | L7: 10030 | M7: 10200 | N7: 10370
A8: 401(k) | B8: Investment | C8: 42000 | D8: 42504 | E8: 43008 | F8: 43512 | G8: 44016 | H8: 44520 | I8: 45024 | J8: 45528 | K8: 46032 | L8: 46536 | M8: 47040 | N8: 47544
A9: Roth IRA | B9: Investment | C9: 15500 | D9: 15686 | E9: 15872 | F9: 16058 | G9: 16244 | H9: 16430 | I9: 16616 | J9: 16802 | K9: 16988 | L9: 17174 | M9: 17360 | N9: 17546
A10: Brokerage | B10: Investment | C10: 6200 | D10: 6274 | E10: 6349 | F10: 6423 | G10: 6498 | H10: 6572 | I10: 6646 | J10: 6721 | K10: 6795 | L10: 6870 | M10: 6944 | N10: 7018
A11: Home (est. value) | B11: Property | C11: 385000 | D11: 386540 | E11: 388080 | F11: 389620 | G11: 391160 | H11: 392700 | I11: 394240 | J11: 395780 | K11: 397320 | L11: 398860 | M11: 400400 | N11: 401940
A12: Car (est. value) | B12: Property | C12: 17000 | D12: 17068 | E12: 17136 | F12: 17204 | G12: 17272 | H12: 17340 | I12: 17408 | J12: 17476 | K12: 17544 | L12: 17612 | M12: 17680 | N12: 17748
A13: Mortgage | B13: Debt | C13: -298000 | D13: -295020 | E13: -292040 | F13: -289060 | G13: -286080 | H13: -283100 | I13: -280120 | J13: -277140 | K13: -274160 | L13: -271180 | M13: -268200 | N13: -265220
A14: Car loan | B14: Debt | C14: -11800 | D14: -11682 | E14: -11564 | F14: -11446 | G14: -11328 | H14: -11210 | I14: -11092 | J14: -10974 | K14: -10856 | L14: -10738 | M14: -10620 | N14: -10502
A15: Credit cards | B15: Debt | C15: -3100 | D15: -3069 | E15: -3038 | F15: -3007 | G15: -2976 | H15: -2945 | I15: -2914 | J15: -2883 | K15: -2852 | L15: -2821 | M15: -2790 | N15: -2759
A16: Student loan | B16: Debt | C16: -18500 | D16: -18315 | E16: -18130 | F16: -17945 | G16: -17760 | H16: -17575 | I16: -17390 | J16: -17205 | K16: -17020 | L16: -16835 | M16: -16650 | N16: -16465
A23: Total cash | C23: =SUMIF($B$6:$B$22,"Cash",C6:C22) -> 11700 | D23: =SUMIF($B$6:$B$22,"Cash",D6:D22) -> 11934 | E23: =SUMIF($B$6:$B$22,"Cash",E6:E22) -> 12168 | F23: =SUMIF($B$6:$B$22,"Cash",F6:F22) -> 12402 | G23: =SUMIF($B$6:$B$22,"Cash",G6:G22) -> 12636 | H23: =SUMIF($B$6:$B$22,"Cash",H6:H22) -> 12870 | I23: =SUMIF($B$6:$B$22,"Cash",I6:I22) -> 13104 | J23: =SUMIF($B$6:$B$22,"Cash",J6:J22) -> 13338 | ... N23: =SUMIF($B$6:$B$22,"Cash",N6:N22) -> 14274
A24: Total investments | C24: =SUMIF($B$6:$B$22,"Investment",C6:C22) -> 63700 | D24: =SUMIF($B$6:$B$22,"Investment",D6:D22) -> 64464 | E24: =SUMIF($B$6:$B$22,"Investment",E6:E22) -> 65229 | F24: =SUMIF($B$6:$B$22,"Investment",F6:F22) -> 65993 | G24: =SUMIF($B$6:$B$22,"Investment",G6:G22) -> 66758 | H24: =SUMIF($B$6:$B$22,"Investment",H6:H22) -> 67522 | I24: =SUMIF($B$6:$B$22,"Investment",I6:I22) -> 68286 | J24: =SUMIF($B$6:$B$22,"Investment",J6:J22) -> 69051 | ... N24: =SUMIF($B$6:$B$22,"Investment",N6:N22) -> 72108
A25: Total property | C25: =SUMIF($B$6:$B$22,"Property",C6:C22) -> 402000 | D25: =SUMIF($B$6:$B$22,"Property",D6:D22) -> 403608 | E25: =SUMIF($B$6:$B$22,"Property",E6:E22) -> 405216 | F25: =SUMIF($B$6:$B$22,"Property",F6:F22) -> 406824 | G25: =SUMIF($B$6:$B$22,"Property",G6:G22) -> 408432 | H25: =SUMIF($B$6:$B$22,"Property",H6:H22) -> 410040 | I25: =SUMIF($B$6:$B$22,"Property",I6:I22) -> 411648 | J25: =SUMIF($B$6:$B$22,"Property",J6:J22) -> 413256 | ... N25: =SUMIF($B$6:$B$22,"Property",N6:N22) -> 419688
A26: Total debt | C26: =SUMIF($B$6:$B$22,"Debt",C6:C22) -> -331400 | D26: =SUMIF($B$6:$B$22,"Debt",D6:D22) -> -328086 | E26: =SUMIF($B$6:$B$22,"Debt",E6:E22) -> -324772 | F26: =SUMIF($B$6:$B$22,"Debt",F6:F22) -> -321458 | G26: =SUMIF($B$6:$B$22,"Debt",G6:G22) -> -318144 | H26: =SUMIF($B$6:$B$22,"Debt",H6:H22) -> -314830 | I26: =SUMIF($B$6:$B$22,"Debt",I6:I22) -> -311516 | J26: =SUMIF($B$6:$B$22,"Debt",J6:J22) -> -308202 | ... N26: =SUMIF($B$6:$B$22,"Debt",N6:N22) -> -294946
A27: NET WORTH | C27: =IF(COUNT(C6:C22)=0,"",C23+C24+C25+C26) -> 146000 | D27: =IF(COUNT(D6:D22)=0,"",D23+D24+D25+D26) -> 151920 | E27: =IF(COUNT(E6:E22)=0,"",E23+E24+E25+E26) -> 157841 | F27: =IF(COUNT(F6:F22)=0,"",F23+F24+F25+F26) -> 163761 | G27: =IF(COUNT(G6:G22)=0,"",G23+G24+G25+G26) -> 169682 | H27: =IF(COUNT(H6:H22)=0,"",H23+H24+H25+H26) -> 175602 | I27: =IF(COUNT(I6:I22)=0,"",I23+I24+I25+I26) -> 181522 | J27: =IF(COUNT(J6:J22)=0,"",J23+J24+J25+J26) -> 187443 | ... N27: =IF(COUNT(N6:N22)=0,"",N23+N24+N25+N26) -> 211124
A28: Change vs prior month | D28: =IF(OR(D27="",C27=""),"",D27-C27) -> 5920 | E28: =IF(OR(E27="",D27=""),"",E27-D27) -> 5921 | F28: =IF(OR(F27="",E27=""),"",F27-E27) -> 5920 | G28: =IF(OR(G27="",F27=""),"",G27-F27) -> 5921 | H28: =IF(OR(H27="",G27=""),"",H27-G27) -> 5920 | I28: =IF(OR(I27="",H27=""),"",I27-H27) -> 5920 | J28: =IF(OR(J27="",I27=""),"",J27-I27) -> 5921 | K28: =IF(OR(K27="",J27=""),"",K27-J27) -> 5920 | ... N28: =IF(OR(N27="",M27=""),"",N27-M27) -> 5920
A29: Debt-to-asset ratio | C29: =IF(C27="","",IF((C23+C24+C25)=0,0,-C26/(C23+C24+C25))) -> 0.69417679 | D29: =IF(D27="","",IF((D23+D24+D25)=0,0,-D26/(D23+D24+D25))) -> 0.68350396 | E29: =IF(E27="","",IF((E23+E24+E25)=0,0,-E26/(E23+E24+E25))) -> 0.67294499 | F29: =IF(F27="","",IF((F23+F24+F25)=0,0,-F26/(F23+F24+F25))) -> 0.66250085 | G29: =IF(G27="","",IF((G23+G24+G25)=0,0,-G26/(G23+G24+G25))) -> 0.65216696 | H29: =IF(H27="","",IF((H23+H24+H25)=0,0,-H26/(H23+H24+H25))) -> 0.64194425 | I29: =IF(I27="","",IF((I23+I24+I25)=0,0,-I26/(I23+I24+I25))) -> 0.6318296 | J29: =IF(J27="","",IF((J23+J24+J25)=0,0,-J26/(J23+J24+J25))) -> 0.62182005 | ... N29: =IF(N27="","",IF((N23+N24+N25)=0,0,-N26/(N23+N24+N25))) -> 0.58281661
